Workbook

Sheet README
A1: Independent DCF Validation Workbook
A2: Track A Phase 2A — Independent spreadsheet validator, built in a fresh session with no exposure to this repository's DCF/WACC implementation.
A4: Purpose
A5: This workbook independently reconstructs the Discounted Cash Flow (DCF) and WACC/CAPM calculations described in docs/model-specifications/dcf.md and docs/model-specifications/wacc-capm.md, entered as real, cell-by-cell Excel formulas from the written specification's prose and equations — never by reading, importing, or copying formulas from src/dcf_model/dcf.py or any other implementation file in this repository. Its purpose is to provide a second, mechanically independent calculation path that could catch a systematic formula bug the codebase's own test suite could never catch (a test written to match an incorrect implementation would still pass). See docs/independent-validation-plan.md and L-012 in docs/limitations-register.md.
A7: What this workbook does NOT do
A8: It does not import, execute, or call any code from this repository. It does not compare its own output against a live run of the codebase — the 'codebase output' columns on the Summary & Reconciliation sheet are deliberately left blank, to be filled in by a separate future session per the validation plan's explicit two-session design. It makes no investment recommendation of any kind.
A10: Sheet inventory
A11: Sheet | B11: Contents
A12: README | B12: This sheet.
A13: Sources | B13: Every data source, hostname, and retrieval detail used to build this workbook.
A14: Assumptions | B14: Every shared modeling assumption, with its source and rationale.
A15: Summary & Reconciliation | B15: Cross-company summary of every key output, plus the (currently blank) reconciliation-vs-codebase table.
A16: Inputs_<TICKER> (x4) | B16: Frozen raw facts and assumptions for one company — all hardcoded input cells (blue font).
A17: DCF_<TICKER> (x4) | B17: Every DCF/WACC formula for one company (black font, gray fill = computed, never hardcoded), with spec-section labels and local Validation Checks.
A18: Sensitivity_<TICKER> (x4) | B18: One-variable and two-way sensitivity tables for one company, with direction checks.
A19: Research Outlook | B19: Narrative interpretation of the independent findings, fragility discussion, and the profitability-is-not-established disclaimer.
A20: Validation Checks | B20: Cross-company rollup of every PASS/FAIL/PENDING check, plus the sign-off checklist from independent-validation-plan.md.
A22: Legend
A23: Blue text | B23: Hardcoded input — a frozen fact or a stated assumption. Never a formula.
A24: Black text, gray fill | B24: A live formula, computed from other cells. Never a pasted/hardcoded result.
A25: PASS | B25: Check succeeded.
A26: FAIL | B26: Check failed — investigated and documented (never silently forced to PASS).
A27: PENDING | B27: Cannot be evaluated yet (e.g. awaiting the codebase-output comparison from a separate future session).
A29: Companies validated
A30: Ticker | B30: Entity | C30: Profile (confirmed from frozen data) | D30: Revenue CAGR | E30: Avg Op Margin
A31: MSFT | B31: MICROSOFT CORPORATION | C31: Large-cap, capital-light, high-margin | D31: 13.74% | E31: 44.18%
A32: CAT | B32: CATERPILLAR INC | C32: Capital-intensive, moderate leverage | D32: 7.31% | E32: 16.56%
A33: INTC | B33: INTEL CORP | C33: Mature, negative/near-zero recent revenue growth | D33: -9.55% | E33: 0.46%
A34: VZ | B34: VERIZON COMMUNICATIONS INC | C34: Meaningfully leveraged (recommended 4th profile) | D34: 0.85% | E34: 21.22%
A36: Reproducibility
A37: Generated by build_workbook_v2.py (this directory), which loads snapshots/*.json and writes every formula programmatically via xlsx_lite.py (a small stdlib-only OOXML writer — openpyxl, xlsxwriter, and LibreOffice were not available in this build environment, and installing dependencies is out of scope for this task). Re-run: python3 build_workbook_v2.py

Sheet Sources
A1: Data Sources
A2: Full per-field provenance is in source_manifest.csv alongside this workbook. This sheet summarizes.
A4: Hostnames contacted (read-only, unauthenticated)
A5: Hostname | B5: Purpose | C5: Endpoint pattern used
A6: www.sec.gov | B6: CIK ticker lookup | C6: https://www.sec.gov/files/company_tickers.json
A7: data.sec.gov | B7: Primary financial-statement facts (XBRL) | C7: https://data.sec.gov/api/xbrl/companyfacts/CIK{10-digit}.json
A8: query1/query2.finance.yahoo.com (via yfinance) | B8: Current price, shares outstanding, beta, sector | C8: yfinance Ticker.info / Ticker.fast_info
A10: MSFT — MICROSOFT CORPORATION (CIK 0000789019)
A11: Field | B11: Fiscal Period / Timestamp | C11: XBRL Tag / Source | D11: Filing Accession | E11: Filed / Retrieved Date | F11: Provenance | G11: Source URL
A12: Revenue | B12: 2022-06-30 | C12: RevenueFromContractWithCustomerExcludingAssessedTax | D12: 0001564590-22-026876 | E12: 2022-07-28 | F12: reported | G12: https://www.sec.gov/Archives/edgar/data/789019/000156459022026876/0001564590-22-026876-index.htm
A13: EBIT/Operating Income | B13: 2022-06-30 | C13: OperatingIncomeLoss | D13: 0001564590-22-026876 | E13: 2022-07-28 | F13: reported | G13: https://www.sec.gov/Archives/edgar/data/789019/000156459022026876/0001564590-22-026876-index.htm
A14: Revenue | B14: 2023-06-30 | C14: RevenueFromContractWithCustomerExcludingAssessedTax | D14: 0000950170-23-035122 | E14: 2023-07-27 | F14: reported | G14: https://www.sec.gov/Archives/edgar/data/789019/000095017023035122/0000950170-23-035122-index.htm
A15: EBIT/Operating Income | B15: 2023-06-30 | C15: OperatingIncomeLoss | D15: 0000950170-23-035122 | E15: 2023-07-27 | F15: reported | G15: https://www.sec.gov/Archives/edgar/data/789019/000095017023035122/0000950170-23-035122-index.htm
A16: Revenue | B16: 2024-06-30 | C16: RevenueFromContractWithCustomerExcludingAssessedTax | D16: 0000950170-24-087843 | E16: 2024-07-30 | F16: reported | G16: https://www.sec.gov/Archives/edgar/data/789019/000095017024087843/0000950170-24-087843-index.htm
A17: EBIT/Operating Income | B17: 2024-06-30 | C17: OperatingIncomeLoss | D17: 0000950170-24-087843 | E17: 2024-07-30 | F17: reported | G17: https://www.sec.gov/Archives/edgar/data/789019/000095017024087843/0000950170-24-087843-index.htm
A18: Revenue | B18: 2025-06-30 | C18: RevenueFromContractWithCustomerExcludingAssessedTax | D18: 0000950170-25-100235 | E18: 2025-07-30 | F18: reported | G18: https://www.sec.gov/Archives/edgar/data/789019/000095017025100235/0000950170-25-100235-index.htm
A19: EBIT/Operating Income | B19: 2025-06-30 | C19: OperatingIncomeLoss | D19: 0000950170-25-100235 | E19: 2025-07-30 | F19: reported | G19: https://www.sec.gov/Archives/edgar/data/789019/000095017025100235/0000950170-25-100235-index.htm
A20: Revenue | B20: 2026-06-30 | C20: RevenueFromContractWithCustomerExcludingAssessedTax | D20: 0001193125-26-323660 | E20: 2026-07-29 | F20: reported | G20: https://www.sec.gov/Archives/edgar/data/789019/000119312526323660/0001193125-26-323660-index.htm
A21: EBIT/Operating Income | B21: 2026-06-30 | C21: OperatingIncomeLoss | D21: 0001193125-26-323660 | E21: 2026-07-29 | F21: reported | G21: https://www.sec.gov/Archives/edgar/data/789019/000119312526323660/0001193125-26-323660-index.htm
A22: Pretax Income (latest) | B22: 2026-06-30 | C22: IncomeLossFromContinuingOperationsBeforeIncomeTaxesExtraordinaryItemsNoncontrollingInterest | D22: 0001193125-26-323660 | E22: 2026-07-29 | F22: reported | G22: https://www.sec.gov/Archives/edgar/data/789019/000119312526323660/0001193125-26-323660-index.htm
... A28: Total Debt (latest, derived) | B28: 2026-06-30 | C28: Total Debt = LongTermDebtNoncurrent ($31,067,000,000) + LongTermDebtCurrent ($9,227,000,000) = $40,294,000,000 | D28: 0001193125-26-323660 | E28: 2026-07-29 | F28: derived (sum of components above) | G28: https://www.sec.gov/Archives/edgar/data/789019/000119312526323660/0001193125-26-323660-index.htm
A29: Price / Shares / Beta / Sector | B29: 2026-08-17T17:22:55.505484+00:00 | C29: yfinance Ticker.info | E29: 2026-08-17T17:22:55.505484+00:00 | F29: reported (unchanged from original freeze) | G29: https://finance.yahoo.com/quote/MSFT
A31: CAT — CATERPILLAR INC (CIK 0000018230)
A32: Field | B32: Fiscal Period / Timestamp | C32: XBRL Tag / Source | D32: Filing Accession | E32: Filed / Retrieved Date | F32: Provenance | G32: Source URL
A33: Revenue | B33: 2021-12-31 | C33: Revenues | D33: 0000018230-22-000050 | E33: 2022-02-16 | F33: reported | G33: https://www.sec.gov/Archives/edgar/data/18230/000001823022000050/0000018230-22-000050-index.htm
A34: EBIT/Operating Income | B34: 2021-12-31 | C34: OperatingIncomeLoss | D34: 0000018230-22-000050 | E34: 2022-02-16 | F34: reported | G34: https://www.sec.gov/Archives/edgar/data/18230/000001823022000050/0000018230-22-000050-index.htm
A35: Revenue | B35: 2022-12-31 | C35: Revenues | D35: 0000018230-23-000011 | E35: 2023-02-15 | F35: reported | G35: https://www.sec.gov/Archives/edgar/data/18230/000001823023000011/0000018230-23-000011-index.htm
A36: EBIT/Operating Income | B36: 2022-12-31 | C36: OperatingIncomeLoss | D36: 0000018230-23-000011 | E36: 2023-02-15 | F36: reported | G36: https://www.sec.gov/Archives/edgar/data/18230/000001823023000011/0000018230-23-000011-index.htm
A37: Revenue | B37: 2023-12-31 | C37: Revenues | D37: 0000018230-24-000009 | E37: 2024-02-16 | F37: reported | G37: https://www.sec.gov/Archives/edgar/data/18230/000001823024000009/0000018230-24-000009-index.htm
A38: EBIT/Operating Income | B38: 2023-12-31 | C38: OperatingIncomeLoss | D38: 0000018230-24-000009 | E38: 2024-02-16 | F38: reported | G38: https://www.sec.gov/Archives/edgar/data/18230/000001823024000009/0000018230-24-000009-index.htm
A39: Revenue | B39: 2024-12-31 | C39: Revenues | D39: 0000018230-25-000008 | E39: 2025-02-14 | F39: reported | G39: https://www.sec.gov/Archives/edgar/data/18230/000001823025000008/0000018230-25-000008-index.htm
A40: EBIT/Operating Income | B40: 2024-12-31 | C40: OperatingIncomeLoss | D40: 0000018230-25-000008 | E40: 2025-02-14 | F40: reported | G40: https://www.sec.gov/Archives/edgar/data/18230/000001823025000008/0000018230-25-000008-index.htm
A41: Revenue | B41: 2025-12-31 | C41: Revenues | D41: 0000018230-26-000008 | E41: 2026-02-13 | F41: reported | G41: https://www.sec.gov/Archives/edgar/data/18230/000001823026000008/0000018230-26-000008-index.htm
A42: EBIT/Operating Income | B42: 2025-12-31 | C42: OperatingIncomeLoss | D42: 0000018230-26-000008 | E42: 2026-02-13 | F42: reported | G42: https://www.sec.gov/Archives/edgar/data/18230/000001823026000008/0000018230-26-000008-index.htm
A43: Pretax Income (latest) | B43: 2025-12-31 | C43: IncomeLossFromContinuingOperationsBeforeIncomeTaxesMinorityInterestAndIncomeLossFromEquityMethodInvestments | D43: 0000018230-26-000008 | E43: 2026-02-13 | F43: reported | G43: https://www.sec.gov/Archives/edgar/data/18230/000001823026000008/0000018230-26-000008-index.htm
... A49: Total Debt (latest, derived) | B49: 2025-12-31 | C49: Total Debt = LongTermDebtNoncurrent ($30,696,000,000) + ShortTermBorrowings ($5,514,000,000) = $36,210,000,000 | D49: 0000018230-26-000008 | E49: 2026-02-13 | F49: derived (sum of components above) | G49: https://www.sec.gov/Archives/edgar/data/18230/000001823026000008/0000018230-26-000008-index.htm
A50: Price / Shares / Beta / Sector | B50: 2026-08-17T17:22:56.069590+00:00 | C50: yfinance Ticker.info | E50: 2026-08-17T17:22:56.069590+00:00 | F50: reported (unchanged from original freeze) | G50: https://finance.yahoo.com/quote/CAT
A52: INTC — INTEL CORP (CIK 0000050863)
A53: Field | B53: Fiscal Period / Timestamp | C53: XBRL Tag / Source | D53: Filing Accession | E53: Filed / Retrieved Date | F53: Provenance | G53: Source URL
A54: Revenue | B54: 2021-12-25 | C54: RevenueFromContractWithCustomerExcludingAssessedTax | D54: 0000050863-22-000007 | E54: 2022-01-27 | F54: reported | G54: https://www.sec.gov/Archives/edgar/data/50863/000005086322000007/0000050863-22-000007-index.htm
A55: EBIT/Operating Income | B55: 2021-12-25 | C55: OperatingIncomeLoss | D55: 0000050863-22-000007 | E55: 2022-01-27 | F55: reported | G55: https://www.sec.gov/Archives/edgar/data/50863/000005086322000007/0000050863-22-000007-index.htm
A56: Revenue | B56: 2022-12-31 | C56: RevenueFromContractWithCustomerExcludingAssessedTax | D56: 0000050863-23-000006 | E56: 2023-01-27 | F56: reported | G56: https://www.sec.gov/Archives/edgar/data/50863/000005086323000006/0000050863-23-000006-index.htm
A57: EBIT/Operating Income | B57: 2022-12-31 | C57: OperatingIncomeLoss | D57: 0000050863-23-000006 | E57: 2023-01-27 | F57: reported | G57: https://www.sec.gov/Archives/edgar/data/50863/000005086323000006/0000050863-23-000006-index.htm
A58: Revenue | B58: 2023-12-30 | C58: RevenueFromContractWithCustomerExcludingAssessedTax | D58: 0000050863-24-000010 | E58: 2024-01-26 | F58: reported | G58: https://www.sec.gov/Archives/edgar/data/50863/000005086324000010/0000050863-24-000010-index.htm
A59: EBIT/Operating Income | B59: 2023-12-30 | C59: OperatingIncomeLoss | D59: 0000050863-24-000010 | E59: 2024-01-26 | F59: reported | G59: https://www.sec.gov/Archives/edgar/data/50863/000005086324000010/0000050863-24-000010-index.htm
A60: Revenue | B60: 2024-12-28 | C60: RevenueFromContractWithCustomerExcludingAssessedTax | D60: 0000050863-25-000009 | E60: 2025-01-31 | F60: reported | G60: https://www.sec.gov/Archives/edgar/data/50863/000005086325000009/0000050863-25-000009-index.htm
A61: EBIT/Operating Income | B61: 2024-12-28 | C61: OperatingIncomeLoss | D61: 0000050863-25-000009 | E61: 2025-01-31 | F61: reported | G61: https://www.sec.gov/Archives/edgar/data/50863/000005086325000009/0000050863-25-000009-index.htm
A62: Revenue | B62: 2025-12-27 | C62: RevenueFromContractWithCustomerExcludingAssessedTax | D62: 0000050863-26-000011 | E62: 2026-01-23 | F62: reported | G62: https://www.sec.gov/Archives/edgar/data/50863/000005086326000011/0000050863-26-000011-index.htm
A63: EBIT/Operating Income | B63: 2025-12-27 | C63: OperatingIncomeLoss | D63: 0000050863-26-000011 | E63: 2026-01-23 | F63: reported | G63: https://www.sec.gov/Archives/edgar/data/50863/000005086326000011/0000050863-26-000011-index.htm
A64: Pretax Income (latest) | B64: 2025-12-27 | C64: IncomeLossFromContinuingOperationsBeforeIncomeTaxesExtraordinaryItemsNoncontrollingInterest | D64: 0000050863-26-000011 | E64: 2026-01-23 | F64: reported | G64: https://www.sec.gov/Archives/edgar/data/50863/000005086326000011/0000050863-26-000011-index.htm
... A70: Total Debt (latest, derived) | B70: 2025-12-27 | C70: Total Debt = LongTermDebtNoncurrent ($44,086,000,000) + LongTermDebtCurrent ($2,499,000,000) = $46,585,000,000 | D70: 0000050863-26-000011 | E70: 2026-01-23 | F70: derived (sum of components above) | G70: https://www.sec.gov/Archives/edgar/data/50863/000005086326000011/0000050863-26-000011-index.htm
A71: Price / Shares / Beta / Sector | B71: 2026-08-17T17:22:56.613849+00:00 | C71: yfinance Ticker.info | E71: 2026-08-17T17:22:56.613849+00:00 | F71: reported (unchanged from original freeze) | G71: https://finance.yahoo.com/quote/INTC
A73: VZ — VERIZON COMMUNICATIONS INC (CIK 0000732712)
A74: Field | B74: Fiscal Period / Timestamp | C74: XBRL Tag / Source | D74: Filing Accession | E74: Filed / Retrieved Date | F74: Provenance | G74: Source URL
A75: Revenue | B75: 2021-12-31 | C75: Revenues | D75: 0000732712-22-000008 | E75: 2022-02-11 | F75: reported | G75: https://www.sec.gov/Archives/edgar/data/732712/000073271222000008/0000732712-22-000008-index.htm
A76: EBIT/Operating Income | B76: 2021-12-31 | C76: OperatingIncomeLoss | D76: 0000732712-22-000008 | E76: 2022-02-11 | F76: reported | G76: https://www.sec.gov/Archives/edgar/data/732712/000073271222000008/0000732712-22-000008-index.htm
A77: Revenue | B77: 2022-12-31 | C77: Revenues | D77: 0000732712-23-000012 | E77: 2023-02-10 | F77: reported | G77: https://www.sec.gov/Archives/edgar/data/732712/000073271223000012/0000732712-23-000012-index.htm
A78: EBIT/Operating Income | B78: 2022-12-31 | C78: OperatingIncomeLoss | D78: 0000732712-23-000012 | E78: 2023-02-10 | F78: reported | G78: https://www.sec.gov/Archives/edgar/data/732712/000073271223000012/0000732712-23-000012-index.htm
A79: Revenue | B79: 2023-12-31 | C79: Revenues | D79: 0000732712-24-000010 | E79: 2024-02-09 | F79: reported | G79: https://www.sec.gov/Archives/edgar/data/732712/000073271224000010/0000732712-24-000010-index.htm
A80: EBIT/Operating Income | B80: 2023-12-31 | C80: OperatingIncomeLoss | D80: 0000732712-24-000010 | E80: 2024-02-09 | F80: reported | G80: https://www.sec.gov/Archives/edgar/data/732712/000073271224000010/0000732712-24-000010-index.htm
A81: Revenue | B81: 2024-12-31 | C81: Revenues | D81: 0000732712-25-000006 | E81: 2025-02-12 | F81: reported | G81: https://www.sec.gov/Archives/edgar/data/732712/000073271225000006/0000732712-25-000006-index.htm
A82: EBIT/Operating Income | B82: 2024-12-31 | C82: OperatingIncomeLoss | D82: 0000732712-25-000006 | E82: 2025-02-12 | F82: reported | G82: https://www.sec.gov/Archives/edgar/data/732712/000073271225000006/0000732712-25-000006-index.htm
A83: Revenue | B83: 2025-12-31 | C83: Revenues | D83: 0000732712-26-000007 | E83: 2026-02-17 | F83: reported | G83: https://www.sec.gov/Archives/edgar/data/732712/000073271226000007/0000732712-26-000007-index.htm
A84: EBIT/Operating Income | B84: 2025-12-31 | C84: OperatingIncomeLoss | D84: 0000732712-26-000007 | E84: 2026-02-17 | F84: reported | G84: https://www.sec.gov/Archives/edgar/data/732712/000073271226000007/0000732712-26-000007-index.htm
A85: Pretax Income (latest) | B85: 2025-12-31 | C85: IncomeLossFromContinuingOperationsBeforeIncomeTaxesExtraordinaryItemsNoncontrollingInterest | D85: 0000732712-26-000007 | E85: 2026-02-17 | F85: reported | G85: https://www.sec.gov/Archives/edgar/data/732712/000073271226000007/0000732712-26-000007-index.htm
... A89: Total Debt (latest, reported) | B89: 2025-12-31 | C89: DebtLongtermAndShorttermCombinedAmount | D89: 0000732712-26-000007 | E89: 2026-02-17 | F89: reported | G89: https://www.sec.gov/Archives/edgar/data/732712/000073271226000007/0000732712-26-000007-index.htm
A90: Price / Shares / Beta / Sector | B90: 2026-08-17T17:22:57.201272+00:00 | C90: yfinance Ticker.info | E90: 2026-08-17T17:22:57.201272+00:00 | F90: reported (unchanged from original freeze) | G90: https://finance.yahoo.com/quote/VZ

Sheet Assumptions
A1: Assumptions
A2: Per docs/assumptions-register.md and the task's shared-assumption directive.
A4: Shared assumptions (identical for every company unless noted)
A5: Assumption | B5: Value | C5: Register ID | D5: Rationale
A6: Risk-free rate | B6: 4.0% | C6: A-001 | D6: 10Y Treasury proxy; fixed per task directive rather than a live fetch (SEC/yfinance macro endpoints not required here).
A7: Market risk premium | B7: 5.5% | C7: A-009 | D7: Standard long-run U.S. equity risk premium estimate.
A8: Terminal growth rate | B8: 2.5% | C8: A-003 | D8: Roughly tracks long-run nominal GDP growth; bounded well under typical WACC.
A9: Projection period | B9: 5 years | C9: — | D9: Standard explicit DCF forecast window.
A10: D&A % of revenue | B10: 3% | C10: A-004 | D10: Fixed simplifying assumption, not derived per-company.
A11: CapEx % of revenue | B11: 4% | C11: A-004 | D11: Fixed simplifying assumption, not derived per-company.
A12: ΔNWC % of revenue change | B12: 1% | C12: A-004 | D12: Applied to the CHANGE in revenue, not revenue itself (avoids double-counting).
A13: WACC clamp | B13: [5%, 20%] | C13: A-006 | D13: Prevents a degenerate beta/rate combination from producing a nonsensical discount rate.
A14: Terminal growth clamp | B14: [0%, 5%] | C14: spec (dcf.md) | D14: Keeps WACC−g well-behaved.
A15: Historical revenue growth cap | B15: 25% (uncapped below) | C15: A-002 | D15: Caps a hyper-growth anomaly; deliberately NOT floored — a shrinking company's negative CAGR is used as-is.
A17: Company-specific derived values & disclosed fallbacks
A18: Ticker | B18: Tax Rate (derived) | C18: Method | D18: Cost of Debt (derived) | E18: Method | F18: Note
A19: MSFT | B19: 19.40% | C19: derived | D19: 7.57% | E19: derived
A20: CAT | B20: 23.98% | C20: derived | D20: 5.09% | E20: derived
A21: INTC | B21: 98.33% | C21: derived | D21: 2.34% | E21: derived | F21: Tax rate 98.3% is technically in [0,1) but economically extreme — latest-year pretax income ($1.56B) is nearly fully offset by tax provision ($1.53B), likely a valuation-allowance/one-time effect on a slim profit base. Used as-is per spec (in-range values are not overridden); flagged prominently here and in Research Outlook, not silently smoothed.
A22: VZ | B22: 22.34% | C22: derived | D22: 4.23% | E22: derived
A24: Missing-data fallbacks actually triggered in this validation
A25: None. All four companies had complete SEC EDGAR data for every required field (revenue, EBIT/operating income — one derived via Pretax+Interest for periods without a reported OperatingIncomeLoss tag, pretax income, tax provision, interest expense, total debt, cash) and complete yfinance market data (price, shares, beta, sector). No DEFAULT_TAX_RATE=21%, DEFAULT_COST_OF_DEBT=5%, DEFAULT_BETA=1.0, or DEFAULT_REVENUE_GROWTH/MARGIN fallback was triggered for any of the four companies — every derived value below is a genuine derivation from frozen facts, not a fallback default.

Sheet Inputs_MSFT
A1: Inputs — MSFT (MICROSOFT CORPORATION) | Frozen 2026-08-17T17:23:45.327319+00:00
A2: Profile: Large-cap, capital-light, high-margin | CIK 0000789019 | All USD values are actual dollars (not thousands/millions) unless noted.
A4: SECTION 1 — Historical Annual Data (SEC EDGAR, frozen)
A5: Fiscal Year End | B5: Revenue (USD) | C5: EBIT / Operating Income (USD) | D5: Provenance
A6: 44742 | B6: 198270000000 | C6: 83383000000 | D6: XBRL tag: RevenueFromContractWithCustomerExcludingAssessedTax
A7: 45107 | B7: 211915000000 | C7: 88523000000 | D7: XBRL tag: RevenueFromContractWithCustomerExcludingAssessedTax
A8: 45473 | B8: 245122000000 | C8: 109433000000 | D8: XBRL tag: RevenueFromContractWithCustomerExcludingAssessedTax
A9: 45838 | B9: 281724000000 | C9: 128528000000 | D9: XBRL tag: RevenueFromContractWithCustomerExcludingAssessedTax
A10: 46203 | B10: 331839000000 | C10: 155237000000 | D10: XBRL tag: RevenueFromContractWithCustomerExcludingAssessedTax
A12: SECTION 2 — Latest-Year Facts (SEC EDGAR, frozen)
A13: Latest Complete Fiscal Year End | B13: 46203
A14: Pretax Income (USD) | B14: 165934000000
A15: Tax Provision (USD) | B15: 32185000000
A16: Interest Expense (USD) | B16: 3051000000 | D16: Method: reported; tag: InterestExpenseNonoperating
A17: Total Debt (USD) | B17: 40294000000 | D17: Total Debt = LongTermDebtNoncurrent ($31,067,000,000) + LongTermDebtCurrent ($9,227,000,000) = $40,294,000,000 | Full per-component provenance (XBRL tag, accession, filed date, source URL): see Sources sheet.
A18: Cash & Equivalents (USD) | B18: 20935000000
A20: SECTION 3 — Market Data (Yahoo Finance via yfinance, frozen)
A21: Current Price (USD/share) | B21: 479.78
A22: Shares Outstanding | B22: 7425545491
A23: Beta (levered equity) | B23: 1.099
A24: Sector (GICS) | B24: Technology
A26: SECTION 4 — Assumptions (shared across companies unless noted; assumptions-register.md)
A27: Risk-free rate (A-001) | B27: 0.04
A28: Market risk premium (A-009) | B28: 0.055
A29: Terminal growth rate, base case (A-003) | B29: 0.025
A30: Projection years | B30: 5
A31: D&A % of revenue (A-004) | B31: 0.03
A32: CapEx % of revenue (A-004) | B32: 0.04
A33: ΔNWC % of revenue change (A-004) | B33: 0.01
A34: WACC clamp — minimum (A-006) | B34: 0.05
A35: WACC clamp — maximum (A-006) | B35: 0.2
A36: Terminal growth clamp — minimum | B36: 0
A37: Terminal growth clamp — maximum | B37: 0.05
A38: Historical revenue growth cap (A-002) | B38: 0.25

Sheet DCF_MSFT
A1: DCF Valuation — MSFT (MICROSOFT CORPORATION) [V2 — Track A Phase 2C]
A2: Every formula below is entered independently from docs/model-specifications/dcf.md and wacc-capm.md prose/equations — never copied from src/dcf_model/dcf.py. V2: years_elapsed now uses actual fiscal-period-end date subtraction, per the Track A Phase 2C specification clarification (A-028/L-019) — see row below.
A4: SECTION 1 — Historical Revenue CAGR & Operating Margin [dcf.md §Historical revenue-growth and operating-margin derivation]
A5: Years elapsed = (latest fiscal date − earliest fiscal date) / 365.25 [V2; A-028] | B5: =('Inputs_MSFT'!$A$10-'Inputs_MSFT'!$A$6)/365.25 -> 4 | D5: Spec: dcf.md — years_elapsed is ACTUAL elapsed calendar days between the earliest- and latest-dated valid observations / 365.25, never (periods−1) (A-028; Track A Phase 2C, resolving the ambiguity Phase 2B found).
A6: Diagnostic — naive (N periods − 1) years [V1's convention; NOT used below] | B6: 4 | C6: REGULAR | D6: Fiscal calendar is evenly spaced for this company — actual years_elapsed equals the naive (N periods − 1) count to within floating-point noise, so V1 and V2 agree here by coincidence, not because (periods − 1) is a generally correct convention.
A8: Raw Revenue CAGR = (Rev_latest/Rev_earliest)^(1/years) − 1 | B8: =('Inputs_MSFT'!$B$10/'Inputs_MSFT'!$B$6)^(1/B5)-1 -> 0.13741147
A9: Capped Revenue CAGR (cap A-002; NOT floored below) | B9: =MIN(B8,'Inputs_MSFT'!$B$38) -> 0.13741147 | D9: Spec: dcf.md — capped at MAX_REVENUE_GROWTH_RATE=25%, unbounded below (A-002)
A10: Average Historical Operating Margin = simple average of EBIT_t/Revenue_t | B10: =('Inputs_MSFT'!$C$6/'Inputs_MSFT'!$B$6+'Inputs_MSFT'!$C$7/'Inputs_MSFT'!$B$7+'Inputs_MSFT'!$C$8/'Inputs_MSFT'!$B$8+'Inputs_MSFT'!$C$9/'Inputs_MSFT'!$B$9+'Inputs_MSFT'!$C$10/'Inputs_MSFT'!$B$10)/5 -> 0.44175047
A12: SECTION 2 — WACC via CAPM [wacc-capm.md §Formula]
A13: Market Capitalization = Price × Shares Outstanding | B13: ='Inputs_MSFT'!$B$21*'Inputs_MSFT'!$B$22 -> 3.5626282e+12
A14: Effective Tax Rate = Tax Provision / Pretax Income (latest FY) | B14: ='Inputs_MSFT'!$B$15/'Inputs_MSFT'!$B$14 -> 0.19396266 | D14: Method: derived. Spec: wacc-capm.md — derived as tax_provision/pretax_income, valid range [0,1); DEFAULT_TAX_RATE=21% only on missing data.
A15: Cost of Debt = |Interest Expense| / Total Debt (latest FY) | B15: =ABS('Inputs_MSFT'!$B$16)/'Inputs_MSFT'!$B$17 -> 0.075718469
A16: Cost of Equity (CAPM) = Rf + Beta × MRP | B16: ='Inputs_MSFT'!$B$27+'Inputs_MSFT'!$B$23*'Inputs_MSFT'!$B$28 -> 0.100445
A17: After-Tax Cost of Debt = Cost of Debt × (1 − Tax Rate) | B17: =B15*(1-B14) -> 0.061031914
A18: Weight of Equity = MktCap / (MktCap + Total Debt) | B18: =B13/(B13+'Inputs_MSFT'!$B$17) -> 0.9888163
A19: Weight of Debt = Total Debt / (MktCap + Total Debt) | B19: ='Inputs_MSFT'!$B$17/(B13+'Inputs_MSFT'!$B$17) -> 0.0111837
A20: Raw WACC = We×Re + Wd×Rd(after-tax) | B20: =B18*B16+B19*B17 -> 0.10000422
A21: Final WACC — clamped to [5%,20%] (A-006), via MEDIAN(raw,min,max) | B21: =MEDIAN(B20,'Inputs_MSFT'!$B$34,'Inputs_MSFT'!$B$35) -> 0.10000422 | D21: MEDIAN(x,min,max) is a standard single-formula clamp: returns min if x<min, max if x>max, else x.
A23: SECTION 3 — 5-Year Free Cash Flow Projection [dcf.md §Free Cash Flow projection]
B24: Year 0 (base, actual) | C24: Year 1 | D24: Year 2 | E24: Year 3 | F24: Year 4 | G24: Year 5
A25: Revenue = Revenue_(t-1) × (1 + growth) | B25: ='Inputs_MSFT'!$B$10 -> 331839000000 | C25: =B25*(1+$B$9) -> 3.7743749e+11 | D25: =C25*(1+$B$9) -> 4.2930173e+11 | E25: =D25*(1+$B$9) -> 4.8829271e+11 | F25: =E25*(1+$B$9) -> 5.5538973e+11 | G25: =F25*(1+$B$9) -> 6.3170665e+11
A26: EBIT = Revenue × Operating Margin | C26: =C25*$B$10 -> 1.6673319e+11 | D26: =D25*$B$10 -> 1.8964424e+11 | E26: =E25*$B$10 -> 2.1570353e+11 | F26: =F25*$B$10 -> 2.4534367e+11 | G26: =G25*$B$10 -> 2.7905671e+11
A27: NOPAT = EBIT × (1 − Tax Rate) | C27: =C26*(1-$B$14) -> 1.3439317e+11 | D27: =D26*(1-$B$14) -> 1.5286034e+11 | E27: =E26*(1-$B$14) -> 1.738651e+11 | F27: =F26*(1-$B$14) -> 1.9775616e+11 | G27: =G26*(1-$B$14) -> 2.2493013e+11
A28: D&A = Revenue × D&A% (A-004) | C28: =C25*'Inputs_MSFT'!$B$31 -> 1.1323125e+10 | D28: =D25*'Inputs_MSFT'!$B$31 -> 1.2879052e+10 | E28: =E25*'Inputs_MSFT'!$B$31 -> 1.4648781e+10 | F28: =F25*'Inputs_MSFT'!$B$31 -> 1.6661692e+10 | G28: =G25*'Inputs_MSFT'!$B$31 -> 1.89512e+10
A29: CapEx = Revenue × CapEx% (A-004) | C29: =C25*'Inputs_MSFT'!$B$32 -> 1.5097499e+10 | D29: =D25*'Inputs_MSFT'!$B$32 -> 1.7172069e+10 | E29: =E25*'Inputs_MSFT'!$B$32 -> 1.9531708e+10 | F29: =F25*'Inputs_MSFT'!$B$32 -> 2.2215589e+10 | G29: =G25*'Inputs_MSFT'!$B$32 -> 2.5268266e+10
A30: ΔNWC = NWC% × (Revenue_t − Revenue_(t-1)) (A-004) | C30: ='Inputs_MSFT'!$B$33*(C25-B25) -> 4.5598486e+08 | D30: ='Inputs_MSFT'!$B$33*(D25-C25) -> 5.1864241e+08 | E30: ='Inputs_MSFT'!$B$33*(E25-D25) -> 5.8990983e+08 | F30: ='Inputs_MSFT'!$B$33*(F25-E25) -> 6.7097021e+08 | G30: ='Inputs_MSFT'!$B$33*(G25-F25) -> 7.6316921e+08
A31: Unlevered FCF = NOPAT + D&A − CapEx − ΔNWC | C31: =C27+C28-C29-C30 -> 1.3016281e+11 | D31: =D27+D28-D29-D30 -> 1.4804868e+11 | E31: =E27+E28-E29-E30 -> 1.6839226e+11 | F31: =F27+F28-F29-F30 -> 1.9153129e+11 | G31: =G27+G28-G29-G30 -> 2.1784989e+11
A33: SECTION 4 — Terminal Value (Gordon Growth) [dcf.md §Terminal value]
A34: Terminal Value = FCF_Y5 × (1+g) / (WACC − g) | B34: =G31*(1+'Inputs_MSFT'!$B$29)/(B21-'Inputs_MSFT'!$B$29) -> 2.9771145e+12
A35: Check: Final WACC > Terminal Growth Rate? | B35: =IF(B21>'Inputs_MSFT'!$B$29,"PASS","FAIL") -> PASS
A37: SECTION 5 — Discounting & Enterprise-to-Equity Bridge [dcf.md §Discounting and the Enterprise-to-Equity bridge]
A38: PV(FCF_t) = FCF_t / (1+WACC)^t | C38: =C31/(1+$B$21)^1 -> 1.1832938e+11 | D38: =D31/(1+$B$21)^2 -> 1.2235334e+11 | E38: =E31/(1+$B$21)^3 -> 1.2651415e+11 | F38: =F31/(1+$B$21)^4 -> 1.3081645e+11 | G38: =G31/(1+$B$21)^5 -> 1.3526505e+11
A39: Sum of PV(FCF Years 1-5) | B39: =SUM(C38:G38) -> 6.3327836e+11
A40: PV(Terminal Value) = TV / (1+WACC)^5 | B40: =B34/(1+B21)^5 -> 1.8485184e+12
A41: Enterprise Value = Sum PV(FCF) + PV(Terminal Value) | B41: =B39+B40 -> 2.4817968e+12
A42: Equity Value = Enterprise Value − Total Debt + Cash | B42: =B41-'Inputs_MSFT'!$B$17+'Inputs_MSFT'!$B$18 -> 2.4624378e+12
A43: Intrinsic Value per Share = Equity Value / Shares Outstanding | B43: =B42/'Inputs_MSFT'!$B$22 -> 331.61709
A44: Current Price / Intrinsic Value (descriptive ratio, NOT a recommendation) | B44: ='Inputs_MSFT'!$B$21/B43 -> 1.4467891
A46: SECTION 6 — Validation Checks (local to this company)
A47: WACC within documented clamp [5%,20%]? | B47: =IF(AND(B21>='Inputs_MSFT'!$B$34,B21<='Inputs_MSFT'!$B$35),"PASS","FAIL") -> PASS
A48: Enterprise Value is a finite number? | B48: =IF(ISNUMBER(B41),"PASS","FAIL") -> PASS
A49: Intrinsic Value per Share is a finite number? | B49: =IF(ISNUMBER(B43),"PASS","FAIL") -> PASS
A50: Intrinsic Value per Share is positive? | B50: =IF(B43>0,"PASS","FAIL") -> PASS
A51: Effective tax rate within valid [0,1) range? | B51: =IF(AND(B14>=0,B14<1),"PASS","FAIL") -> PASS
A52: Final WACC exceeds terminal growth rate? | B52: =IF(B21>'Inputs_MSFT'!$B$29,"PASS","FAIL") -> PASS

Sheet Sensitivity_MSFT
A1: Sensitivity Analysis — MSFT
A2: One variable at a time, other inputs held at base case. Per docs/independent-validation-plan.md §Sensitivity tables.
A4: TABLE 1 — WACC Sensitivity (range [5%,20%], base FCF path held fixed) [dcf.md Terminal Value + discounting]
A5: WACC | B5: Terminal Value | C5: Enterprise Value | D5: Equity Value | E5: Intrinsic Value/Share
A6: 0.05 | B6: =IF($A$6<='Inputs_MSFT'!$B$29,"n/a (WACC<=g)",'DCF_MSFT'!$G$31*(1+'Inputs_MSFT'!$B$29)/($A$6-'Inputs_MSFT'!$B$29)) -> 8.9318455e+12 | C6: =IF(B6="n/a (WACC<=g)","n/a",SUMPRODUCT('DCF_MSFT'!$C$31:$G$31,1/(1+$A$6)^{1,2,3,4,5})+B6/(1+$A$6)^5) -> 7.7303117e+12 | D6: =IF(C6="n/a","n/a",C6-'Inputs_MSFT'!$B$17+'Inputs_MSFT'!$B$18) -> 7.7109527e+12 | E6: =IF(D6="n/a","n/a",D6/'Inputs_MSFT'!$B$22) -> 1038.4359
A7: 0.075 | B7: =IF($A$7<='Inputs_MSFT'!$B$29,"n/a (WACC<=g)",'DCF_MSFT'!$G$31*(1+'Inputs_MSFT'!$B$29)/($A$7-'Inputs_MSFT'!$B$29)) -> 4.4659228e+12 | C7: =IF(B7="n/a (WACC<=g)","n/a",SUMPRODUCT('DCF_MSFT'!$C$31:$G$31,1/(1+$A$7)^{1,2,3,4,5})+B7/(1+$A$7)^5) -> 3.7906832e+12 | D7: =IF(C7="n/a","n/a",C7-'Inputs_MSFT'!$B$17+'Inputs_MSFT'!$B$18) -> 3.7713242e+12 | E7: =IF(D7="n/a","n/a",D7/'Inputs_MSFT'!$B$22) -> 507.88514
A8: 0.1 | B8: =IF($A$8<='Inputs_MSFT'!$B$29,"n/a (WACC<=g)",'DCF_MSFT'!$G$31*(1+'Inputs_MSFT'!$B$29)/($A$8-'Inputs_MSFT'!$B$29)) -> 2.9772818e+12 | C8: =IF(B8="n/a (WACC<=g)","n/a",SUMPRODUCT('DCF_MSFT'!$C$31:$G$31,1/(1+$A$8)^{1,2,3,4,5})+B8/(1+$A$8)^5) -> 2.4819436e+12 | D8: =IF(C8="n/a","n/a",C8-'Inputs_MSFT'!$B$17+'Inputs_MSFT'!$B$18) -> 2.4625846e+12 | E8: =IF(D8="n/a","n/a",D8/'Inputs_MSFT'!$B$22) -> 331.63686
A9: 0.125 | B9: =IF($A$9<='Inputs_MSFT'!$B$29,"n/a (WACC<=g)",'DCF_MSFT'!$G$31*(1+'Inputs_MSFT'!$B$29)/($A$9-'Inputs_MSFT'!$B$29)) -> 2.2329614e+12 | C9: =IF(B9="n/a (WACC<=g)","n/a",SUMPRODUCT('DCF_MSFT'!$C$31:$G$31,1/(1+$A$9)^{1,2,3,4,5})+B9/(1+$A$9)^5) -> 1.8305425e+12 | D9: =IF(C9="n/a","n/a",C9-'Inputs_MSFT'!$B$17+'Inputs_MSFT'!$B$18) -> 1.8111835e+12 | E9: =IF(D9="n/a","n/a",D9/'Inputs_MSFT'!$B$22) -> 243.91251
A10: 0.15 | B10: =IF($A$10<='Inputs_MSFT'!$B$29,"n/a (WACC<=g)",'DCF_MSFT'!$G$31*(1+'Inputs_MSFT'!$B$29)/($A$10-'Inputs_MSFT'!$B$29)) -> 1.7863691e+12 | C10: =IF(B10="n/a (WACC<=g)","n/a",SUMPRODUCT('DCF_MSFT'!$C$31:$G$31,1/(1+$A$10)^{1,2,3,4,5})+B10/(1+$A$10)^5) -> 1.4418115e+12 | D10: =IF(C10="n/a","n/a",C10-'Inputs_MSFT'!$B$17+'Inputs_MSFT'!$B$18) -> 1.4224525e+12 | E10: =IF(D10="n/a","n/a",D10/'Inputs_MSFT'!$B$22) -> 191.56202
A11: 0.175 | B11: =IF($A$11<='Inputs_MSFT'!$B$29,"n/a (WACC<=g)",'DCF_MSFT'!$G$31*(1+'Inputs_MSFT'!$B$29)/($A$11-'Inputs_MSFT'!$B$29)) -> 1.4886409e+12 | C11: =IF(B11="n/a (WACC<=g)","n/a",SUMPRODUCT('DCF_MSFT'!$C$31:$G$31,1/(1+$A$11)^{1,2,3,4,5})+B11/(1+$A$11)^5) -> 1.1842238e+12 | D11: =IF(C11="n/a","n/a",C11-'Inputs_MSFT'!$B$17+'Inputs_MSFT'!$B$18) -> 1.1648648e+12 | E11: =IF(D11="n/a","n/a",D11/'Inputs_MSFT'!$B$22) -> 156.87263
A12: 0.2 | B12: =IF($A$12<='Inputs_MSFT'!$B$29,"n/a (WACC<=g)",'DCF_MSFT'!$G$31*(1+'Inputs_MSFT'!$B$29)/($A$12-'Inputs_MSFT'!$B$29)) -> 1.2759779e+12 | C12: =IF(B12="n/a (WACC<=g)","n/a",SUMPRODUCT('DCF_MSFT'!$C$31:$G$31,1/(1+$A$12)^{1,2,3,4,5})+B12/(1+$A$12)^5) -> 1.0014323e+12 | D12: =IF(C12="n/a","n/a",C12-'Inputs_MSFT'!$B$17+'Inputs_MSFT'!$B$18) -> 9.8207328e+11 | E12: =IF(D12="n/a","n/a",D12/'Inputs_MSFT'!$B$22) -> 132.25604
A13: Direction check: IV decreases as WACC rises? | B13: =IF(E6>E12,"PASS (as expected)","FAIL — investigate (see note)") -> PASS (as expected)
A16: TABLE 2 — Terminal Growth Rate Sensitivity (range [0%,5%]); invalid where g>=WACC
A17: Terminal Growth g | B17: Terminal Value | C17: Enterprise Value | D17: Equity Value | E17: Intrinsic Value/Share
A18: 0 | B18: =IF($A$18>='DCF_MSFT'!$B$21,"n/a (g>=WACC)",'DCF_MSFT'!$G$31*(1+$A$18)/('DCF_MSFT'!$B$21-$A$18)) -> 2.1784071e+12 | C18: =IF(B18="n/a (g>=WACC)","n/a",'DCF_MSFT'!$B$39+B18/(1+'DCF_MSFT'!$B$21)^5) -> 1.9858718e+12 | D18: =IF(C18="n/a","n/a",C18-'Inputs_MSFT'!$B$17+'Inputs_MSFT'!$B$18) -> 1.9665128e+12 | E18: =IF(D18="n/a","n/a",D18/'Inputs_MSFT'!$B$22) -> 264.83076
A19: 0.01 | B19: =IF($A$19>='DCF_MSFT'!$B$21,"n/a (g>=WACC)",'DCF_MSFT'!$G$31*(1+$A$19)/('DCF_MSFT'!$B$21-$A$19)) -> 2.4446454e+12 | C19: =IF(B19="n/a (g>=WACC)","n/a",'DCF_MSFT'!$B$39+B19/(1+'DCF_MSFT'!$B$21)^5) -> 2.1511817e+12 | D19: =IF(C19="n/a","n/a",C19-'Inputs_MSFT'!$B$17+'Inputs_MSFT'!$B$18) -> 2.1318227e+12 | E19: =IF(D19="n/a","n/a",D19/'Inputs_MSFT'!$B$22) -> 287.09308
A20: 0.02 | B20: =IF($A$20>='DCF_MSFT'!$B$21,"n/a (g>=WACC)",'DCF_MSFT'!$G$31*(1+$A$20)/('DCF_MSFT'!$B$21-$A$20)) -> 2.7774397e+12 | C20: =IF(B20="n/a (g>=WACC)","n/a",'DCF_MSFT'!$B$39+B20/(1+'DCF_MSFT'!$B$21)^5) -> 2.3578169e+12 | D20: =IF(C20="n/a","n/a",C20-'Inputs_MSFT'!$B$17+'Inputs_MSFT'!$B$18) -> 2.3384579e+12 | E20: =IF(D20="n/a","n/a",D20/'Inputs_MSFT'!$B$22) -> 314.92068
A21: 0.025 | B21: =IF($A$21>='DCF_MSFT'!$B$21,"n/a (g>=WACC)",'DCF_MSFT'!$G$31*(1+$A$21)/('DCF_MSFT'!$B$21-$A$21)) -> 2.9771145e+12 | C21: =IF(B21="n/a (g>=WACC)","n/a",'DCF_MSFT'!$B$39+B21/(1+'DCF_MSFT'!$B$21)^5) -> 2.4817968e+12 | D21: =IF(C21="n/a","n/a",C21-'Inputs_MSFT'!$B$17+'Inputs_MSFT'!$B$18) -> 2.4624378e+12 | E21: =IF(D21="n/a","n/a",D21/'Inputs_MSFT'!$B$22) -> 331.61709
A22: 0.03 | B22: =IF($A$22>='DCF_MSFT'!$B$21,"n/a (g>=WACC)",'DCF_MSFT'!$G$31*(1+$A$22)/('DCF_MSFT'!$B$21-$A$22)) -> 3.2053125e+12 | C22: =IF(B22="n/a (g>=WACC)","n/a",'DCF_MSFT'!$B$39+B22/(1+'DCF_MSFT'!$B$21)^5) -> 2.6234871e+12 | D22: =IF(C22="n/a","n/a",C22-'Inputs_MSFT'!$B$17+'Inputs_MSFT'!$B$18) -> 2.6041281e+12 | E22: =IF(D22="n/a","n/a",D22/'Inputs_MSFT'!$B$22) -> 350.69856
A23: 0.04 | B23: =IF($A$23>='DCF_MSFT'!$B$21,"n/a (g>=WACC)",'DCF_MSFT'!$G$31*(1+$A$23)/('DCF_MSFT'!$B$21-$A$23)) -> 3.7757995e+12 | C23: =IF(B23="n/a (g>=WACC)","n/a",'DCF_MSFT'!$B$39+B23/(1+'DCF_MSFT'!$B$21)^5) -> 2.9777078e+12 | D23: =IF(C23="n/a","n/a",C23-'Inputs_MSFT'!$B$17+'Inputs_MSFT'!$B$18) -> 2.9583488e+12 | E23: =IF(D23="n/a","n/a",D23/'Inputs_MSFT'!$B$22) -> 398.40155
A24: 0.05 | B24: =IF($A$24>='DCF_MSFT'!$B$21,"n/a (g>=WACC)",'DCF_MSFT'!$G$31*(1+$A$24)/('DCF_MSFT'!$B$21-$A$24)) -> 4.574462e+12 | C24: =IF(B24="n/a (g>=WACC)","n/a",'DCF_MSFT'!$B$39+B24/(1+'DCF_MSFT'!$B$21)^5) -> 3.4736049e+12 | D24: =IF(C24="n/a","n/a",C24-'Inputs_MSFT'!$B$17+'Inputs_MSFT'!$B$18) -> 3.4542459e+12 | E24: =IF(D24="n/a","n/a",D24/'Inputs_MSFT'!$B$22) -> 465.18413
A25: Direction check: IV increases as terminal growth rises (where valid)? | B25: =IF(E18<E24,"PASS (as expected)","FAIL — investigate (see note)") -> PASS (as expected)
A28: TABLE 3 — Revenue Growth Sensitivity (range [-10%,40%]); base WACC & margin held fixed
A29: Growth g | B29: Rev Y1 | C29: Rev Y2 | D29: Rev Y3 | E29: Rev Y4 | F29: Rev Y5 | G29: FCF Y1 | H29: FCF Y2 | I29: FCF Y3 | J29: FCF Y4 | K29: FCF Y5 | L29: Terminal Value | M29: Enterprise Value | N29: Equity Value | O29: Intrinsic Value/Share
A30: -0.1 | B30: ='DCF_MSFT'!$B$25*(1+$A$30) -> 298655100000 | C30: =B30*(1+$A$30) -> 268789590000 | D30: =C30*(1+$A$30) -> 241910631000 | E30: =D30*(1+$A$30) -> 217719567900 | F30: =E30*(1+$A$30) -> 195947611110 | G30: =B30*'DCF_MSFT'!$B$10*(1-'DCF_MSFT'!$B$14)+B30*'Inputs_MSFT'!$B$31-B30*'Inputs_MSFT'!$B$32-'Inputs_MSFT'!$B$33*(B30-'DCF_MSFT'!$B$25) -> 1.0368662e+11 | H30: =C30*'DCF_MSFT'!$B$10*(1-'DCF_MSFT'!$B$14)+C30*'Inputs_MSFT'!$B$31-C30*'Inputs_MSFT'!$B$32-'Inputs_MSFT'!$B$33*(C30-B30) -> 9.3317962e+10 | I30: =D30*'DCF_MSFT'!$B$10*(1-'DCF_MSFT'!$B$14)+D30*'Inputs_MSFT'!$B$31-D30*'Inputs_MSFT'!$B$32-'Inputs_MSFT'!$B$33*(D30-C30) -> 8.3986166e+10 | J30: =E30*'DCF_MSFT'!$B$10*(1-'DCF_MSFT'!$B$14)+E30*'Inputs_MSFT'!$B$31-E30*'Inputs_MSFT'!$B$32-'Inputs_MSFT'!$B$33*(E30-D30) -> 7.5587549e+10 | K30: =F30*'DCF_MSFT'!$B$10*(1-'DCF_MSFT'!$B$14)+F30*'Inputs_MSFT'!$B$31-F30*'Inputs_MSFT'!$B$32-'Inputs_MSFT'!$B$33*(F30-E30) -> 6.8028794e+10 | L30: =K30*(1+'Inputs_MSFT'!$B$29)/('DCF_MSFT'!$B$21-'Inputs_MSFT'!$B$29) -> 9.2967459e+11 | M30: =SUMPRODUCT(G30:K30,1/(1+'DCF_MSFT'!$B$21)^{1,2,3,4,5})+L30/(1+'DCF_MSFT'!$B$21)^5 -> 9.0559118e+11 | N30: =M30-'Inputs_MSFT'!$B$17+'Inputs_MSFT'!$B$18 -> 8.8623218e+11 | O30: =N30/'Inputs_MSFT'!$B$22 -> 119.3491
A31: -0.05 | B31: ='DCF_MSFT'!$B$25*(1+$A$31) -> 315247050000 | C31: =B31*(1+$A$31) -> 299484697500 | D31: =C31*(1+$A$31) -> 284510462625 | E31: =D31*(1+$A$31) -> 2.7028494e+11 | F31: =E31*(1+$A$31) -> 2.5677069e+11 | G31: =B31*'DCF_MSFT'!$B$10*(1-'DCF_MSFT'!$B$14)+B31*'Inputs_MSFT'!$B$31-B31*'Inputs_MSFT'!$B$32-'Inputs_MSFT'!$B$33*(B31-'DCF_MSFT'!$B$25) -> 1.0926264e+11 | H31: =C31*'DCF_MSFT'!$B$10*(1-'DCF_MSFT'!$B$14)+C31*'Inputs_MSFT'!$B$31-C31*'Inputs_MSFT'!$B$32-'Inputs_MSFT'!$B$33*(C31-B31) -> 1.0379951e+11 | I31: =D31*'DCF_MSFT'!$B$10*(1-'DCF_MSFT'!$B$14)+D31*'Inputs_MSFT'!$B$31-D31*'Inputs_MSFT'!$B$32-'Inputs_MSFT'!$B$33*(D31-C31) -> 9.860953e+10 | J31: =E31*'DCF_MSFT'!$B$10*(1-'DCF_MSFT'!$B$14)+E31*'Inputs_MSFT'!$B$31-E31*'Inputs_MSFT'!$B$32-'Inputs_MSFT'!$B$33*(E31-D31) -> 9.3679054e+10 | K31: =F31*'DCF_MSFT'!$B$10*(1-'DCF_MSFT'!$B$14)+F31*'Inputs_MSFT'!$B$31-F31*'Inputs_MSFT'!$B$32-'Inputs_MSFT'!$B$33*(F31-E31) -> 8.8995101e+10 | L31: =K31*(1+'Inputs_MSFT'!$B$29)/('DCF_MSFT'!$B$21-'Inputs_MSFT'!$B$29) -> 1.216198e+12 | M31: =SUMPRODUCT(G31:K31,1/(1+'DCF_MSFT'!$B$21)^{1,2,3,4,5})+L31/(1+'DCF_MSFT'!$B$21)^5 -> 1.1335891e+12 | N31: =M31-'Inputs_MSFT'!$B$17+'Inputs_MSFT'!$B$18 -> 1.1142301e+12 | O31: =N31/'Inputs_MSFT'!$B$22 -> 150.05363
A32: 0 | B32: ='DCF_MSFT'!$B$25*(1+$A$32) -> 331839000000 | C32: =B32*(1+$A$32) -> 331839000000 | D32: =C32*(1+$A$32) -> 331839000000 | E32: =D32*(1+$A$32) -> 331839000000 | F32: =E32*(1+$A$32) -> 331839000000 | G32: =B32*'DCF_MSFT'!$B$10*(1-'DCF_MSFT'!$B$14)+B32*'Inputs_MSFT'!$B$31-B32*'Inputs_MSFT'!$B$32-'Inputs_MSFT'!$B$33*(B32-'DCF_MSFT'!$B$25) -> 1.1483865e+11 | H32: =C32*'DCF_MSFT'!$B$10*(1-'DCF_MSFT'!$B$14)+C32*'Inputs_MSFT'!$B$31-C32*'Inputs_MSFT'!$B$32-'Inputs_MSFT'!$B$33*(C32-B32) -> 1.1483865e+11 | I32: =D32*'DCF_MSFT'!$B$10*(1-'DCF_MSFT'!$B$14)+D32*'Inputs_MSFT'!$B$31-D32*'Inputs_MSFT'!$B$32-'Inputs_MSFT'!$B$33*(D32-C32) -> 1.1483865e+11 | J32: =E32*'DCF_MSFT'!$B$10*(1-'DCF_MSFT'!$B$14)+E32*'Inputs_MSFT'!$B$31-E32*'Inputs_MSFT'!$B$32-'Inputs_MSFT'!$B$33*(E32-D32) -> 1.1483865e+11 | K32: =F32*'DCF_MSFT'!$B$10*(1-'DCF_MSFT'!$B$14)+F32*'Inputs_MSFT'!$B$31-F32*'Inputs_MSFT'!$B$32-'Inputs_MSFT'!$B$33*(F32-E32) -> 1.1483865e+11 | L32: =K32*(1+'Inputs_MSFT'!$B$29)/('DCF_MSFT'!$B$21-'Inputs_MSFT'!$B$29) -> 1.5693733e+12 | M32: =SUMPRODUCT(G32:K32,1/(1+'DCF_MSFT'!$B$21)^{1,2,3,4,5})+L32/(1+'DCF_MSFT'!$B$21)^5 -> 1.4097628e+12 | N32: =M32-'Inputs_MSFT'!$B$17+'Inputs_MSFT'!$B$18 -> 1.3904038e+12 | O32: =N32/'Inputs_MSFT'!$B$22 -> 187.24602
A33: 0.05 | B33: ='DCF_MSFT'!$B$25*(1+$A$33) -> 348430950000 | C33: =B33*(1+$A$33) -> 365852497500 | D33: =C33*(1+$A$33) -> 384145122375 | E33: =D33*(1+$A$33) -> 4.0335238e+11 | F33: =E33*(1+$A$33) -> 4.2352e+11 | G33: =B33*'DCF_MSFT'!$B$10*(1-'DCF_MSFT'!$B$14)+B33*'Inputs_MSFT'!$B$31-B33*'Inputs_MSFT'!$B$32-'Inputs_MSFT'!$B$33*(B33-'DCF_MSFT'!$B$25) -> 1.2041466e+11 | H33: =C33*'DCF_MSFT'!$B$10*(1-'DCF_MSFT'!$B$14)+C33*'Inputs_MSFT'!$B$31-C33*'Inputs_MSFT'!$B$32-'Inputs_MSFT'!$B$33*(C33-B33) -> 1.264354e+11 | I33: =D33*'DCF_MSFT'!$B$10*(1-'DCF_MSFT'!$B$14)+D33*'Inputs_MSFT'!$B$31-D33*'Inputs_MSFT'!$B$32-'Inputs_MSFT'!$B$33*(D33-C33) -> 1.3275717e+11 | J33: =E33*'DCF_MSFT'!$B$10*(1-'DCF_MSFT'!$B$14)+E33*'Inputs_MSFT'!$B$31-E33*'Inputs_MSFT'!$B$32-'Inputs_MSFT'!$B$33*(E33-D33) -> 1.3939502e+11 | K33: =F33*'DCF_MSFT'!$B$10*(1-'DCF_MSFT'!$B$14)+F33*'Inputs_MSFT'!$B$31-F33*'Inputs_MSFT'!$B$32-'Inputs_MSFT'!$B$33*(F33-E33) -> 1.4636478e+11 | L33: =K33*(1+'Inputs_MSFT'!$B$29)/('DCF_MSFT'!$B$21-'Inputs_MSFT'!$B$29) -> 2.0002062e+12 | M33: =SUMPRODUCT(G33:K33,1/(1+'DCF_MSFT'!$B$21)^{1,2,3,4,5})+L33/(1+'DCF_MSFT'!$B$21)^5 -> 1.7417333e+12 | N33: =M33-'Inputs_MSFT'!$B$17+'Inputs_MSFT'!$B$18 -> 1.7223743e+12 | O33: =N33/'Inputs_MSFT'!$B$22 -> 231.95257
A34: 0.1 | B34: ='DCF_MSFT'!$B$25*(1+$A$34) -> 365022900000 | C34: =B34*(1+$A$34) -> 4.0152519e+11 | D34: =C34*(1+$A$34) -> 4.4167771e+11 | E34: =D34*(1+$A$34) -> 4.8584548e+11 | F34: =E34*(1+$A$34) -> 5.3443003e+11 | G34: =B34*'DCF_MSFT'!$B$10*(1-'DCF_MSFT'!$B$14)+B34*'Inputs_MSFT'!$B$31-B34*'Inputs_MSFT'!$B$32-'Inputs_MSFT'!$B$33*(B34-'DCF_MSFT'!$B$25) -> 1.2599068e+11 | H34: =C34*'DCF_MSFT'!$B$10*(1-'DCF_MSFT'!$B$14)+C34*'Inputs_MSFT'!$B$31-C34*'Inputs_MSFT'!$B$32-'Inputs_MSFT'!$B$33*(C34-B34) -> 1.3858974e+11 | I34: =D34*'DCF_MSFT'!$B$10*(1-'DCF_MSFT'!$B$14)+D34*'Inputs_MSFT'!$B$31-D34*'Inputs_MSFT'!$B$32-'Inputs_MSFT'!$B$33*(D34-C34) -> 1.5244872e+11 | J34: =E34*'DCF_MSFT'!$B$10*(1-'DCF_MSFT'!$B$14)+E34*'Inputs_MSFT'!$B$31-E34*'Inputs_MSFT'!$B$32-'Inputs_MSFT'!$B$33*(E34-D34) -> 1.6769359e+11 | K34: =F34*'DCF_MSFT'!$B$10*(1-'DCF_MSFT'!$B$14)+F34*'Inputs_MSFT'!$B$31-F34*'Inputs_MSFT'!$B$32-'Inputs_MSFT'!$B$33*(F34-E34) -> 1.8446295e+11 | L34: =K34*(1+'Inputs_MSFT'!$B$29)/('DCF_MSFT'!$B$21-'Inputs_MSFT'!$B$29) -> 2.5208519e+12 | M34: =SUMPRODUCT(G34:K34,1/(1+'DCF_MSFT'!$B$21)^{1,2,3,4,5})+L34/(1+'DCF_MSFT'!$B$21)^5 -> 2.137899e+12 | N34: =M34-'Inputs_MSFT'!$B$17+'Inputs_MSFT'!$B$18 -> 2.11854e+12 | O34: =N34/'Inputs_MSFT'!$B$22 -> 285.3043
A35: 0.2 | B35: ='DCF_MSFT'!$B$25*(1+$A$35) -> 398206800000 | C35: =B35*(1+$A$35) -> 477848160000 | D35: =C35*(1+$A$35) -> 573417792000 | E35: =D35*(1+$A$35) -> 688101350400 | F35: =E35*(1+$A$35) -> 825721620480 | G35: =B35*'DCF_MSFT'!$B$10*(1-'DCF_MSFT'!$B$14)+B35*'Inputs_MSFT'!$B$31-B35*'Inputs_MSFT'!$B$32-'Inputs_MSFT'!$B$33*(B35-'DCF_MSFT'!$B$25) -> 1.371427e+11 | H35: =C35*'DCF_MSFT'!$B$10*(1-'DCF_MSFT'!$B$14)+C35*'Inputs_MSFT'!$B$31-C35*'Inputs_MSFT'!$B$32-'Inputs_MSFT'!$B$33*(C35-B35) -> 1.6457124e+11 | I35: =D35*'DCF_MSFT'!$B$10*(1-'DCF_MSFT'!$B$14)+D35*'Inputs_MSFT'!$B$31-D35*'Inputs_MSFT'!$B$32-'Inputs_MSFT'!$B$33*(D35-C35) -> 1.9748549e+11 | J35: =E35*'DCF_MSFT'!$B$10*(1-'DCF_MSFT'!$B$14)+E35*'Inputs_MSFT'!$B$31-E35*'Inputs_MSFT'!$B$32-'Inputs_MSFT'!$B$33*(E35-D35) -> 2.3698259e+11 | K35: =F35*'DCF_MSFT'!$B$10*(1-'DCF_MSFT'!$B$14)+F35*'Inputs_MSFT'!$B$31-F35*'Inputs_MSFT'!$B$32-'Inputs_MSFT'!$B$33*(F35-E35) -> 2.8437911e+11 | L35: =K35*(1+'Inputs_MSFT'!$B$29)/('DCF_MSFT'!$B$21-'Inputs_MSFT'!$B$29) -> 3.886296e+12 | M35: =SUMPRODUCT(G35:K35,1/(1+'DCF_MSFT'!$B$21)^{1,2,3,4,5})+L35/(1+'DCF_MSFT'!$B$21)^5 -> 3.1605263e+12 | N35: =M35-'Inputs_MSFT'!$B$17+'Inputs_MSFT'!$B$18 -> 3.1411673e+12 | O35: =N35/'Inputs_MSFT'!$B$22 -> 423.02176
A36: 0.3 | B36: ='DCF_MSFT'!$B$25*(1+$A$36) -> 431390700000 | C36: =B36*(1+$A$36) -> 560807910000 | D36: =C36*(1+$A$36) -> 729050283000 | E36: =D36*(1+$A$36) -> 947765367900 | F36: =E36*(1+$A$36) -> 1232094978270 | G36: =B36*'DCF_MSFT'!$B$10*(1-'DCF_MSFT'!$B$14)+B36*'Inputs_MSFT'!$B$31-B36*'Inputs_MSFT'!$B$32-'Inputs_MSFT'!$B$33*(B36-'DCF_MSFT'!$B$25) -> 1.4829473e+11 | H36: =C36*'DCF_MSFT'!$B$10*(1-'DCF_MSFT'!$B$14)+C36*'Inputs_MSFT'!$B$31-C36*'Inputs_MSFT'!$B$32-'Inputs_MSFT'!$B$33*(C36-B36) -> 1.9278315e+11 | I36: =D36*'DCF_MSFT'!$B$10*(1-'DCF_MSFT'!$B$14)+D36*'Inputs_MSFT'!$B$31-D36*'Inputs_MSFT'!$B$32-'Inputs_MSFT'!$B$33*(D36-C36) -> 2.5061809e+11 | J36: =E36*'DCF_MSFT'!$B$10*(1-'DCF_MSFT'!$B$14)+E36*'Inputs_MSFT'!$B$31-E36*'Inputs_MSFT'!$B$32-'Inputs_MSFT'!$B$33*(E36-D36) -> 3.2580352e+11 | K36: =F36*'DCF_MSFT'!$B$10*(1-'DCF_MSFT'!$B$14)+F36*'Inputs_MSFT'!$B$31-F36*'Inputs_MSFT'!$B$32-'Inputs_MSFT'!$B$33*(F36-E36) -> 4.2354457e+11 | L36: =K36*(1+'Inputs_MSFT'!$B$29)/('DCF_MSFT'!$B$21-'Inputs_MSFT'!$B$29) -> 5.7881171e+12 | M36: =SUMPRODUCT(G36:K36,1/(1+'DCF_MSFT'!$B$21)^{1,2,3,4,5})+L36/(1+'DCF_MSFT'!$B$21)^5 -> 4.5618316e+12 | N36: =M36-'Inputs_MSFT'!$B$17+'Inputs_MSFT'!$B$18 -> 4.5424726e+12 | O36: =N36/'Inputs_MSFT'!$B$22 -> 611.73587
A37: 0.4 | B37: ='DCF_MSFT'!$B$25*(1+$A$37) -> 464574600000 | C37: =B37*(1+$A$37) -> 650404440000 | D37: =C37*(1+$A$37) -> 910566216000 | E37: =D37*(1+$A$37) -> 1274792702400 | F37: =E37*(1+$A$37) -> 1784709783360 | G37: =B37*'DCF_MSFT'!$B$10*(1-'DCF_MSFT'!$B$14)+B37*'Inputs_MSFT'!$B$31-B37*'Inputs_MSFT'!$B$32-'Inputs_MSFT'!$B$33*(B37-'DCF_MSFT'!$B$25) -> 1.5944675e+11 | H37: =C37*'DCF_MSFT'!$B$10*(1-'DCF_MSFT'!$B$14)+C37*'Inputs_MSFT'!$B$31-C37*'Inputs_MSFT'!$B$32-'Inputs_MSFT'!$B$33*(C37-B37) -> 2.2322546e+11 | I37: =D37*'DCF_MSFT'!$B$10*(1-'DCF_MSFT'!$B$14)+D37*'Inputs_MSFT'!$B$31-D37*'Inputs_MSFT'!$B$32-'Inputs_MSFT'!$B$33*(D37-C37) -> 3.1251564e+11 | J37: =E37*'DCF_MSFT'!$B$10*(1-'DCF_MSFT'!$B$14)+E37*'Inputs_MSFT'!$B$31-E37*'Inputs_MSFT'!$B$32-'Inputs_MSFT'!$B$33*(E37-D37) -> 4.3752189e+11 | K37: =F37*'DCF_MSFT'!$B$10*(1-'DCF_MSFT'!$B$14)+F37*'Inputs_MSFT'!$B$31-F37*'Inputs_MSFT'!$B$32-'Inputs_MSFT'!$B$33*(F37-E37) -> 6.1253065e+11 | L37: =K37*(1+'Inputs_MSFT'!$B$29)/('DCF_MSFT'!$B$21-'Inputs_MSFT'!$B$29) -> 8.3707817e+12 | M37: =SUMPRODUCT(G37:K37,1/(1+'DCF_MSFT'!$B$21)^{1,2,3,4,5})+L37/(1+'DCF_MSFT'!$B$21)^5 -> 6.4408805e+12 | N37: =M37-'Inputs_MSFT'!$B$17+'Inputs_MSFT'!$B$18 -> 6.4215215e+12 | O37: =N37/'Inputs_MSFT'!$B$22 -> 864.78784
A38: Direction check: IV increases as revenue growth rises? | B38: =IF(O30<O37,"PASS (as expected)","FAIL — investigate (see note)") -> PASS (as expected)
A41: TABLE 4 — Operating Margin Sensitivity (range [0%,60%]); base revenue path & WACC held fixed
A42: Margin | B42: FCF Y1 | C42: FCF Y2 | D42: FCF Y3 | E42: FCF Y4 | F42: FCF Y5 | G42: Terminal Value | H42: Enterprise Value | I42: Equity Value | J42: Intrinsic Value/Share
A43: 0 | B43: ='DCF_MSFT'!$C$25*$A$43*(1-'DCF_MSFT'!$B$14)+'DCF_MSFT'!$C$28-'DCF_MSFT'!$C$29-'DCF_MSFT'!$C$30 -> -4.2303597e+09 | C43: ='DCF_MSFT'!$D$25*$A$43*(1-'DCF_MSFT'!$B$14)+'DCF_MSFT'!$D$28-'DCF_MSFT'!$D$29-'DCF_MSFT'!$D$30 -> -4.8116597e+09 | D43: ='DCF_MSFT'!$E$25*$A$43*(1-'DCF_MSFT'!$B$14)+'DCF_MSFT'!$E$28-'DCF_MSFT'!$E$29-'DCF_MSFT'!$E$30 -> -5.4728369e+09 | E43: ='DCF_MSFT'!$F$25*$A$43*(1-'DCF_MSFT'!$B$14)+'DCF_MSFT'!$F$28-'DCF_MSFT'!$F$29-'DCF_MSFT'!$F$30 -> -6.2248675e+09 | F43: ='DCF_MSFT'!$G$25*$A$43*(1-'DCF_MSFT'!$B$14)+'DCF_MSFT'!$G$28-'DCF_MSFT'!$G$29-'DCF_MSFT'!$G$30 -> -7.0802357e+09 | G43: =F43*(1+'Inputs_MSFT'!$B$29)/('DCF_MSFT'!$B$21-'Inputs_MSFT'!$B$29) -> -9.6757783e+10 | H43: =SUMPRODUCT(B43:F43,1/(1+'DCF_MSFT'!$B$21)^{1,2,3,4,5})+G43/(1+'DCF_MSFT'!$B$21)^5 -> -8.0659698e+10 | I43: =H43-'Inputs_MSFT'!$B$17+'Inputs_MSFT'!$B$18 -> -1.000187e+11 | J43: =I43/'Inputs_MSFT'!$B$22 -> -13.469542
A44: 0.1 | B44: ='DCF_MSFT'!$C$25*$A$44*(1-'DCF_MSFT'!$B$14)+'DCF_MSFT'!$C$28-'DCF_MSFT'!$C$29-'DCF_MSFT'!$C$30 -> 2.6192511e+10 | C44: ='DCF_MSFT'!$D$25*$A$44*(1-'DCF_MSFT'!$B$14)+'DCF_MSFT'!$D$28-'DCF_MSFT'!$D$29-'DCF_MSFT'!$D$30 -> 2.9791663e+10 | D44: ='DCF_MSFT'!$E$25*$A$44*(1-'DCF_MSFT'!$B$14)+'DCF_MSFT'!$E$28-'DCF_MSFT'!$E$29-'DCF_MSFT'!$E$30 -> 3.3885379e+10 | E44: ='DCF_MSFT'!$F$25*$A$44*(1-'DCF_MSFT'!$B$14)+'DCF_MSFT'!$F$28-'DCF_MSFT'!$F$29-'DCF_MSFT'!$F$30 -> 3.8541619e+10 | F44: ='DCF_MSFT'!$G$25*$A$44*(1-'DCF_MSFT'!$B$14)+'DCF_MSFT'!$G$28-'DCF_MSFT'!$G$29-'DCF_MSFT'!$G$30 -> 4.3837679e+10 | G44: =F44*(1+'Inputs_MSFT'!$B$29)/('DCF_MSFT'!$B$21-'Inputs_MSFT'!$B$29) -> 5.9908127e+11 | H44: =SUMPRODUCT(B44:F44,1/(1+'DCF_MSFT'!$B$21)^{1,2,3,4,5})+G44/(1+'DCF_MSFT'!$B$21)^5 -> 4.9940907e+11 | I44: =H44-'Inputs_MSFT'!$B$17+'Inputs_MSFT'!$B$18 -> 4.8005007e+11 | J44: =I44/'Inputs_MSFT'!$B$22 -> 64.648459
A45: 0.2 | B45: ='DCF_MSFT'!$C$25*$A$45*(1-'DCF_MSFT'!$B$14)+'DCF_MSFT'!$C$28-'DCF_MSFT'!$C$29-'DCF_MSFT'!$C$30 -> 5.6615382e+10 | C45: ='DCF_MSFT'!$D$25*$A$45*(1-'DCF_MSFT'!$B$14)+'DCF_MSFT'!$D$28-'DCF_MSFT'!$D$29-'DCF_MSFT'!$D$30 -> 6.4394985e+10 | D45: ='DCF_MSFT'!$E$25*$A$45*(1-'DCF_MSFT'!$B$14)+'DCF_MSFT'!$E$28-'DCF_MSFT'!$E$29-'DCF_MSFT'!$E$30 -> 7.3243595e+10 | E45: ='DCF_MSFT'!$F$25*$A$45*(1-'DCF_MSFT'!$B$14)+'DCF_MSFT'!$F$28-'DCF_MSFT'!$F$29-'DCF_MSFT'!$F$30 -> 8.3308105e+10 | F45: ='DCF_MSFT'!$G$25*$A$45*(1-'DCF_MSFT'!$B$14)+'DCF_MSFT'!$G$28-'DCF_MSFT'!$G$29-'DCF_MSFT'!$G$30 -> 9.4755594e+10 | G45: =F45*(1+'Inputs_MSFT'!$B$29)/('DCF_MSFT'!$B$21-'Inputs_MSFT'!$B$29) -> 1.2949203e+12 | H45: =SUMPRODUCT(B45:F45,1/(1+'DCF_MSFT'!$B$21)^{1,2,3,4,5})+G45/(1+'DCF_MSFT'!$B$21)^5 -> 1.0794778e+12 | I45: =H45-'Inputs_MSFT'!$B$17+'Inputs_MSFT'!$B$18 -> 1.0601188e+12 | J45: =I45/'Inputs_MSFT'!$B$22 -> 142.76646
A46: 0.3 | B46: ='DCF_MSFT'!$C$25*$A$46*(1-'DCF_MSFT'!$B$14)+'DCF_MSFT'!$C$28-'DCF_MSFT'!$C$29-'DCF_MSFT'!$C$30 -> 8.7038252e+10 | C46: ='DCF_MSFT'!$D$25*$A$46*(1-'DCF_MSFT'!$B$14)+'DCF_MSFT'!$D$28-'DCF_MSFT'!$D$29-'DCF_MSFT'!$D$30 -> 9.8998307e+10 | D46: ='DCF_MSFT'!$E$25*$A$46*(1-'DCF_MSFT'!$B$14)+'DCF_MSFT'!$E$28-'DCF_MSFT'!$E$29-'DCF_MSFT'!$E$30 -> 1.1260181e+11 | E46: ='DCF_MSFT'!$F$25*$A$46*(1-'DCF_MSFT'!$B$14)+'DCF_MSFT'!$F$28-'DCF_MSFT'!$F$29-'DCF_MSFT'!$F$30 -> 1.2807459e+11 | F46: ='DCF_MSFT'!$G$25*$A$46*(1-'DCF_MSFT'!$B$14)+'DCF_MSFT'!$G$28-'DCF_MSFT'!$G$29-'DCF_MSFT'!$G$30 -> 1.4567351e+11 | G46: =F46*(1+'Inputs_MSFT'!$B$29)/('DCF_MSFT'!$B$21-'Inputs_MSFT'!$B$29) -> 1.9907594e+12 | H46: =SUMPRODUCT(B46:F46,1/(1+'DCF_MSFT'!$B$21)^{1,2,3,4,5})+G46/(1+'DCF_MSFT'!$B$21)^5 -> 1.6595466e+12 | I46: =H46-'Inputs_MSFT'!$B$17+'Inputs_MSFT'!$B$18 -> 1.6401876e+12 | J46: =I46/'Inputs_MSFT'!$B$22 -> 220.88446
A47: 0.4 | B47: ='DCF_MSFT'!$C$25*$A$47*(1-'DCF_MSFT'!$B$14)+'DCF_MSFT'!$C$28-'DCF_MSFT'!$C$29-'DCF_MSFT'!$C$30 -> 1.1746112e+11 | C47: ='DCF_MSFT'!$D$25*$A$47*(1-'DCF_MSFT'!$B$14)+'DCF_MSFT'!$D$28-'DCF_MSFT'!$D$29-'DCF_MSFT'!$D$30 -> 1.3360163e+11 | D47: ='DCF_MSFT'!$E$25*$A$47*(1-'DCF_MSFT'!$B$14)+'DCF_MSFT'!$E$28-'DCF_MSFT'!$E$29-'DCF_MSFT'!$E$30 -> 1.5196003e+11 | E47: ='DCF_MSFT'!$F$25*$A$47*(1-'DCF_MSFT'!$B$14)+'DCF_MSFT'!$F$28-'DCF_MSFT'!$F$29-'DCF_MSFT'!$F$30 -> 1.7284108e+11 | F47: ='DCF_MSFT'!$G$25*$A$47*(1-'DCF_MSFT'!$B$14)+'DCF_MSFT'!$G$28-'DCF_MSFT'!$G$29-'DCF_MSFT'!$G$30 -> 1.9659142e+11 | G47: =F47*(1+'Inputs_MSFT'!$B$29)/('DCF_MSFT'!$B$21-'Inputs_MSFT'!$B$29) -> 2.6865984e+12 | H47: =SUMPRODUCT(B47:F47,1/(1+'DCF_MSFT'!$B$21)^{1,2,3,4,5})+G47/(1+'DCF_MSFT'!$B$21)^5 -> 2.2396154e+12 | I47: =H47-'Inputs_MSFT'!$B$17+'Inputs_MSFT'!$B$18 -> 2.2202564e+12 | J47: =I47/'Inputs_MSFT'!$B$22 -> 299.00246
A48: 0.5 | B48: ='DCF_MSFT'!$C$25*$A$48*(1-'DCF_MSFT'!$B$14)+'DCF_MSFT'!$C$28-'DCF_MSFT'!$C$29-'DCF_MSFT'!$C$30 -> 1.4788399e+11 | C48: ='DCF_MSFT'!$D$25*$A$48*(1-'DCF_MSFT'!$B$14)+'DCF_MSFT'!$D$28-'DCF_MSFT'!$D$29-'DCF_MSFT'!$D$30 -> 1.6820495e+11 | D48: ='DCF_MSFT'!$E$25*$A$48*(1-'DCF_MSFT'!$B$14)+'DCF_MSFT'!$E$28-'DCF_MSFT'!$E$29-'DCF_MSFT'!$E$30 -> 1.9131824e+11 | E48: ='DCF_MSFT'!$F$25*$A$48*(1-'DCF_MSFT'!$B$14)+'DCF_MSFT'!$F$28-'DCF_MSFT'!$F$29-'DCF_MSFT'!$F$30 -> 2.1760756e+11 | F48: ='DCF_MSFT'!$G$25*$A$48*(1-'DCF_MSFT'!$B$14)+'DCF_MSFT'!$G$28-'DCF_MSFT'!$G$29-'DCF_MSFT'!$G$30 -> 2.4750934e+11 | G48: =F48*(1+'Inputs_MSFT'!$B$29)/('DCF_MSFT'!$B$21-'Inputs_MSFT'!$B$29) -> 3.3824375e+12 | H48: =SUMPRODUCT(B48:F48,1/(1+'DCF_MSFT'!$B$21)^{1,2,3,4,5})+G48/(1+'DCF_MSFT'!$B$21)^5 -> 2.8196842e+12 | I48: =H48-'Inputs_MSFT'!$B$17+'Inputs_MSFT'!$B$18 -> 2.8003252e+12 | J48: =I48/'Inputs_MSFT'!$B$22 -> 377.12046
A49: 0.6 | B49: ='DCF_MSFT'!$C$25*$A$49*(1-'DCF_MSFT'!$B$14)+'DCF_MSFT'!$C$28-'DCF_MSFT'!$C$29-'DCF_MSFT'!$C$30 -> 1.7830686e+11 | C49: ='DCF_MSFT'!$D$25*$A$49*(1-'DCF_MSFT'!$B$14)+'DCF_MSFT'!$D$28-'DCF_MSFT'!$D$29-'DCF_MSFT'!$D$30 -> 2.0280827e+11 | D49: ='DCF_MSFT'!$E$25*$A$49*(1-'DCF_MSFT'!$B$14)+'DCF_MSFT'!$E$28-'DCF_MSFT'!$E$29-'DCF_MSFT'!$E$30 -> 2.3067646e+11 | E49: ='DCF_MSFT'!$F$25*$A$49*(1-'DCF_MSFT'!$B$14)+'DCF_MSFT'!$F$28-'DCF_MSFT'!$F$29-'DCF_MSFT'!$F$30 -> 2.6237405e+11 | F49: ='DCF_MSFT'!$G$25*$A$49*(1-'DCF_MSFT'!$B$14)+'DCF_MSFT'!$G$28-'DCF_MSFT'!$G$29-'DCF_MSFT'!$G$30 -> 2.9842725e+11 | G49: =F49*(1+'Inputs_MSFT'!$B$29)/('DCF_MSFT'!$B$21-'Inputs_MSFT'!$B$29) -> 4.0782766e+12 | H49: =SUMPRODUCT(B49:F49,1/(1+'DCF_MSFT'!$B$21)^{1,2,3,4,5})+G49/(1+'DCF_MSFT'!$B$21)^5 -> 3.3997529e+12 | I49: =H49-'Inputs_MSFT'!$B$17+'Inputs_MSFT'!$B$18 -> 3.3803939e+12 | J49: =I49/'Inputs_MSFT'!$B$22 -> 455.23847
A50: Direction check: IV increases as operating margin rises? | B50: =IF(J43<J49,"PASS (as expected)","FAIL — investigate") -> PASS (as expected)
A53: TABLE 5 — Two-Way Sensitivity: WACC (rows) × Terminal Growth (columns) — Intrinsic Value/Share
A54: WACC \ g | B54: 0 | C54: 0.01 | D54: 0.02 | E54: 0.03 | F54: 0.04 | G54: 0.05
A55: 0.05 | B55: =IF(B$54>=$A55,"n/a",(SUMPRODUCT('DCF_MSFT'!$C$31:$G$31,1/(1+$A55)^{1,2,3,4,5})+('DCF_MSFT'!$G$31*(1+B$54)/($A55-B$54))/(1+$A55)^5-'Inputs_MSFT'!$B$17+'Inputs_MSFT'!$B$18)/'Inputs_MSFT'!$B$22) -> 555.70865 | C55: =IF(C$54>=$A55,"n/a",(SUMPRODUCT('DCF_MSFT'!$C$31:$G$31,1/(1+$A55)^{1,2,3,4,5})+('DCF_MSFT'!$G$31*(1+C$54)/($A55-C$54))/(1+$A55)^5-'Inputs_MSFT'!$B$17+'Inputs_MSFT'!$B$18)/'Inputs_MSFT'!$B$22) -> 676.39045 | D55: =IF(D$54>=$A55,"n/a",(SUMPRODUCT('DCF_MSFT'!$C$31:$G$31,1/(1+$A55)^{1,2,3,4,5})+('DCF_MSFT'!$G$31*(1+D$54)/($A55-D$54))/(1+$A55)^5-'Inputs_MSFT'!$B$17+'Inputs_MSFT'!$B$18)/'Inputs_MSFT'!$B$22) -> 877.52679 | E55: =IF(E$54>=$A55,"n/a",(SUMPRODUCT('DCF_MSFT'!$C$31:$G$31,1/(1+$A55)^{1,2,3,4,5})+('DCF_MSFT'!$G$31*(1+E$54)/($A55-E$54))/(1+$A55)^5-'Inputs_MSFT'!$B$17+'Inputs_MSFT'!$B$18)/'Inputs_MSFT'!$B$22) -> 1279.7995 | F55: =IF(F$54>=$A55,"n/a",(SUMPRODUCT('DCF_MSFT'!$C$31:$G$31,1/(1+$A55)^{1,2,3,4,5})+('DCF_MSFT'!$G$31*(1+F$54)/($A55-F$54))/(1+$A55)^5-'Inputs_MSFT'!$B$17+'Inputs_MSFT'!$B$18)/'Inputs_MSFT'!$B$22) -> 2486.6175 | G55: =IF(G$54>=$A55,"n/a",(SUMPRODUCT('DCF_MSFT'!$C$31:$G$31,1/(1+$A55)^{1,2,3,4,5})+('DCF_MSFT'!$G$31*(1+G$54)/($A55-G$54))/(1+$A55)^5-'Inputs_MSFT'!$B$17+'Inputs_MSFT'!$B$18)/'Inputs_MSFT'!$B$22) -> n/a
A56: 0.08 | B56: =IF(B$54>=$A56,"n/a",(SUMPRODUCT('DCF_MSFT'!$C$31:$G$31,1/(1+$A56)^{1,2,3,4,5})+('DCF_MSFT'!$G$31*(1+B$54)/($A56-B$54))/(1+$A56)^5-'Inputs_MSFT'!$B$17+'Inputs_MSFT'!$B$18)/'Inputs_MSFT'!$B$22) -> 337.23093 | C56: =IF(C$54>=$A56,"n/a",(SUMPRODUCT('DCF_MSFT'!$C$31:$G$31,1/(1+$A56)^{1,2,3,4,5})+('DCF_MSFT'!$G$31*(1+C$54)/($A56-C$54))/(1+$A56)^5-'Inputs_MSFT'!$B$17+'Inputs_MSFT'!$B$18)/'Inputs_MSFT'!$B$22) -> 375.73848 | D56: =IF(D$54>=$A56,"n/a",(SUMPRODUCT('DCF_MSFT'!$C$31:$G$31,1/(1+$A56)^{1,2,3,4,5})+('DCF_MSFT'!$G$31*(1+D$54)/($A56-D$54))/(1+$A56)^5-'Inputs_MSFT'!$B$17+'Inputs_MSFT'!$B$18)/'Inputs_MSFT'!$B$22) -> 427.08189 | E56: =IF(E$54>=$A56,"n/a",(SUMPRODUCT('DCF_MSFT'!$C$31:$G$31,1/(1+$A56)^{1,2,3,4,5})+('DCF_MSFT'!$G$31*(1+E$54)/($A56-E$54))/(1+$A56)^5-'Inputs_MSFT'!$B$17+'Inputs_MSFT'!$B$18)/'Inputs_MSFT'!$B$22) -> 498.96266 | F56: =IF(F$54>=$A56,"n/a",(SUMPRODUCT('DCF_MSFT'!$C$31:$G$31,1/(1+$A56)^{1,2,3,4,5})+('DCF_MSFT'!$G$31*(1+F$54)/($A56-F$54))/(1+$A56)^5-'Inputs_MSFT'!$B$17+'Inputs_MSFT'!$B$18)/'Inputs_MSFT'!$B$22) -> 606.78381 | G56: =IF(G$54>=$A56,"n/a",(SUMPRODUCT('DCF_MSFT'!$C$31:$G$31,1/(1+$A56)^{1,2,3,4,5})+('DCF_MSFT'!$G$31*(1+G$54)/($A56-G$54))/(1+$A56)^5-'Inputs_MSFT'!$B$17+'Inputs_MSFT'!$B$18)/'Inputs_MSFT'!$B$22) -> 786.48573
A57: 0.11 | B57: =IF(B$54>=$A57,"n/a",(SUMPRODUCT('DCF_MSFT'!$C$31:$G$31,1/(1+$A57)^{1,2,3,4,5})+('DCF_MSFT'!$G$31*(1+B$54)/($A57-B$54))/(1+$A57)^5-'Inputs_MSFT'!$B$17+'Inputs_MSFT'!$B$18)/'Inputs_MSFT'!$B$22) -> 238.62827 | C57: =IF(C$54>=$A57,"n/a",(SUMPRODUCT('DCF_MSFT'!$C$31:$G$31,1/(1+$A57)^{1,2,3,4,5})+('DCF_MSFT'!$G$31*(1+C$54)/($A57-C$54))/(1+$A57)^5-'Inputs_MSFT'!$B$17+'Inputs_MSFT'!$B$18)/'Inputs_MSFT'!$B$22) -> 256.19716 | D57: =IF(D$54>=$A57,"n/a",(SUMPRODUCT('DCF_MSFT'!$C$31:$G$31,1/(1+$A57)^{1,2,3,4,5})+('DCF_MSFT'!$G$31*(1+D$54)/($A57-D$54))/(1+$A57)^5-'Inputs_MSFT'!$B$17+'Inputs_MSFT'!$B$18)/'Inputs_MSFT'!$B$22) -> 277.67026 | E57: =IF(E$54>=$A57,"n/a",(SUMPRODUCT('DCF_MSFT'!$C$31:$G$31,1/(1+$A57)^{1,2,3,4,5})+('DCF_MSFT'!$G$31*(1+E$54)/($A57-E$54))/(1+$A57)^5-'Inputs_MSFT'!$B$17+'Inputs_MSFT'!$B$18)/'Inputs_MSFT'!$B$22) -> 304.51162 | F57: =IF(F$54>=$A57,"n/a",(SUMPRODUCT('DCF_MSFT'!$C$31:$G$31,1/(1+$A57)^{1,2,3,4,5})+('DCF_MSFT'!$G$31*(1+F$54)/($A57-F$54))/(1+$A57)^5-'Inputs_MSFT'!$B$17+'Inputs_MSFT'!$B$18)/'Inputs_MSFT'!$B$22) -> 339.02194 | G57: =IF(G$54>=$A57,"n/a",(SUMPRODUCT('DCF_MSFT'!$C$31:$G$31,1/(1+$A57)^{1,2,3,4,5})+('DCF_MSFT'!$G$31*(1+G$54)/($A57-G$54))/(1+$A57)^5-'Inputs_MSFT'!$B$17+'Inputs_MSFT'!$B$18)/'Inputs_MSFT'!$B$22) -> 385.03571
A58: 0.14 | B58: =IF(B$54>=$A58,"n/a",(SUMPRODUCT('DCF_MSFT'!$C$31:$G$31,1/(1+$A58)^{1,2,3,4,5})+('DCF_MSFT'!$G$31*(1+B$54)/($A58-B$54))/(1+$A58)^5-'Inputs_MSFT'!$B$17+'Inputs_MSFT'!$B$18)/'Inputs_MSFT'!$B$22) -> 182.76343 | C58: =IF(C$54>=$A58,"n/a",(SUMPRODUCT('DCF_MSFT'!$C$31:$G$31,1/(1+$A58)^{1,2,3,4,5})+('DCF_MSFT'!$G$31*(1+C$54)/($A58-C$54))/(1+$A58)^5-'Inputs_MSFT'!$B$17+'Inputs_MSFT'!$B$18)/'Inputs_MSFT'!$B$22) -> 192.3076 | D58: =IF(D$54>=$A58,"n/a",(SUMPRODUCT('DCF_MSFT'!$C$31:$G$31,1/(1+$A58)^{1,2,3,4,5})+('DCF_MSFT'!$G$31*(1+D$54)/($A58-D$54))/(1+$A58)^5-'Inputs_MSFT'!$B$17+'Inputs_MSFT'!$B$18)/'Inputs_MSFT'!$B$22) -> 203.44247 | E58: =IF(E$54>=$A58,"n/a",(SUMPRODUCT('DCF_MSFT'!$C$31:$G$31,1/(1+$A58)^{1,2,3,4,5})+('DCF_MSFT'!$G$31*(1+E$54)/($A58-E$54))/(1+$A58)^5-'Inputs_MSFT'!$B$17+'Inputs_MSFT'!$B$18)/'Inputs_MSFT'!$B$22) -> 216.60186 | F58: =IF(F$54>=$A58,"n/a",(SUMPRODUCT('DCF_MSFT'!$C$31:$G$31,1/(1+$A58)^{1,2,3,4,5})+('DCF_MSFT'!$G$31*(1+F$54)/($A58-F$54))/(1+$A58)^5-'Inputs_MSFT'!$B$17+'Inputs_MSFT'!$B$18)/'Inputs_MSFT'!$B$22) -> 232.39312 | G58: =IF(G$54>=$A58,"n/a",(SUMPRODUCT('DCF_MSFT'!$C$31:$G$31,1/(1+$A58)^{1,2,3,4,5})+('DCF_MSFT'!$G$31*(1+G$54)/($A58-G$54))/(1+$A58)^5-'Inputs_MSFT'!$B$17+'Inputs_MSFT'!$B$18)/'Inputs_MSFT'!$B$22) -> 251.69355
A59: 0.17 | B59: =IF(B$54>=$A59,"n/a",(SUMPRODUCT('DCF_MSFT'!$C$31:$G$31,1/(1+$A59)^{1,2,3,4,5})+('DCF_MSFT'!$G$31*(1+B$54)/($A59-B$54))/(1+$A59)^5-'Inputs_MSFT'!$B$17+'Inputs_MSFT'!$B$18)/'Inputs_MSFT'!$B$22) -> 146.95879 | C59: =IF(C$54>=$A59,"n/a",(SUMPRODUCT('DCF_MSFT'!$C$31:$G$31,1/(1+$A59)^{1,2,3,4,5})+('DCF_MSFT'!$G$31*(1+C$54)/($A59-C$54))/(1+$A59)^5-'Inputs_MSFT'!$B$17+'Inputs_MSFT'!$B$18)/'Inputs_MSFT'!$B$22) -> 152.71474 | D59: =IF(D$54>=$A59,"n/a",(SUMPRODUCT('DCF_MSFT'!$C$31:$G$31,1/(1+$A59)^{1,2,3,4,5})+('DCF_MSFT'!$G$31*(1+D$54)/($A59-D$54))/(1+$A59)^5-'Inputs_MSFT'!$B$17+'Inputs_MSFT'!$B$18)/'Inputs_MSFT'!$B$22) -> 159.23814 | E59: =IF(E$54>=$A59,"n/a",(SUMPRODUCT('DCF_MSFT'!$C$31:$G$31,1/(1+$A59)^{1,2,3,4,5})+('DCF_MSFT'!$G$31*(1+E$54)/($A59-E$54))/(1+$A59)^5-'Inputs_MSFT'!$B$17+'Inputs_MSFT'!$B$18)/'Inputs_MSFT'!$B$22) -> 166.69346 | F59: =IF(F$54>=$A59,"n/a",(SUMPRODUCT('DCF_MSFT'!$C$31:$G$31,1/(1+$A59)^{1,2,3,4,5})+('DCF_MSFT'!$G$31*(1+F$54)/($A59-F$54))/(1+$A59)^5-'Inputs_MSFT'!$B$17+'Inputs_MSFT'!$B$18)/'Inputs_MSFT'!$B$22) -> 175.29575 | G59: =IF(G$54>=$A59,"n/a",(SUMPRODUCT('DCF_MSFT'!$C$31:$G$31,1/(1+$A59)^{1,2,3,4,5})+('DCF_MSFT'!$G$31*(1+G$54)/($A59-G$54))/(1+$A59)^5-'Inputs_MSFT'!$B$17+'Inputs_MSFT'!$B$18)/'Inputs_MSFT'!$B$22) -> 185.33176
A60: 0.2 | B60: =IF(B$54>=$A60,"n/a",(SUMPRODUCT('DCF_MSFT'!$C$31:$G$31,1/(1+$A60)^{1,2,3,4,5})+('DCF_MSFT'!$G$31*(1+B$54)/($A60-B$54))/(1+$A60)^5-'Inputs_MSFT'!$B$17+'Inputs_MSFT'!$B$18)/'Inputs_MSFT'!$B$22) -> 122.15012 | C60: =IF(C$54>=$A60,"n/a",(SUMPRODUCT('DCF_MSFT'!$C$31:$G$31,1/(1+$A60)^{1,2,3,4,5})+('DCF_MSFT'!$G$31*(1+C$54)/($A60-C$54))/(1+$A60)^5-'Inputs_MSFT'!$B$17+'Inputs_MSFT'!$B$18)/'Inputs_MSFT'!$B$22) -> 125.87336 | D60: =IF(D$54>=$A60,"n/a",(SUMPRODUCT('DCF_MSFT'!$C$31:$G$31,1/(1+$A60)^{1,2,3,4,5})+('DCF_MSFT'!$G$31*(1+D$54)/($A60-D$54))/(1+$A60)^5-'Inputs_MSFT'!$B$17+'Inputs_MSFT'!$B$18)/'Inputs_MSFT'!$B$22) -> 130.01028 | E60: =IF(E$54>=$A60,"n/a",(SUMPRODUCT('DCF_MSFT'!$C$31:$G$31,1/(1+$A60)^{1,2,3,4,5})+('DCF_MSFT'!$G$31*(1+E$54)/($A60-E$54))/(1+$A60)^5-'Inputs_MSFT'!$B$17+'Inputs_MSFT'!$B$18)/'Inputs_MSFT'!$B$22) -> 134.63391 | F60: =IF(F$54>=$A60,"n/a",(SUMPRODUCT('DCF_MSFT'!$C$31:$G$31,1/(1+$A60)^{1,2,3,4,5})+('DCF_MSFT'!$G$31*(1+F$54)/($A60-F$54))/(1+$A60)^5-'Inputs_MSFT'!$B$17+'Inputs_MSFT'!$B$18)/'Inputs_MSFT'!$B$22) -> 139.83549 | G60: =IF(G$54>=$A60,"n/a",(SUMPRODUCT('DCF_MSFT'!$C$31:$G$31,1/(1+$A60)^{1,2,3,4,5})+('DCF_MSFT'!$G$31*(1+G$54)/($A60-G$54))/(1+$A60)^5-'Inputs_MSFT'!$B$17+'Inputs_MSFT'!$B$18)/'Inputs_MSFT'!$B$22) -> 145.73061

Sheet Inputs_CAT
A1: Inputs — CAT (CATERPILLAR INC) | Frozen 2026-08-17T17:23:45.327869+00:00
A2: Profile: Capital-intensive, moderate leverage | CIK 0000018230 | All USD values are actual dollars (not thousands/millions) unless noted.
A4: SECTION 1 — Historical Annual Data (SEC EDGAR, frozen)
A5: Fiscal Year End | B5: Revenue (USD) | C5: EBIT / Operating Income (USD) | D5: Provenance
A6: 44561 | B6: 50971000000 | C6: 6878000000 | D6: XBRL tag: Revenues
A7: 44926 | B7: 59427000000 | C7: 7904000000 | D7: XBRL tag: Revenues
A8: 45291 | B8: 67060000000 | C8: 12966000000 | D8: XBRL tag: Revenues
A9: 45657 | B9: 64809000000 | C9: 13072000000 | D9: XBRL tag: Revenues
A10: 46022 | B10: 67589000000 | C10: 11151000000 | D10: XBRL tag: Revenues
A12: SECTION 2 — Latest-Year Facts (SEC EDGAR, frozen)
A13: Latest Complete Fiscal Year End | B13: 46022
A14: Pretax Income (USD) | B14: 11541000000
A15: Tax Provision (USD) | B15: 2768000000
A16: Interest Expense (USD) | B16: 1842000000 | D16: Method: proxy_cash_paid_interest; tag: InterestPaidNet
A17: Total Debt (USD) | B17: 36210000000 | D17: Total Debt = LongTermDebtNoncurrent ($30,696,000,000) + ShortTermBorrowings ($5,514,000,000) = $36,210,000,000 | Full per-component provenance (XBRL tag, accession, filed date, source URL): see Sources sheet.
A18: Cash & Equivalents (USD) | B18: 9980000000
A20: SECTION 3 — Market Data (Yahoo Finance via yfinance, frozen)
A21: Current Price (USD/share) | B21: 886
A22: Shares Outstanding | B22: 459674889
A23: Beta (levered equity) | B23: 1.605
A24: Sector (GICS) | B24: Industrials
A26: SECTION 4 — Assumptions (shared across companies unless noted; assumptions-register.md)
A27: Risk-free rate (A-001) | B27: 0.04
A28: Market risk premium (A-009) | B28: 0.055
A29: Terminal growth rate, base case (A-003) | B29: 0.025
A30: Projection years | B30: 5
A31: D&A % of revenue (A-004) | B31: 0.03
A32: CapEx % of revenue (A-004) | B32: 0.04
A33: ΔNWC % of revenue change (A-004) | B33: 0.01
A34: WACC clamp — minimum (A-006) | B34: 0.05
A35: WACC clamp — maximum (A-006) | B35: 0.2
A36: Terminal growth clamp — minimum | B36: 0
A37: Terminal growth clamp — maximum | B37: 0.05
A38: Historical revenue growth cap (A-002) | B38: 0.25

Sheet DCF_CAT
A1: DCF Valuation — CAT (CATERPILLAR INC) [V2 — Track A Phase 2C]
A2: Every formula below is entered independently from docs/model-specifications/dcf.md and wacc-capm.md prose/equations — never copied from src/dcf_model/dcf.py. V2: years_elapsed now uses actual fiscal-period-end date subtraction, per the Track A Phase 2C specification clarification (A-028/L-019) — see row below.
A4: SECTION 1 — Historical Revenue CAGR & Operating Margin [dcf.md §Historical revenue-growth and operating-margin derivation]
A5: Years elapsed = (latest fiscal date − earliest fiscal date) / 365.25 [V2; A-028] | B5: =('Inputs_CAT'!$A$10-'Inputs_CAT'!$A$6)/365.25 -> 4 | D5: Spec: dcf.md — years_elapsed is ACTUAL elapsed calendar days between the earliest- and latest-dated valid observations / 365.25, never (periods−1) (A-028; Track A Phase 2C, resolving the ambiguity Phase 2B found).
A6: Diagnostic — naive (N periods − 1) years [V1's convention; NOT used below] | B6: 4 | C6: REGULAR | D6: Fiscal calendar is evenly spaced for this company — actual years_elapsed equals the naive (N periods − 1) count to within floating-point noise, so V1 and V2 agree here by coincidence, not because (periods − 1) is a generally correct convention.
A8: Raw Revenue CAGR = (Rev_latest/Rev_earliest)^(1/years) − 1 | B8: =('Inputs_CAT'!$B$10/'Inputs_CAT'!$B$6)^(1/B5)-1 -> 0.073095112
A9: Capped Revenue CAGR (cap A-002; NOT floored below) | B9: =MIN(B8,'Inputs_CAT'!$B$38) -> 0.073095112 | D9: Spec: dcf.md — capped at MAX_REVENUE_GROWTH_RATE=25%, unbounded below (A-002)
A10: Average Historical Operating Margin = simple average of EBIT_t/Revenue_t | B10: =('Inputs_CAT'!$C$6/'Inputs_CAT'!$B$6+'Inputs_CAT'!$C$7/'Inputs_CAT'!$B$7+'Inputs_CAT'!$C$8/'Inputs_CAT'!$B$8+'Inputs_CAT'!$C$9/'Inputs_CAT'!$B$9+'Inputs_CAT'!$C$10/'Inputs_CAT'!$B$10)/5 -> 0.16559502
A12: SECTION 2 — WACC via CAPM [wacc-capm.md §Formula]
A13: Market Capitalization = Price × Shares Outstanding | B13: ='Inputs_CAT'!$B$21*'Inputs_CAT'!$B$22 -> 407271951654
A14: Effective Tax Rate = Tax Provision / Pretax Income (latest FY) | B14: ='Inputs_CAT'!$B$15/'Inputs_CAT'!$B$14 -> 0.23984057 | D14: Method: derived. Spec: wacc-capm.md — derived as tax_provision/pretax_income, valid range [0,1); DEFAULT_TAX_RATE=21% only on missing data.
A15: Cost of Debt = |Interest Expense| / Total Debt (latest FY) | B15: =ABS('Inputs_CAT'!$B$16)/'Inputs_CAT'!$B$17 -> 0.050869925
A16: Cost of Equity (CAPM) = Rf + Beta × MRP | B16: ='Inputs_CAT'!$B$27+'Inputs_CAT'!$B$23*'Inputs_CAT'!$B$28 -> 0.128275
A17: After-Tax Cost of Debt = Cost of Debt × (1 − Tax Rate) | B17: =B15*(1-B14) -> 0.038669254
A18: Weight of Equity = MktCap / (MktCap + Total Debt) | B18: =B13/(B13+'Inputs_CAT'!$B$17) -> 0.91835068
A19: Weight of Debt = Total Debt / (MktCap + Total Debt) | B19: ='Inputs_CAT'!$B$17/(B13+'Inputs_CAT'!$B$17) -> 0.08164932
A20: Raw WACC = We×Re + Wd×Rd(after-tax) | B20: =B18*B16+B19*B17 -> 0.12095875
A21: Final WACC — clamped to [5%,20%] (A-006), via MEDIAN(raw,min,max) | B21: =MEDIAN(B20,'Inputs_CAT'!$B$34,'Inputs_CAT'!$B$35) -> 0.12095875 | D21: MEDIAN(x,min,max) is a standard single-formula clamp: returns min if x<min, max if x>max, else x.
A23: SECTION 3 — 5-Year Free Cash Flow Projection [dcf.md §Free Cash Flow projection]
B24: Year 0 (base, actual) | C24: Year 1 | D24: Year 2 | E24: Year 3 | F24: Year 4 | G24: Year 5
A25: Revenue = Revenue_(t-1) × (1 + growth) | B25: ='Inputs_CAT'!$B$10 -> 67589000000 | C25: =B25*(1+$B$9) -> 7.2529426e+10 | D25: =C25*(1+$B$9) -> 7.7830972e+10 | E25: =D25*(1+$B$9) -> 8.3520036e+10 | F25: =E25*(1+$B$9) -> 8.9624942e+10 | G25: =F25*(1+$B$9) -> 9.6176087e+10
A26: EBIT = Revenue × Operating Margin | C26: =C25*$B$10 -> 1.2010511e+10 | D26: =D25*$B$10 -> 1.2888421e+10 | E26: =E25*$B$10 -> 1.3830502e+10 | F26: =F25*$B$10 -> 1.4841444e+10 | G26: =G25*$B$10 -> 1.5926281e+10
A27: NOPAT = EBIT × (1 − Tax Rate) | C27: =C26*(1-$B$14) -> 9.1299035e+09 | D27: =D26*(1-$B$14) -> 9.7972548e+09 | E27: =E26*(1-$B$14) -> 1.0513386e+10 | F27: =F26*(1-$B$14) -> 1.1281863e+10 | G27: =G26*(1-$B$14) -> 1.2106512e+10
A28: D&A = Revenue × D&A% (A-004) | C28: =C25*'Inputs_CAT'!$B$31 -> 2.1758828e+09 | D28: =D25*'Inputs_CAT'!$B$31 -> 2.3349292e+09 | E28: =E25*'Inputs_CAT'!$B$31 -> 2.5056011e+09 | F28: =F25*'Inputs_CAT'!$B$31 -> 2.6887483e+09 | G28: =G25*'Inputs_CAT'!$B$31 -> 2.8852826e+09
A29: CapEx = Revenue × CapEx% (A-004) | C29: =C25*'Inputs_CAT'!$B$32 -> 2.901177e+09 | D29: =D25*'Inputs_CAT'!$B$32 -> 3.1132389e+09 | E29: =E25*'Inputs_CAT'!$B$32 -> 3.3408014e+09 | F29: =F25*'Inputs_CAT'!$B$32 -> 3.5849977e+09 | G29: =G25*'Inputs_CAT'!$B$32 -> 3.8470435e+09
A30: ΔNWC = NWC% × (Revenue_t − Revenue_(t-1)) (A-004) | C30: ='Inputs_CAT'!$B$33*(C25-B25) -> 49404255 | D30: ='Inputs_CAT'!$B$33*(D25-C25) -> 53015465 | E30: ='Inputs_CAT'!$B$33*(E25-D25) -> 56890636 | F30: ='Inputs_CAT'!$B$33*(F25-E25) -> 61049064 | G30: ='Inputs_CAT'!$B$33*(G25-F25) -> 65511452
A31: Unlevered FCF = NOPAT + D&A − CapEx − ΔNWC | C31: =C27+C28-C29-C30 -> 8.355205e+09 | D31: =D27+D28-D29-D30 -> 8.9659296e+09 | E31: =E27+E28-E29-E30 -> 9.6212953e+09 | F31: =F27+F28-F29-F30 -> 1.0324565e+10 | G31: =G27+G28-G29-G30 -> 1.107924e+10
A33: SECTION 4 — Terminal Value (Gordon Growth) [dcf.md §Terminal value]
A34: Terminal Value = FCF_Y5 × (1+g) / (WACC − g) | B34: =G31*(1+'Inputs_CAT'!$B$29)/(B21-'Inputs_CAT'!$B$29) -> 1.1834482e+11
A35: Check: Final WACC > Terminal Growth Rate? | B35: =IF(B21>'Inputs_CAT'!$B$29,"PASS","FAIL") -> PASS
A37: SECTION 5 — Discounting & Enterprise-to-Equity Bridge [dcf.md §Discounting and the Enterprise-to-Equity bridge]
A38: PV(FCF_t) = FCF_t / (1+WACC)^t | C38: =C31/(1+$B$21)^1 -> 7.453624e+09 | D38: =D31/(1+$B$21)^2 -> 7.1353628e+09 | E38: =E31/(1+$B$21)^3 -> 6.8306911e+09 | F38: =F31/(1+$B$21)^4 -> 6.5390285e+09 | G38: =G31/(1+$B$21)^5 -> 6.2598196e+09
A39: Sum of PV(FCF Years 1-5) | B39: =SUM(C38:G38) -> 3.4218526e+10
A40: PV(Terminal Value) = TV / (1+WACC)^5 | B40: =B34/(1+B21)^5 -> 6.6865345e+10
A41: Enterprise Value = Sum PV(FCF) + PV(Terminal Value) | B41: =B39+B40 -> 1.0108387e+11
A42: Equity Value = Enterprise Value − Total Debt + Cash | B42: =B41-'Inputs_CAT'!$B$17+'Inputs_CAT'!$B$18 -> 7.4853871e+10
A43: Intrinsic Value per Share = Equity Value / Shares Outstanding | B43: =B42/'Inputs_CAT'!$B$22 -> 162.8409
A44: Current Price / Intrinsic Value (descriptive ratio, NOT a recommendation) | B44: ='Inputs_CAT'!$B$21/B43 -> 5.4408936
A46: SECTION 6 — Validation Checks (local to this company)
A47: WACC within documented clamp [5%,20%]? | B47: =IF(AND(B21>='Inputs_CAT'!$B$34,B21<='Inputs_CAT'!$B$35),"PASS","FAIL") -> PASS
A48: Enterprise Value is a finite number? | B48: =IF(ISNUMBER(B41),"PASS","FAIL") -> PASS
A49: Intrinsic Value per Share is a finite number? | B49: =IF(ISNUMBER(B43),"PASS","FAIL") -> PASS
A50: Intrinsic Value per Share is positive? | B50: =IF(B43>0,"PASS","FAIL") -> PASS
A51: Effective tax rate within valid [0,1) range? | B51: =IF(AND(B14>=0,B14<1),"PASS","FAIL") -> PASS
A52: Final WACC exceeds terminal growth rate? | B52: =IF(B21>'Inputs_CAT'!$B$29,"PASS","FAIL") -> PASS

Sheet Sensitivity_CAT
A1: Sensitivity Analysis — CAT
A2: One variable at a time, other inputs held at base case. Per docs/independent-validation-plan.md §Sensitivity tables.
A4: TABLE 1 — WACC Sensitivity (range [5%,20%], base FCF path held fixed) [dcf.md Terminal Value + discounting]
A5: WACC | B5: Terminal Value | C5: Enterprise Value | D5: Equity Value | E5: Intrinsic Value/Share
A6: 0.05 | B6: =IF($A$6<='Inputs_CAT'!$B$29,"n/a (WACC<=g)",'DCF_CAT'!$G$31*(1+'Inputs_CAT'!$B$29)/($A$6-'Inputs_CAT'!$B$29)) -> 4.5424885e+11 | C6: =IF(B6="n/a (WACC<=g)","n/a",SUMPRODUCT('DCF_CAT'!$C$31:$G$31,1/(1+$A$6)^{1,2,3,4,5})+B6/(1+$A$6)^5) -> 3.9749171e+11 | D6: =IF(C6="n/a","n/a",C6-'Inputs_CAT'!$B$17+'Inputs_CAT'!$B$18) -> 3.7126171e+11 | E6: =IF(D6="n/a","n/a",D6/'Inputs_CAT'!$B$22) -> 807.66151
A7: 0.075 | B7: =IF($A$7<='Inputs_CAT'!$B$29,"n/a (WACC<=g)",'DCF_CAT'!$G$31*(1+'Inputs_CAT'!$B$29)/($A$7-'Inputs_CAT'!$B$29)) -> 2.2712442e+11 | C7: =IF(B7="n/a (WACC<=g)","n/a",SUMPRODUCT('DCF_CAT'!$C$31:$G$31,1/(1+$A$7)^{1,2,3,4,5})+B7/(1+$A$7)^5) -> 1.9692942e+11 | D7: =IF(C7="n/a","n/a",C7-'Inputs_CAT'!$B$17+'Inputs_CAT'!$B$18) -> 1.7069942e+11 | E7: =IF(D7="n/a","n/a",D7/'Inputs_CAT'!$B$22) -> 371.34814
A8: 0.1 | B8: =IF($A$8<='Inputs_CAT'!$B$29,"n/a (WACC<=g)",'DCF_CAT'!$G$31*(1+'Inputs_CAT'!$B$29)/($A$8-'Inputs_CAT'!$B$29)) -> 1.5141628e+11 | C8: =IF(B8="n/a (WACC<=g)","n/a",SUMPRODUCT('DCF_CAT'!$C$31:$G$31,1/(1+$A$8)^{1,2,3,4,5})+B8/(1+$A$8)^5) -> 1.3018287e+11 | D8: =IF(C8="n/a","n/a",C8-'Inputs_CAT'!$B$17+'Inputs_CAT'!$B$18) -> 1.0395287e+11 | E8: =IF(D8="n/a","n/a",D8/'Inputs_CAT'!$B$22) -> 226.14434
A9: 0.125 | B9: =IF($A$9<='Inputs_CAT'!$B$29,"n/a (WACC<=g)",'DCF_CAT'!$G$31*(1+'Inputs_CAT'!$B$29)/($A$9-'Inputs_CAT'!$B$29)) -> 1.1356221e+11 | C9: =IF(B9="n/a (WACC<=g)","n/a",SUMPRODUCT('DCF_CAT'!$C$31:$G$31,1/(1+$A$9)^{1,2,3,4,5})+B9/(1+$A$9)^5) -> 9.6881109e+10 | D9: =IF(C9="n/a","n/a",C9-'Inputs_CAT'!$B$17+'Inputs_CAT'!$B$18) -> 7.0651109e+10 | E9: =IF(D9="n/a","n/a",D9/'Inputs_CAT'!$B$22) -> 153.698
A10: 0.15 | B10: =IF($A$10<='Inputs_CAT'!$B$29,"n/a (WACC<=g)",'DCF_CAT'!$G$31*(1+'Inputs_CAT'!$B$29)/($A$10-'Inputs_CAT'!$B$29)) -> 9.0849769e+10 | C10: =IF(B10="n/a (WACC<=g)","n/a",SUMPRODUCT('DCF_CAT'!$C$31:$G$31,1/(1+$A$10)^{1,2,3,4,5})+B10/(1+$A$10)^5) -> 7.695092e+10 | D10: =IF(C10="n/a","n/a",C10-'Inputs_CAT'!$B$17+'Inputs_CAT'!$B$18) -> 5.072092e+10 | E10: =IF(D10="n/a","n/a",D10/'Inputs_CAT'!$B$22) -> 110.34085
A11: 0.175 | B11: =IF($A$11<='Inputs_CAT'!$B$29,"n/a (WACC<=g)",'DCF_CAT'!$G$31*(1+'Inputs_CAT'!$B$29)/($A$11-'Inputs_CAT'!$B$29)) -> 7.5708141e+10 | C11: =IF(B11="n/a (WACC<=g)","n/a",SUMPRODUCT('DCF_CAT'!$C$31:$G$31,1/(1+$A$11)^{1,2,3,4,5})+B11/(1+$A$11)^5) -> 6.3701935e+10 | D11: =IF(C11="n/a","n/a",C11-'Inputs_CAT'!$B$17+'Inputs_CAT'!$B$18) -> 3.7471935e+10 | E11: =IF(D11="n/a","n/a",D11/'Inputs_CAT'!$B$22) -> 81.518342
A12: 0.2 | B12: =IF($A$12<='Inputs_CAT'!$B$29,"n/a (WACC<=g)",'DCF_CAT'!$G$31*(1+'Inputs_CAT'!$B$29)/($A$12-'Inputs_CAT'!$B$29)) -> 6.4892692e+10 | C12: =IF(B12="n/a (WACC<=g)","n/a",SUMPRODUCT('DCF_CAT'!$C$31:$G$31,1/(1+$A$12)^{1,2,3,4,5})+B12/(1+$A$12)^5) -> 5.4267359e+10 | D12: =IF(C12="n/a","n/a",C12-'Inputs_CAT'!$B$17+'Inputs_CAT'!$B$18) -> 2.8037359e+10 | E12: =IF(D12="n/a","n/a",D12/'Inputs_CAT'!$B$22) -> 60.993889
A13: Direction check: IV decreases as WACC rises? | B13: =IF(E6>E12,"PASS (as expected)","FAIL — investigate (see note)") -> PASS (as expected)
A16: TABLE 2 — Terminal Growth Rate Sensitivity (range [0%,5%]); invalid where g>=WACC
A17: Terminal Growth g | B17: Terminal Value | C17: Enterprise Value | D17: Equity Value | E17: Intrinsic Value/Share
A18: 0 | B18: =IF($A$18>='DCF_CAT'!$B$21,"n/a (g>=WACC)",'DCF_CAT'!$G$31*(1+$A$18)/('DCF_CAT'!$B$21-$A$18)) -> 9.1595193e+10 | C18: =IF(B18="n/a (g>=WACC)","n/a",'DCF_CAT'!$B$39+B18/(1+'DCF_CAT'!$B$21)^5) -> 8.5970214e+10 | D18: =IF(C18="n/a","n/a",C18-'Inputs_CAT'!$B$17+'Inputs_CAT'!$B$18) -> 5.9740214e+10 | E18: =IF(D18="n/a","n/a",D18/'Inputs_CAT'!$B$22) -> 129.96188
A19: 0.01 | B19: =IF($A$19>='DCF_CAT'!$B$21,"n/a (g>=WACC)",'DCF_CAT'!$G$31*(1+$A$19)/('DCF_CAT'!$B$21-$A$19)) -> 1.0084858e+11 | C19: =IF(B19="n/a (g>=WACC)","n/a",'DCF_CAT'!$B$39+B19/(1+'DCF_CAT'!$B$21)^5) -> 9.1198419e+10 | D19: =IF(C19="n/a","n/a",C19-'Inputs_CAT'!$B$17+'Inputs_CAT'!$B$18) -> 6.4968419e+10 | E19: =IF(D19="n/a","n/a",D19/'Inputs_CAT'!$B$22) -> 141.33558
A20: 0.02 | B20: =IF($A$20>='DCF_CAT'!$B$21,"n/a (g>=WACC)",'DCF_CAT'!$G$31*(1+$A$20)/('DCF_CAT'!$B$21-$A$20)) -> 1.1193507e+11 | C20: =IF(B20="n/a (g>=WACC)","n/a",'DCF_CAT'!$B$39+B20/(1+'DCF_CAT'!$B$21)^5) -> 9.7462335e+10 | D20: =IF(C20="n/a","n/a",C20-'Inputs_CAT'!$B$17+'Inputs_CAT'!$B$18) -> 7.1232335e+10 | E20: =IF(D20="n/a","n/a",D20/'Inputs_CAT'!$B$22) -> 154.96242
A21: 0.025 | B21: =IF($A$21>='DCF_CAT'!$B$21,"n/a (g>=WACC)",'DCF_CAT'!$G$31*(1+$A$21)/('DCF_CAT'!$B$21-$A$21)) -> 1.1834482e+11 | C21: =IF(B21="n/a (g>=WACC)","n/a",'DCF_CAT'!$B$39+B21/(1+'DCF_CAT'!$B$21)^5) -> 1.0108387e+11 | D21: =IF(C21="n/a","n/a",C21-'Inputs_CAT'!$B$17+'Inputs_CAT'!$B$18) -> 7.4853871e+10 | E21: =IF(D21="n/a","n/a",D21/'Inputs_CAT'!$B$22) -> 162.8409
A22: 0.03 | B22: =IF($A$22>='DCF_CAT'!$B$21,"n/a (g>=WACC)",'DCF_CAT'!$G$31*(1+$A$22)/('DCF_CAT'!$B$21-$A$22)) -> 1.2545926e+11 | C22: =IF(B22="n/a (g>=WACC)","n/a",'DCF_CAT'!$B$39+B22/(1+'DCF_CAT'!$B$21)^5) -> 1.0510356e+11 | D22: =IF(C22="n/a","n/a",C22-'Inputs_CAT'!$B$17+'Inputs_CAT'!$B$18) -> 7.887356e+10 | E22: =IF(D22="n/a","n/a",D22/'Inputs_CAT'!$B$22) -> 171.58553
A23: 0.04 | B23: =IF($A$23>='DCF_CAT'!$B$21,"n/a (g>=WACC)",'DCF_CAT'!$G$31*(1+$A$23)/('DCF_CAT'!$B$21-$A$23)) -> 1.4232445e+11 | C23: =IF(B23="n/a (g>=WACC)","n/a",'DCF_CAT'!$B$39+B23/(1+'DCF_CAT'!$B$21)^5) -> 1.1463247e+11 | D23: =IF(C23="n/a","n/a",C23-'Inputs_CAT'!$B$17+'Inputs_CAT'!$B$18) -> 8.8402468e+10 | E23: =IF(D23="n/a","n/a",D23/'Inputs_CAT'!$B$22) -> 192.3152
A24: 0.05 | B24: =IF($A$24>='DCF_CAT'!$B$21,"n/a (g>=WACC)",'DCF_CAT'!$G$31*(1+$A$24)/('DCF_CAT'!$B$21-$A$24)) -> 1.6394316e+11 | C24: =IF(B24="n/a (g>=WACC)","n/a",'DCF_CAT'!$B$39+B24/(1+'DCF_CAT'!$B$21)^5) -> 1.2684714e+11 | D24: =IF(C24="n/a","n/a",C24-'Inputs_CAT'!$B$17+'Inputs_CAT'!$B$18) -> 1.0061714e+11 | E24: =IF(D24="n/a","n/a",D24/'Inputs_CAT'!$B$22) -> 218.88761
A25: Direction check: IV increases as terminal growth rises (where valid)? | B25: =IF(E18<E24,"PASS (as expected)","FAIL — investigate (see note)") -> PASS (as expected)
A28: TABLE 3 — Revenue Growth Sensitivity (range [-10%,40%]); base WACC & margin held fixed
A29: Growth g | B29: Rev Y1 | C29: Rev Y2 | D29: Rev Y3 | E29: Rev Y4 | F29: Rev Y5 | G29: FCF Y1 | H29: FCF Y2 | I29: FCF Y3 | J29: FCF Y4 | K29: FCF Y5 | L29: Terminal Value | M29: Enterprise Value | N29: Equity Value | O29: Intrinsic Value/Share
A30: -0.1 | B30: ='DCF_CAT'!$B$25*(1+$A$30) -> 60830100000 | C30: =B30*(1+$A$30) -> 54747090000 | D30: =C30*(1+$A$30) -> 49272381000 | E30: =D30*(1+$A$30) -> 44345142900 | F30: =E30*(1+$A$30) -> 39910628610 | G30: =B30*'DCF_CAT'!$B$10*(1-'DCF_CAT'!$B$14)+B30*'Inputs_CAT'!$B$31-B30*'Inputs_CAT'!$B$32-'Inputs_CAT'!$B$33*(B30-'DCF_CAT'!$B$25) -> 7.1164966e+09 | H30: =C30*'DCF_CAT'!$B$10*(1-'DCF_CAT'!$B$14)+C30*'Inputs_CAT'!$B$31-C30*'Inputs_CAT'!$B$32-'Inputs_CAT'!$B$33*(C30-B30) -> 6.404847e+09 | I30: =D30*'DCF_CAT'!$B$10*(1-'DCF_CAT'!$B$14)+D30*'Inputs_CAT'!$B$31-D30*'Inputs_CAT'!$B$32-'Inputs_CAT'!$B$33*(D30-C30) -> 5.7643623e+09 | J30: =E30*'DCF_CAT'!$B$10*(1-'DCF_CAT'!$B$14)+E30*'Inputs_CAT'!$B$31-E30*'Inputs_CAT'!$B$32-'Inputs_CAT'!$B$33*(E30-D30) -> 5.187926e+09 | K30: =F30*'DCF_CAT'!$B$10*(1-'DCF_CAT'!$B$14)+F30*'Inputs_CAT'!$B$31-F30*'Inputs_CAT'!$B$32-'Inputs_CAT'!$B$33*(F30-E30) -> 4.6691334e+09 | L30: =K30*(1+'Inputs_CAT'!$B$29)/('DCF_CAT'!$B$21-'Inputs_CAT'!$B$29) -> 4.9874156e+10 | M30: =SUMPRODUCT(G30:K30,1/(1+'DCF_CAT'!$B$21)^{1,2,3,4,5})+L30/(1+'DCF_CAT'!$B$21)^5 -> 4.964115e+10 | N30: =M30-'Inputs_CAT'!$B$17+'Inputs_CAT'!$B$18 -> 2.341115e+10 | O30: =N30/'Inputs_CAT'!$B$22 -> 50.9298
A31: -0.05 | B31: ='DCF_CAT'!$B$25*(1+$A$31) -> 64209550000 | C31: =B31*(1+$A$31) -> 60999072500 | D31: =C31*(1+$A$31) -> 57949118875 | E31: =D31*(1+$A$31) -> 5.5051663e+10 | F31: =E31*(1+$A$31) -> 5.229908e+10 | G31: =B31*'DCF_CAT'!$B$10*(1-'DCF_CAT'!$B$14)+B31*'Inputs_CAT'!$B$31-B31*'Inputs_CAT'!$B$32-'Inputs_CAT'!$B$33*(B31-'DCF_CAT'!$B$25) -> 7.4743081e+09 | H31: =C31*'DCF_CAT'!$B$10*(1-'DCF_CAT'!$B$14)+C31*'Inputs_CAT'!$B$31-C31*'Inputs_CAT'!$B$32-'Inputs_CAT'!$B$33*(C31-B31) -> 7.1005927e+09 | I31: =D31*'DCF_CAT'!$B$10*(1-'DCF_CAT'!$B$14)+D31*'Inputs_CAT'!$B$31-D31*'Inputs_CAT'!$B$32-'Inputs_CAT'!$B$33*(D31-C31) -> 6.7455631e+09 | J31: =E31*'DCF_CAT'!$B$10*(1-'DCF_CAT'!$B$14)+E31*'Inputs_CAT'!$B$31-E31*'Inputs_CAT'!$B$32-'Inputs_CAT'!$B$33*(E31-D31) -> 6.4082849e+09 | K31: =F31*'DCF_CAT'!$B$10*(1-'DCF_CAT'!$B$14)+F31*'Inputs_CAT'!$B$31-F31*'Inputs_CAT'!$B$32-'Inputs_CAT'!$B$33*(F31-E31) -> 6.0878707e+09 | L31: =K31*(1+'Inputs_CAT'!$B$29)/('DCF_CAT'!$B$21-'Inputs_CAT'!$B$29) -> 6.5028643e+10 | M31: =SUMPRODUCT(G31:K31,1/(1+'DCF_CAT'!$B$21)^{1,2,3,4,5})+L31/(1+'DCF_CAT'!$B$21)^5 -> 6.1347511e+10 | N31: =M31-'Inputs_CAT'!$B$17+'Inputs_CAT'!$B$18 -> 3.5117511e+10 | O31: =N31/'Inputs_CAT'!$B$22 -> 76.39641
A32: 0 | B32: ='DCF_CAT'!$B$25*(1+$A$32) -> 67589000000 | C32: =B32*(1+$A$32) -> 67589000000 | D32: =C32*(1+$A$32) -> 67589000000 | E32: =D32*(1+$A$32) -> 67589000000 | F32: =E32*(1+$A$32) -> 67589000000 | G32: =B32*'DCF_CAT'!$B$10*(1-'DCF_CAT'!$B$14)+B32*'Inputs_CAT'!$B$31-B32*'Inputs_CAT'!$B$32-'Inputs_CAT'!$B$33*(B32-'DCF_CAT'!$B$25) -> 7.8321196e+09 | H32: =C32*'DCF_CAT'!$B$10*(1-'DCF_CAT'!$B$14)+C32*'Inputs_CAT'!$B$31-C32*'Inputs_CAT'!$B$32-'Inputs_CAT'!$B$33*(C32-B32) -> 7.8321196e+09 | I32: =D32*'DCF_CAT'!$B$10*(1-'DCF_CAT'!$B$14)+D32*'Inputs_CAT'!$B$31-D32*'Inputs_CAT'!$B$32-'Inputs_CAT'!$B$33*(D32-C32) -> 7.8321196e+09 | J32: =E32*'DCF_CAT'!$B$10*(1-'DCF_CAT'!$B$14)+E32*'Inputs_CAT'!$B$31-E32*'Inputs_CAT'!$B$32-'Inputs_CAT'!$B$33*(E32-D32) -> 7.8321196e+09 | K32: =F32*'DCF_CAT'!$B$10*(1-'DCF_CAT'!$B$14)+F32*'Inputs_CAT'!$B$31-F32*'Inputs_CAT'!$B$32-'Inputs_CAT'!$B$33*(F32-E32) -> 7.8321196e+09 | L32: =K32*(1+'Inputs_CAT'!$B$29)/('DCF_CAT'!$B$21-'Inputs_CAT'!$B$29) -> 8.366014e+10 | M32: =SUMPRODUCT(G32:K32,1/(1+'DCF_CAT'!$B$21)^{1,2,3,4,5})+L32/(1+'DCF_CAT'!$B$21)^5 -> 7.5434458e+10 | N32: =M32-'Inputs_CAT'!$B$17+'Inputs_CAT'!$B$18 -> 4.9204458e+10 | O32: =N32/'Inputs_CAT'!$B$22 -> 107.04187
A33: 0.05 | B33: ='DCF_CAT'!$B$25*(1+$A$33) -> 70968450000 | C33: =B33*(1+$A$33) -> 74516872500 | D33: =C33*(1+$A$33) -> 78242716125 | E33: =D33*(1+$A$33) -> 8.2154852e+10 | F33: =E33*(1+$A$33) -> 8.6262595e+10 | G33: =B33*'DCF_CAT'!$B$10*(1-'DCF_CAT'!$B$14)+B33*'Inputs_CAT'!$B$31-B33*'Inputs_CAT'!$B$32-'Inputs_CAT'!$B$33*(B33-'DCF_CAT'!$B$25) -> 8.1899311e+09 | H33: =C33*'DCF_CAT'!$B$10*(1-'DCF_CAT'!$B$14)+C33*'Inputs_CAT'!$B$31-C33*'Inputs_CAT'!$B$32-'Inputs_CAT'!$B$33*(C33-B33) -> 8.5994276e+09 | I33: =D33*'DCF_CAT'!$B$10*(1-'DCF_CAT'!$B$14)+D33*'Inputs_CAT'!$B$31-D33*'Inputs_CAT'!$B$32-'Inputs_CAT'!$B$33*(D33-C33) -> 9.029399e+09 | J33: =E33*'DCF_CAT'!$B$10*(1-'DCF_CAT'!$B$14)+E33*'Inputs_CAT'!$B$31-E33*'Inputs_CAT'!$B$32-'Inputs_CAT'!$B$33*(E33-D33) -> 9.480869e+09 | K33: =F33*'DCF_CAT'!$B$10*(1-'DCF_CAT'!$B$14)+F33*'Inputs_CAT'!$B$31-F33*'Inputs_CAT'!$B$32-'Inputs_CAT'!$B$33*(F33-E33) -> 9.9549124e+09 | L33: =K33*(1+'Inputs_CAT'!$B$29)/('DCF_CAT'!$B$21-'Inputs_CAT'!$B$29) -> 1.0633512e+11 | M33: =SUMPRODUCT(G33:K33,1/(1+'DCF_CAT'!$B$21)^{1,2,3,4,5})+L33/(1+'DCF_CAT'!$B$21)^5 -> 9.2269402e+10 | N33: =M33-'Inputs_CAT'!$B$17+'Inputs_CAT'!$B$18 -> 6.6039402e+10 | O33: =N33/'Inputs_CAT'!$B$22 -> 143.66545
A34: 0.1 | B34: ='DCF_CAT'!$B$25*(1+$A$34) -> 74347900000 | C34: =B34*(1+$A$34) -> 81782690000 | D34: =C34*(1+$A$34) -> 89960959000 | E34: =D34*(1+$A$34) -> 9.8957055e+10 | F34: =E34*(1+$A$34) -> 1.0885276e+11 | G34: =B34*'DCF_CAT'!$B$10*(1-'DCF_CAT'!$B$14)+B34*'Inputs_CAT'!$B$31-B34*'Inputs_CAT'!$B$32-'Inputs_CAT'!$B$33*(B34-'DCF_CAT'!$B$25) -> 8.5477426e+09 | H34: =C34*'DCF_CAT'!$B$10*(1-'DCF_CAT'!$B$14)+C34*'Inputs_CAT'!$B$31-C34*'Inputs_CAT'!$B$32-'Inputs_CAT'!$B$33*(C34-B34) -> 9.4025168e+09 | I34: =D34*'DCF_CAT'!$B$10*(1-'DCF_CAT'!$B$14)+D34*'Inputs_CAT'!$B$31-D34*'Inputs_CAT'!$B$32-'Inputs_CAT'!$B$33*(D34-C34) -> 1.0342768e+10 | J34: =E34*'DCF_CAT'!$B$10*(1-'DCF_CAT'!$B$14)+E34*'Inputs_CAT'!$B$31-E34*'Inputs_CAT'!$B$32-'Inputs_CAT'!$B$33*(E34-D34) -> 1.1377045e+10 | K34: =F34*'DCF_CAT'!$B$10*(1-'DCF_CAT'!$B$14)+F34*'Inputs_CAT'!$B$31-F34*'Inputs_CAT'!$B$32-'Inputs_CAT'!$B$33*(F34-E34) -> 1.251475e+10 | L34: =K34*(1+'Inputs_CAT'!$B$29)/('DCF_CAT'!$B$21-'Inputs_CAT'!$B$29) -> 1.3367846e+11 | M34: =SUMPRODUCT(G34:K34,1/(1+'DCF_CAT'!$B$21)^{1,2,3,4,5})+L34/(1+'DCF_CAT'!$B$21)^5 -> 1.1225653e+11 | N34: =M34-'Inputs_CAT'!$B$17+'Inputs_CAT'!$B$18 -> 8.6026528e+10 | O34: =N34/'Inputs_CAT'!$B$22 -> 187.14646
A35: 0.2 | B35: ='DCF_CAT'!$B$25*(1+$A$35) -> 81106800000 | C35: =B35*(1+$A$35) -> 97328160000 | D35: =C35*(1+$A$35) -> 116793792000 | E35: =D35*(1+$A$35) -> 140152550400 | F35: =E35*(1+$A$35) -> 168183060480 | G35: =B35*'DCF_CAT'!$B$10*(1-'DCF_CAT'!$B$14)+B35*'Inputs_CAT'!$B$31-B35*'Inputs_CAT'!$B$32-'Inputs_CAT'!$B$33*(B35-'DCF_CAT'!$B$25) -> 9.2633655e+09 | H35: =C35*'DCF_CAT'!$B$10*(1-'DCF_CAT'!$B$14)+C35*'Inputs_CAT'!$B$31-C35*'Inputs_CAT'!$B$32-'Inputs_CAT'!$B$33*(C35-B35) -> 1.1116039e+10 | I35: =D35*'DCF_CAT'!$B$10*(1-'DCF_CAT'!$B$14)+D35*'Inputs_CAT'!$B$31-D35*'Inputs_CAT'!$B$32-'Inputs_CAT'!$B$33*(D35-C35) -> 1.3339246e+10 | J35: =E35*'DCF_CAT'!$B$10*(1-'DCF_CAT'!$B$14)+E35*'Inputs_CAT'!$B$31-E35*'Inputs_CAT'!$B$32-'Inputs_CAT'!$B$33*(E35-D35) -> 1.6007096e+10 | K35: =F35*'DCF_CAT'!$B$10*(1-'DCF_CAT'!$B$14)+F35*'Inputs_CAT'!$B$31-F35*'Inputs_CAT'!$B$32-'Inputs_CAT'!$B$33*(F35-E35) -> 1.9208515e+10 | L35: =K35*(1+'Inputs_CAT'!$B$29)/('DCF_CAT'!$B$21-'Inputs_CAT'!$B$29) -> 2.0517907e+11 | M35: =SUMPRODUCT(G35:K35,1/(1+'DCF_CAT'!$B$21)^{1,2,3,4,5})+L35/(1+'DCF_CAT'!$B$21)^5 -> 1.6349856e+11 | N35: =M35-'Inputs_CAT'!$B$17+'Inputs_CAT'!$B$18 -> 1.3726856e+11 | O35: =N35/'Inputs_CAT'!$B$22 -> 298.62097
A36: 0.3 | B36: ='DCF_CAT'!$B$25*(1+$A$36) -> 87865700000 | C36: =B36*(1+$A$36) -> 114225410000 | D36: =C36*(1+$A$36) -> 148493033000 | E36: =D36*(1+$A$36) -> 193040942900 | F36: =E36*(1+$A$36) -> 250953225770 | G36: =B36*'DCF_CAT'!$B$10*(1-'DCF_CAT'!$B$14)+B36*'Inputs_CAT'!$B$31-B36*'Inputs_CAT'!$B$32-'Inputs_CAT'!$B$33*(B36-'DCF_CAT'!$B$25) -> 9.9789885e+09 | H36: =C36*'DCF_CAT'!$B$10*(1-'DCF_CAT'!$B$14)+C36*'Inputs_CAT'!$B$31-C36*'Inputs_CAT'!$B$32-'Inputs_CAT'!$B$33*(C36-B36) -> 1.2972685e+10 | I36: =D36*'DCF_CAT'!$B$10*(1-'DCF_CAT'!$B$14)+D36*'Inputs_CAT'!$B$31-D36*'Inputs_CAT'!$B$32-'Inputs_CAT'!$B$33*(D36-C36) -> 1.6864491e+10 | J36: =E36*'DCF_CAT'!$B$10*(1-'DCF_CAT'!$B$14)+E36*'Inputs_CAT'!$B$31-E36*'Inputs_CAT'!$B$32-'Inputs_CAT'!$B$33*(E36-D36) -> 2.1923838e+10 | K36: =F36*'DCF_CAT'!$B$10*(1-'DCF_CAT'!$B$14)+F36*'Inputs_CAT'!$B$31-F36*'Inputs_CAT'!$B$32-'Inputs_CAT'!$B$33*(F36-E36) -> 2.8500989e+10 | L36: =K36*(1+'Inputs_CAT'!$B$29)/('DCF_CAT'!$B$21-'Inputs_CAT'!$B$29) -> 3.0443824e+11 | M36: =SUMPRODUCT(G36:K36,1/(1+'DCF_CAT'!$B$21)^{1,2,3,4,5})+L36/(1+'DCF_CAT'!$B$21)^5 -> 2.3319681e+11 | N36: =M36-'Inputs_CAT'!$B$17+'Inputs_CAT'!$B$18 -> 2.0696681e+11 | O36: =N36/'Inputs_CAT'!$B$22 -> 450.24607
A37: 0.4 | B37: ='DCF_CAT'!$B$25*(1+$A$37) -> 94624600000 | C37: =B37*(1+$A$37) -> 1.3247444e+11 | D37: =C37*(1+$A$37) -> 1.8546422e+11 | E37: =D37*(1+$A$37) -> 2.596499e+11 | F37: =E37*(1+$A$37) -> 3.6350986e+11 | G37: =B37*'DCF_CAT'!$B$10*(1-'DCF_CAT'!$B$14)+B37*'Inputs_CAT'!$B$31-B37*'Inputs_CAT'!$B$32-'Inputs_CAT'!$B$33*(B37-'DCF_CAT'!$B$25) -> 1.0694611e+10 | H37: =C37*'DCF_CAT'!$B$10*(1-'DCF_CAT'!$B$14)+C37*'Inputs_CAT'!$B$31-C37*'Inputs_CAT'!$B$32-'Inputs_CAT'!$B$33*(C37-B37) -> 1.4972456e+10 | I37: =D37*'DCF_CAT'!$B$10*(1-'DCF_CAT'!$B$14)+D37*'Inputs_CAT'!$B$31-D37*'Inputs_CAT'!$B$32-'Inputs_CAT'!$B$33*(D37-C37) -> 2.0961438e+10 | J37: =E37*'DCF_CAT'!$B$10*(1-'DCF_CAT'!$B$14)+E37*'Inputs_CAT'!$B$31-E37*'Inputs_CAT'!$B$32-'Inputs_CAT'!$B$33*(E37-D37) -> 2.9346014e+10 | K37: =F37*'DCF_CAT'!$B$10*(1-'DCF_CAT'!$B$14)+F37*'Inputs_CAT'!$B$31-F37*'Inputs_CAT'!$B$32-'Inputs_CAT'!$B$33*(F37-E37) -> 4.1084419e+10 | L37: =K37*(1+'Inputs_CAT'!$B$29)/('DCF_CAT'!$B$21-'Inputs_CAT'!$B$29) -> 4.3885033e+11 | M37: =SUMPRODUCT(G37:K37,1/(1+'DCF_CAT'!$B$21)^{1,2,3,4,5})+L37/(1+'DCF_CAT'!$B$21)^5 -> 3.2608927e+11 | N37: =M37-'Inputs_CAT'!$B$17+'Inputs_CAT'!$B$18 -> 2.9985927e+11 | O37: =N37/'Inputs_CAT'!$B$22 -> 652.32903
A38: Direction check: IV increases as revenue growth rises? | B38: =IF(O30<O37,"PASS (as expected)","FAIL — investigate (see note)") -> PASS (as expected)
A41: TABLE 4 — Operating Margin Sensitivity (range [0%,60%]); base revenue path & WACC held fixed
A42: Margin | B42: FCF Y1 | C42: FCF Y2 | D42: FCF Y3 | E42: FCF Y4 | F42: FCF Y5 | G42: Terminal Value | H42: Enterprise Value | I42: Equity Value | J42: Intrinsic Value/Share
A43: 0 | B43: ='DCF_CAT'!$C$25*$A$43*(1-'DCF_CAT'!$B$14)+'DCF_CAT'!$C$28-'DCF_CAT'!$C$29-'DCF_CAT'!$C$30 -> -7.7469851e+08 | C43: ='DCF_CAT'!$D$25*$A$43*(1-'DCF_CAT'!$B$14)+'DCF_CAT'!$D$28-'DCF_CAT'!$D$29-'DCF_CAT'!$D$30 -> -8.3132519e+08 | D43: ='DCF_CAT'!$E$25*$A$43*(1-'DCF_CAT'!$B$14)+'DCF_CAT'!$E$28-'DCF_CAT'!$E$29-'DCF_CAT'!$E$30 -> -8.9209099e+08 | E43: ='DCF_CAT'!$F$25*$A$43*(1-'DCF_CAT'!$B$14)+'DCF_CAT'!$F$28-'DCF_CAT'!$F$29-'DCF_CAT'!$F$30 -> -9.5729848e+08 | F43: ='DCF_CAT'!$G$25*$A$43*(1-'DCF_CAT'!$B$14)+'DCF_CAT'!$G$28-'DCF_CAT'!$G$29-'DCF_CAT'!$G$30 -> -1.0272723e+09 | G43: =F43*(1+'Inputs_CAT'!$B$29)/('DCF_CAT'!$B$21-'Inputs_CAT'!$B$29) -> -1.0972987e+10 | H43: =SUMPRODUCT(B43:F43,1/(1+'DCF_CAT'!$B$21)^{1,2,3,4,5})+G43/(1+'DCF_CAT'!$B$21)^5 -> -9.3725438e+09 | I43: =H43-'Inputs_CAT'!$B$17+'Inputs_CAT'!$B$18 -> -3.5602544e+10 | J43: =I43/'Inputs_CAT'!$B$22 -> -77.451574
A44: 0.1 | B44: ='DCF_CAT'!$C$25*$A$44*(1-'DCF_CAT'!$B$14)+'DCF_CAT'!$C$28-'DCF_CAT'!$C$29-'DCF_CAT'!$C$30 -> 4.7386942e+09 | C44: ='DCF_CAT'!$D$25*$A$44*(1-'DCF_CAT'!$B$14)+'DCF_CAT'!$D$28-'DCF_CAT'!$D$29-'DCF_CAT'!$D$30 -> 5.0850696e+09 | D44: ='DCF_CAT'!$E$25*$A$44*(1-'DCF_CAT'!$B$14)+'DCF_CAT'!$E$28-'DCF_CAT'!$E$29-'DCF_CAT'!$E$30 -> 5.4567633e+09 | E44: ='DCF_CAT'!$F$25*$A$44*(1-'DCF_CAT'!$B$14)+'DCF_CAT'!$F$28-'DCF_CAT'!$F$29-'DCF_CAT'!$F$30 -> 5.855626e+09 | F44: ='DCF_CAT'!$G$25*$A$44*(1-'DCF_CAT'!$B$14)+'DCF_CAT'!$G$28-'DCF_CAT'!$G$29-'DCF_CAT'!$G$30 -> 6.2836437e+09 | G44: =F44*(1+'Inputs_CAT'!$B$29)/('DCF_CAT'!$B$21-'Inputs_CAT'!$B$29) -> 6.7119826e+10 | H44: =SUMPRODUCT(B44:F44,1/(1+'DCF_CAT'!$B$21)^{1,2,3,4,5})+G44/(1+'DCF_CAT'!$B$21)^5 -> 5.7330198e+10 | I44: =H44-'Inputs_CAT'!$B$17+'Inputs_CAT'!$B$18 -> 3.1100198e+10 | J44: =I44/'Inputs_CAT'!$B$22 -> 67.656943
A45: 0.2 | B45: ='DCF_CAT'!$C$25*$A$45*(1-'DCF_CAT'!$B$14)+'DCF_CAT'!$C$28-'DCF_CAT'!$C$29-'DCF_CAT'!$C$30 -> 1.0252087e+10 | C45: ='DCF_CAT'!$D$25*$A$45*(1-'DCF_CAT'!$B$14)+'DCF_CAT'!$D$28-'DCF_CAT'!$D$29-'DCF_CAT'!$D$30 -> 1.1001464e+10 | D45: ='DCF_CAT'!$E$25*$A$45*(1-'DCF_CAT'!$B$14)+'DCF_CAT'!$E$28-'DCF_CAT'!$E$29-'DCF_CAT'!$E$30 -> 1.1805618e+10 | E45: ='DCF_CAT'!$F$25*$A$45*(1-'DCF_CAT'!$B$14)+'DCF_CAT'!$F$28-'DCF_CAT'!$F$29-'DCF_CAT'!$F$30 -> 1.2668551e+10 | F45: ='DCF_CAT'!$G$25*$A$45*(1-'DCF_CAT'!$B$14)+'DCF_CAT'!$G$28-'DCF_CAT'!$G$29-'DCF_CAT'!$G$30 -> 1.359456e+10 | G45: =F45*(1+'Inputs_CAT'!$B$29)/('DCF_CAT'!$B$21-'Inputs_CAT'!$B$29) -> 1.4521264e+11 | H45: =SUMPRODUCT(B45:F45,1/(1+'DCF_CAT'!$B$21)^{1,2,3,4,5})+G45/(1+'DCF_CAT'!$B$21)^5 -> 1.2403294e+11 | I45: =H45-'Inputs_CAT'!$B$17+'Inputs_CAT'!$B$18 -> 9.7802939e+10 | J45: =I45/'Inputs_CAT'!$B$22 -> 212.76546
A46: 0.3 | B46: ='DCF_CAT'!$C$25*$A$46*(1-'DCF_CAT'!$B$14)+'DCF_CAT'!$C$28-'DCF_CAT'!$C$29-'DCF_CAT'!$C$30 -> 1.576548e+10 | C46: ='DCF_CAT'!$D$25*$A$46*(1-'DCF_CAT'!$B$14)+'DCF_CAT'!$D$28-'DCF_CAT'!$D$29-'DCF_CAT'!$D$30 -> 1.6917859e+10 | D46: ='DCF_CAT'!$E$25*$A$46*(1-'DCF_CAT'!$B$14)+'DCF_CAT'!$E$28-'DCF_CAT'!$E$29-'DCF_CAT'!$E$30 -> 1.8154472e+10 | E46: ='DCF_CAT'!$F$25*$A$46*(1-'DCF_CAT'!$B$14)+'DCF_CAT'!$F$28-'DCF_CAT'!$F$29-'DCF_CAT'!$F$30 -> 1.9481475e+10 | F46: ='DCF_CAT'!$G$25*$A$46*(1-'DCF_CAT'!$B$14)+'DCF_CAT'!$G$28-'DCF_CAT'!$G$29-'DCF_CAT'!$G$30 -> 2.0905476e+10 | G46: =F46*(1+'Inputs_CAT'!$B$29)/('DCF_CAT'!$B$21-'Inputs_CAT'!$B$29) -> 2.2330545e+11 | H46: =SUMPRODUCT(B46:F46,1/(1+'DCF_CAT'!$B$21)^{1,2,3,4,5})+G46/(1+'DCF_CAT'!$B$21)^5 -> 1.9073568e+11 | I46: =H46-'Inputs_CAT'!$B$17+'Inputs_CAT'!$B$18 -> 1.6450568e+11 | J46: =I46/'Inputs_CAT'!$B$22 -> 357.87398
A47: 0.4 | B47: ='DCF_CAT'!$C$25*$A$47*(1-'DCF_CAT'!$B$14)+'DCF_CAT'!$C$28-'DCF_CAT'!$C$29-'DCF_CAT'!$C$30 -> 2.1278872e+10 | C47: ='DCF_CAT'!$D$25*$A$47*(1-'DCF_CAT'!$B$14)+'DCF_CAT'!$D$28-'DCF_CAT'!$D$29-'DCF_CAT'!$D$30 -> 2.2834254e+10 | D47: ='DCF_CAT'!$E$25*$A$47*(1-'DCF_CAT'!$B$14)+'DCF_CAT'!$E$28-'DCF_CAT'!$E$29-'DCF_CAT'!$E$30 -> 2.4503326e+10 | E47: ='DCF_CAT'!$F$25*$A$47*(1-'DCF_CAT'!$B$14)+'DCF_CAT'!$F$28-'DCF_CAT'!$F$29-'DCF_CAT'!$F$30 -> 2.62944e+10 | F47: ='DCF_CAT'!$G$25*$A$47*(1-'DCF_CAT'!$B$14)+'DCF_CAT'!$G$28-'DCF_CAT'!$G$29-'DCF_CAT'!$G$30 -> 2.8216392e+10 | G47: =F47*(1+'Inputs_CAT'!$B$29)/('DCF_CAT'!$B$21-'Inputs_CAT'!$B$29) -> 3.0139827e+11 | H47: =SUMPRODUCT(B47:F47,1/(1+'DCF_CAT'!$B$21)^{1,2,3,4,5})+G47/(1+'DCF_CAT'!$B$21)^5 -> 2.5743842e+11 | I47: =H47-'Inputs_CAT'!$B$17+'Inputs_CAT'!$B$18 -> 2.3120842e+11 | J47: =I47/'Inputs_CAT'!$B$22 -> 502.98249
A48: 0.5 | B48: ='DCF_CAT'!$C$25*$A$48*(1-'DCF_CAT'!$B$14)+'DCF_CAT'!$C$28-'DCF_CAT'!$C$29-'DCF_CAT'!$C$30 -> 2.6792265e+10 | C48: ='DCF_CAT'!$D$25*$A$48*(1-'DCF_CAT'!$B$14)+'DCF_CAT'!$D$28-'DCF_CAT'!$D$29-'DCF_CAT'!$D$30 -> 2.8750649e+10 | D48: ='DCF_CAT'!$E$25*$A$48*(1-'DCF_CAT'!$B$14)+'DCF_CAT'!$E$28-'DCF_CAT'!$E$29-'DCF_CAT'!$E$30 -> 3.085218e+10 | E48: ='DCF_CAT'!$F$25*$A$48*(1-'DCF_CAT'!$B$14)+'DCF_CAT'!$F$28-'DCF_CAT'!$F$29-'DCF_CAT'!$F$30 -> 3.3107324e+10 | F48: ='DCF_CAT'!$G$25*$A$48*(1-'DCF_CAT'!$B$14)+'DCF_CAT'!$G$28-'DCF_CAT'!$G$29-'DCF_CAT'!$G$30 -> 3.5527308e+10 | G48: =F48*(1+'Inputs_CAT'!$B$29)/('DCF_CAT'!$B$21-'Inputs_CAT'!$B$29) -> 3.7949108e+11 | H48: =SUMPRODUCT(B48:F48,1/(1+'DCF_CAT'!$B$21)^{1,2,3,4,5})+G48/(1+'DCF_CAT'!$B$21)^5 -> 3.2414116e+11 | I48: =H48-'Inputs_CAT'!$B$17+'Inputs_CAT'!$B$18 -> 2.9791116e+11 | J48: =I48/'Inputs_CAT'!$B$22 -> 648.09101
A49: 0.6 | B49: ='DCF_CAT'!$C$25*$A$49*(1-'DCF_CAT'!$B$14)+'DCF_CAT'!$C$28-'DCF_CAT'!$C$29-'DCF_CAT'!$C$30 -> 3.2305658e+10 | C49: ='DCF_CAT'!$D$25*$A$49*(1-'DCF_CAT'!$B$14)+'DCF_CAT'!$D$28-'DCF_CAT'!$D$29-'DCF_CAT'!$D$30 -> 3.4667043e+10 | D49: ='DCF_CAT'!$E$25*$A$49*(1-'DCF_CAT'!$B$14)+'DCF_CAT'!$E$28-'DCF_CAT'!$E$29-'DCF_CAT'!$E$30 -> 3.7201035e+10 | E49: ='DCF_CAT'!$F$25*$A$49*(1-'DCF_CAT'!$B$14)+'DCF_CAT'!$F$28-'DCF_CAT'!$F$29-'DCF_CAT'!$F$30 -> 3.9920249e+10 | F49: ='DCF_CAT'!$G$25*$A$49*(1-'DCF_CAT'!$B$14)+'DCF_CAT'!$G$28-'DCF_CAT'!$G$29-'DCF_CAT'!$G$30 -> 4.2838224e+10 | G49: =F49*(1+'Inputs_CAT'!$B$29)/('DCF_CAT'!$B$21-'Inputs_CAT'!$B$29) -> 4.5758389e+11 | H49: =SUMPRODUCT(B49:F49,1/(1+'DCF_CAT'!$B$21)^{1,2,3,4,5})+G49/(1+'DCF_CAT'!$B$21)^5 -> 3.908439e+11 | I49: =H49-'Inputs_CAT'!$B$17+'Inputs_CAT'!$B$18 -> 3.646139e+11 | J49: =I49/'Inputs_CAT'!$B$22 -> 793.19953
A50: Direction check: IV increases as operating margin rises? | B50: =IF(J43<J49,"PASS (as expected)","FAIL — investigate") -> PASS (as expected)
A53: TABLE 5 — Two-Way Sensitivity: WACC (rows) × Terminal Growth (columns) — Intrinsic Value/Share
A54: WACC \ g | B54: 0 | C54: 0.01 | D54: 0.02 | E54: 0.03 | F54: 0.04 | G54: 0.05
A55: 0.05 | B55: =IF(B$54>=$A55,"n/a",(SUMPRODUCT('DCF_CAT'!$C$31:$G$31,1/(1+$A55)^{1,2,3,4,5})+('DCF_CAT'!$G$31*(1+B$54)/($A55-B$54))/(1+$A55)^5-'Inputs_CAT'!$B$17+'Inputs_CAT'!$B$18)/'Inputs_CAT'!$B$22) -> 411.08042 | C55: =IF(C$54>=$A55,"n/a",(SUMPRODUCT('DCF_CAT'!$C$31:$G$31,1/(1+$A55)^{1,2,3,4,5})+('DCF_CAT'!$G$31*(1+C$54)/($A55-C$54))/(1+$A55)^5-'Inputs_CAT'!$B$17+'Inputs_CAT'!$B$18)/'Inputs_CAT'!$B$22) -> 510.2257 | D55: =IF(D$54>=$A55,"n/a",(SUMPRODUCT('DCF_CAT'!$C$31:$G$31,1/(1+$A55)^{1,2,3,4,5})+('DCF_CAT'!$G$31*(1+D$54)/($A55-D$54))/(1+$A55)^5-'Inputs_CAT'!$B$17+'Inputs_CAT'!$B$18)/'Inputs_CAT'!$B$22) -> 675.46781 | E55: =IF(E$54>=$A55,"n/a",(SUMPRODUCT('DCF_CAT'!$C$31:$G$31,1/(1+$A55)^{1,2,3,4,5})+('DCF_CAT'!$G$31*(1+E$54)/($A55-E$54))/(1+$A55)^5-'Inputs_CAT'!$B$17+'Inputs_CAT'!$B$18)/'Inputs_CAT'!$B$22) -> 1005.9521 | F55: =IF(F$54>=$A55,"n/a",(SUMPRODUCT('DCF_CAT'!$C$31:$G$31,1/(1+$A55)^{1,2,3,4,5})+('DCF_CAT'!$G$31*(1+F$54)/($A55-F$54))/(1+$A55)^5-'Inputs_CAT'!$B$17+'Inputs_CAT'!$B$18)/'Inputs_CAT'!$B$22) -> 1997.4048 | G55: =IF(G$54>=$A55,"n/a",(SUMPRODUCT('DCF_CAT'!$C$31:$G$31,1/(1+$A55)^{1,2,3,4,5})+('DCF_CAT'!$G$31*(1+G$54)/($A55-G$54))/(1+$A55)^5-'Inputs_CAT'!$B$17+'Inputs_CAT'!$B$18)/'Inputs_CAT'!$B$22) -> n/a
A56: 0.08 | B56: =IF(B$54>=$A56,"n/a",(SUMPRODUCT('DCF_CAT'!$C$31:$G$31,1/(1+$A56)^{1,2,3,4,5})+('DCF_CAT'!$G$31*(1+B$54)/($A56-B$54))/(1+$A56)^5-'Inputs_CAT'!$B$17+'Inputs_CAT'!$B$18)/'Inputs_CAT'!$B$22) -> 231.06407 | C56: =IF(C$54>=$A56,"n/a",(SUMPRODUCT('DCF_CAT'!$C$31:$G$31,1/(1+$A56)^{1,2,3,4,5})+('DCF_CAT'!$G$31*(1+C$54)/($A56-C$54))/(1+$A56)^5-'Inputs_CAT'!$B$17+'Inputs_CAT'!$B$18)/'Inputs_CAT'!$B$22) -> 262.69968 | D56: =IF(D$54>=$A56,"n/a",(SUMPRODUCT('DCF_CAT'!$C$31:$G$31,1/(1+$A56)^{1,2,3,4,5})+('DCF_CAT'!$G$31*(1+D$54)/($A56-D$54))/(1+$A56)^5-'Inputs_CAT'!$B$17+'Inputs_CAT'!$B$18)/'Inputs_CAT'!$B$22) -> 304.88048 | E56: =IF(E$54>=$A56,"n/a",(SUMPRODUCT('DCF_CAT'!$C$31:$G$31,1/(1+$A56)^{1,2,3,4,5})+('DCF_CAT'!$G$31*(1+E$54)/($A56-E$54))/(1+$A56)^5-'Inputs_CAT'!$B$17+'Inputs_CAT'!$B$18)/'Inputs_CAT'!$B$22) -> 363.93361 | F56: =IF(F$54>=$A56,"n/a",(SUMPRODUCT('DCF_CAT'!$C$31:$G$31,1/(1+$A56)^{1,2,3,4,5})+('DCF_CAT'!$G$31*(1+F$54)/($A56-F$54))/(1+$A56)^5-'Inputs_CAT'!$B$17+'Inputs_CAT'!$B$18)/'Inputs_CAT'!$B$22) -> 452.51331 | G56: =IF(G$54>=$A56,"n/a",(SUMPRODUCT('DCF_CAT'!$C$31:$G$31,1/(1+$A56)^{1,2,3,4,5})+('DCF_CAT'!$G$31*(1+G$54)/($A56-G$54))/(1+$A56)^5-'Inputs_CAT'!$B$17+'Inputs_CAT'!$B$18)/'Inputs_CAT'!$B$22) -> 600.14613
A57: 0.11 | B57: =IF(B$54>=$A57,"n/a",(SUMPRODUCT('DCF_CAT'!$C$31:$G$31,1/(1+$A57)^{1,2,3,4,5})+('DCF_CAT'!$G$31*(1+B$54)/($A57-B$54))/(1+$A57)^5-'Inputs_CAT'!$B$17+'Inputs_CAT'!$B$18)/'Inputs_CAT'!$B$22) -> 149.57942 | C57: =IF(C$54>=$A57,"n/a",(SUMPRODUCT('DCF_CAT'!$C$31:$G$31,1/(1+$A57)^{1,2,3,4,5})+('DCF_CAT'!$G$31*(1+C$54)/($A57-C$54))/(1+$A57)^5-'Inputs_CAT'!$B$17+'Inputs_CAT'!$B$18)/'Inputs_CAT'!$B$22) -> 164.01302 | D57: =IF(D$54>=$A57,"n/a",(SUMPRODUCT('DCF_CAT'!$C$31:$G$31,1/(1+$A57)^{1,2,3,4,5})+('DCF_CAT'!$G$31*(1+D$54)/($A57-D$54))/(1+$A57)^5-'Inputs_CAT'!$B$17+'Inputs_CAT'!$B$18)/'Inputs_CAT'!$B$22) -> 181.65408 | E57: =IF(E$54>=$A57,"n/a",(SUMPRODUCT('DCF_CAT'!$C$31:$G$31,1/(1+$A57)^{1,2,3,4,5})+('DCF_CAT'!$G$31*(1+E$54)/($A57-E$54))/(1+$A57)^5-'Inputs_CAT'!$B$17+'Inputs_CAT'!$B$18)/'Inputs_CAT'!$B$22) -> 203.70541 | F57: =IF(F$54>=$A57,"n/a",(SUMPRODUCT('DCF_CAT'!$C$31:$G$31,1/(1+$A57)^{1,2,3,4,5})+('DCF_CAT'!$G$31*(1+F$54)/($A57-F$54))/(1+$A57)^5-'Inputs_CAT'!$B$17+'Inputs_CAT'!$B$18)/'Inputs_CAT'!$B$22) -> 232.05712 | G57: =IF(G$54>=$A57,"n/a",(SUMPRODUCT('DCF_CAT'!$C$31:$G$31,1/(1+$A57)^{1,2,3,4,5})+('DCF_CAT'!$G$31*(1+G$54)/($A57-G$54))/(1+$A57)^5-'Inputs_CAT'!$B$17+'Inputs_CAT'!$B$18)/'Inputs_CAT'!$B$22) -> 269.8594
A58: 0.14 | B58: =IF(B$54>=$A58,"n/a",(SUMPRODUCT('DCF_CAT'!$C$31:$G$31,1/(1+$A58)^{1,2,3,4,5})+('DCF_CAT'!$G$31*(1+B$54)/($A58-B$54))/(1+$A58)^5-'Inputs_CAT'!$B$17+'Inputs_CAT'!$B$18)/'Inputs_CAT'!$B$22) -> 103.24885 | C58: =IF(C$54>=$A58,"n/a",(SUMPRODUCT('DCF_CAT'!$C$31:$G$31,1/(1+$A58)^{1,2,3,4,5})+('DCF_CAT'!$G$31*(1+C$54)/($A58-C$54))/(1+$A58)^5-'Inputs_CAT'!$B$17+'Inputs_CAT'!$B$18)/'Inputs_CAT'!$B$22) -> 111.08979 | D58: =IF(D$54>=$A58,"n/a",(SUMPRODUCT('DCF_CAT'!$C$31:$G$31,1/(1+$A58)^{1,2,3,4,5})+('DCF_CAT'!$G$31*(1+D$54)/($A58-D$54))/(1+$A58)^5-'Inputs_CAT'!$B$17+'Inputs_CAT'!$B$18)/'Inputs_CAT'!$B$22) -> 120.23756 | E58: =IF(E$54>=$A58,"n/a",(SUMPRODUCT('DCF_CAT'!$C$31:$G$31,1/(1+$A58)^{1,2,3,4,5})+('DCF_CAT'!$G$31*(1+E$54)/($A58-E$54))/(1+$A58)^5-'Inputs_CAT'!$B$17+'Inputs_CAT'!$B$18)/'Inputs_CAT'!$B$22) -> 131.04856 | F58: =IF(F$54>=$A58,"n/a",(SUMPRODUCT('DCF_CAT'!$C$31:$G$31,1/(1+$A58)^{1,2,3,4,5})+('DCF_CAT'!$G$31*(1+F$54)/($A58-F$54))/(1+$A58)^5-'Inputs_CAT'!$B$17+'Inputs_CAT'!$B$18)/'Inputs_CAT'!$B$22) -> 144.02176 | G58: =IF(G$54>=$A58,"n/a",(SUMPRODUCT('DCF_CAT'!$C$31:$G$31,1/(1+$A58)^{1,2,3,4,5})+('DCF_CAT'!$G$31*(1+G$54)/($A58-G$54))/(1+$A58)^5-'Inputs_CAT'!$B$17+'Inputs_CAT'!$B$18)/'Inputs_CAT'!$B$22) -> 159.87789
A59: 0.17 | B59: =IF(B$54>=$A59,"n/a",(SUMPRODUCT('DCF_CAT'!$C$31:$G$31,1/(1+$A59)^{1,2,3,4,5})+('DCF_CAT'!$G$31*(1+B$54)/($A59-B$54))/(1+$A59)^5-'Inputs_CAT'!$B$17+'Inputs_CAT'!$B$18)/'Inputs_CAT'!$B$22) -> 73.43654 | C59: =IF(C$54>=$A59,"n/a",(SUMPRODUCT('DCF_CAT'!$C$31:$G$31,1/(1+$A59)^{1,2,3,4,5})+('DCF_CAT'!$G$31*(1+C$54)/($A59-C$54))/(1+$A59)^5-'Inputs_CAT'!$B$17+'Inputs_CAT'!$B$18)/'Inputs_CAT'!$B$22) -> 78.165296 | D59: =IF(D$54>=$A59,"n/a",(SUMPRODUCT('DCF_CAT'!$C$31:$G$31,1/(1+$A59)^{1,2,3,4,5})+('DCF_CAT'!$G$31*(1+D$54)/($A59-D$54))/(1+$A59)^5-'Inputs_CAT'!$B$17+'Inputs_CAT'!$B$18)/'Inputs_CAT'!$B$22) -> 83.524552 | E59: =IF(E$54>=$A59,"n/a",(SUMPRODUCT('DCF_CAT'!$C$31:$G$31,1/(1+$A59)^{1,2,3,4,5})+('DCF_CAT'!$G$31*(1+E$54)/($A59-E$54))/(1+$A59)^5-'Inputs_CAT'!$B$17+'Inputs_CAT'!$B$18)/'Inputs_CAT'!$B$22) -> 89.649416 | F59: =IF(F$54>=$A59,"n/a",(SUMPRODUCT('DCF_CAT'!$C$31:$G$31,1/(1+$A59)^{1,2,3,4,5})+('DCF_CAT'!$G$31*(1+F$54)/($A59-F$54))/(1+$A59)^5-'Inputs_CAT'!$B$17+'Inputs_CAT'!$B$18)/'Inputs_CAT'!$B$22) -> 96.716567 | G59: =IF(G$54>=$A59,"n/a",(SUMPRODUCT('DCF_CAT'!$C$31:$G$31,1/(1+$A59)^{1,2,3,4,5})+('DCF_CAT'!$G$31*(1+G$54)/($A59-G$54))/(1+$A59)^5-'Inputs_CAT'!$B$17+'Inputs_CAT'!$B$18)/'Inputs_CAT'!$B$22) -> 104.96158
A60: 0.2 | B60: =IF(B$54>=$A60,"n/a",(SUMPRODUCT('DCF_CAT'!$C$31:$G$31,1/(1+$A60)^{1,2,3,4,5})+('DCF_CAT'!$G$31*(1+B$54)/($A60-B$54))/(1+$A60)^5-'Inputs_CAT'!$B$17+'Inputs_CAT'!$B$18)/'Inputs_CAT'!$B$22) -> 52.691441 | C60: =IF(C$54>=$A60,"n/a",(SUMPRODUCT('DCF_CAT'!$C$31:$G$31,1/(1+$A60)^{1,2,3,4,5})+('DCF_CAT'!$G$31*(1+C$54)/($A60-C$54))/(1+$A60)^5-'Inputs_CAT'!$B$17+'Inputs_CAT'!$B$18)/'Inputs_CAT'!$B$22) -> 55.750238 | D60: =IF(D$54>=$A60,"n/a",(SUMPRODUCT('DCF_CAT'!$C$31:$G$31,1/(1+$A60)^{1,2,3,4,5})+('DCF_CAT'!$G$31*(1+D$54)/($A60-D$54))/(1+$A60)^5-'Inputs_CAT'!$B$17+'Inputs_CAT'!$B$18)/'Inputs_CAT'!$B$22) -> 59.148901 | E60: =IF(E$54>=$A60,"n/a",(SUMPRODUCT('DCF_CAT'!$C$31:$G$31,1/(1+$A60)^{1,2,3,4,5})+('DCF_CAT'!$G$31*(1+E$54)/($A60-E$54))/(1+$A60)^5-'Inputs_CAT'!$B$17+'Inputs_CAT'!$B$18)/'Inputs_CAT'!$B$22) -> 62.947406 | F60: =IF(F$54>=$A60,"n/a",(SUMPRODUCT('DCF_CAT'!$C$31:$G$31,1/(1+$A60)^{1,2,3,4,5})+('DCF_CAT'!$G$31*(1+F$54)/($A60-F$54))/(1+$A60)^5-'Inputs_CAT'!$B$17+'Inputs_CAT'!$B$18)/'Inputs_CAT'!$B$22) -> 67.220725 | G60: =IF(G$54>=$A60,"n/a",(SUMPRODUCT('DCF_CAT'!$C$31:$G$31,1/(1+$A60)^{1,2,3,4,5})+('DCF_CAT'!$G$31*(1+G$54)/($A60-G$54))/(1+$A60)^5-'Inputs_CAT'!$B$17+'Inputs_CAT'!$B$18)/'Inputs_CAT'!$B$22) -> 72.06382

Sheet Inputs_INTC
A1: Inputs — INTC (INTEL CORP) | Frozen 2026-08-17T17:23:45.328242+00:00
A2: Profile: Mature, negative/near-zero recent revenue growth | CIK 0000050863 | All USD values are actual dollars (not thousands/millions) unless noted.
A4: SECTION 1 — Historical Annual Data (SEC EDGAR, frozen)
A5: Fiscal Year End | B5: Revenue (USD) | C5: EBIT / Operating Income (USD) | D5: Provenance
A6: 44555 | B6: 79024000000 | C6: 19456000000 | D6: XBRL tag: RevenueFromContractWithCustomerExcludingAssessedTax
A7: 44926 | B7: 63054000000 | C7: 2334000000 | D7: XBRL tag: RevenueFromContractWithCustomerExcludingAssessedTax
A8: 45290 | B8: 54228000000 | C8: 93000000 | D8: XBRL tag: RevenueFromContractWithCustomerExcludingAssessedTax
A9: 45654 | B9: 53101000000 | C9: -11678000000 | D9: XBRL tag: RevenueFromContractWithCustomerExcludingAssessedTax
A10: 46018 | B10: 52853000000 | C10: -2214000000 | D10: XBRL tag: RevenueFromContractWithCustomerExcludingAssessedTax
A12: SECTION 2 — Latest-Year Facts (SEC EDGAR, frozen)
A13: Latest Complete Fiscal Year End | B13: 46018
A14: Pretax Income (USD) | B14: 1557000000
A15: Tax Provision (USD) | B15: 1531000000
A16: Interest Expense (USD) | B16: 1091000000 | D16: Method: reported; tag: InterestExpenseNonoperating
A17: Total Debt (USD) | B17: 46585000000 | D17: Total Debt = LongTermDebtNoncurrent ($44,086,000,000) + LongTermDebtCurrent ($2,499,000,000) = $46,585,000,000 | Full per-component provenance (XBRL tag, accession, filed date, source URL): see Sources sheet.
A18: Cash & Equivalents (USD) | B18: 14265000000
A20: SECTION 3 — Market Data (Yahoo Finance via yfinance, frozen)
A21: Current Price (USD/share) | B21: 104.125
A22: Shares Outstanding | B22: 5286105262
A23: Beta (levered equity) | B23: 2.241
A24: Sector (GICS) | B24: Technology
A26: SECTION 4 — Assumptions (shared across companies unless noted; assumptions-register.md)
A27: Risk-free rate (A-001) | B27: 0.04
A28: Market risk premium (A-009) | B28: 0.055
A29: Terminal growth rate, base case (A-003) | B29: 0.025
A30: Projection years | B30: 5
A31: D&A % of revenue (A-004) | B31: 0.03
A32: CapEx % of revenue (A-004) | B32: 0.04
A33: ΔNWC % of revenue change (A-004) | B33: 0.01
A34: WACC clamp — minimum (A-006) | B34: 0.05
A35: WACC clamp — maximum (A-006) | B35: 0.2
A36: Terminal growth clamp — minimum | B36: 0
A37: Terminal growth clamp — maximum | B37: 0.05
A38: Historical revenue growth cap (A-002) | B38: 0.25

Sheet DCF_INTC
A1: DCF Valuation — INTC (INTEL CORP) [V2 — Track A Phase 2C]
A2: Every formula below is entered independently from docs/model-specifications/dcf.md and wacc-capm.md prose/equations — never copied from src/dcf_model/dcf.py. V2: years_elapsed now uses actual fiscal-period-end date subtraction, per the Track A Phase 2C specification clarification (A-028/L-019) — see row below.
A4: SECTION 1 — Historical Revenue CAGR & Operating Margin [dcf.md §Historical revenue-growth and operating-margin derivation]
A5: Years elapsed = (latest fiscal date − earliest fiscal date) / 365.25 [V2; A-028] | B5: =('Inputs_INTC'!$A$10-'Inputs_INTC'!$A$6)/365.25 -> 4.0054757 | D5: Spec: dcf.md — years_elapsed is ACTUAL elapsed calendar days between the earliest- and latest-dated valid observations / 365.25, never (periods−1) (A-028; Track A Phase 2C, resolving the ambiguity Phase 2B found).
A6: Diagnostic — naive (N periods − 1) years [V1's convention; NOT used below] | B6: 4 | C6: IRREGULAR | D6: IRREGULAR FISCAL CALENDAR DETECTED — actual years_elapsed (4.005476) ≠ naive count (4). This is the exact condition that made V1 (COUNT−1) diverge from the codebase for this company in Track A Phase 2B — see docs/model-change-log.md.
A8: Raw Revenue CAGR = (Rev_latest/Rev_earliest)^(1/years) − 1 | B8: =('Inputs_INTC'!$B$10/'Inputs_INTC'!$B$6)^(1/B5)-1 -> -0.095544173
A9: Capped Revenue CAGR (cap A-002; NOT floored below) | B9: =MIN(B8,'Inputs_INTC'!$B$38) -> -0.095544173 | D9: Spec: dcf.md — capped at MAX_REVENUE_GROWTH_RATE=25%, unbounded below (A-002)
A10: Average Historical Operating Margin = simple average of EBIT_t/Revenue_t | B10: =('Inputs_INTC'!$C$6/'Inputs_INTC'!$B$6+'Inputs_INTC'!$C$7/'Inputs_INTC'!$B$7+'Inputs_INTC'!$C$8/'Inputs_INTC'!$B$8+'Inputs_INTC'!$C$9/'Inputs_INTC'!$B$9+'Inputs_INTC'!$C$10/'Inputs_INTC'!$B$10)/5 -> 0.0046248517
A12: SECTION 2 — WACC via CAPM [wacc-capm.md §Formula]
A13: Market Capitalization = Price × Shares Outstanding | B13: ='Inputs_INTC'!$B$21*'Inputs_INTC'!$B$22 -> 5.5041571e+11
A14: Effective Tax Rate = Tax Provision / Pretax Income (latest FY) | B14: ='Inputs_INTC'!$B$15/'Inputs_INTC'!$B$14 -> 0.98330122 | D14: Method: derived. Spec: wacc-capm.md — derived as tax_provision/pretax_income, valid range [0,1); DEFAULT_TAX_RATE=21% only on missing data.
A15: Cost of Debt = |Interest Expense| / Total Debt (latest FY) | B15: =ABS('Inputs_INTC'!$B$16)/'Inputs_INTC'!$B$17 -> 0.023419556
A16: Cost of Equity (CAPM) = Rf + Beta × MRP | B16: ='Inputs_INTC'!$B$27+'Inputs_INTC'!$B$23*'Inputs_INTC'!$B$28 -> 0.163255
A17: After-Tax Cost of Debt = Cost of Debt × (1 − Tax Rate) | B17: =B15*(1-B14) -> 0.000391078
A18: Weight of Equity = MktCap / (MktCap + Total Debt) | B18: =B13/(B13+'Inputs_INTC'!$B$17) -> 0.92196827
A19: Weight of Debt = Total Debt / (MktCap + Total Debt) | B19: ='Inputs_INTC'!$B$17/(B13+'Inputs_INTC'!$B$17) -> 0.078031733
A20: Raw WACC = We×Re + Wd×Rd(after-tax) | B20: =B18*B16+B19*B17 -> 0.15054645
A21: Final WACC — clamped to [5%,20%] (A-006), via MEDIAN(raw,min,max) | B21: =MEDIAN(B20,'Inputs_INTC'!$B$34,'Inputs_INTC'!$B$35) -> 0.15054645 | D21: MEDIAN(x,min,max) is a standard single-formula clamp: returns min if x<min, max if x>max, else x.
A23: SECTION 3 — 5-Year Free Cash Flow Projection [dcf.md §Free Cash Flow projection]
B24: Year 0 (base, actual) | C24: Year 1 | D24: Year 2 | E24: Year 3 | F24: Year 4 | G24: Year 5
A25: Revenue = Revenue_(t-1) × (1 + growth) | B25: ='Inputs_INTC'!$B$10 -> 52853000000 | C25: =B25*(1+$B$9) -> 4.7803204e+10 | D25: =C25*(1+$B$9) -> 4.3235886e+10 | E25: =D25*(1+$B$9) -> 3.9104949e+10 | F25: =E25*(1+$B$9) -> 3.5368699e+10 | G25: =F25*(1+$B$9) -> 3.1989426e+10
A26: EBIT = Revenue × Operating Margin | C26: =C25*$B$10 -> 2.2108273e+08 | D26: =D25*$B$10 -> 1.9995956e+08 | E26: =E25*$B$10 -> 1.8085459e+08 | F26: =F25*$B$10 -> 1.6357499e+08 | G26: =G25*$B$10 -> 1.4794635e+08
A27: NOPAT = EBIT × (1 − Tax Rate) | C27: =C26*(1-$B$14) -> 3691811.8 | D27: =D26*(1-$B$14) -> 3339080.7 | E27: =E26*(1-$B$14) -> 3020051 | F27: =F26*(1-$B$14) -> 2731502.7 | G27: =G26*(1-$B$14) -> 2470523.6
A28: D&A = Revenue × D&A% (A-004) | C28: =C25*'Inputs_INTC'!$B$31 -> 1.4340961e+09 | D28: =D25*'Inputs_INTC'!$B$31 -> 1.2970766e+09 | E28: =E25*'Inputs_INTC'!$B$31 -> 1.1731485e+09 | F28: =F25*'Inputs_INTC'!$B$31 -> 1.061061e+09 | G28: =G25*'Inputs_INTC'!$B$31 -> 9.5968278e+08
A29: CapEx = Revenue × CapEx% (A-004) | C29: =C25*'Inputs_INTC'!$B$32 -> 1.9121282e+09 | D29: =D25*'Inputs_INTC'!$B$32 -> 1.7294355e+09 | E29: =E25*'Inputs_INTC'!$B$32 -> 1.564198e+09 | F29: =F25*'Inputs_INTC'!$B$32 -> 1.414748e+09 | G29: =G25*'Inputs_INTC'!$B$32 -> 1.279577e+09
A30: ΔNWC = NWC% × (Revenue_t − Revenue_(t-1)) (A-004) | C30: ='Inputs_INTC'!$B$33*(C25-B25) -> -50497962 | D30: ='Inputs_INTC'!$B$33*(D25-C25) -> -45673176 | E30: ='Inputs_INTC'!$B$33*(E25-D25) -> -41309370 | F30: ='Inputs_INTC'!$B$33*(F25-E25) -> -37362500 | G30: ='Inputs_INTC'!$B$33*(G25-F25) -> -33792731
A31: Unlevered FCF = NOPAT + D&A − CapEx − ΔNWC | C31: =C27+C28-C29-C30 -> -4.2384226e+08 | D31: =D27+D28-D29-D30 -> -3.8334661e+08 | E31: =E27+E28-E29-E30 -> -3.4672007e+08 | F31: =F27+F28-F29-F30 -> -3.1359299e+08 | G31: =G27+G28-G29-G30 -> -2.8363101e+08
A33: SECTION 4 — Terminal Value (Gordon Growth) [dcf.md §Terminal value]
A34: Terminal Value = FCF_Y5 × (1+g) / (WACC − g) | B34: =G31*(1+'Inputs_INTC'!$B$29)/(B21-'Inputs_INTC'!$B$29) -> -2.3156512e+09
A35: Check: Final WACC > Terminal Growth Rate? | B35: =IF(B21>'Inputs_INTC'!$B$29,"PASS","FAIL") -> PASS
A37: SECTION 5 — Discounting & Enterprise-to-Equity Bridge [dcf.md §Discounting and the Enterprise-to-Equity bridge]
A38: PV(FCF_t) = FCF_t / (1+WACC)^t | C38: =C31/(1+$B$21)^1 -> -3.6838345e+08 | D38: =D31/(1+$B$21)^2 -> -2.8958983e+08 | E38: =E31/(1+$B$21)^3 -> -2.276494e+08 | F38: =F31/(1+$B$21)^4 -> -1.7895743e+08 | G38: =G31/(1+$B$21)^5 -> -1.4068018e+08
A39: Sum of PV(FCF Years 1-5) | B39: =SUM(C38:G38) -> -1.2052603e+09
A40: PV(Terminal Value) = TV / (1+WACC)^5 | B40: =B34/(1+B21)^5 -> -1.1485565e+09
A41: Enterprise Value = Sum PV(FCF) + PV(Terminal Value) | B41: =B39+B40 -> -2.3538168e+09
A42: Equity Value = Enterprise Value − Total Debt + Cash | B42: =B41-'Inputs_INTC'!$B$17+'Inputs_INTC'!$B$18 -> -3.4673817e+10
A43: Intrinsic Value per Share = Equity Value / Shares Outstanding | B43: =B42/'Inputs_INTC'!$B$22 -> -6.5594261
A44: Current Price / Intrinsic Value (descriptive ratio, NOT a recommendation) | B44: ='Inputs_INTC'!$B$21/B43 -> -15.874102
A46: SECTION 6 — Validation Checks (local to this company)
A47: WACC within documented clamp [5%,20%]? | B47: =IF(AND(B21>='Inputs_INTC'!$B$34,B21<='Inputs_INTC'!$B$35),"PASS","FAIL") -> PASS
A48: Enterprise Value is a finite number? | B48: =IF(ISNUMBER(B41),"PASS","FAIL") -> PASS
A49: Intrinsic Value per Share is a finite number? | B49: =IF(ISNUMBER(B43),"PASS","FAIL") -> PASS
A50: Intrinsic Value per Share is positive? | B50: =IF(B43>0,"PASS","FAIL") -> FAIL | D50: Negative base-case IV is a legitimate model output here (structurally negative unlevered FCF under fixed A-004 percentages + near-100% latest-year effective tax rate) — see Research Outlook. Not a workbook defect.
A51: Effective tax rate within valid [0,1) range? | B51: =IF(AND(B14>=0,B14<1),"PASS","FAIL") -> PASS
A52: Final WACC exceeds terminal growth rate? | B52: =IF(B21>'Inputs_INTC'!$B$29,"PASS","FAIL") -> PASS

Sheet Sensitivity_INTC
A1: Sensitivity Analysis — INTC
A2: One variable at a time, other inputs held at base case. Per docs/independent-validation-plan.md §Sensitivity tables.
A4: TABLE 1 — WACC Sensitivity (range [5%,20%], base FCF path held fixed) [dcf.md Terminal Value + discounting]
A5: WACC | B5: Terminal Value | C5: Enterprise Value | D5: Equity Value | E5: Intrinsic Value/Share
A6: 0.05 | B6: =IF($A$6<='Inputs_INTC'!$B$29,"n/a (WACC<=g)",'DCF_INTC'!$G$31*(1+'Inputs_INTC'!$B$29)/($A$6-'Inputs_INTC'!$B$29)) -> -1.1628871e+10 | C6: =IF(B6="n/a (WACC<=g)","n/a",SUMPRODUCT('DCF_INTC'!$C$31:$G$31,1/(1+$A$6)^{1,2,3,4,5})+B6/(1+$A$6)^5) -> -1.0642627e+10 | D6: =IF(C6="n/a","n/a",C6-'Inputs_INTC'!$B$17+'Inputs_INTC'!$B$18) -> -4.2962627e+10 | E6: =IF(D6="n/a","n/a",D6/'Inputs_INTC'!$B$22) -> -8.1274633
A7: 0.075 | B7: =IF($A$7<='Inputs_INTC'!$B$29,"n/a (WACC<=g)",'DCF_INTC'!$G$31*(1+'Inputs_INTC'!$B$29)/($A$7-'Inputs_INTC'!$B$29)) -> -5.8144356e+09 | C7: =IF(B7="n/a (WACC<=g)","n/a",SUMPRODUCT('DCF_INTC'!$C$31:$G$31,1/(1+$A$7)^{1,2,3,4,5})+B7/(1+$A$7)^5) -> -5.4875697e+09 | D7: =IF(C7="n/a","n/a",C7-'Inputs_INTC'!$B$17+'Inputs_INTC'!$B$18) -> -3.780757e+10 | E7: =IF(D7="n/a","n/a",D7/'Inputs_INTC'!$B$22) -> -7.1522544
A8: 0.1 | B8: =IF($A$8<='Inputs_INTC'!$B$29,"n/a (WACC<=g)",'DCF_INTC'!$G$31*(1+'Inputs_INTC'!$B$29)/($A$8-'Inputs_INTC'!$B$29)) -> -3.8762904e+09 | C8: =IF(B8="n/a (WACC<=g)","n/a",SUMPRODUCT('DCF_INTC'!$C$31:$G$31,1/(1+$A$8)^{1,2,3,4,5})+B8/(1+$A$8)^5) -> -3.7597946e+09 | D8: =IF(C8="n/a","n/a",C8-'Inputs_INTC'!$B$17+'Inputs_INTC'!$B$18) -> -3.6079795e+10 | E8: =IF(D8="n/a","n/a",D8/'Inputs_INTC'!$B$22) -> -6.8254022
A9: 0.125 | B9: =IF($A$9<='Inputs_INTC'!$B$29,"n/a (WACC<=g)",'DCF_INTC'!$G$31*(1+'Inputs_INTC'!$B$29)/($A$9-'Inputs_INTC'!$B$29)) -> -2.9072178e+09 | C9: =IF(B9="n/a (WACC<=g)","n/a",SUMPRODUCT('DCF_INTC'!$C$31:$G$31,1/(1+$A$9)^{1,2,3,4,5})+B9/(1+$A$9)^5) -> -2.8896214e+09 | D9: =IF(C9="n/a","n/a",C9-'Inputs_INTC'!$B$17+'Inputs_INTC'!$B$18) -> -3.5209621e+10 | E9: =IF(D9="n/a","n/a",D9/'Inputs_INTC'!$B$22) -> -6.660787
A10: 0.15 | B10: =IF($A$10<='Inputs_INTC'!$B$29,"n/a (WACC<=g)",'DCF_INTC'!$G$31*(1+'Inputs_INTC'!$B$29)/($A$10-'Inputs_INTC'!$B$29)) -> -2.3257743e+09 | C10: =IF(B10="n/a (WACC<=g)","n/a",SUMPRODUCT('DCF_INTC'!$C$31:$G$31,1/(1+$A$10)^{1,2,3,4,5})+B10/(1+$A$10)^5) -> -2.3630311e+09 | D10: =IF(C10="n/a","n/a",C10-'Inputs_INTC'!$B$17+'Inputs_INTC'!$B$18) -> -3.4683031e+10 | E10: =IF(D10="n/a","n/a",D10/'Inputs_INTC'!$B$22) -> -6.5611692
A11: 0.175 | B11: =IF($A$11<='Inputs_INTC'!$B$29,"n/a (WACC<=g)",'DCF_INTC'!$G$31*(1+'Inputs_INTC'!$B$29)/($A$11-'Inputs_INTC'!$B$29)) -> -1.9381452e+09 | C11: =IF(B11="n/a (WACC<=g)","n/a",SUMPRODUCT('DCF_INTC'!$C$31:$G$31,1/(1+$A$11)^{1,2,3,4,5})+B11/(1+$A$11)^5) -> -2.0086254e+09 | D11: =IF(C11="n/a","n/a",C11-'Inputs_INTC'!$B$17+'Inputs_INTC'!$B$18) -> -3.4328625e+10 | E11: =IF(D11="n/a","n/a",D11/'Inputs_INTC'!$B$22) -> -6.4941244
A12: 0.2 | B12: =IF($A$12<='Inputs_INTC'!$B$29,"n/a (WACC<=g)",'DCF_INTC'!$G$31*(1+'Inputs_INTC'!$B$29)/($A$12-'Inputs_INTC'!$B$29)) -> -1.6612673e+09 | C12: =IF(B12="n/a (WACC<=g)","n/a",SUMPRODUCT('DCF_INTC'!$C$31:$G$31,1/(1+$A$12)^{1,2,3,4,5})+B12/(1+$A$12)^5) -> -1.7529052e+09 | D12: =IF(C12="n/a","n/a",C12-'Inputs_INTC'!$B$17+'Inputs_INTC'!$B$18) -> -3.4072905e+10 | E12: =IF(D12="n/a","n/a",D12/'Inputs_INTC'!$B$22) -> -6.4457485
A13: Direction check: IV decreases as WACC rises? | B13: =IF(E6>E12,"PASS (as expected)","FAIL — investigate (see note)") -> FAIL — investigate (see note) | F13: INVESTIGATED: base-case FCF is negative every year for this company, so higher WACC discounts a negative stream LESS, making IV rise (not fall) with WACC. This is mathematically correct DCF behavior for negative cash flows, not a workbook defect — see Research Outlook.
A16: TABLE 2 — Terminal Growth Rate Sensitivity (range [0%,5%]); invalid where g>=WACC
A17: Terminal Growth g | B17: Terminal Value | C17: Enterprise Value | D17: Equity Value | E17: Intrinsic Value/Share
A18: 0 | B18: =IF($A$18>='DCF_INTC'!$B$21,"n/a (g>=WACC)",'DCF_INTC'!$G$31*(1+$A$18)/('DCF_INTC'!$B$21-$A$18)) -> -1.88401e+09 | C18: =IF(B18="n/a (g>=WACC)","n/a",'DCF_INTC'!$B$39+B18/(1+'DCF_INTC'!$B$21)^5) -> -2.139724e+09 | D18: =IF(C18="n/a","n/a",C18-'Inputs_INTC'!$B$17+'Inputs_INTC'!$B$18) -> -3.4459724e+10 | E18: =IF(D18="n/a","n/a",D18/'Inputs_INTC'!$B$22) -> -6.518925
A19: 0.01 | B19: =IF($A$19>='DCF_INTC'!$B$21,"n/a (g>=WACC)",'DCF_INTC'!$G$31*(1+$A$19)/('DCF_INTC'!$B$21-$A$19)) -> -2.0382395e+09 | C19: =IF(B19="n/a (g>=WACC)","n/a",'DCF_INTC'!$B$39+B19/(1+'DCF_INTC'!$B$21)^5) -> -2.2162214e+09 | D19: =IF(C19="n/a","n/a",C19-'Inputs_INTC'!$B$17+'Inputs_INTC'!$B$18) -> -3.4536221e+10 | E19: =IF(D19="n/a","n/a",D19/'Inputs_INTC'!$B$22) -> -6.5333965
A20: 0.02 | B20: =IF($A$20>='DCF_INTC'!$B$21,"n/a (g>=WACC)",'DCF_INTC'!$G$31*(1+$A$20)/('DCF_INTC'!$B$21-$A$20)) -> -2.2160973e+09 | C20: =IF(B20="n/a (g>=WACC)","n/a",'DCF_INTC'!$B$39+B20/(1+'DCF_INTC'!$B$21)^5) -> -2.3044383e+09 | D20: =IF(C20="n/a","n/a",C20-'Inputs_INTC'!$B$17+'Inputs_INTC'!$B$18) -> -3.4624438e+10 | E20: =IF(D20="n/a","n/a",D20/'Inputs_INTC'!$B$22) -> -6.5500849
A21: 0.025 | B21: =IF($A$21>='DCF_INTC'!$B$21,"n/a (g>=WACC)",'DCF_INTC'!$G$31*(1+$A$21)/('DCF_INTC'!$B$21-$A$21)) -> -2.3156512e+09 | C21: =IF(B21="n/a (g>=WACC)","n/a",'DCF_INTC'!$B$39+B21/(1+'DCF_INTC'!$B$21)^5) -> -2.3538168e+09 | D21: =IF(C21="n/a","n/a",C21-'Inputs_INTC'!$B$17+'Inputs_INTC'!$B$18) -> -3.4673817e+10 | E21: =IF(D21="n/a","n/a",D21/'Inputs_INTC'!$B$22) -> -6.5594261
A22: 0.03 | B22: =IF($A$22>='DCF_INTC'!$B$21,"n/a (g>=WACC)",'DCF_INTC'!$G$31*(1+$A$22)/('DCF_INTC'!$B$21-$A$22)) -> -2.4234637e+09 | C22: =IF(B22="n/a (g>=WACC)","n/a",'DCF_INTC'!$B$39+B22/(1+'DCF_INTC'!$B$21)^5) -> -2.4072915e+09 | D22: =IF(C22="n/a","n/a",C22-'Inputs_INTC'!$B$17+'Inputs_INTC'!$B$18) -> -3.4727292e+10 | E22: =IF(D22="n/a","n/a",D22/'Inputs_INTC'!$B$22) -> -6.5695422
A23: 0.04 | B23: =IF($A$23>='DCF_INTC'!$B$21,"n/a (g>=WACC)",'DCF_INTC'!$G$31*(1+$A$23)/('DCF_INTC'!$B$21-$A$23)) -> -2.6683467e+09 | C23: =IF(B23="n/a (g>=WACC)","n/a",'DCF_INTC'!$B$39+B23/(1+'DCF_INTC'!$B$21)^5) -> -2.5287528e+09 | D23: =IF(C23="n/a","n/a",C23-'Inputs_INTC'!$B$17+'Inputs_INTC'!$B$18) -> -3.4848753e+10 | E23: =IF(D23="n/a","n/a",D23/'Inputs_INTC'!$B$22) -> -6.5925196
A24: 0.05 | B24: =IF($A$24>='DCF_INTC'!$B$21,"n/a (g>=WACC)",'DCF_INTC'!$G$31*(1+$A$24)/('DCF_INTC'!$B$21-$A$24)) -> -2.9619402e+09 | C24: =IF(B24="n/a (g>=WACC)","n/a",'DCF_INTC'!$B$39+B24/(1+'DCF_INTC'!$B$21)^5) -> -2.6743743e+09 | D24: =IF(C24="n/a","n/a",C24-'Inputs_INTC'!$B$17+'Inputs_INTC'!$B$18) -> -3.4994374e+10 | E24: =IF(D24="n/a","n/a",D24/'Inputs_INTC'!$B$22) -> -6.6200676
A25: Direction check: IV increases as terminal growth rises (where valid)? | B25: =IF(E18<E24,"PASS (as expected)","FAIL — investigate (see note)") -> FAIL — investigate (see note) | F25: INVESTIGATED: base-case FCF is negative, so a higher terminal growth rate makes the (negative) terminal value MORE negative, not less — IV falls as g rises. Mathematically correct given negative FCF, not a defect. See Research Outlook.
A28: TABLE 3 — Revenue Growth Sensitivity (range [-10%,40%]); base WACC & margin held fixed
A29: Growth g | B29: Rev Y1 | C29: Rev Y2 | D29: Rev Y3 | E29: Rev Y4 | F29: Rev Y5 | G29: FCF Y1 | H29: FCF Y2 | I29: FCF Y3 | J29: FCF Y4 | K29: FCF Y5 | L29: Terminal Value | M29: Enterprise Value | N29: Equity Value | O29: Intrinsic Value/Share
A30: -0.1 | B30: ='DCF_INTC'!$B$25*(1+$A$30) -> 47567700000 | C30: =B30*(1+$A$30) -> 42810930000 | D30: =C30*(1+$A$30) -> 38529837000 | E30: =D30*(1+$A$30) -> 34676853300 | F30: =E30*(1+$A$30) -> 31209167970 | G30: =B30*'DCF_INTC'!$B$10*(1-'DCF_INTC'!$B$14)+B30*'Inputs_INTC'!$B$31-B30*'Inputs_INTC'!$B$32-'Inputs_INTC'!$B$33*(B30-'DCF_INTC'!$B$25) -> -4.1915038e+08 | H30: =C30*'DCF_INTC'!$B$10*(1-'DCF_INTC'!$B$14)+C30*'Inputs_INTC'!$B$31-C30*'Inputs_INTC'!$B$32-'Inputs_INTC'!$B$33*(C30-B30) -> -3.7723534e+08 | I30: =D30*'DCF_INTC'!$B$10*(1-'DCF_INTC'!$B$14)+D30*'Inputs_INTC'!$B$31-D30*'Inputs_INTC'!$B$32-'Inputs_INTC'!$B$33*(D30-C30) -> -3.395118e+08 | J30: =E30*'DCF_INTC'!$B$10*(1-'DCF_INTC'!$B$14)+E30*'Inputs_INTC'!$B$31-E30*'Inputs_INTC'!$B$32-'Inputs_INTC'!$B$33*(E30-D30) -> -3.0556062e+08 | K30: =F30*'DCF_INTC'!$B$10*(1-'DCF_INTC'!$B$14)+F30*'Inputs_INTC'!$B$31-F30*'Inputs_INTC'!$B$32-'Inputs_INTC'!$B$33*(F30-E30) -> -2.7500456e+08 | L30: =K30*(1+'Inputs_INTC'!$B$29)/('DCF_INTC'!$B$21-'Inputs_INTC'!$B$29) -> -2.2452223e+09 | M30: =SUMPRODUCT(G30:K30,1/(1+'DCF_INTC'!$B$21)^{1,2,3,4,5})+L30/(1+'DCF_INTC'!$B$21)^5 -> -2.2965944e+09 | N30: =M30-'Inputs_INTC'!$B$17+'Inputs_INTC'!$B$18 -> -3.4616594e+10 | O30: =N30/'Inputs_INTC'!$B$22 -> -6.548601
A31: -0.05 | B31: ='DCF_INTC'!$B$25*(1+$A$31) -> 50210350000 | C31: =B31*(1+$A$31) -> 47699832500 | D31: =C31*(1+$A$31) -> 45314840875 | E31: =D31*(1+$A$31) -> 4.3049099e+10 | F31: =E31*(1+$A$31) -> 4.0896644e+10 | G31: =B31*'DCF_INTC'!$B$10*(1-'DCF_INTC'!$B$14)+B31*'Inputs_INTC'!$B$31-B31*'Inputs_INTC'!$B$32-'Inputs_INTC'!$B$33*(B31-'DCF_INTC'!$B$25) -> -4.7179929e+08 | H31: =C31*'DCF_INTC'!$B$10*(1-'DCF_INTC'!$B$14)+C31*'Inputs_INTC'!$B$31-C31*'Inputs_INTC'!$B$32-'Inputs_INTC'!$B$33*(C31-B31) -> -4.4820932e+08 | I31: =D31*'DCF_INTC'!$B$10*(1-'DCF_INTC'!$B$14)+D31*'Inputs_INTC'!$B$31-D31*'Inputs_INTC'!$B$32-'Inputs_INTC'!$B$33*(D31-C31) -> -4.2579886e+08 | J31: =E31*'DCF_INTC'!$B$10*(1-'DCF_INTC'!$B$14)+E31*'Inputs_INTC'!$B$31-E31*'Inputs_INTC'!$B$32-'Inputs_INTC'!$B$33*(E31-D31) -> -4.0450891e+08 | K31: =F31*'DCF_INTC'!$B$10*(1-'DCF_INTC'!$B$14)+F31*'Inputs_INTC'!$B$31-F31*'Inputs_INTC'!$B$32-'Inputs_INTC'!$B$33*(F31-E31) -> -3.8428347e+08 | L31: =K31*(1+'Inputs_INTC'!$B$29)/('DCF_INTC'!$B$21-'Inputs_INTC'!$B$29) -> -3.137409e+09 | M31: =SUMPRODUCT(G31:K31,1/(1+'DCF_INTC'!$B$21)^{1,2,3,4,5})+L31/(1+'DCF_INTC'!$B$21)^5 -> -3.005815e+09 | N31: =M31-'Inputs_INTC'!$B$17+'Inputs_INTC'!$B$18 -> -3.5325815e+10 | O31: =N31/'Inputs_INTC'!$B$22 -> -6.682768
A32: 0 | B32: ='DCF_INTC'!$B$25*(1+$A$32) -> 52853000000 | C32: =B32*(1+$A$32) -> 52853000000 | D32: =C32*(1+$A$32) -> 52853000000 | E32: =D32*(1+$A$32) -> 52853000000 | F32: =E32*(1+$A$32) -> 52853000000 | G32: =B32*'DCF_INTC'!$B$10*(1-'DCF_INTC'!$B$14)+B32*'Inputs_INTC'!$B$31-B32*'Inputs_INTC'!$B$32-'Inputs_INTC'!$B$33*(B32-'DCF_INTC'!$B$25) -> -5.244482e+08 | H32: =C32*'DCF_INTC'!$B$10*(1-'DCF_INTC'!$B$14)+C32*'Inputs_INTC'!$B$31-C32*'Inputs_INTC'!$B$32-'Inputs_INTC'!$B$33*(C32-B32) -> -5.244482e+08 | I32: =D32*'DCF_INTC'!$B$10*(1-'DCF_INTC'!$B$14)+D32*'Inputs_INTC'!$B$31-D32*'Inputs_INTC'!$B$32-'Inputs_INTC'!$B$33*(D32-C32) -> -5.244482e+08 | J32: =E32*'DCF_INTC'!$B$10*(1-'DCF_INTC'!$B$14)+E32*'Inputs_INTC'!$B$31-E32*'Inputs_INTC'!$B$32-'Inputs_INTC'!$B$33*(E32-D32) -> -5.244482e+08 | K32: =F32*'DCF_INTC'!$B$10*(1-'DCF_INTC'!$B$14)+F32*'Inputs_INTC'!$B$31-F32*'Inputs_INTC'!$B$32-'Inputs_INTC'!$B$33*(F32-E32) -> -5.244482e+08 | L32: =K32*(1+'Inputs_INTC'!$B$29)/('DCF_INTC'!$B$21-'Inputs_INTC'!$B$29) -> -4.2817572e+09 | M32: =SUMPRODUCT(G32:K32,1/(1+'DCF_INTC'!$B$21)^{1,2,3,4,5})+L32/(1+'DCF_INTC'!$B$21)^5 -> -3.8794991e+09 | N32: =M32-'Inputs_INTC'!$B$17+'Inputs_INTC'!$B$18 -> -3.6199499e+10 | O32: =N32/'Inputs_INTC'!$B$22 -> -6.8480473
A33: 0.05 | B33: ='DCF_INTC'!$B$25*(1+$A$33) -> 55495650000 | C33: =B33*(1+$A$33) -> 58270432500 | D33: =C33*(1+$A$33) -> 61183954125 | E33: =D33*(1+$A$33) -> 6.4243152e+10 | F33: =E33*(1+$A$33) -> 6.7455309e+10 | G33: =B33*'DCF_INTC'!$B$10*(1-'DCF_INTC'!$B$14)+B33*'Inputs_INTC'!$B$31-B33*'Inputs_INTC'!$B$32-'Inputs_INTC'!$B$33*(B33-'DCF_INTC'!$B$25) -> -5.7709711e+08 | H33: =C33*'DCF_INTC'!$B$10*(1-'DCF_INTC'!$B$14)+C33*'Inputs_INTC'!$B$31-C33*'Inputs_INTC'!$B$32-'Inputs_INTC'!$B$33*(C33-B33) -> -6.0595196e+08 | I33: =D33*'DCF_INTC'!$B$10*(1-'DCF_INTC'!$B$14)+D33*'Inputs_INTC'!$B$31-D33*'Inputs_INTC'!$B$32-'Inputs_INTC'!$B$33*(D33-C33) -> -6.3624956e+08 | J33: =E33*'DCF_INTC'!$B$10*(1-'DCF_INTC'!$B$14)+E33*'Inputs_INTC'!$B$31-E33*'Inputs_INTC'!$B$32-'Inputs_INTC'!$B$33*(E33-D33) -> -6.6806204e+08 | K33: =F33*'DCF_INTC'!$B$10*(1-'DCF_INTC'!$B$14)+F33*'Inputs_INTC'!$B$31-F33*'Inputs_INTC'!$B$32-'Inputs_INTC'!$B$33*(F33-E33) -> -7.0146514e+08 | L33: =K33*(1+'Inputs_INTC'!$B$29)/('DCF_INTC'!$B$21-'Inputs_INTC'!$B$29) -> -5.7269783e+09 | M33: =SUMPRODUCT(G33:K33,1/(1+'DCF_INTC'!$B$21)^{1,2,3,4,5})+L33/(1+'DCF_INTC'!$B$21)^5 -> -4.9468169e+09 | N33: =M33-'Inputs_INTC'!$B$17+'Inputs_INTC'!$B$18 -> -3.7266817e+10 | O33: =N33/'Inputs_INTC'!$B$22 -> -7.0499574
A34: 0.1 | B34: ='DCF_INTC'!$B$25*(1+$A$34) -> 5.81383e+10 | C34: =B34*(1+$A$34) -> 6.395213e+10 | D34: =C34*(1+$A$34) -> 7.0347343e+10 | E34: =D34*(1+$A$34) -> 7.7382077e+10 | F34: =E34*(1+$A$34) -> 8.5120285e+10 | G34: =B34*'DCF_INTC'!$B$10*(1-'DCF_INTC'!$B$14)+B34*'Inputs_INTC'!$B$31-B34*'Inputs_INTC'!$B$32-'Inputs_INTC'!$B$33*(B34-'DCF_INTC'!$B$25) -> -6.2974602e+08 | H34: =C34*'DCF_INTC'!$B$10*(1-'DCF_INTC'!$B$14)+C34*'Inputs_INTC'!$B$31-C34*'Inputs_INTC'!$B$32-'Inputs_INTC'!$B$33*(C34-B34) -> -6.9272062e+08 | I34: =D34*'DCF_INTC'!$B$10*(1-'DCF_INTC'!$B$14)+D34*'Inputs_INTC'!$B$31-D34*'Inputs_INTC'!$B$32-'Inputs_INTC'!$B$33*(D34-C34) -> -7.6199268e+08 | J34: =E34*'DCF_INTC'!$B$10*(1-'DCF_INTC'!$B$14)+E34*'Inputs_INTC'!$B$31-E34*'Inputs_INTC'!$B$32-'Inputs_INTC'!$B$33*(E34-D34) -> -8.3819195e+08 | K34: =F34*'DCF_INTC'!$B$10*(1-'DCF_INTC'!$B$14)+F34*'Inputs_INTC'!$B$31-F34*'Inputs_INTC'!$B$32-'Inputs_INTC'!$B$33*(F34-E34) -> -9.2201114e+08 | L34: =K34*(1+'Inputs_INTC'!$B$29)/('DCF_INTC'!$B$21-'Inputs_INTC'!$B$29) -> -7.527584e+09 | M34: =SUMPRODUCT(G34:K34,1/(1+'DCF_INTC'!$B$21)^{1,2,3,4,5})+L34/(1+'DCF_INTC'!$B$21)^5 -> -6.2402577e+09 | N34: =M34-'Inputs_INTC'!$B$17+'Inputs_INTC'!$B$18 -> -3.8560258e+10 | O34: =N34/'Inputs_INTC'!$B$22 -> -7.2946443
A35: 0.2 | B35: ='DCF_INTC'!$B$25*(1+$A$35) -> 63423600000 | C35: =B35*(1+$A$35) -> 76108320000 | D35: =C35*(1+$A$35) -> 91329984000 | E35: =D35*(1+$A$35) -> 109595980800 | F35: =E35*(1+$A$35) -> 131515176960 | G35: =B35*'DCF_INTC'!$B$10*(1-'DCF_INTC'!$B$14)+B35*'Inputs_INTC'!$B$31-B35*'Inputs_INTC'!$B$32-'Inputs_INTC'!$B$33*(B35-'DCF_INTC'!$B$25) -> -7.3504383e+08 | H35: =C35*'DCF_INTC'!$B$10*(1-'DCF_INTC'!$B$14)+C35*'Inputs_INTC'!$B$31-C35*'Inputs_INTC'!$B$32-'Inputs_INTC'!$B$33*(C35-B35) -> -8.820526e+08 | I35: =D35*'DCF_INTC'!$B$10*(1-'DCF_INTC'!$B$14)+D35*'Inputs_INTC'!$B$31-D35*'Inputs_INTC'!$B$32-'Inputs_INTC'!$B$33*(D35-C35) -> -1.0584631e+09 | J35: =E35*'DCF_INTC'!$B$10*(1-'DCF_INTC'!$B$14)+E35*'Inputs_INTC'!$B$31-E35*'Inputs_INTC'!$B$32-'Inputs_INTC'!$B$33*(E35-D35) -> -1.2701557e+09 | K35: =F35*'DCF_INTC'!$B$10*(1-'DCF_INTC'!$B$14)+F35*'Inputs_INTC'!$B$31-F35*'Inputs_INTC'!$B$32-'Inputs_INTC'!$B$33*(F35-E35) -> -1.5241869e+09 | L35: =K35*(1+'Inputs_INTC'!$B$29)/('DCF_INTC'!$B$21-'Inputs_INTC'!$B$29) -> -1.2443933e+10 | M35: =SUMPRODUCT(G35:K35,1/(1+'DCF_INTC'!$B$21)^{1,2,3,4,5})+L35/(1+'DCF_INTC'!$B$21)^5 -> -9.653141e+09 | N35: =M35-'Inputs_INTC'!$B$17+'Inputs_INTC'!$B$18 -> -4.1973141e+10 | O35: =N35/'Inputs_INTC'!$B$22 -> -7.9402772
A36: 0.3 | B36: ='DCF_INTC'!$B$25*(1+$A$36) -> 68708900000 | C36: =B36*(1+$A$36) -> 89321570000 | D36: =C36*(1+$A$36) -> 116118041000 | E36: =D36*(1+$A$36) -> 150953453300 | F36: =E36*(1+$A$36) -> 196239489290 | G36: =B36*'DCF_INTC'!$B$10*(1-'DCF_INTC'!$B$14)+B36*'Inputs_INTC'!$B$31-B36*'Inputs_INTC'!$B$32-'Inputs_INTC'!$B$33*(B36-'DCF_INTC'!$B$25) -> -8.4034165e+08 | H36: =C36*'DCF_INTC'!$B$10*(1-'DCF_INTC'!$B$14)+C36*'Inputs_INTC'!$B$31-C36*'Inputs_INTC'!$B$32-'Inputs_INTC'!$B$33*(C36-B36) -> -1.0924442e+09 | I36: =D36*'DCF_INTC'!$B$10*(1-'DCF_INTC'!$B$14)+D36*'Inputs_INTC'!$B$31-D36*'Inputs_INTC'!$B$32-'Inputs_INTC'!$B$33*(D36-C36) -> -1.4201774e+09 | J36: =E36*'DCF_INTC'!$B$10*(1-'DCF_INTC'!$B$14)+E36*'Inputs_INTC'!$B$31-E36*'Inputs_INTC'!$B$32-'Inputs_INTC'!$B$33*(E36-D36) -> -1.8462306e+09 | K36: =F36*'DCF_INTC'!$B$10*(1-'DCF_INTC'!$B$14)+F36*'Inputs_INTC'!$B$31-F36*'Inputs_INTC'!$B$32-'Inputs_INTC'!$B$33*(F36-E36) -> -2.4000998e+09 | L36: =K36*(1+'Inputs_INTC'!$B$29)/('DCF_INTC'!$B$21-'Inputs_INTC'!$B$29) -> -1.9595157e+10 | M36: =SUMPRODUCT(G36:K36,1/(1+'DCF_INTC'!$B$21)^{1,2,3,4,5})+L36/(1+'DCF_INTC'!$B$21)^5 -> -1.4451275e+10 | N36: =M36-'Inputs_INTC'!$B$17+'Inputs_INTC'!$B$18 -> -4.6771275e+10 | O36: =N36/'Inputs_INTC'!$B$22 -> -8.8479651
A37: 0.4 | B37: ='DCF_INTC'!$B$25*(1+$A$37) -> 73994200000 | C37: =B37*(1+$A$37) -> 103591880000 | D37: =C37*(1+$A$37) -> 145028632000 | E37: =D37*(1+$A$37) -> 203040084800 | F37: =E37*(1+$A$37) -> 284256118720 | G37: =B37*'DCF_INTC'!$B$10*(1-'DCF_INTC'!$B$14)+B37*'Inputs_INTC'!$B$31-B37*'Inputs_INTC'!$B$32-'Inputs_INTC'!$B$33*(B37-'DCF_INTC'!$B$25) -> -9.4563947e+08 | H37: =C37*'DCF_INTC'!$B$10*(1-'DCF_INTC'!$B$14)+C37*'Inputs_INTC'!$B$31-C37*'Inputs_INTC'!$B$32-'Inputs_INTC'!$B$33*(C37-B37) -> -1.3238953e+09 | I37: =D37*'DCF_INTC'!$B$10*(1-'DCF_INTC'!$B$14)+D37*'Inputs_INTC'!$B$31-D37*'Inputs_INTC'!$B$32-'Inputs_INTC'!$B$33*(D37-C37) -> -1.8534534e+09 | J37: =E37*'DCF_INTC'!$B$10*(1-'DCF_INTC'!$B$14)+E37*'Inputs_INTC'!$B$31-E37*'Inputs_INTC'!$B$32-'Inputs_INTC'!$B$33*(E37-D37) -> -2.5948347e+09 | K37: =F37*'DCF_INTC'!$B$10*(1-'DCF_INTC'!$B$14)+F37*'Inputs_INTC'!$B$31-F37*'Inputs_INTC'!$B$32-'Inputs_INTC'!$B$33*(F37-E37) -> -3.6327686e+09 | L37: =K37*(1+'Inputs_INTC'!$B$29)/('DCF_INTC'!$B$21-'Inputs_INTC'!$B$29) -> -2.9659046e+10 | M37: =SUMPRODUCT(G37:K37,1/(1+'DCF_INTC'!$B$21)^{1,2,3,4,5})+L37/(1+'DCF_INTC'!$B$21)^5 -> -2.1032385e+10 | N37: =M37-'Inputs_INTC'!$B$17+'Inputs_INTC'!$B$18 -> -5.3352385e+10 | O37: =N37/'Inputs_INTC'!$B$22 -> -10.092948
A38: Direction check: IV increases as revenue growth rises? | B38: =IF(O30<O37,"PASS (as expected)","FAIL — investigate (see note)") -> FAIL — investigate (see note) | P38: INVESTIGATED: this company's unit economics (margin*(1-tax)+D&A%-CapEx%) are structurally negative per dollar of revenue, so growing revenue faster only compounds losses — IV falls as growth rises. Mathematically correct, not a defect. See Research Outlook.
A41: TABLE 4 — Operating Margin Sensitivity (range [0%,60%]); base revenue path & WACC held fixed
A42: Margin | B42: FCF Y1 | C42: FCF Y2 | D42: FCF Y3 | E42: FCF Y4 | F42: FCF Y5 | G42: Terminal Value | H42: Enterprise Value | I42: Equity Value | J42: Intrinsic Value/Share
A43: 0 | B43: ='DCF_INTC'!$C$25*$A$43*(1-'DCF_INTC'!$B$14)+'DCF_INTC'!$C$28-'DCF_INTC'!$C$29-'DCF_INTC'!$C$30 -> -4.2753408e+08 | C43: ='DCF_INTC'!$D$25*$A$43*(1-'DCF_INTC'!$B$14)+'DCF_INTC'!$D$28-'DCF_INTC'!$D$29-'DCF_INTC'!$D$30 -> -3.8668569e+08 | D43: ='DCF_INTC'!$E$25*$A$43*(1-'DCF_INTC'!$B$14)+'DCF_INTC'!$E$28-'DCF_INTC'!$E$29-'DCF_INTC'!$E$30 -> -3.4974012e+08 | E43: ='DCF_INTC'!$F$25*$A$43*(1-'DCF_INTC'!$B$14)+'DCF_INTC'!$F$28-'DCF_INTC'!$F$29-'DCF_INTC'!$F$30 -> -3.1632449e+08 | F43: ='DCF_INTC'!$G$25*$A$43*(1-'DCF_INTC'!$B$14)+'DCF_INTC'!$G$28-'DCF_INTC'!$G$29-'DCF_INTC'!$G$30 -> -2.8610153e+08 | G43: =F43*(1+'Inputs_INTC'!$B$29)/('DCF_INTC'!$B$21-'Inputs_INTC'!$B$29) -> -2.3358213e+09 | H43: =SUMPRODUCT(B43:F43,1/(1+'DCF_INTC'!$B$21)^{1,2,3,4,5})+G43/(1+'DCF_INTC'!$B$21)^5 -> -2.3743194e+09 | I43: =H43-'Inputs_INTC'!$B$17+'Inputs_INTC'!$B$18 -> -3.4694319e+10 | J43: =I43/'Inputs_INTC'!$B$22 -> -6.5633047
A44: 0.1 | B44: ='DCF_INTC'!$C$25*$A$44*(1-'DCF_INTC'!$B$14)+'DCF_INTC'!$C$28-'DCF_INTC'!$C$29-'DCF_INTC'!$C$30 -> -3.4770856e+08 | C44: ='DCF_INTC'!$D$25*$A$44*(1-'DCF_INTC'!$B$14)+'DCF_INTC'!$D$28-'DCF_INTC'!$D$29-'DCF_INTC'!$D$30 -> -3.1448703e+08 | D44: ='DCF_INTC'!$E$25*$A$44*(1-'DCF_INTC'!$B$14)+'DCF_INTC'!$E$28-'DCF_INTC'!$E$29-'DCF_INTC'!$E$30 -> -2.8443963e+08 | E44: ='DCF_INTC'!$F$25*$A$44*(1-'DCF_INTC'!$B$14)+'DCF_INTC'!$F$28-'DCF_INTC'!$F$29-'DCF_INTC'!$F$30 -> -2.5726308e+08 | F44: ='DCF_INTC'!$G$25*$A$44*(1-'DCF_INTC'!$B$14)+'DCF_INTC'!$G$28-'DCF_INTC'!$G$29-'DCF_INTC'!$G$30 -> -2.3268309e+08 | G44: =F44*(1+'Inputs_INTC'!$B$29)/('DCF_INTC'!$B$21-'Inputs_INTC'!$B$29) -> -1.8996967e+09 | H44: =SUMPRODUCT(B44:F44,1/(1+'DCF_INTC'!$B$21)^{1,2,3,4,5})+G44/(1+'DCF_INTC'!$B$21)^5 -> -1.9310067e+09 | I44: =H44-'Inputs_INTC'!$B$17+'Inputs_INTC'!$B$18 -> -3.4251007e+10 | J44: =I44/'Inputs_INTC'!$B$22 -> -6.4794409
A45: 0.2 | B45: ='DCF_INTC'!$C$25*$A$45*(1-'DCF_INTC'!$B$14)+'DCF_INTC'!$C$28-'DCF_INTC'!$C$29-'DCF_INTC'!$C$30 -> -2.6788304e+08 | C45: ='DCF_INTC'!$D$25*$A$45*(1-'DCF_INTC'!$B$14)+'DCF_INTC'!$D$28-'DCF_INTC'!$D$29-'DCF_INTC'!$D$30 -> -2.4228838e+08 | D45: ='DCF_INTC'!$E$25*$A$45*(1-'DCF_INTC'!$B$14)+'DCF_INTC'!$E$28-'DCF_INTC'!$E$29-'DCF_INTC'!$E$30 -> -2.1913914e+08 | E45: ='DCF_INTC'!$F$25*$A$45*(1-'DCF_INTC'!$B$14)+'DCF_INTC'!$F$28-'DCF_INTC'!$F$29-'DCF_INTC'!$F$30 -> -1.9820167e+08 | F45: ='DCF_INTC'!$G$25*$A$45*(1-'DCF_INTC'!$B$14)+'DCF_INTC'!$G$28-'DCF_INTC'!$G$29-'DCF_INTC'!$G$30 -> -1.7926465e+08 | G45: =F45*(1+'Inputs_INTC'!$B$29)/('DCF_INTC'!$B$21-'Inputs_INTC'!$B$29) -> -1.4635721e+09 | H45: =SUMPRODUCT(B45:F45,1/(1+'DCF_INTC'!$B$21)^{1,2,3,4,5})+G45/(1+'DCF_INTC'!$B$21)^5 -> -1.487694e+09 | I45: =H45-'Inputs_INTC'!$B$17+'Inputs_INTC'!$B$18 -> -3.3807694e+10 | J45: =I45/'Inputs_INTC'!$B$22 -> -6.3955772
A46: 0.3 | B46: ='DCF_INTC'!$C$25*$A$46*(1-'DCF_INTC'!$B$14)+'DCF_INTC'!$C$28-'DCF_INTC'!$C$29-'DCF_INTC'!$C$30 -> -1.8805753e+08 | C46: ='DCF_INTC'!$D$25*$A$46*(1-'DCF_INTC'!$B$14)+'DCF_INTC'!$D$28-'DCF_INTC'!$D$29-'DCF_INTC'!$D$30 -> -1.7008972e+08 | D46: ='DCF_INTC'!$E$25*$A$46*(1-'DCF_INTC'!$B$14)+'DCF_INTC'!$E$28-'DCF_INTC'!$E$29-'DCF_INTC'!$E$30 -> -1.5383864e+08 | E46: ='DCF_INTC'!$F$25*$A$46*(1-'DCF_INTC'!$B$14)+'DCF_INTC'!$F$28-'DCF_INTC'!$F$29-'DCF_INTC'!$F$30 -> -1.3914026e+08 | F46: ='DCF_INTC'!$G$25*$A$46*(1-'DCF_INTC'!$B$14)+'DCF_INTC'!$G$28-'DCF_INTC'!$G$29-'DCF_INTC'!$G$30 -> -1.2584622e+08 | G46: =F46*(1+'Inputs_INTC'!$B$29)/('DCF_INTC'!$B$21-'Inputs_INTC'!$B$29) -> -1.0274474e+09 | H46: =SUMPRODUCT(B46:F46,1/(1+'DCF_INTC'!$B$21)^{1,2,3,4,5})+G46/(1+'DCF_INTC'!$B$21)^5 -> -1.0443814e+09 | I46: =H46-'Inputs_INTC'!$B$17+'Inputs_INTC'!$B$18 -> -3.3364381e+10 | J46: =I46/'Inputs_INTC'!$B$22 -> -6.3117134
A47: 0.4 | B47: ='DCF_INTC'!$C$25*$A$47*(1-'DCF_INTC'!$B$14)+'DCF_INTC'!$C$28-'DCF_INTC'!$C$29-'DCF_INTC'!$C$30 -> -1.0823201e+08 | C47: ='DCF_INTC'!$D$25*$A$47*(1-'DCF_INTC'!$B$14)+'DCF_INTC'!$D$28-'DCF_INTC'!$D$29-'DCF_INTC'!$D$30 -> -97891071 | D47: ='DCF_INTC'!$E$25*$A$47*(1-'DCF_INTC'!$B$14)+'DCF_INTC'!$E$28-'DCF_INTC'!$E$29-'DCF_INTC'!$E$30 -> -88538149 | E47: ='DCF_INTC'!$F$25*$A$47*(1-'DCF_INTC'!$B$14)+'DCF_INTC'!$F$28-'DCF_INTC'!$F$29-'DCF_INTC'!$F$30 -> -80078845 | F47: ='DCF_INTC'!$G$25*$A$47*(1-'DCF_INTC'!$B$14)+'DCF_INTC'!$G$28-'DCF_INTC'!$G$29-'DCF_INTC'!$G$30 -> -72427778 | G47: =F47*(1+'Inputs_INTC'!$B$29)/('DCF_INTC'!$B$21-'Inputs_INTC'!$B$29) -> -5.9132277e+08 | H47: =SUMPRODUCT(B47:F47,1/(1+'DCF_INTC'!$B$21)^{1,2,3,4,5})+G47/(1+'DCF_INTC'!$B$21)^5 -> -6.0106871e+08 | I47: =H47-'Inputs_INTC'!$B$17+'Inputs_INTC'!$B$18 -> -3.2921069e+10 | J47: =I47/'Inputs_INTC'!$B$22 -> -6.2278496
A48: 0.5 | B48: ='DCF_INTC'!$C$25*$A$48*(1-'DCF_INTC'!$B$14)+'DCF_INTC'!$C$28-'DCF_INTC'!$C$29-'DCF_INTC'!$C$30 -> -28406492 | C48: ='DCF_INTC'!$D$25*$A$48*(1-'DCF_INTC'!$B$14)+'DCF_INTC'!$D$28-'DCF_INTC'!$D$29-'DCF_INTC'!$D$30 -> -25692417 | D48: ='DCF_INTC'!$E$25*$A$48*(1-'DCF_INTC'!$B$14)+'DCF_INTC'!$E$28-'DCF_INTC'!$E$29-'DCF_INTC'!$E$30 -> -23237656 | E48: ='DCF_INTC'!$F$25*$A$48*(1-'DCF_INTC'!$B$14)+'DCF_INTC'!$F$28-'DCF_INTC'!$F$29-'DCF_INTC'!$F$30 -> -21017434 | F48: ='DCF_INTC'!$G$25*$A$48*(1-'DCF_INTC'!$B$14)+'DCF_INTC'!$G$28-'DCF_INTC'!$G$29-'DCF_INTC'!$G$30 -> -19009340 | G48: =F48*(1+'Inputs_INTC'!$B$29)/('DCF_INTC'!$B$21-'Inputs_INTC'!$B$29) -> -1.5519813e+08 | H48: =SUMPRODUCT(B48:F48,1/(1+'DCF_INTC'!$B$21)^{1,2,3,4,5})+G48/(1+'DCF_INTC'!$B$21)^5 -> -1.5775604e+08 | I48: =H48-'Inputs_INTC'!$B$17+'Inputs_INTC'!$B$18 -> -3.2477756e+10 | J48: =I48/'Inputs_INTC'!$B$22 -> -6.1439859
A49: 0.6 | B49: ='DCF_INTC'!$C$25*$A$49*(1-'DCF_INTC'!$B$14)+'DCF_INTC'!$C$28-'DCF_INTC'!$C$29-'DCF_INTC'!$C$30 -> 51419025 | C49: ='DCF_INTC'!$D$25*$A$49*(1-'DCF_INTC'!$B$14)+'DCF_INTC'!$D$28-'DCF_INTC'!$D$29-'DCF_INTC'!$D$30 -> 46506237 | D49: ='DCF_INTC'!$E$25*$A$49*(1-'DCF_INTC'!$B$14)+'DCF_INTC'!$E$28-'DCF_INTC'!$E$29-'DCF_INTC'!$E$30 -> 42062837 | E49: ='DCF_INTC'!$F$25*$A$49*(1-'DCF_INTC'!$B$14)+'DCF_INTC'!$F$28-'DCF_INTC'!$F$29-'DCF_INTC'!$F$30 -> 38043978 | F49: ='DCF_INTC'!$G$25*$A$49*(1-'DCF_INTC'!$B$14)+'DCF_INTC'!$G$28-'DCF_INTC'!$G$29-'DCF_INTC'!$G$30 -> 34409098 | G49: =F49*(1+'Inputs_INTC'!$B$29)/('DCF_INTC'!$B$21-'Inputs_INTC'!$B$29) -> 2.8092651e+08 | H49: =SUMPRODUCT(B49:F49,1/(1+'DCF_INTC'!$B$21)^{1,2,3,4,5})+G49/(1+'DCF_INTC'!$B$21)^5 -> 2.8555663e+08 | I49: =H49-'Inputs_INTC'!$B$17+'Inputs_INTC'!$B$18 -> -3.2034443e+10 | J49: =I49/'Inputs_INTC'!$B$22 -> -6.0601221
A50: Direction check: IV increases as operating margin rises? | B50: =IF(J43<J49,"PASS (as expected)","FAIL — investigate") -> PASS (as expected)
A53: TABLE 5 — Two-Way Sensitivity: WACC (rows) × Terminal Growth (columns) — Intrinsic Value/Share
A54: WACC \ g | B54: 0 | C54: 0.01 | D54: 0.02 | E54: 0.03 | F54: 0.04 | G54: 0.05
A55: 0.05 | B55: =IF(B$54>=$A55,"n/a",(SUMPRODUCT('DCF_INTC'!$C$31:$G$31,1/(1+$A55)^{1,2,3,4,5})+('DCF_INTC'!$G$31*(1+B$54)/($A55-B$54))/(1+$A55)^5-'Inputs_INTC'!$B$17+'Inputs_INTC'!$B$18)/'Inputs_INTC'!$B$22) -> -7.2446057 | C55: =IF(C$54>=$A55,"n/a",(SUMPRODUCT('DCF_INTC'!$C$31:$G$31,1/(1+$A55)^{1,2,3,4,5})+('DCF_INTC'!$G$31*(1+C$54)/($A55-C$54))/(1+$A55)^5-'Inputs_INTC'!$B$17+'Inputs_INTC'!$B$18)/'Inputs_INTC'!$B$22) -> -7.4653201 | D55: =IF(D$54>=$A55,"n/a",(SUMPRODUCT('DCF_INTC'!$C$31:$G$31,1/(1+$A55)^{1,2,3,4,5})+('DCF_INTC'!$G$31*(1+D$54)/($A55-D$54))/(1+$A55)^5-'Inputs_INTC'!$B$17+'Inputs_INTC'!$B$18)/'Inputs_INTC'!$B$22) -> -7.8331775 | E55: =IF(E$54>=$A55,"n/a",(SUMPRODUCT('DCF_INTC'!$C$31:$G$31,1/(1+$A55)^{1,2,3,4,5})+('DCF_INTC'!$G$31*(1+E$54)/($A55-E$54))/(1+$A55)^5-'Inputs_INTC'!$B$17+'Inputs_INTC'!$B$18)/'Inputs_INTC'!$B$22) -> -8.5688922 | F55: =IF(F$54>=$A55,"n/a",(SUMPRODUCT('DCF_INTC'!$C$31:$G$31,1/(1+$A55)^{1,2,3,4,5})+('DCF_INTC'!$G$31*(1+F$54)/($A55-F$54))/(1+$A55)^5-'Inputs_INTC'!$B$17+'Inputs_INTC'!$B$18)/'Inputs_INTC'!$B$22) -> -10.776036 | G55: =IF(G$54>=$A55,"n/a",(SUMPRODUCT('DCF_INTC'!$C$31:$G$31,1/(1+$A55)^{1,2,3,4,5})+('DCF_INTC'!$G$31*(1+G$54)/($A55-G$54))/(1+$A55)^5-'Inputs_INTC'!$B$17+'Inputs_INTC'!$B$18)/'Inputs_INTC'!$B$22) -> n/a
A56: 0.08 | B56: =IF(B$54>=$A56,"n/a",(SUMPRODUCT('DCF_INTC'!$C$31:$G$31,1/(1+$A56)^{1,2,3,4,5})+('DCF_INTC'!$G$31*(1+B$54)/($A56-B$54))/(1+$A56)^5-'Inputs_INTC'!$B$17+'Inputs_INTC'!$B$18)/'Inputs_INTC'!$B$22) -> -6.8392145 | C56: =IF(C$54>=$A56,"n/a",(SUMPRODUCT('DCF_INTC'!$C$31:$G$31,1/(1+$A56)^{1,2,3,4,5})+('DCF_INTC'!$G$31*(1+C$54)/($A56-C$54))/(1+$A56)^5-'Inputs_INTC'!$B$17+'Inputs_INTC'!$B$18)/'Inputs_INTC'!$B$22) -> -6.9096408 | D56: =IF(D$54>=$A56,"n/a",(SUMPRODUCT('DCF_INTC'!$C$31:$G$31,1/(1+$A56)^{1,2,3,4,5})+('DCF_INTC'!$G$31*(1+D$54)/($A56-D$54))/(1+$A56)^5-'Inputs_INTC'!$B$17+'Inputs_INTC'!$B$18)/'Inputs_INTC'!$B$22) -> -7.0035426 | E56: =IF(E$54>=$A56,"n/a",(SUMPRODUCT('DCF_INTC'!$C$31:$G$31,1/(1+$A56)^{1,2,3,4,5})+('DCF_INTC'!$G$31*(1+E$54)/($A56-E$54))/(1+$A56)^5-'Inputs_INTC'!$B$17+'Inputs_INTC'!$B$18)/'Inputs_INTC'!$B$22) -> -7.135005 | F56: =IF(F$54>=$A56,"n/a",(SUMPRODUCT('DCF_INTC'!$C$31:$G$31,1/(1+$A56)^{1,2,3,4,5})+('DCF_INTC'!$G$31*(1+F$54)/($A56-F$54))/(1+$A56)^5-'Inputs_INTC'!$B$17+'Inputs_INTC'!$B$18)/'Inputs_INTC'!$B$22) -> -7.3321986 | G56: =IF(G$54>=$A56,"n/a",(SUMPRODUCT('DCF_INTC'!$C$31:$G$31,1/(1+$A56)^{1,2,3,4,5})+('DCF_INTC'!$G$31*(1+G$54)/($A56-G$54))/(1+$A56)^5-'Inputs_INTC'!$B$17+'Inputs_INTC'!$B$18)/'Inputs_INTC'!$B$22) -> -7.6608547
A57: 0.11 | B57: =IF(B$54>=$A57,"n/a",(SUMPRODUCT('DCF_INTC'!$C$31:$G$31,1/(1+$A57)^{1,2,3,4,5})+('DCF_INTC'!$G$31*(1+B$54)/($A57-B$54))/(1+$A57)^5-'Inputs_INTC'!$B$17+'Inputs_INTC'!$B$18)/'Inputs_INTC'!$B$22) -> -6.6535903 | C57: =IF(C$54>=$A57,"n/a",(SUMPRODUCT('DCF_INTC'!$C$31:$G$31,1/(1+$A57)^{1,2,3,4,5})+('DCF_INTC'!$G$31*(1+C$54)/($A57-C$54))/(1+$A57)^5-'Inputs_INTC'!$B$17+'Inputs_INTC'!$B$18)/'Inputs_INTC'!$B$22) -> -6.685722 | D57: =IF(D$54>=$A57,"n/a",(SUMPRODUCT('DCF_INTC'!$C$31:$G$31,1/(1+$A57)^{1,2,3,4,5})+('DCF_INTC'!$G$31*(1+D$54)/($A57-D$54))/(1+$A57)^5-'Inputs_INTC'!$B$17+'Inputs_INTC'!$B$18)/'Inputs_INTC'!$B$22) -> -6.724994 | E57: =IF(E$54>=$A57,"n/a",(SUMPRODUCT('DCF_INTC'!$C$31:$G$31,1/(1+$A57)^{1,2,3,4,5})+('DCF_INTC'!$G$31*(1+E$54)/($A57-E$54))/(1+$A57)^5-'Inputs_INTC'!$B$17+'Inputs_INTC'!$B$18)/'Inputs_INTC'!$B$22) -> -6.774084 | F57: =IF(F$54>=$A57,"n/a",(SUMPRODUCT('DCF_INTC'!$C$31:$G$31,1/(1+$A57)^{1,2,3,4,5})+('DCF_INTC'!$G$31*(1+F$54)/($A57-F$54))/(1+$A57)^5-'Inputs_INTC'!$B$17+'Inputs_INTC'!$B$18)/'Inputs_INTC'!$B$22) -> -6.8371998 | G57: =IF(G$54>=$A57,"n/a",(SUMPRODUCT('DCF_INTC'!$C$31:$G$31,1/(1+$A57)^{1,2,3,4,5})+('DCF_INTC'!$G$31*(1+G$54)/($A57-G$54))/(1+$A57)^5-'Inputs_INTC'!$B$17+'Inputs_INTC'!$B$18)/'Inputs_INTC'!$B$22) -> -6.9213542
A58: 0.14 | B58: =IF(B$54>=$A58,"n/a",(SUMPRODUCT('DCF_INTC'!$C$31:$G$31,1/(1+$A58)^{1,2,3,4,5})+('DCF_INTC'!$G$31*(1+B$54)/($A58-B$54))/(1+$A58)^5-'Inputs_INTC'!$B$17+'Inputs_INTC'!$B$18)/'Inputs_INTC'!$B$22) -> -6.5465929 | C58: =IF(C$54>=$A58,"n/a",(SUMPRODUCT('DCF_INTC'!$C$31:$G$31,1/(1+$A58)^{1,2,3,4,5})+('DCF_INTC'!$G$31*(1+C$54)/($A58-C$54))/(1+$A58)^5-'Inputs_INTC'!$B$17+'Inputs_INTC'!$B$18)/'Inputs_INTC'!$B$22) -> -6.5640482 | D58: =IF(D$54>=$A58,"n/a",(SUMPRODUCT('DCF_INTC'!$C$31:$G$31,1/(1+$A58)^{1,2,3,4,5})+('DCF_INTC'!$G$31*(1+D$54)/($A58-D$54))/(1+$A58)^5-'Inputs_INTC'!$B$17+'Inputs_INTC'!$B$18)/'Inputs_INTC'!$B$22) -> -6.5844127 | E58: =IF(E$54>=$A58,"n/a",(SUMPRODUCT('DCF_INTC'!$C$31:$G$31,1/(1+$A58)^{1,2,3,4,5})+('DCF_INTC'!$G$31*(1+E$54)/($A58-E$54))/(1+$A58)^5-'Inputs_INTC'!$B$17+'Inputs_INTC'!$B$18)/'Inputs_INTC'!$B$22) -> -6.6084799 | F58: =IF(F$54>=$A58,"n/a",(SUMPRODUCT('DCF_INTC'!$C$31:$G$31,1/(1+$A58)^{1,2,3,4,5})+('DCF_INTC'!$G$31*(1+F$54)/($A58-F$54))/(1+$A58)^5-'Inputs_INTC'!$B$17+'Inputs_INTC'!$B$18)/'Inputs_INTC'!$B$22) -> -6.6373604 | G58: =IF(G$54>=$A58,"n/a",(SUMPRODUCT('DCF_INTC'!$C$31:$G$31,1/(1+$A58)^{1,2,3,4,5})+('DCF_INTC'!$G$31*(1+G$54)/($A58-G$54))/(1+$A58)^5-'Inputs_INTC'!$B$17+'Inputs_INTC'!$B$18)/'Inputs_INTC'!$B$22) -> -6.6726589
A59: 0.17 | B59: =IF(B$54>=$A59,"n/a",(SUMPRODUCT('DCF_INTC'!$C$31:$G$31,1/(1+$A59)^{1,2,3,4,5})+('DCF_INTC'!$G$31*(1+B$54)/($A59-B$54))/(1+$A59)^5-'Inputs_INTC'!$B$17+'Inputs_INTC'!$B$18)/'Inputs_INTC'!$B$22) -> -6.4766928 | C59: =IF(C$54>=$A59,"n/a",(SUMPRODUCT('DCF_INTC'!$C$31:$G$31,1/(1+$A59)^{1,2,3,4,5})+('DCF_INTC'!$G$31*(1+C$54)/($A59-C$54))/(1+$A59)^5-'Inputs_INTC'!$B$17+'Inputs_INTC'!$B$18)/'Inputs_INTC'!$B$22) -> -6.4872199 | D59: =IF(D$54>=$A59,"n/a",(SUMPRODUCT('DCF_INTC'!$C$31:$G$31,1/(1+$A59)^{1,2,3,4,5})+('DCF_INTC'!$G$31*(1+D$54)/($A59-D$54))/(1+$A59)^5-'Inputs_INTC'!$B$17+'Inputs_INTC'!$B$18)/'Inputs_INTC'!$B$22) -> -6.4991505 | E59: =IF(E$54>=$A59,"n/a",(SUMPRODUCT('DCF_INTC'!$C$31:$G$31,1/(1+$A59)^{1,2,3,4,5})+('DCF_INTC'!$G$31*(1+E$54)/($A59-E$54))/(1+$A59)^5-'Inputs_INTC'!$B$17+'Inputs_INTC'!$B$18)/'Inputs_INTC'!$B$22) -> -6.5127855 | F59: =IF(F$54>=$A59,"n/a",(SUMPRODUCT('DCF_INTC'!$C$31:$G$31,1/(1+$A59)^{1,2,3,4,5})+('DCF_INTC'!$G$31*(1+F$54)/($A59-F$54))/(1+$A59)^5-'Inputs_INTC'!$B$17+'Inputs_INTC'!$B$18)/'Inputs_INTC'!$B$22) -> -6.5285182 | G59: =IF(G$54>=$A59,"n/a",(SUMPRODUCT('DCF_INTC'!$C$31:$G$31,1/(1+$A59)^{1,2,3,4,5})+('DCF_INTC'!$G$31*(1+G$54)/($A59-G$54))/(1+$A59)^5-'Inputs_INTC'!$B$17+'Inputs_INTC'!$B$18)/'Inputs_INTC'!$B$22) -> -6.546873
A60: 0.2 | B60: =IF(B$54>=$A60,"n/a",(SUMPRODUCT('DCF_INTC'!$C$31:$G$31,1/(1+$A60)^{1,2,3,4,5})+('DCF_INTC'!$G$31*(1+B$54)/($A60-B$54))/(1+$A60)^5-'Inputs_INTC'!$B$17+'Inputs_INTC'!$B$18)/'Inputs_INTC'!$B$22) -> -6.4272658 | C60: =IF(C$54>=$A60,"n/a",(SUMPRODUCT('DCF_INTC'!$C$31:$G$31,1/(1+$A60)^{1,2,3,4,5})+('DCF_INTC'!$G$31*(1+C$54)/($A60-C$54))/(1+$A60)^5-'Inputs_INTC'!$B$17+'Inputs_INTC'!$B$18)/'Inputs_INTC'!$B$22) -> -6.4340753 | D60: =IF(D$54>=$A60,"n/a",(SUMPRODUCT('DCF_INTC'!$C$31:$G$31,1/(1+$A60)^{1,2,3,4,5})+('DCF_INTC'!$G$31*(1+D$54)/($A60-D$54))/(1+$A60)^5-'Inputs_INTC'!$B$17+'Inputs_INTC'!$B$18)/'Inputs_INTC'!$B$22) -> -6.4416413 | E60: =IF(E$54>=$A60,"n/a",(SUMPRODUCT('DCF_INTC'!$C$31:$G$31,1/(1+$A60)^{1,2,3,4,5})+('DCF_INTC'!$G$31*(1+E$54)/($A60-E$54))/(1+$A60)^5-'Inputs_INTC'!$B$17+'Inputs_INTC'!$B$18)/'Inputs_INTC'!$B$22) -> -6.4500974 | F60: =IF(F$54>=$A60,"n/a",(SUMPRODUCT('DCF_INTC'!$C$31:$G$31,1/(1+$A60)^{1,2,3,4,5})+('DCF_INTC'!$G$31*(1+F$54)/($A60-F$54))/(1+$A60)^5-'Inputs_INTC'!$B$17+'Inputs_INTC'!$B$18)/'Inputs_INTC'!$B$22) -> -6.4596105 | G60: =IF(G$54>=$A60,"n/a",(SUMPRODUCT('DCF_INTC'!$C$31:$G$31,1/(1+$A60)^{1,2,3,4,5})+('DCF_INTC'!$G$31*(1+G$54)/($A60-G$54))/(1+$A60)^5-'Inputs_INTC'!$B$17+'Inputs_INTC'!$B$18)/'Inputs_INTC'!$B$22) -> -6.4703921

Sheet Inputs_VZ
A1: Inputs — VZ (VERIZON COMMUNICATIONS INC) | Frozen 2026-08-17T17:23:45.328585+00:00
A2: Profile: Meaningfully leveraged (recommended 4th profile) | CIK 0000732712 | All USD values are actual dollars (not thousands/millions) unless noted.
A4: SECTION 1 — Historical Annual Data (SEC EDGAR, frozen)
A5: Fiscal Year End | B5: Revenue (USD) | C5: EBIT / Operating Income (USD) | D5: Provenance
A6: 44561 | B6: 133613000000 | C6: 32448000000 | D6: XBRL tag: Revenues
A7: 44926 | B7: 136835000000 | C7: 30467000000 | D7: XBRL tag: Revenues
A8: 45291 | B8: 133974000000 | C8: 22877000000 | D8: XBRL tag: Revenues
A9: 45657 | B9: 134788000000 | C9: 28686000000 | D9: XBRL tag: Revenues
A10: 46022 | B10: 138191000000 | C10: 29259000000 | D10: XBRL tag: Revenues
A12: SECTION 2 — Latest-Year Facts (SEC EDGAR, frozen)
A13: Latest Complete Fiscal Year End | B13: 46022
A14: Pretax Income (USD) | B14: 22672000000
A15: Tax Provision (USD) | B15: 5064000000
A16: Interest Expense (USD) | B16: 6694000000 | D16: Method: reported; tag: InterestExpenseNonoperating
A17: Total Debt (USD) | B17: 158150000000 | D17: Total Debt = DebtLongtermAndShorttermCombinedAmount (reported directly, not summed) = $158,150,000,000 | Full per-component provenance (XBRL tag, accession, filed date, source URL): see Sources sheet.
A18: Cash & Equivalents (USD) | B18: 19048000000
A20: SECTION 3 — Market Data (Yahoo Finance via yfinance, frozen)
A21: Current Price (USD/share) | B21: 48.155
A22: Shares Outstanding | B22: 4154775202
A23: Beta (levered equity) | B23: 0.231
A24: Sector (GICS) | B24: Communication Services
A26: SECTION 4 — Assumptions (shared across companies unless noted; assumptions-register.md)
A27: Risk-free rate (A-001) | B27: 0.04
A28: Market risk premium (A-009) | B28: 0.055
A29: Terminal growth rate, base case (A-003) | B29: 0.025
A30: Projection years | B30: 5
A31: D&A % of revenue (A-004) | B31: 0.03
A32: CapEx % of revenue (A-004) | B32: 0.04
A33: ΔNWC % of revenue change (A-004) | B33: 0.01
A34: WACC clamp — minimum (A-006) | B34: 0.05
A35: WACC clamp — maximum (A-006) | B35: 0.2
A36: Terminal growth clamp — minimum | B36: 0
A37: Terminal growth clamp — maximum | B37: 0.05
A38: Historical revenue growth cap (A-002) | B38: 0.25

Sheet DCF_VZ
A1: DCF Valuation — VZ (VERIZON COMMUNICATIONS INC) [V2 — Track A Phase 2C]
A2: Every formula below is entered independently from docs/model-specifications/dcf.md and wacc-capm.md prose/equations — never copied from src/dcf_model/dcf.py. V2: years_elapsed now uses actual fiscal-period-end date subtraction, per the Track A Phase 2C specification clarification (A-028/L-019) — see row below.
A4: SECTION 1 — Historical Revenue CAGR & Operating Margin [dcf.md §Historical revenue-growth and operating-margin derivation]
A5: Years elapsed = (latest fiscal date − earliest fiscal date) / 365.25 [V2; A-028] | B5: =('Inputs_VZ'!$A$10-'Inputs_VZ'!$A$6)/365.25 -> 4 | D5: Spec: dcf.md — years_elapsed is ACTUAL elapsed calendar days between the earliest- and latest-dated valid observations / 365.25, never (periods−1) (A-028; Track A Phase 2C, resolving the ambiguity Phase 2B found).
A6: Diagnostic — naive (N periods − 1) years [V1's convention; NOT used below] | B6: 4 | C6: REGULAR | D6: Fiscal calendar is evenly spaced for this company — actual years_elapsed equals the naive (N periods − 1) count to within floating-point noise, so V1 and V2 agree here by coincidence, not because (periods − 1) is a generally correct convention.
A8: Raw Revenue CAGR = (Rev_latest/Rev_earliest)^(1/years) − 1 | B8: =('Inputs_VZ'!$B$10/'Inputs_VZ'!$B$6)^(1/B5)-1 -> 0.0084578735
A9: Capped Revenue CAGR (cap A-002; NOT floored below) | B9: =MIN(B8,'Inputs_VZ'!$B$38) -> 0.0084578735 | D9: Spec: dcf.md — capped at MAX_REVENUE_GROWTH_RATE=25%, unbounded below (A-002)
A10: Average Historical Operating Margin = simple average of EBIT_t/Revenue_t | B10: =('Inputs_VZ'!$C$6/'Inputs_VZ'!$B$6+'Inputs_VZ'!$C$7/'Inputs_VZ'!$B$7+'Inputs_VZ'!$C$8/'Inputs_VZ'!$B$8+'Inputs_VZ'!$C$9/'Inputs_VZ'!$B$9+'Inputs_VZ'!$C$10/'Inputs_VZ'!$B$10)/5 -> 0.21216289
A12: SECTION 2 — WACC via CAPM [wacc-capm.md §Formula]
A13: Market Capitalization = Price × Shares Outstanding | B13: ='Inputs_VZ'!$B$21*'Inputs_VZ'!$B$22 -> 2.000732e+11
A14: Effective Tax Rate = Tax Provision / Pretax Income (latest FY) | B14: ='Inputs_VZ'!$B$15/'Inputs_VZ'!$B$14 -> 0.22335921 | D14: Method: derived. Spec: wacc-capm.md — derived as tax_provision/pretax_income, valid range [0,1); DEFAULT_TAX_RATE=21% only on missing data.
A15: Cost of Debt = |Interest Expense| / Total Debt (latest FY) | B15: =ABS('Inputs_VZ'!$B$16)/'Inputs_VZ'!$B$17 -> 0.042326905
A16: Cost of Equity (CAPM) = Rf + Beta × MRP | B16: ='Inputs_VZ'!$B$27+'Inputs_VZ'!$B$23*'Inputs_VZ'!$B$28 -> 0.052705
A17: After-Tax Cost of Debt = Cost of Debt × (1 − Tax Rate) | B17: =B15*(1-B14) -> 0.032872801
A18: Weight of Equity = MktCap / (MktCap + Total Debt) | B18: =B13/(B13+'Inputs_VZ'!$B$17) -> 0.55851547
A19: Weight of Debt = Total Debt / (MktCap + Total Debt) | B19: ='Inputs_VZ'!$B$17/(B13+'Inputs_VZ'!$B$17) -> 0.44148453
A20: Raw WACC = We×Re + Wd×Rd(after-tax) | B20: =B18*B16+B19*B17 -> 0.043949391
A21: Final WACC — clamped to [5%,20%] (A-006), via MEDIAN(raw,min,max) | B21: =MEDIAN(B20,'Inputs_VZ'!$B$34,'Inputs_VZ'!$B$35) -> 0.05 | D21: MEDIAN(x,min,max) is a standard single-formula clamp: returns min if x<min, max if x>max, else x.
A23: SECTION 3 — 5-Year Free Cash Flow Projection [dcf.md §Free Cash Flow projection]
B24: Year 0 (base, actual) | C24: Year 1 | D24: Year 2 | E24: Year 3 | F24: Year 4 | G24: Year 5
A25: Revenue = Revenue_(t-1) × (1 + growth) | B25: ='Inputs_VZ'!$B$10 -> 138191000000 | C25: =B25*(1+$B$9) -> 1.393598e+11 | D25: =C25*(1+$B$9) -> 1.4053849e+11 | E25: =D25*(1+$B$9) -> 1.4172715e+11 | F25: =E25*(1+$B$9) -> 1.4292586e+11 | G25: =F25*(1+$B$9) -> 1.4413471e+11
A26: EBIT = Revenue × Operating Margin | C26: =C25*$B$10 -> 2.9566978e+10 | D26: =D25*$B$10 -> 2.9817052e+10 | E26: =E25*$B$10 -> 3.0069241e+10 | F26: =F25*$B$10 -> 3.0323563e+10 | G26: =G25*$B$10 -> 3.0580036e+10
A27: NOPAT = EBIT × (1 − Tax Rate) | C27: =C26*(1-$B$14) -> 2.2962921e+10 | D27: =D26*(1-$B$14) -> 2.3157139e+10 | E27: =E26*(1-$B$14) -> 2.3352999e+10 | F27: =F26*(1-$B$14) -> 2.3550516e+10 | G27: =G26*(1-$B$14) -> 2.3749703e+10
A28: D&A = Revenue × D&A% (A-004) | C28: =C25*'Inputs_VZ'!$B$31 -> 4.1807941e+09 | D28: =D25*'Inputs_VZ'!$B$31 -> 4.2161547e+09 | E28: =E25*'Inputs_VZ'!$B$31 -> 4.2518144e+09 | F28: =F25*'Inputs_VZ'!$B$31 -> 4.2877757e+09 | G28: =G25*'Inputs_VZ'!$B$31 -> 4.3240412e+09
A29: CapEx = Revenue × CapEx% (A-004) | C29: =C25*'Inputs_VZ'!$B$32 -> 5.5743921e+09 | D29: =D25*'Inputs_VZ'!$B$32 -> 5.6215396e+09 | E29: =E25*'Inputs_VZ'!$B$32 -> 5.6690859e+09 | F29: =F25*'Inputs_VZ'!$B$32 -> 5.7170343e+09 | G29: =G25*'Inputs_VZ'!$B$32 -> 5.7653882e+09
A30: ΔNWC = NWC% × (Revenue_t − Revenue_(t-1)) (A-004) | C30: ='Inputs_VZ'!$B$33*(C25-B25) -> 11688020 | D30: ='Inputs_VZ'!$B$33*(D25-C25) -> 11786876 | E30: ='Inputs_VZ'!$B$33*(E25-D25) -> 11886568 | F30: ='Inputs_VZ'!$B$33*(F25-E25) -> 11987103 | G30: ='Inputs_VZ'!$B$33*(G25-F25) -> 12088488
A31: Unlevered FCF = NOPAT + D&A − CapEx − ΔNWC | C31: =C27+C28-C29-C30 -> 2.1557635e+10 | D31: =D27+D28-D29-D30 -> 2.1739967e+10 | E31: =E27+E28-E29-E30 -> 2.1923841e+10 | F31: =F27+F28-F29-F30 -> 2.210927e+10 | G31: =G27+G28-G29-G30 -> 2.2296268e+10
A33: SECTION 4 — Terminal Value (Gordon Growth) [dcf.md §Terminal value]
A34: Terminal Value = FCF_Y5 × (1+g) / (WACC − g) | B34: =G31*(1+'Inputs_VZ'!$B$29)/(B21-'Inputs_VZ'!$B$29) -> 9.1414697e+11
A35: Check: Final WACC > Terminal Growth Rate? | B35: =IF(B21>'Inputs_VZ'!$B$29,"PASS","FAIL") -> PASS
A37: SECTION 5 — Discounting & Enterprise-to-Equity Bridge [dcf.md §Discounting and the Enterprise-to-Equity bridge]
A38: PV(FCF_t) = FCF_t / (1+WACC)^t | C38: =C31/(1+$B$21)^1 -> 2.0531081e+10 | D38: =D31/(1+$B$21)^2 -> 1.9718791e+10 | E38: =E31/(1+$B$21)^3 -> 1.8938638e+10 | F38: =F31/(1+$B$21)^4 -> 1.8189351e+10 | G38: =G31/(1+$B$21)^5 -> 1.7469709e+10
A39: Sum of PV(FCF Years 1-5) | B39: =SUM(C38:G38) -> 9.4847571e+10
A40: PV(Terminal Value) = TV / (1+WACC)^5 | B40: =B34/(1+B21)^5 -> 7.1625807e+11
A41: Enterprise Value = Sum PV(FCF) + PV(Terminal Value) | B41: =B39+B40 -> 8.1110564e+11
A42: Equity Value = Enterprise Value − Total Debt + Cash | B42: =B41-'Inputs_VZ'!$B$17+'Inputs_VZ'!$B$18 -> 6.7200364e+11
A43: Intrinsic Value per Share = Equity Value / Shares Outstanding | B43: =B42/'Inputs_VZ'!$B$22 -> 161.74248
A44: Current Price / Intrinsic Value (descriptive ratio, NOT a recommendation) | B44: ='Inputs_VZ'!$B$21/B43 -> 0.29772636
A46: SECTION 6 — Validation Checks (local to this company)
A47: WACC within documented clamp [5%,20%]? | B47: =IF(AND(B21>='Inputs_VZ'!$B$34,B21<='Inputs_VZ'!$B$35),"PASS","FAIL") -> PASS
A48: Enterprise Value is a finite number? | B48: =IF(ISNUMBER(B41),"PASS","FAIL") -> PASS
A49: Intrinsic Value per Share is a finite number? | B49: =IF(ISNUMBER(B43),"PASS","FAIL") -> PASS
A50: Intrinsic Value per Share is positive? | B50: =IF(B43>0,"PASS","FAIL") -> PASS
A51: Effective tax rate within valid [0,1) range? | B51: =IF(AND(B14>=0,B14<1),"PASS","FAIL") -> PASS
A52: Final WACC exceeds terminal growth rate? | B52: =IF(B21>'Inputs_VZ'!$B$29,"PASS","FAIL") -> PASS

Sheet Sensitivity_VZ
A1: Sensitivity Analysis — VZ
A2: One variable at a time, other inputs held at base case. Per docs/independent-validation-plan.md §Sensitivity tables.
A4: TABLE 1 — WACC Sensitivity (range [5%,20%], base FCF path held fixed) [dcf.md Terminal Value + discounting]
A5: WACC | B5: Terminal Value | C5: Enterprise Value | D5: Equity Value | E5: Intrinsic Value/Share
A6: 0.05 | B6: =IF($A$6<='Inputs_VZ'!$B$29,"n/a (WACC<=g)",'DCF_VZ'!$G$31*(1+'Inputs_VZ'!$B$29)/($A$6-'Inputs_VZ'!$B$29)) -> 9.1414697e+11 | C6: =IF(B6="n/a (WACC<=g)","n/a",SUMPRODUCT('DCF_VZ'!$C$31:$G$31,1/(1+$A$6)^{1,2,3,4,5})+B6/(1+$A$6)^5) -> 8.1110564e+11 | D6: =IF(C6="n/a","n/a",C6-'Inputs_VZ'!$B$17+'Inputs_VZ'!$B$18) -> 6.7200364e+11 | E6: =IF(D6="n/a","n/a",D6/'Inputs_VZ'!$B$22) -> 161.74248
A7: 0.075 | B7: =IF($A$7<='Inputs_VZ'!$B$29,"n/a (WACC<=g)",'DCF_VZ'!$G$31*(1+'Inputs_VZ'!$B$29)/($A$7-'Inputs_VZ'!$B$29)) -> 4.5707348e+11 | C7: =IF(B7="n/a (WACC<=g)","n/a",SUMPRODUCT('DCF_VZ'!$C$31:$G$31,1/(1+$A$7)^{1,2,3,4,5})+B7/(1+$A$7)^5) -> 4.0697832e+11 | D7: =IF(C7="n/a","n/a",C7-'Inputs_VZ'!$B$17+'Inputs_VZ'!$B$18) -> 2.6787632e+11 | E7: =IF(D7="n/a","n/a",D7/'Inputs_VZ'!$B$22) -> 64.474323
A8: 0.1 | B8: =IF($A$8<='Inputs_VZ'!$B$29,"n/a (WACC<=g)",'DCF_VZ'!$G$31*(1+'Inputs_VZ'!$B$29)/($A$8-'Inputs_VZ'!$B$29)) -> 3.0471566e+11 | C8: =IF(B8="n/a (WACC<=g)","n/a",SUMPRODUCT('DCF_VZ'!$C$31:$G$31,1/(1+$A$8)^{1,2,3,4,5})+B8/(1+$A$8)^5) -> 2.7218608e+11 | D8: =IF(C8="n/a","n/a",C8-'Inputs_VZ'!$B$17+'Inputs_VZ'!$B$18) -> 1.3308408e+11 | E8: =IF(D8="n/a","n/a",D8/'Inputs_VZ'!$B$22) -> 32.031595
A9: 0.125 | B9: =IF($A$9<='Inputs_VZ'!$B$29,"n/a (WACC<=g)",'DCF_VZ'!$G$31*(1+'Inputs_VZ'!$B$29)/($A$9-'Inputs_VZ'!$B$29)) -> 2.2853674e+11 | C9: =IF(B9="n/a (WACC<=g)","n/a",SUMPRODUCT('DCF_VZ'!$C$31:$G$31,1/(1+$A$9)^{1,2,3,4,5})+B9/(1+$A$9)^5) -> 2.0473462e+11 | D9: =IF(C9="n/a","n/a",C9-'Inputs_VZ'!$B$17+'Inputs_VZ'!$B$18) -> 6.5632624e+10 | E9: =IF(D9="n/a","n/a",D9/'Inputs_VZ'!$B$22) -> 15.796913
A10: 0.15 | B10: =IF($A$10<='Inputs_VZ'!$B$29,"n/a (WACC<=g)",'DCF_VZ'!$G$31*(1+'Inputs_VZ'!$B$29)/($A$10-'Inputs_VZ'!$B$29)) -> 1.8282939e+11 | C10: =IF(B10="n/a (WACC<=g)","n/a",SUMPRODUCT('DCF_VZ'!$C$31:$G$31,1/(1+$A$10)^{1,2,3,4,5})+B10/(1+$A$10)^5) -> 1.6422434e+11 | D10: =IF(C10="n/a","n/a",C10-'Inputs_VZ'!$B$17+'Inputs_VZ'!$B$18) -> 2.5122343e+10 | E10: =IF(D10="n/a","n/a",D10/'Inputs_VZ'!$B$22) -> 6.0466191
A11: 0.175 | B11: =IF($A$11<='Inputs_VZ'!$B$29,"n/a (WACC<=g)",'DCF_VZ'!$G$31*(1+'Inputs_VZ'!$B$29)/($A$11-'Inputs_VZ'!$B$29)) -> 1.5235783e+11 | C11: =IF(B11="n/a (WACC<=g)","n/a",SUMPRODUCT('DCF_VZ'!$C$31:$G$31,1/(1+$A$11)^{1,2,3,4,5})+B11/(1+$A$11)^5) -> 1.3718817e+11 | D11: =IF(C11="n/a","n/a",C11-'Inputs_VZ'!$B$17+'Inputs_VZ'!$B$18) -> -1.9138342e+09 | E11: =IF(D11="n/a","n/a",D11/'Inputs_VZ'!$B$22) -> -0.46063484
A12: 0.2 | B12: =IF($A$12<='Inputs_VZ'!$B$29,"n/a (WACC<=g)",'DCF_VZ'!$G$31*(1+'Inputs_VZ'!$B$29)/($A$12-'Inputs_VZ'!$B$29)) -> 1.3059242e+11 | C12: =IF(B12="n/a (WACC<=g)","n/a",SUMPRODUCT('DCF_VZ'!$C$31:$G$31,1/(1+$A$12)^{1,2,3,4,5})+B12/(1+$A$12)^5) -> 1.178541e+11 | D12: =IF(C12="n/a","n/a",C12-'Inputs_VZ'!$B$17+'Inputs_VZ'!$B$18) -> -2.1247897e+10 | E12: =IF(D12="n/a","n/a",D12/'Inputs_VZ'!$B$22) -> -5.1140905
A13: Direction check: IV decreases as WACC rises? | B13: =IF(E6>E12,"PASS (as expected)","FAIL — investigate (see note)") -> PASS (as expected)
A16: TABLE 2 — Terminal Growth Rate Sensitivity (range [0%,5%]); invalid where g>=WACC
A17: Terminal Growth g | B17: Terminal Value | C17: Enterprise Value | D17: Equity Value | E17: Intrinsic Value/Share
A18: 0 | B18: =IF($A$18>='DCF_VZ'!$B$21,"n/a (g>=WACC)",'DCF_VZ'!$G$31*(1+$A$18)/('DCF_VZ'!$B$21-$A$18)) -> 4.4592535e+11 | C18: =IF(B18="n/a (g>=WACC)","n/a",'DCF_VZ'!$B$39+B18/(1+'DCF_VZ'!$B$21)^5) -> 4.4424175e+11 | D18: =IF(C18="n/a","n/a",C18-'Inputs_VZ'!$B$17+'Inputs_VZ'!$B$18) -> 3.0513975e+11 | E18: =IF(D18="n/a","n/a",D18/'Inputs_VZ'!$B$22) -> 73.443143
A19: 0.01 | B19: =IF($A$19>='DCF_VZ'!$B$21,"n/a (g>=WACC)",'DCF_VZ'!$G$31*(1+$A$19)/('DCF_VZ'!$B$21-$A$19)) -> 5.6298075e+11 | C19: =IF(B19="n/a (g>=WACC)","n/a",'DCF_VZ'!$B$39+B19/(1+'DCF_VZ'!$B$21)^5) -> 5.3595772e+11 | D19: =IF(C19="n/a","n/a",C19-'Inputs_VZ'!$B$17+'Inputs_VZ'!$B$18) -> 3.9685572e+11 | E19: =IF(D19="n/a","n/a",D19/'Inputs_VZ'!$B$22) -> 95.517977
A20: 0.02 | B20: =IF($A$20>='DCF_VZ'!$B$21,"n/a (g>=WACC)",'DCF_VZ'!$G$31*(1+$A$20)/('DCF_VZ'!$B$21-$A$20)) -> 7.580731e+11 | C20: =IF(B20="n/a (g>=WACC)","n/a",'DCF_VZ'!$B$39+B20/(1+'DCF_VZ'!$B$21)^5) -> 6.8881768e+11 | D20: =IF(C20="n/a","n/a",C20-'Inputs_VZ'!$B$17+'Inputs_VZ'!$B$18) -> 5.4971568e+11 | E20: =IF(D20="n/a","n/a",D20/'Inputs_VZ'!$B$22) -> 132.30937
A21: 0.025 | B21: =IF($A$21>='DCF_VZ'!$B$21,"n/a (g>=WACC)",'DCF_VZ'!$G$31*(1+$A$21)/('DCF_VZ'!$B$21-$A$21)) -> 9.1414697e+11 | C21: =IF(B21="n/a (g>=WACC)","n/a",'DCF_VZ'!$B$39+B21/(1+'DCF_VZ'!$B$21)^5) -> 8.1110564e+11 | D21: =IF(C21="n/a","n/a",C21-'Inputs_VZ'!$B$17+'Inputs_VZ'!$B$18) -> 6.7200364e+11 | E21: =IF(D21="n/a","n/a",D21/'Inputs_VZ'!$B$22) -> 161.74248
A22: 0.03 | B22: =IF($A$22>='DCF_VZ'!$B$21,"n/a (g>=WACC)",'DCF_VZ'!$G$31*(1+$A$22)/('DCF_VZ'!$B$21-$A$22)) -> 1.1482578e+12 | C22: =IF(B22="n/a (g>=WACC)","n/a",'DCF_VZ'!$B$39+B22/(1+'DCF_VZ'!$B$21)^5) -> 9.9453759e+11 | D22: =IF(C22="n/a","n/a",C22-'Inputs_VZ'!$B$17+'Inputs_VZ'!$B$18) -> 8.5543559e+11 | E22: =IF(D22="n/a","n/a",D22/'Inputs_VZ'!$B$22) -> 205.89215
A23: 0.04 | B23: =IF($A$23>='DCF_VZ'!$B$21,"n/a (g>=WACC)",'DCF_VZ'!$G$31*(1+$A$23)/('DCF_VZ'!$B$21-$A$23)) -> 2.3188118e+12 | C23: =IF(B23="n/a (g>=WACC)","n/a",'DCF_VZ'!$B$39+B23/(1+'DCF_VZ'!$B$21)^5) -> 1.9116973e+12 | D23: =IF(C23="n/a","n/a",C23-'Inputs_VZ'!$B$17+'Inputs_VZ'!$B$18) -> 1.7725953e+12 | E23: =IF(D23="n/a","n/a",D23/'Inputs_VZ'!$B$22) -> 426.64049
A24: 0.05 | B24: =IF($A$24>='DCF_VZ'!$B$21,"n/a (g>=WACC)",'DCF_VZ'!$G$31*(1+$A$24)/('DCF_VZ'!$B$21-$A$24)) -> n/a | C24: =IF(B24="n/a (g>=WACC)","n/a",'DCF_VZ'!$B$39+B24/(1+'DCF_VZ'!$B$21)^5) -> n/a | D24: =IF(C24="n/a","n/a",C24-'Inputs_VZ'!$B$17+'Inputs_VZ'!$B$18) -> n/a | E24: =IF(D24="n/a","n/a",D24/'Inputs_VZ'!$B$22) -> n/a
A25: Direction check: IV increases as terminal growth rises (where valid)? | B25: =IF(E18<E23,"PASS (as expected)","FAIL — investigate (see note)") -> PASS (as expected)
A28: TABLE 3 — Revenue Growth Sensitivity (range [-10%,40%]); base WACC & margin held fixed
A29: Growth g | B29: Rev Y1 | C29: Rev Y2 | D29: Rev Y3 | E29: Rev Y4 | F29: Rev Y5 | G29: FCF Y1 | H29: FCF Y2 | I29: FCF Y3 | J29: FCF Y4 | K29: FCF Y5 | L29: Terminal Value | M29: Enterprise Value | N29: Equity Value | O29: Intrinsic Value/Share
A30: -0.1 | B30: ='DCF_VZ'!$B$25*(1+$A$30) -> 124371900000 | C30: =B30*(1+$A$30) -> 111934710000 | D30: =C30*(1+$A$30) -> 100741239000 | E30: =D30*(1+$A$30) -> 90667115100 | F30: =E30*(1+$A$30) -> 81600403590 | G30: =B30*'DCF_VZ'!$B$10*(1-'DCF_VZ'!$B$14)+B30*'Inputs_VZ'!$B$31-B30*'Inputs_VZ'!$B$32-'Inputs_VZ'!$B$33*(B30-'DCF_VZ'!$B$25) -> 1.9387772e+10 | H30: =C30*'DCF_VZ'!$B$10*(1-'DCF_VZ'!$B$14)+C30*'Inputs_VZ'!$B$31-C30*'Inputs_VZ'!$B$32-'Inputs_VZ'!$B$33*(C30-B30) -> 1.7448994e+10 | I30: =D30*'DCF_VZ'!$B$10*(1-'DCF_VZ'!$B$14)+D30*'Inputs_VZ'!$B$31-D30*'Inputs_VZ'!$B$32-'Inputs_VZ'!$B$33*(D30-C30) -> 1.5704095e+10 | J30: =E30*'DCF_VZ'!$B$10*(1-'DCF_VZ'!$B$14)+E30*'Inputs_VZ'!$B$31-E30*'Inputs_VZ'!$B$32-'Inputs_VZ'!$B$33*(E30-D30) -> 1.4133685e+10 | K30: =F30*'DCF_VZ'!$B$10*(1-'DCF_VZ'!$B$14)+F30*'Inputs_VZ'!$B$31-F30*'Inputs_VZ'!$B$32-'Inputs_VZ'!$B$33*(F30-E30) -> 1.2720317e+10 | L30: =K30*(1+'Inputs_VZ'!$B$29)/('DCF_VZ'!$B$21-'Inputs_VZ'!$B$29) -> 5.2153299e+11 | M30: =SUMPRODUCT(G30:K30,1/(1+'DCF_VZ'!$B$21)^{1,2,3,4,5})+L30/(1+'DCF_VZ'!$B$21)^5 -> 4.7808635e+11 | N30: =M30-'Inputs_VZ'!$B$17+'Inputs_VZ'!$B$18 -> 3.3898435e+11 | O30: =N30/'Inputs_VZ'!$B$22 -> 81.589095
A31: -0.05 | B31: ='DCF_VZ'!$B$25*(1+$A$31) -> 131281450000 | C31: =B31*(1+$A$31) -> 124717377500 | D31: =C31*(1+$A$31) -> 118481508625 | E31: =D31*(1+$A$31) -> 1.1255743e+11 | F31: =E31*(1+$A$31) -> 1.0692956e+11 | G31: =B31*'DCF_VZ'!$B$10*(1-'DCF_VZ'!$B$14)+B31*'Inputs_VZ'!$B$31-B31*'Inputs_VZ'!$B$32-'Inputs_VZ'!$B$33*(B31-'DCF_VZ'!$B$25) -> 2.0388097e+10 | H31: =C31*'DCF_VZ'!$B$10*(1-'DCF_VZ'!$B$14)+C31*'Inputs_VZ'!$B$31-C31*'Inputs_VZ'!$B$32-'Inputs_VZ'!$B$33*(C31-B31) -> 1.9368692e+10 | I31: =D31*'DCF_VZ'!$B$10*(1-'DCF_VZ'!$B$14)+D31*'Inputs_VZ'!$B$31-D31*'Inputs_VZ'!$B$32-'Inputs_VZ'!$B$33*(D31-C31) -> 1.8400258e+10 | J31: =E31*'DCF_VZ'!$B$10*(1-'DCF_VZ'!$B$14)+E31*'Inputs_VZ'!$B$31-E31*'Inputs_VZ'!$B$32-'Inputs_VZ'!$B$33*(E31-D31) -> 1.7480245e+10 | K31: =F31*'DCF_VZ'!$B$10*(1-'DCF_VZ'!$B$14)+F31*'Inputs_VZ'!$B$31-F31*'Inputs_VZ'!$B$32-'Inputs_VZ'!$B$33*(F31-E31) -> 1.6606233e+10 | L31: =K31*(1+'Inputs_VZ'!$B$29)/('DCF_VZ'!$B$21-'Inputs_VZ'!$B$29) -> 6.8085554e+11 | M31: =SUMPRODUCT(G31:K31,1/(1+'DCF_VZ'!$B$21)^{1,2,3,4,5})+L31/(1+'DCF_VZ'!$B$21)^5 -> 6.1374063e+11 | N31: =M31-'Inputs_VZ'!$B$17+'Inputs_VZ'!$B$18 -> 4.7463863e+11 | O31: =N31/'Inputs_VZ'!$B$22 -> 114.2393
A32: 0 | B32: ='DCF_VZ'!$B$25*(1+$A$32) -> 138191000000 | C32: =B32*(1+$A$32) -> 138191000000 | D32: =C32*(1+$A$32) -> 138191000000 | E32: =D32*(1+$A$32) -> 138191000000 | F32: =E32*(1+$A$32) -> 138191000000 | G32: =B32*'DCF_VZ'!$B$10*(1-'DCF_VZ'!$B$14)+B32*'Inputs_VZ'!$B$31-B32*'Inputs_VZ'!$B$32-'Inputs_VZ'!$B$33*(B32-'DCF_VZ'!$B$25) -> 2.1388423e+10 | H32: =C32*'DCF_VZ'!$B$10*(1-'DCF_VZ'!$B$14)+C32*'Inputs_VZ'!$B$31-C32*'Inputs_VZ'!$B$32-'Inputs_VZ'!$B$33*(C32-B32) -> 2.1388423e+10 | I32: =D32*'DCF_VZ'!$B$10*(1-'DCF_VZ'!$B$14)+D32*'Inputs_VZ'!$B$31-D32*'Inputs_VZ'!$B$32-'Inputs_VZ'!$B$33*(D32-C32) -> 2.1388423e+10 | J32: =E32*'DCF_VZ'!$B$10*(1-'DCF_VZ'!$B$14)+E32*'Inputs_VZ'!$B$31-E32*'Inputs_VZ'!$B$32-'Inputs_VZ'!$B$33*(E32-D32) -> 2.1388423e+10 | K32: =F32*'DCF_VZ'!$B$10*(1-'DCF_VZ'!$B$14)+F32*'Inputs_VZ'!$B$31-F32*'Inputs_VZ'!$B$32-'Inputs_VZ'!$B$33*(F32-E32) -> 2.1388423e+10 | L32: =K32*(1+'Inputs_VZ'!$B$29)/('DCF_VZ'!$B$21-'Inputs_VZ'!$B$29) -> 8.7692534e+11 | M32: =SUMPRODUCT(G32:K32,1/(1+'DCF_VZ'!$B$21)^{1,2,3,4,5})+L32/(1+'DCF_VZ'!$B$21)^5 -> 7.7969462e+11 | N32: =M32-'Inputs_VZ'!$B$17+'Inputs_VZ'!$B$18 -> 6.4059262e+11 | O32: =N32/'Inputs_VZ'!$B$22 -> 154.18226
A33: 0.05 | B33: ='DCF_VZ'!$B$25*(1+$A$33) -> 145100550000 | C33: =B33*(1+$A$33) -> 152355577500 | D33: =C33*(1+$A$33) -> 159973356375 | E33: =D33*(1+$A$33) -> 1.6797202e+11 | F33: =E33*(1+$A$33) -> 1.7637063e+11 | G33: =B33*'DCF_VZ'!$B$10*(1-'DCF_VZ'!$B$14)+B33*'Inputs_VZ'!$B$31-B33*'Inputs_VZ'!$B$32-'Inputs_VZ'!$B$33*(B33-'DCF_VZ'!$B$25) -> 2.2388748e+10 | H33: =C33*'DCF_VZ'!$B$10*(1-'DCF_VZ'!$B$14)+C33*'Inputs_VZ'!$B$31-C33*'Inputs_VZ'!$B$32-'Inputs_VZ'!$B$33*(C33-B33) -> 2.3508186e+10 | I33: =D33*'DCF_VZ'!$B$10*(1-'DCF_VZ'!$B$14)+D33*'Inputs_VZ'!$B$31-D33*'Inputs_VZ'!$B$32-'Inputs_VZ'!$B$33*(D33-C33) -> 2.4683595e+10 | J33: =E33*'DCF_VZ'!$B$10*(1-'DCF_VZ'!$B$14)+E33*'Inputs_VZ'!$B$31-E33*'Inputs_VZ'!$B$32-'Inputs_VZ'!$B$33*(E33-D33) -> 2.5917775e+10 | K33: =F33*'DCF_VZ'!$B$10*(1-'DCF_VZ'!$B$14)+F33*'Inputs_VZ'!$B$31-F33*'Inputs_VZ'!$B$32-'Inputs_VZ'!$B$33*(F33-E33) -> 2.7213664e+10 | L33: =K33*(1+'Inputs_VZ'!$B$29)/('DCF_VZ'!$B$21-'Inputs_VZ'!$B$29) -> 1.1157602e+12 | M33: =SUMPRODUCT(G33:K33,1/(1+'DCF_VZ'!$B$21)^{1,2,3,4,5})+L33/(1+'DCF_VZ'!$B$21)^5 -> 9.8084041e+11 | N33: =M33-'Inputs_VZ'!$B$17+'Inputs_VZ'!$B$18 -> 8.4173841e+11 | O33: =N33/'Inputs_VZ'!$B$22 -> 202.59542
A34: 0.1 | B34: ='DCF_VZ'!$B$25*(1+$A$34) -> 152010100000 | C34: =B34*(1+$A$34) -> 167211110000 | D34: =C34*(1+$A$34) -> 183932221000 | E34: =D34*(1+$A$34) -> 2.0232544e+11 | F34: =E34*(1+$A$34) -> 2.2255799e+11 | G34: =B34*'DCF_VZ'!$B$10*(1-'DCF_VZ'!$B$14)+B34*'Inputs_VZ'!$B$31-B34*'Inputs_VZ'!$B$32-'Inputs_VZ'!$B$33*(B34-'DCF_VZ'!$B$25) -> 2.3389074e+10 | H34: =C34*'DCF_VZ'!$B$10*(1-'DCF_VZ'!$B$14)+C34*'Inputs_VZ'!$B$31-C34*'Inputs_VZ'!$B$32-'Inputs_VZ'!$B$33*(C34-B34) -> 2.5727982e+10 | I34: =D34*'DCF_VZ'!$B$10*(1-'DCF_VZ'!$B$14)+D34*'Inputs_VZ'!$B$31-D34*'Inputs_VZ'!$B$32-'Inputs_VZ'!$B$33*(D34-C34) -> 2.830078e+10 | J34: =E34*'DCF_VZ'!$B$10*(1-'DCF_VZ'!$B$14)+E34*'Inputs_VZ'!$B$31-E34*'Inputs_VZ'!$B$32-'Inputs_VZ'!$B$33*(E34-D34) -> 3.1130858e+10 | K34: =F34*'DCF_VZ'!$B$10*(1-'DCF_VZ'!$B$14)+F34*'Inputs_VZ'!$B$31-F34*'Inputs_VZ'!$B$32-'Inputs_VZ'!$B$33*(F34-E34) -> 3.4243943e+10 | L34: =K34*(1+'Inputs_VZ'!$B$29)/('DCF_VZ'!$B$21-'Inputs_VZ'!$B$29) -> 1.4040017e+12 | M34: =SUMPRODUCT(G34:K34,1/(1+'DCF_VZ'!$B$21)^{1,2,3,4,5})+L34/(1+'DCF_VZ'!$B$21)^5 -> 1.2225731e+12 | N34: =M34-'Inputs_VZ'!$B$17+'Inputs_VZ'!$B$18 -> 1.0834711e+12 | O34: =N34/'Inputs_VZ'!$B$22 -> 260.77732
A35: 0.2 | B35: ='DCF_VZ'!$B$25*(1+$A$35) -> 165829200000 | C35: =B35*(1+$A$35) -> 198995040000 | D35: =C35*(1+$A$35) -> 238794048000 | E35: =D35*(1+$A$35) -> 286552857600 | F35: =E35*(1+$A$35) -> 343863429120 | G35: =B35*'DCF_VZ'!$B$10*(1-'DCF_VZ'!$B$14)+B35*'Inputs_VZ'!$B$31-B35*'Inputs_VZ'!$B$32-'Inputs_VZ'!$B$33*(B35-'DCF_VZ'!$B$25) -> 2.5389725e+10 | H35: =C35*'DCF_VZ'!$B$10*(1-'DCF_VZ'!$B$14)+C35*'Inputs_VZ'!$B$31-C35*'Inputs_VZ'!$B$32-'Inputs_VZ'!$B$33*(C35-B35) -> 3.046767e+10 | I35: =D35*'DCF_VZ'!$B$10*(1-'DCF_VZ'!$B$14)+D35*'Inputs_VZ'!$B$31-D35*'Inputs_VZ'!$B$32-'Inputs_VZ'!$B$33*(D35-C35) -> 3.6561205e+10 | J35: =E35*'DCF_VZ'!$B$10*(1-'DCF_VZ'!$B$14)+E35*'Inputs_VZ'!$B$31-E35*'Inputs_VZ'!$B$32-'Inputs_VZ'!$B$33*(E35-D35) -> 4.3873446e+10 | K35: =F35*'DCF_VZ'!$B$10*(1-'DCF_VZ'!$B$14)+F35*'Inputs_VZ'!$B$31-F35*'Inputs_VZ'!$B$32-'Inputs_VZ'!$B$33*(F35-E35) -> 5.2648135e+10 | L35: =K35*(1+'Inputs_VZ'!$B$29)/('DCF_VZ'!$B$21-'Inputs_VZ'!$B$29) -> 2.1585735e+12 | M35: =SUMPRODUCT(G35:K35,1/(1+'DCF_VZ'!$B$21)^{1,2,3,4,5})+L35/(1+'DCF_VZ'!$B$21)^5 -> 1.8520435e+12 | N35: =M35-'Inputs_VZ'!$B$17+'Inputs_VZ'!$B$18 -> 1.7129415e+12 | O35: =N35/'Inputs_VZ'!$B$22 -> 412.2826
A36: 0.3 | B36: ='DCF_VZ'!$B$25*(1+$A$36) -> 179648300000 | C36: =B36*(1+$A$36) -> 233542790000 | D36: =C36*(1+$A$36) -> 303605627000 | E36: =D36*(1+$A$36) -> 394687315100 | F36: =E36*(1+$A$36) -> 513093509630 | G36: =B36*'DCF_VZ'!$B$10*(1-'DCF_VZ'!$B$14)+B36*'Inputs_VZ'!$B$31-B36*'Inputs_VZ'!$B$32-'Inputs_VZ'!$B$33*(B36-'DCF_VZ'!$B$25) -> 2.7390377e+10 | H36: =C36*'DCF_VZ'!$B$10*(1-'DCF_VZ'!$B$14)+C36*'Inputs_VZ'!$B$31-C36*'Inputs_VZ'!$B$32-'Inputs_VZ'!$B$33*(C36-B36) -> 3.560749e+10 | I36: =D36*'DCF_VZ'!$B$10*(1-'DCF_VZ'!$B$14)+D36*'Inputs_VZ'!$B$31-D36*'Inputs_VZ'!$B$32-'Inputs_VZ'!$B$33*(D36-C36) -> 4.6289737e+10 | J36: =E36*'DCF_VZ'!$B$10*(1-'DCF_VZ'!$B$14)+E36*'Inputs_VZ'!$B$31-E36*'Inputs_VZ'!$B$32-'Inputs_VZ'!$B$33*(E36-D36) -> 6.0176658e+10 | K36: =F36*'DCF_VZ'!$B$10*(1-'DCF_VZ'!$B$14)+F36*'Inputs_VZ'!$B$31-F36*'Inputs_VZ'!$B$32-'Inputs_VZ'!$B$33*(F36-E36) -> 7.8229655e+10 | L36: =K36*(1+'Inputs_VZ'!$B$29)/('DCF_VZ'!$B$21-'Inputs_VZ'!$B$29) -> 3.2074158e+12 | M36: =SUMPRODUCT(G36:K36,1/(1+'DCF_VZ'!$B$21)^{1,2,3,4,5})+L36/(1+'DCF_VZ'!$B$21)^5 -> 2.7222666e+12 | N36: =M36-'Inputs_VZ'!$B$17+'Inputs_VZ'!$B$18 -> 2.5831646e+12 | O36: =N36/'Inputs_VZ'!$B$22 -> 621.73391
A37: 0.4 | B37: ='DCF_VZ'!$B$25*(1+$A$37) -> 193467400000 | C37: =B37*(1+$A$37) -> 2.7085436e+11 | D37: =C37*(1+$A$37) -> 3.791961e+11 | E37: =D37*(1+$A$37) -> 5.3087455e+11 | F37: =E37*(1+$A$37) -> 7.4322436e+11 | G37: =B37*'DCF_VZ'!$B$10*(1-'DCF_VZ'!$B$14)+B37*'Inputs_VZ'!$B$31-B37*'Inputs_VZ'!$B$32-'Inputs_VZ'!$B$33*(B37-'DCF_VZ'!$B$25) -> 2.9391028e+10 | H37: =C37*'DCF_VZ'!$B$10*(1-'DCF_VZ'!$B$14)+C37*'Inputs_VZ'!$B$31-C37*'Inputs_VZ'!$B$32-'Inputs_VZ'!$B$33*(C37-B37) -> 4.1147439e+10 | I37: =D37*'DCF_VZ'!$B$10*(1-'DCF_VZ'!$B$14)+D37*'Inputs_VZ'!$B$31-D37*'Inputs_VZ'!$B$32-'Inputs_VZ'!$B$33*(D37-C37) -> 5.7606415e+10 | J37: =E37*'DCF_VZ'!$B$10*(1-'DCF_VZ'!$B$14)+E37*'Inputs_VZ'!$B$31-E37*'Inputs_VZ'!$B$32-'Inputs_VZ'!$B$33*(E37-D37) -> 8.0648981e+10 | K37: =F37*'DCF_VZ'!$B$10*(1-'DCF_VZ'!$B$14)+F37*'Inputs_VZ'!$B$31-F37*'Inputs_VZ'!$B$32-'Inputs_VZ'!$B$33*(F37-E37) -> 1.1290857e+11 | L37: =K37*(1+'Inputs_VZ'!$B$29)/('DCF_VZ'!$B$21-'Inputs_VZ'!$B$29) -> 4.6292515e+12 | M37: =SUMPRODUCT(G37:K37,1/(1+'DCF_VZ'!$B$21)^{1,2,3,4,5})+L37/(1+'DCF_VZ'!$B$21)^5 -> 3.8970326e+12 | N37: =M37-'Inputs_VZ'!$B$17+'Inputs_VZ'!$B$18 -> 3.7579306e+12 | O37: =N37/'Inputs_VZ'!$B$22 -> 904.4847
A38: Direction check: IV increases as revenue growth rises? | B38: =IF(O30<O37,"PASS (as expected)","FAIL — investigate (see note)") -> PASS (as expected)
A41: TABLE 4 — Operating Margin Sensitivity (range [0%,60%]); base revenue path & WACC held fixed
A42: Margin | B42: FCF Y1 | C42: FCF Y2 | D42: FCF Y3 | E42: FCF Y4 | F42: FCF Y5 | G42: Terminal Value | H42: Enterprise Value | I42: Equity Value | J42: Intrinsic Value/Share
A43: 0 | B43: ='DCF_VZ'!$C$25*$A$43*(1-'DCF_VZ'!$B$14)+'DCF_VZ'!$C$28-'DCF_VZ'!$C$29-'DCF_VZ'!$C$30 -> -1.405286e+09 | C43: ='DCF_VZ'!$D$25*$A$43*(1-'DCF_VZ'!$B$14)+'DCF_VZ'!$D$28-'DCF_VZ'!$D$29-'DCF_VZ'!$D$30 -> -1.4171718e+09 | D43: ='DCF_VZ'!$E$25*$A$43*(1-'DCF_VZ'!$B$14)+'DCF_VZ'!$E$28-'DCF_VZ'!$E$29-'DCF_VZ'!$E$30 -> -1.429158e+09 | E43: ='DCF_VZ'!$F$25*$A$43*(1-'DCF_VZ'!$B$14)+'DCF_VZ'!$F$28-'DCF_VZ'!$F$29-'DCF_VZ'!$F$30 -> -1.4412457e+09 | F43: ='DCF_VZ'!$G$25*$A$43*(1-'DCF_VZ'!$B$14)+'DCF_VZ'!$G$28-'DCF_VZ'!$G$29-'DCF_VZ'!$G$30 -> -1.4534355e+09 | G43: =F43*(1+'Inputs_VZ'!$B$29)/('DCF_VZ'!$B$21-'Inputs_VZ'!$B$29) -> -5.9590857e+10 | H43: =SUMPRODUCT(B43:F43,1/(1+'DCF_VZ'!$B$21)^{1,2,3,4,5})+G43/(1+'DCF_VZ'!$B$21)^5 -> -5.2873862e+10 | I43: =H43-'Inputs_VZ'!$B$17+'Inputs_VZ'!$B$18 -> -1.9197586e+11 | J43: =I43/'Inputs_VZ'!$B$22 -> -46.206077
A44: 0.1 | B44: ='DCF_VZ'!$C$25*$A$44*(1-'DCF_VZ'!$B$14)+'DCF_VZ'!$C$28-'DCF_VZ'!$C$29-'DCF_VZ'!$C$30 -> 9.4179646e+09 | C44: ='DCF_VZ'!$D$25*$A$44*(1-'DCF_VZ'!$B$14)+'DCF_VZ'!$D$28-'DCF_VZ'!$D$29-'DCF_VZ'!$D$30 -> 9.4976206e+09 | D44: ='DCF_VZ'!$E$25*$A$44*(1-'DCF_VZ'!$B$14)+'DCF_VZ'!$E$28-'DCF_VZ'!$E$29-'DCF_VZ'!$E$30 -> 9.5779503e+09 | E44: ='DCF_VZ'!$F$25*$A$44*(1-'DCF_VZ'!$B$14)+'DCF_VZ'!$F$28-'DCF_VZ'!$F$29-'DCF_VZ'!$F$30 -> 9.6589594e+09 | F44: ='DCF_VZ'!$G$25*$A$44*(1-'DCF_VZ'!$B$14)+'DCF_VZ'!$G$28-'DCF_VZ'!$G$29-'DCF_VZ'!$G$30 -> 9.7406536e+09 | G44: =F44*(1+'Inputs_VZ'!$B$29)/('DCF_VZ'!$B$21-'Inputs_VZ'!$B$29) -> 3.993668e+11 | H44: =SUMPRODUCT(B44:F44,1/(1+'DCF_VZ'!$B$21)^{1,2,3,4,5})+G44/(1+'DCF_VZ'!$B$21)^5 -> 3.5435075e+11 | I44: =H44-'Inputs_VZ'!$B$17+'Inputs_VZ'!$B$18 -> 2.1524875e+11 | J44: =I44/'Inputs_VZ'!$B$22 -> 51.807556
A45: 0.2 | B45: ='DCF_VZ'!$C$25*$A$45*(1-'DCF_VZ'!$B$14)+'DCF_VZ'!$C$28-'DCF_VZ'!$C$29-'DCF_VZ'!$C$30 -> 2.0241215e+10 | C45: ='DCF_VZ'!$D$25*$A$45*(1-'DCF_VZ'!$B$14)+'DCF_VZ'!$D$28-'DCF_VZ'!$D$29-'DCF_VZ'!$D$30 -> 2.0412413e+10 | D45: ='DCF_VZ'!$E$25*$A$45*(1-'DCF_VZ'!$B$14)+'DCF_VZ'!$E$28-'DCF_VZ'!$E$29-'DCF_VZ'!$E$30 -> 2.0585059e+10 | E45: ='DCF_VZ'!$F$25*$A$45*(1-'DCF_VZ'!$B$14)+'DCF_VZ'!$F$28-'DCF_VZ'!$F$29-'DCF_VZ'!$F$30 -> 2.0759164e+10 | F45: ='DCF_VZ'!$G$25*$A$45*(1-'DCF_VZ'!$B$14)+'DCF_VZ'!$G$28-'DCF_VZ'!$G$29-'DCF_VZ'!$G$30 -> 2.0934743e+10 | G45: =F45*(1+'Inputs_VZ'!$B$29)/('DCF_VZ'!$B$21-'Inputs_VZ'!$B$29) -> 8.5832445e+11 | H45: =SUMPRODUCT(B45:F45,1/(1+'DCF_VZ'!$B$21)^{1,2,3,4,5})+G45/(1+'DCF_VZ'!$B$21)^5 -> 7.6157536e+11 | I45: =H45-'Inputs_VZ'!$B$17+'Inputs_VZ'!$B$18 -> 6.2247336e+11 | J45: =I45/'Inputs_VZ'!$B$22 -> 149.82119
A46: 0.3 | B46: ='DCF_VZ'!$C$25*$A$46*(1-'DCF_VZ'!$B$14)+'DCF_VZ'!$C$28-'DCF_VZ'!$C$29-'DCF_VZ'!$C$30 -> 3.1064466e+10 | C46: ='DCF_VZ'!$D$25*$A$46*(1-'DCF_VZ'!$B$14)+'DCF_VZ'!$D$28-'DCF_VZ'!$D$29-'DCF_VZ'!$D$30 -> 3.1327205e+10 | D46: ='DCF_VZ'!$E$25*$A$46*(1-'DCF_VZ'!$B$14)+'DCF_VZ'!$E$28-'DCF_VZ'!$E$29-'DCF_VZ'!$E$30 -> 3.1592167e+10 | E46: ='DCF_VZ'!$F$25*$A$46*(1-'DCF_VZ'!$B$14)+'DCF_VZ'!$F$28-'DCF_VZ'!$F$29-'DCF_VZ'!$F$30 -> 3.1859369e+10 | F46: ='DCF_VZ'!$G$25*$A$46*(1-'DCF_VZ'!$B$14)+'DCF_VZ'!$G$28-'DCF_VZ'!$G$29-'DCF_VZ'!$G$30 -> 3.2128832e+10 | G46: =F46*(1+'Inputs_VZ'!$B$29)/('DCF_VZ'!$B$21-'Inputs_VZ'!$B$29) -> 1.3172821e+12 | H46: =SUMPRODUCT(B46:F46,1/(1+'DCF_VZ'!$B$21)^{1,2,3,4,5})+G46/(1+'DCF_VZ'!$B$21)^5 -> 1.1688e+12 | I46: =H46-'Inputs_VZ'!$B$17+'Inputs_VZ'!$B$18 -> 1.029698e+12 | J46: =I46/'Inputs_VZ'!$B$22 -> 247.83482
A47: 0.4 | B47: ='DCF_VZ'!$C$25*$A$47*(1-'DCF_VZ'!$B$14)+'DCF_VZ'!$C$28-'DCF_VZ'!$C$29-'DCF_VZ'!$C$30 -> 4.1887717e+10 | C47: ='DCF_VZ'!$D$25*$A$47*(1-'DCF_VZ'!$B$14)+'DCF_VZ'!$D$28-'DCF_VZ'!$D$29-'DCF_VZ'!$D$30 -> 4.2241998e+10 | D47: ='DCF_VZ'!$E$25*$A$47*(1-'DCF_VZ'!$B$14)+'DCF_VZ'!$E$28-'DCF_VZ'!$E$29-'DCF_VZ'!$E$30 -> 4.2599275e+10 | E47: ='DCF_VZ'!$F$25*$A$47*(1-'DCF_VZ'!$B$14)+'DCF_VZ'!$F$28-'DCF_VZ'!$F$29-'DCF_VZ'!$F$30 -> 4.2959574e+10 | F47: ='DCF_VZ'!$G$25*$A$47*(1-'DCF_VZ'!$B$14)+'DCF_VZ'!$G$28-'DCF_VZ'!$G$29-'DCF_VZ'!$G$30 -> 4.3322921e+10 | G47: =F47*(1+'Inputs_VZ'!$B$29)/('DCF_VZ'!$B$21-'Inputs_VZ'!$B$29) -> 1.7762398e+12 | H47: =SUMPRODUCT(B47:F47,1/(1+'DCF_VZ'!$B$21)^{1,2,3,4,5})+G47/(1+'DCF_VZ'!$B$21)^5 -> 1.5760246e+12 | I47: =H47-'Inputs_VZ'!$B$17+'Inputs_VZ'!$B$18 -> 1.4369226e+12 | J47: =I47/'Inputs_VZ'!$B$22 -> 345.84845
A48: 0.5 | B48: ='DCF_VZ'!$C$25*$A$48*(1-'DCF_VZ'!$B$14)+'DCF_VZ'!$C$28-'DCF_VZ'!$C$29-'DCF_VZ'!$C$30 -> 5.2710967e+10 | C48: ='DCF_VZ'!$D$25*$A$48*(1-'DCF_VZ'!$B$14)+'DCF_VZ'!$D$28-'DCF_VZ'!$D$29-'DCF_VZ'!$D$30 -> 5.315679e+10 | D48: ='DCF_VZ'!$E$25*$A$48*(1-'DCF_VZ'!$B$14)+'DCF_VZ'!$E$28-'DCF_VZ'!$E$29-'DCF_VZ'!$E$30 -> 5.3606383e+10 | E48: ='DCF_VZ'!$F$25*$A$48*(1-'DCF_VZ'!$B$14)+'DCF_VZ'!$F$28-'DCF_VZ'!$F$29-'DCF_VZ'!$F$30 -> 5.4059779e+10 | F48: ='DCF_VZ'!$G$25*$A$48*(1-'DCF_VZ'!$B$14)+'DCF_VZ'!$G$28-'DCF_VZ'!$G$29-'DCF_VZ'!$G$30 -> 5.451701e+10 | G48: =F48*(1+'Inputs_VZ'!$B$29)/('DCF_VZ'!$B$21-'Inputs_VZ'!$B$29) -> 2.2351974e+12 | H48: =SUMPRODUCT(B48:F48,1/(1+'DCF_VZ'!$B$21)^{1,2,3,4,5})+G48/(1+'DCF_VZ'!$B$21)^5 -> 1.9832492e+12 | I48: =H48-'Inputs_VZ'!$B$17+'Inputs_VZ'!$B$18 -> 1.8441472e+12 | J48: =I48/'Inputs_VZ'!$B$22 -> 443.86209
A49: 0.6 | B49: ='DCF_VZ'!$C$25*$A$49*(1-'DCF_VZ'!$B$14)+'DCF_VZ'!$C$28-'DCF_VZ'!$C$29-'DCF_VZ'!$C$30 -> 6.3534218e+10 | C49: ='DCF_VZ'!$D$25*$A$49*(1-'DCF_VZ'!$B$14)+'DCF_VZ'!$D$28-'DCF_VZ'!$D$29-'DCF_VZ'!$D$30 -> 6.4071582e+10 | D49: ='DCF_VZ'!$E$25*$A$49*(1-'DCF_VZ'!$B$14)+'DCF_VZ'!$E$28-'DCF_VZ'!$E$29-'DCF_VZ'!$E$30 -> 6.4613492e+10 | E49: ='DCF_VZ'!$F$25*$A$49*(1-'DCF_VZ'!$B$14)+'DCF_VZ'!$F$28-'DCF_VZ'!$F$29-'DCF_VZ'!$F$30 -> 6.5159984e+10 | F49: ='DCF_VZ'!$G$25*$A$49*(1-'DCF_VZ'!$B$14)+'DCF_VZ'!$G$28-'DCF_VZ'!$G$29-'DCF_VZ'!$G$30 -> 6.5711099e+10 | G49: =F49*(1+'Inputs_VZ'!$B$29)/('DCF_VZ'!$B$21-'Inputs_VZ'!$B$29) -> 2.6941551e+12 | H49: =SUMPRODUCT(B49:F49,1/(1+'DCF_VZ'!$B$21)^{1,2,3,4,5})+G49/(1+'DCF_VZ'!$B$21)^5 -> 2.3904738e+12 | I49: =H49-'Inputs_VZ'!$B$17+'Inputs_VZ'!$B$18 -> 2.2513718e+12 | J49: =I49/'Inputs_VZ'!$B$22 -> 541.87572
A50: Direction check: IV increases as operating margin rises? | B50: =IF(J43<J49,"PASS (as expected)","FAIL — investigate") -> PASS (as expected)
A53: TABLE 5 — Two-Way Sensitivity: WACC (rows) × Terminal Growth (columns) — Intrinsic Value/Share
A54: WACC \ g | B54: 0 | C54: 0.01 | D54: 0.02 | E54: 0.03 | F54: 0.04 | G54: 0.05
A55: 0.05 | B55: =IF(B$54>=$A55,"n/a",(SUMPRODUCT('DCF_VZ'!$C$31:$G$31,1/(1+$A55)^{1,2,3,4,5})+('DCF_VZ'!$G$31*(1+B$54)/($A55-B$54))/(1+$A55)^5-'Inputs_VZ'!$B$17+'Inputs_VZ'!$B$18)/'Inputs_VZ'!$B$22) -> 73.443143 | C55: =IF(C$54>=$A55,"n/a",(SUMPRODUCT('DCF_VZ'!$C$31:$G$31,1/(1+$A55)^{1,2,3,4,5})+('DCF_VZ'!$G$31*(1+C$54)/($A55-C$54))/(1+$A55)^5-'Inputs_VZ'!$B$17+'Inputs_VZ'!$B$18)/'Inputs_VZ'!$B$22) -> 95.517977 | D55: =IF(D$54>=$A55,"n/a",(SUMPRODUCT('DCF_VZ'!$C$31:$G$31,1/(1+$A55)^{1,2,3,4,5})+('DCF_VZ'!$G$31*(1+D$54)/($A55-D$54))/(1+$A55)^5-'Inputs_VZ'!$B$17+'Inputs_VZ'!$B$18)/'Inputs_VZ'!$B$22) -> 132.30937 | E55: =IF(E$54>=$A55,"n/a",(SUMPRODUCT('DCF_VZ'!$C$31:$G$31,1/(1+$A55)^{1,2,3,4,5})+('DCF_VZ'!$G$31*(1+E$54)/($A55-E$54))/(1+$A55)^5-'Inputs_VZ'!$B$17+'Inputs_VZ'!$B$18)/'Inputs_VZ'!$B$22) -> 205.89215 | F55: =IF(F$54>=$A55,"n/a",(SUMPRODUCT('DCF_VZ'!$C$31:$G$31,1/(1+$A55)^{1,2,3,4,5})+('DCF_VZ'!$G$31*(1+F$54)/($A55-F$54))/(1+$A55)^5-'Inputs_VZ'!$B$17+'Inputs_VZ'!$B$18)/'Inputs_VZ'!$B$22) -> 426.64049 | G55: =IF(G$54>=$A55,"n/a",(SUMPRODUCT('DCF_VZ'!$C$31:$G$31,1/(1+$A55)^{1,2,3,4,5})+('DCF_VZ'!$G$31*(1+G$54)/($A55-G$54))/(1+$A55)^5-'Inputs_VZ'!$B$17+'Inputs_VZ'!$B$18)/'Inputs_VZ'!$B$22) -> n/a
A56: 0.08 | B56: =IF(B$54>=$A56,"n/a",(SUMPRODUCT('DCF_VZ'!$C$31:$G$31,1/(1+$A56)^{1,2,3,4,5})+('DCF_VZ'!$G$31*(1+B$54)/($A56-B$54))/(1+$A56)^5-'Inputs_VZ'!$B$17+'Inputs_VZ'!$B$18)/'Inputs_VZ'!$B$22) -> 33.216573 | C56: =IF(C$54>=$A56,"n/a",(SUMPRODUCT('DCF_VZ'!$C$31:$G$31,1/(1+$A56)^{1,2,3,4,5})+('DCF_VZ'!$G$31*(1+C$54)/($A56-C$54))/(1+$A56)^5-'Inputs_VZ'!$B$17+'Inputs_VZ'!$B$18)/'Inputs_VZ'!$B$22) -> 40.260285 | D56: =IF(D$54>=$A56,"n/a",(SUMPRODUCT('DCF_VZ'!$C$31:$G$31,1/(1+$A56)^{1,2,3,4,5})+('DCF_VZ'!$G$31*(1+D$54)/($A56-D$54))/(1+$A56)^5-'Inputs_VZ'!$B$17+'Inputs_VZ'!$B$18)/'Inputs_VZ'!$B$22) -> 49.651901 | E56: =IF(E$54>=$A56,"n/a",(SUMPRODUCT('DCF_VZ'!$C$31:$G$31,1/(1+$A56)^{1,2,3,4,5})+('DCF_VZ'!$G$31*(1+E$54)/($A56-E$54))/(1+$A56)^5-'Inputs_VZ'!$B$17+'Inputs_VZ'!$B$18)/'Inputs_VZ'!$B$22) -> 62.800163 | F56: =IF(F$54>=$A56,"n/a",(SUMPRODUCT('DCF_VZ'!$C$31:$G$31,1/(1+$A56)^{1,2,3,4,5})+('DCF_VZ'!$G$31*(1+F$54)/($A56-F$54))/(1+$A56)^5-'Inputs_VZ'!$B$17+'Inputs_VZ'!$B$18)/'Inputs_VZ'!$B$22) -> 82.522557 | G56: =IF(G$54>=$A56,"n/a",(SUMPRODUCT('DCF_VZ'!$C$31:$G$31,1/(1+$A56)^{1,2,3,4,5})+('DCF_VZ'!$G$31*(1+G$54)/($A56-G$54))/(1+$A56)^5-'Inputs_VZ'!$B$17+'Inputs_VZ'!$B$18)/'Inputs_VZ'!$B$22) -> 115.39321
A57: 0.11 | B57: =IF(B$54>=$A57,"n/a",(SUMPRODUCT('DCF_VZ'!$C$31:$G$31,1/(1+$A57)^{1,2,3,4,5})+('DCF_VZ'!$G$31*(1+B$54)/($A57-B$54))/(1+$A57)^5-'Inputs_VZ'!$B$17+'Inputs_VZ'!$B$18)/'Inputs_VZ'!$B$22) -> 14.94158 | C57: =IF(C$54>=$A57,"n/a",(SUMPRODUCT('DCF_VZ'!$C$31:$G$31,1/(1+$A57)^{1,2,3,4,5})+('DCF_VZ'!$G$31*(1+C$54)/($A57-C$54))/(1+$A57)^5-'Inputs_VZ'!$B$17+'Inputs_VZ'!$B$18)/'Inputs_VZ'!$B$22) -> 18.155241 | D57: =IF(D$54>=$A57,"n/a",(SUMPRODUCT('DCF_VZ'!$C$31:$G$31,1/(1+$A57)^{1,2,3,4,5})+('DCF_VZ'!$G$31*(1+D$54)/($A57-D$54))/(1+$A57)^5-'Inputs_VZ'!$B$17+'Inputs_VZ'!$B$18)/'Inputs_VZ'!$B$22) -> 22.083048 | E57: =IF(E$54>=$A57,"n/a",(SUMPRODUCT('DCF_VZ'!$C$31:$G$31,1/(1+$A57)^{1,2,3,4,5})+('DCF_VZ'!$G$31*(1+E$54)/($A57-E$54))/(1+$A57)^5-'Inputs_VZ'!$B$17+'Inputs_VZ'!$B$18)/'Inputs_VZ'!$B$22) -> 26.992808 | F57: =IF(F$54>=$A57,"n/a",(SUMPRODUCT('DCF_VZ'!$C$31:$G$31,1/(1+$A57)^{1,2,3,4,5})+('DCF_VZ'!$G$31*(1+F$54)/($A57-F$54))/(1+$A57)^5-'Inputs_VZ'!$B$17+'Inputs_VZ'!$B$18)/'Inputs_VZ'!$B$22) -> 33.305356 | G57: =IF(G$54>=$A57,"n/a",(SUMPRODUCT('DCF_VZ'!$C$31:$G$31,1/(1+$A57)^{1,2,3,4,5})+('DCF_VZ'!$G$31*(1+G$54)/($A57-G$54))/(1+$A57)^5-'Inputs_VZ'!$B$17+'Inputs_VZ'!$B$18)/'Inputs_VZ'!$B$22) -> 41.722086
A58: 0.14 | B58: =IF(B$54>=$A58,"n/a",(SUMPRODUCT('DCF_VZ'!$C$31:$G$31,1/(1+$A58)^{1,2,3,4,5})+('DCF_VZ'!$G$31*(1+B$54)/($A58-B$54))/(1+$A58)^5-'Inputs_VZ'!$B$17+'Inputs_VZ'!$B$18)/'Inputs_VZ'!$B$22) -> 4.5054137 | C58: =IF(C$54>=$A58,"n/a",(SUMPRODUCT('DCF_VZ'!$C$31:$G$31,1/(1+$A58)^{1,2,3,4,5})+('DCF_VZ'!$G$31*(1+C$54)/($A58-C$54))/(1+$A58)^5-'Inputs_VZ'!$B$17+'Inputs_VZ'!$B$18)/'Inputs_VZ'!$B$22) -> 6.2512111 | D58: =IF(D$54>=$A58,"n/a",(SUMPRODUCT('DCF_VZ'!$C$31:$G$31,1/(1+$A58)^{1,2,3,4,5})+('DCF_VZ'!$G$31*(1+D$54)/($A58-D$54))/(1+$A58)^5-'Inputs_VZ'!$B$17+'Inputs_VZ'!$B$18)/'Inputs_VZ'!$B$22) -> 8.2879747 | E58: =IF(E$54>=$A58,"n/a",(SUMPRODUCT('DCF_VZ'!$C$31:$G$31,1/(1+$A58)^{1,2,3,4,5})+('DCF_VZ'!$G$31*(1+E$54)/($A58-E$54))/(1+$A58)^5-'Inputs_VZ'!$B$17+'Inputs_VZ'!$B$18)/'Inputs_VZ'!$B$22) -> 10.695059 | F58: =IF(F$54>=$A58,"n/a",(SUMPRODUCT('DCF_VZ'!$C$31:$G$31,1/(1+$A58)^{1,2,3,4,5})+('DCF_VZ'!$G$31*(1+F$54)/($A58-F$54))/(1+$A58)^5-'Inputs_VZ'!$B$17+'Inputs_VZ'!$B$18)/'Inputs_VZ'!$B$22) -> 13.58356 | G58: =IF(G$54>=$A58,"n/a",(SUMPRODUCT('DCF_VZ'!$C$31:$G$31,1/(1+$A58)^{1,2,3,4,5})+('DCF_VZ'!$G$31*(1+G$54)/($A58-G$54))/(1+$A58)^5-'Inputs_VZ'!$B$17+'Inputs_VZ'!$B$18)/'Inputs_VZ'!$B$22) -> 17.11395
A59: 0.17 | B59: =IF(B$54>=$A59,"n/a",(SUMPRODUCT('DCF_VZ'!$C$31:$G$31,1/(1+$A59)^{1,2,3,4,5})+('DCF_VZ'!$G$31*(1+B$54)/($A59-B$54))/(1+$A59)^5-'Inputs_VZ'!$B$17+'Inputs_VZ'!$B$18)/'Inputs_VZ'!$B$22) -> -2.242601 | C59: =IF(C$54>=$A59,"n/a",(SUMPRODUCT('DCF_VZ'!$C$31:$G$31,1/(1+$A59)^{1,2,3,4,5})+('DCF_VZ'!$G$31*(1+C$54)/($A59-C$54))/(1+$A59)^5-'Inputs_VZ'!$B$17+'Inputs_VZ'!$B$18)/'Inputs_VZ'!$B$22) -> -1.189737 | D59: =IF(D$54>=$A59,"n/a",(SUMPRODUCT('DCF_VZ'!$C$31:$G$31,1/(1+$A59)^{1,2,3,4,5})+('DCF_VZ'!$G$31*(1+D$54)/($A59-D$54))/(1+$A59)^5-'Inputs_VZ'!$B$17+'Inputs_VZ'!$B$18)/'Inputs_VZ'!$B$22) -> 0.0035089297 | E59: =IF(E$54>=$A59,"n/a",(SUMPRODUCT('DCF_VZ'!$C$31:$G$31,1/(1+$A59)^{1,2,3,4,5})+('DCF_VZ'!$G$31*(1+E$54)/($A59-E$54))/(1+$A59)^5-'Inputs_VZ'!$B$17+'Inputs_VZ'!$B$18)/'Inputs_VZ'!$B$22) -> 1.3672185 | F59: =IF(F$54>=$A59,"n/a",(SUMPRODUCT('DCF_VZ'!$C$31:$G$31,1/(1+$A59)^{1,2,3,4,5})+('DCF_VZ'!$G$31*(1+F$54)/($A59-F$54))/(1+$A59)^5-'Inputs_VZ'!$B$17+'Inputs_VZ'!$B$18)/'Inputs_VZ'!$B$22) -> 2.9407296 | G59: =IF(G$54>=$A59,"n/a",(SUMPRODUCT('DCF_VZ'!$C$31:$G$31,1/(1+$A59)^{1,2,3,4,5})+('DCF_VZ'!$G$31*(1+G$54)/($A59-G$54))/(1+$A59)^5-'Inputs_VZ'!$B$17+'Inputs_VZ'!$B$18)/'Inputs_VZ'!$B$22) -> 4.7764925
A60: 0.2 | B60: =IF(B$54>=$A60,"n/a",(SUMPRODUCT('DCF_VZ'!$C$31:$G$31,1/(1+$A60)^{1,2,3,4,5})+('DCF_VZ'!$G$31*(1+B$54)/($A60-B$54))/(1+$A60)^5-'Inputs_VZ'!$B$17+'Inputs_VZ'!$B$18)/'Inputs_VZ'!$B$22) -> -6.9626423 | C60: =IF(C$54>=$A60,"n/a",(SUMPRODUCT('DCF_VZ'!$C$31:$G$31,1/(1+$A60)^{1,2,3,4,5})+('DCF_VZ'!$G$31*(1+C$54)/($A60-C$54))/(1+$A60)^5-'Inputs_VZ'!$B$17+'Inputs_VZ'!$B$18)/'Inputs_VZ'!$B$22) -> -6.2815969 | D60: =IF(D$54>=$A60,"n/a",(SUMPRODUCT('DCF_VZ'!$C$31:$G$31,1/(1+$A60)^{1,2,3,4,5})+('DCF_VZ'!$G$31*(1+D$54)/($A60-D$54))/(1+$A60)^5-'Inputs_VZ'!$B$17+'Inputs_VZ'!$B$18)/'Inputs_VZ'!$B$22) -> -5.5248798 | E60: =IF(E$54>=$A60,"n/a",(SUMPRODUCT('DCF_VZ'!$C$31:$G$31,1/(1+$A60)^{1,2,3,4,5})+('DCF_VZ'!$G$31*(1+E$54)/($A60-E$54))/(1+$A60)^5-'Inputs_VZ'!$B$17+'Inputs_VZ'!$B$18)/'Inputs_VZ'!$B$22) -> -4.6791372 | F60: =IF(F$54>=$A60,"n/a",(SUMPRODUCT('DCF_VZ'!$C$31:$G$31,1/(1+$A60)^{1,2,3,4,5})+('DCF_VZ'!$G$31*(1+F$54)/($A60-F$54))/(1+$A60)^5-'Inputs_VZ'!$B$17+'Inputs_VZ'!$B$18)/'Inputs_VZ'!$B$22) -> -3.7276767 | G60: =IF(G$54>=$A60,"n/a",(SUMPRODUCT('DCF_VZ'!$C$31:$G$31,1/(1+$A60)^{1,2,3,4,5})+('DCF_VZ'!$G$31*(1+G$54)/($A60-G$54))/(1+$A60)^5-'Inputs_VZ'!$B$17+'Inputs_VZ'!$B$18)/'Inputs_VZ'!$B$22) -> -2.6493548

Sheet Summary & Reconciliation
A1: Summary & Reconciliation
A2: Per docs/independent-validation-plan.md §Reconciliation format. 'Codebase Output' is deliberately left blank — populating it is the explicit scope of a SEPARATE future session (never this one). PASS/FAIL/PENDING formulas therefore read PENDING until that column is filled.
A4: Metric | B4: Independent Workbook Output | C4: Codebase Output (fill in future session) | D4: Absolute Difference | E4: Percentage Difference | F4: Documented Tolerance | G4: PASS/FAIL/PENDING | H4: Notes
A5: — MSFT (MICROSOFT CORPORATION) —
A6: Revenue CAGR | B6: ='DCF_MSFT'!$B$9 -> 0.13741147 | D6: =IF(C6="","PENDING",ABS(B6-C6)) -> PENDING | E6: =IF(OR(C6="",C6=0),"PENDING",ABS(B6-C6)/ABS(C6)) -> PENDING | F6: ±0.01pp | G6: =IF(C6="","PENDING",IF(E6<=0.0001,"PASS","FAIL")) -> PENDING
A7: Operating Margin | B7: ='DCF_MSFT'!$B$10 -> 0.44175047 | D7: =IF(C7="","PENDING",ABS(B7-C7)) -> PENDING | E7: =IF(OR(C7="",C7=0),"PENDING",ABS(B7-C7)/ABS(C7)) -> PENDING | F7: ±0.01pp | G7: =IF(C7="","PENDING",IF(E7<=0.0001,"PASS","FAIL")) -> PENDING
A8: Raw WACC | B8: ='DCF_MSFT'!$B$20 -> 0.10000422 | D8: =IF(C8="","PENDING",ABS(B8-C8)) -> PENDING | E8: =IF(OR(C8="",C8=0),"PENDING",ABS(B8-C8)/ABS(C8)) -> PENDING | F8: ±0.05pp | G8: =IF(C8="","PENDING",IF(E8<=0.0005,"PASS","FAIL")) -> PENDING
A9: Final WACC | B9: ='DCF_MSFT'!$B$21 -> 0.10000422 | D9: =IF(C9="","PENDING",ABS(B9-C9)) -> PENDING | E9: =IF(OR(C9="",C9=0),"PENDING",ABS(B9-C9)/ABS(C9)) -> PENDING | F9: ±0.05pp | G9: =IF(C9="","PENDING",IF(E9<=0.0005,"PASS","FAIL")) -> PENDING
A10: FCF Year 1 | B10: ='DCF_MSFT'!$C$31 -> 1.3016281e+11 | D10: =IF(C10="","PENDING",ABS(B10-C10)) -> PENDING | E10: =IF(OR(C10="",C10=0),"PENDING",ABS(B10-C10)/ABS(C10)) -> PENDING | F10: ±0.1% | G10: =IF(C10="","PENDING",IF(E10<=0.001,"PASS","FAIL")) -> PENDING
A11: FCF Year 2 | B11: ='DCF_MSFT'!$D$31 -> 1.4804868e+11 | D11: =IF(C11="","PENDING",ABS(B11-C11)) -> PENDING | E11: =IF(OR(C11="",C11=0),"PENDING",ABS(B11-C11)/ABS(C11)) -> PENDING | F11: ±0.1% | G11: =IF(C11="","PENDING",IF(E11<=0.001,"PASS","FAIL")) -> PENDING
A12: FCF Year 3 | B12: ='DCF_MSFT'!$E$31 -> 1.6839226e+11 | D12: =IF(C12="","PENDING",ABS(B12-C12)) -> PENDING | E12: =IF(OR(C12="",C12=0),"PENDING",ABS(B12-C12)/ABS(C12)) -> PENDING | F12: ±0.1% | G12: =IF(C12="","PENDING",IF(E12<=0.001,"PASS","FAIL")) -> PENDING
A13: FCF Year 4 | B13: ='DCF_MSFT'!$F$31 -> 1.9153129e+11 | D13: =IF(C13="","PENDING",ABS(B13-C13)) -> PENDING | E13: =IF(OR(C13="",C13=0),"PENDING",ABS(B13-C13)/ABS(C13)) -> PENDING | F13: ±0.1% | G13: =IF(C13="","PENDING",IF(E13<=0.001,"PASS","FAIL")) -> PENDING
A14: FCF Year 5 | B14: ='DCF_MSFT'!$G$31 -> 2.1784989e+11 | D14: =IF(C14="","PENDING",ABS(B14-C14)) -> PENDING | E14: =IF(OR(C14="",C14=0),"PENDING",ABS(B14-C14)/ABS(C14)) -> PENDING | F14: ±0.1% | G14: =IF(C14="","PENDING",IF(E14<=0.001,"PASS","FAIL")) -> PENDING
A15: Terminal Value | B15: ='DCF_MSFT'!$B$34 -> 2.9771145e+12 | D15: =IF(C15="","PENDING",ABS(B15-C15)) -> PENDING | E15: =IF(OR(C15="",C15=0),"PENDING",ABS(B15-C15)/ABS(C15)) -> PENDING | F15: ±0.2% | G15: =IF(C15="","PENDING",IF(E15<=0.002,"PASS","FAIL")) -> PENDING
A16: PV of Explicit FCF | B16: ='DCF_MSFT'!$B$39 -> 6.3327836e+11 | D16: =IF(C16="","PENDING",ABS(B16-C16)) -> PENDING | E16: =IF(OR(C16="",C16=0),"PENDING",ABS(B16-C16)/ABS(C16)) -> PENDING | F16: ±0.2% | G16: =IF(C16="","PENDING",IF(E16<=0.002,"PASS","FAIL")) -> PENDING
A17: PV of Terminal Value | B17: ='DCF_MSFT'!$B$40 -> 1.8485184e+12 | D17: =IF(C17="","PENDING",ABS(B17-C17)) -> PENDING | E17: =IF(OR(C17="",C17=0),"PENDING",ABS(B17-C17)/ABS(C17)) -> PENDING | F17: ±0.2% | G17: =IF(C17="","PENDING",IF(E17<=0.002,"PASS","FAIL")) -> PENDING
A18: Enterprise Value | B18: ='DCF_MSFT'!$B$41 -> 2.4817968e+12 | D18: =IF(C18="","PENDING",ABS(B18-C18)) -> PENDING | E18: =IF(OR(C18="",C18=0),"PENDING",ABS(B18-C18)/ABS(C18)) -> PENDING | F18: ±0.2% | G18: =IF(C18="","PENDING",IF(E18<=0.002,"PASS","FAIL")) -> PENDING
A19: Equity Value | B19: ='DCF_MSFT'!$B$42 -> 2.4624378e+12 | D19: =IF(C19="","PENDING",ABS(B19-C19)) -> PENDING | E19: =IF(OR(C19="",C19=0),"PENDING",ABS(B19-C19)/ABS(C19)) -> PENDING | F19: ±0.2% | G19: =IF(C19="","PENDING",IF(E19<=0.002,"PASS","FAIL")) -> PENDING
A20: Intrinsic Value per Share | B20: ='DCF_MSFT'!$B$43 -> 331.61709 | D20: =IF(C20="","PENDING",ABS(B20-C20)) -> PENDING | E20: =IF(OR(C20="",C20=0),"PENDING",ABS(B20-C20)/ABS(C20)) -> PENDING | F20: ±0.5% | G20: =IF(C20="","PENDING",IF(E20<=0.005,"PASS","FAIL")) -> PENDING
A22: — CAT (CATERPILLAR INC) —
A23: Revenue CAGR | B23: ='DCF_CAT'!$B$9 -> 0.073095112 | D23: =IF(C23="","PENDING",ABS(B23-C23)) -> PENDING | E23: =IF(OR(C23="",C23=0),"PENDING",ABS(B23-C23)/ABS(C23)) -> PENDING | F23: ±0.01pp | G23: =IF(C23="","PENDING",IF(E23<=0.0001,"PASS","FAIL")) -> PENDING
A24: Operating Margin | B24: ='DCF_CAT'!$B$10 -> 0.16559502 | D24: =IF(C24="","PENDING",ABS(B24-C24)) -> PENDING | E24: =IF(OR(C24="",C24=0),"PENDING",ABS(B24-C24)/ABS(C24)) -> PENDING | F24: ±0.01pp | G24: =IF(C24="","PENDING",IF(E24<=0.0001,"PASS","FAIL")) -> PENDING
A25: Raw WACC | B25: ='DCF_CAT'!$B$20 -> 0.12095875 | D25: =IF(C25="","PENDING",ABS(B25-C25)) -> PENDING | E25: =IF(OR(C25="",C25=0),"PENDING",ABS(B25-C25)/ABS(C25)) -> PENDING | F25: ±0.05pp | G25: =IF(C25="","PENDING",IF(E25<=0.0005,"PASS","FAIL")) -> PENDING
A26: Final WACC | B26: ='DCF_CAT'!$B$21 -> 0.12095875 | D26: =IF(C26="","PENDING",ABS(B26-C26)) -> PENDING | E26: =IF(OR(C26="",C26=0),"PENDING",ABS(B26-C26)/ABS(C26)) -> PENDING | F26: ±0.05pp | G26: =IF(C26="","PENDING",IF(E26<=0.0005,"PASS","FAIL")) -> PENDING
A27: FCF Year 1 | B27: ='DCF_CAT'!$C$31 -> 8.355205e+09 | D27: =IF(C27="","PENDING",ABS(B27-C27)) -> PENDING | E27: =IF(OR(C27="",C27=0),"PENDING",ABS(B27-C27)/ABS(C27)) -> PENDING | F27: ±0.1% | G27: =IF(C27="","PENDING",IF(E27<=0.001,"PASS","FAIL")) -> PENDING
A28: FCF Year 2 | B28: ='DCF_CAT'!$D$31 -> 8.9659296e+09 | D28: =IF(C28="","PENDING",ABS(B28-C28)) -> PENDING | E28: =IF(OR(C28="",C28=0),"PENDING",ABS(B28-C28)/ABS(C28)) -> PENDING | F28: ±0.1% | G28: =IF(C28="","PENDING",IF(E28<=0.001,"PASS","FAIL")) -> PENDING
A29: FCF Year 3 | B29: ='DCF_CAT'!$E$31 -> 9.6212953e+09 | D29: =IF(C29="","PENDING",ABS(B29-C29)) -> PENDING | E29: =IF(OR(C29="",C29=0),"PENDING",ABS(B29-C29)/ABS(C29)) -> PENDING | F29: ±0.1% | G29: =IF(C29="","PENDING",IF(E29<=0.001,"PASS","FAIL")) -> PENDING
A30: FCF Year 4 | B30: ='DCF_CAT'!$F$31 -> 1.0324565e+10 | D30: =IF(C30="","PENDING",ABS(B30-C30)) -> PENDING | E30: =IF(OR(C30="",C30=0),"PENDING",ABS(B30-C30)/ABS(C30)) -> PENDING | F30: ±0.1% | G30: =IF(C30="","PENDING",IF(E30<=0.001,"PASS","FAIL")) -> PENDING
A31: FCF Year 5 | B31: ='DCF_CAT'!$G$31 -> 1.107924e+10 | D31: =IF(C31="","PENDING",ABS(B31-C31)) -> PENDING | E31: =IF(OR(C31="",C31=0),"PENDING",ABS(B31-C31)/ABS(C31)) -> PENDING | F31: ±0.1% | G31: =IF(C31="","PENDING",IF(E31<=0.001,"PASS","FAIL")) -> PENDING
A32: Terminal Value | B32: ='DCF_CAT'!$B$34 -> 1.1834482e+11 | D32: =IF(C32="","PENDING",ABS(B32-C32)) -> PENDING | E32: =IF(OR(C32="",C32=0),"PENDING",ABS(B32-C32)/ABS(C32)) -> PENDING | F32: ±0.2% | G32: =IF(C32="","PENDING",IF(E32<=0.002,"PASS","FAIL")) -> PENDING
A33: PV of Explicit FCF | B33: ='DCF_CAT'!$B$39 -> 3.4218526e+10 | D33: =IF(C33="","PENDING",ABS(B33-C33)) -> PENDING | E33: =IF(OR(C33="",C33=0),"PENDING",ABS(B33-C33)/ABS(C33)) -> PENDING | F33: ±0.2% | G33: =IF(C33="","PENDING",IF(E33<=0.002,"PASS","FAIL")) -> PENDING
A34: PV of Terminal Value | B34: ='DCF_CAT'!$B$40 -> 6.6865345e+10 | D34: =IF(C34="","PENDING",ABS(B34-C34)) -> PENDING | E34: =IF(OR(C34="",C34=0),"PENDING",ABS(B34-C34)/ABS(C34)) -> PENDING | F34: ±0.2% | G34: =IF(C34="","PENDING",IF(E34<=0.002,"PASS","FAIL")) -> PENDING
A35: Enterprise Value | B35: ='DCF_CAT'!$B$41 -> 1.0108387e+11 | D35: =IF(C35="","PENDING",ABS(B35-C35)) -> PENDING | E35: =IF(OR(C35="",C35=0),"PENDING",ABS(B35-C35)/ABS(C35)) -> PENDING | F35: ±0.2% | G35: =IF(C35="","PENDING",IF(E35<=0.002,"PASS","FAIL")) -> PENDING
A36: Equity Value | B36: ='DCF_CAT'!$B$42 -> 7.4853871e+10 | D36: =IF(C36="","PENDING",ABS(B36-C36)) -> PENDING | E36: =IF(OR(C36="",C36=0),"PENDING",ABS(B36-C36)/ABS(C36)) -> PENDING | F36: ±0.2% | G36: =IF(C36="","PENDING",IF(E36<=0.002,"PASS","FAIL")) -> PENDING
A37: Intrinsic Value per Share | B37: ='DCF_CAT'!$B$43 -> 162.8409 | D37: =IF(C37="","PENDING",ABS(B37-C37)) -> PENDING | E37: =IF(OR(C37="",C37=0),"PENDING",ABS(B37-C37)/ABS(C37)) -> PENDING | F37: ±0.5% | G37: =IF(C37="","PENDING",IF(E37<=0.005,"PASS","FAIL")) -> PENDING
A39: — INTC (INTEL CORP) —
A40: Revenue CAGR | B40: ='DCF_INTC'!$B$9 -> -0.095544173 | D40: =IF(C40="","PENDING",ABS(B40-C40)) -> PENDING | E40: =IF(OR(C40="",C40=0),"PENDING",ABS(B40-C40)/ABS(C40)) -> PENDING | F40: ±0.01pp | G40: =IF(C40="","PENDING",IF(E40<=0.0001,"PASS","FAIL")) -> PENDING
A41: Operating Margin | B41: ='DCF_INTC'!$B$10 -> 0.0046248517 | D41: =IF(C41="","PENDING",ABS(B41-C41)) -> PENDING | E41: =IF(OR(C41="",C41=0),"PENDING",ABS(B41-C41)/ABS(C41)) -> PENDING | F41: ±0.01pp | G41: =IF(C41="","PENDING",IF(E41<=0.0001,"PASS","FAIL")) -> PENDING
A42: Raw WACC | B42: ='DCF_INTC'!$B$20 -> 0.15054645 | D42: =IF(C42="","PENDING",ABS(B42-C42)) -> PENDING | E42: =IF(OR(C42="",C42=0),"PENDING",ABS(B42-C42)/ABS(C42)) -> PENDING | F42: ±0.05pp | G42: =IF(C42="","PENDING",IF(E42<=0.0005,"PASS","FAIL")) -> PENDING
A43: Final WACC | B43: ='DCF_INTC'!$B$21 -> 0.15054645 | D43: =IF(C43="","PENDING",ABS(B43-C43)) -> PENDING | E43: =IF(OR(C43="",C43=0),"PENDING",ABS(B43-C43)/ABS(C43)) -> PENDING | F43: ±0.05pp | G43: =IF(C43="","PENDING",IF(E43<=0.0005,"PASS","FAIL")) -> PENDING
A44: FCF Year 1 | B44: ='DCF_INTC'!$C$31 -> -4.2384226e+08 | D44: =IF(C44="","PENDING",ABS(B44-C44)) -> PENDING | E44: =IF(OR(C44="",C44=0),"PENDING",ABS(B44-C44)/ABS(C44)) -> PENDING | F44: ±0.1% | G44: =IF(C44="","PENDING",IF(E44<=0.001,"PASS","FAIL")) -> PENDING
A45: FCF Year 2 | B45: ='DCF_INTC'!$D$31 -> -3.8334661e+08 | D45: =IF(C45="","PENDING",ABS(B45-C45)) -> PENDING | E45: =IF(OR(C45="",C45=0),"PENDING",ABS(B45-C45)/ABS(C45)) -> PENDING | F45: ±0.1% | G45: =IF(C45="","PENDING",IF(E45<=0.001,"PASS","FAIL")) -> PENDING
A46: FCF Year 3 | B46: ='DCF_INTC'!$E$31 -> -3.4672007e+08 | D46: =IF(C46="","PENDING",ABS(B46-C46)) -> PENDING | E46: =IF(OR(C46="",C46=0),"PENDING",ABS(B46-C46)/ABS(C46)) -> PENDING | F46: ±0.1% | G46: =IF(C46="","PENDING",IF(E46<=0.001,"PASS","FAIL")) -> PENDING
A47: FCF Year 4 | B47: ='DCF_INTC'!$F$31 -> -3.1359299e+08 | D47: =IF(C47="","PENDING",ABS(B47-C47)) -> PENDING | E47: =IF(OR(C47="",C47=0),"PENDING",ABS(B47-C47)/ABS(C47)) -> PENDING | F47: ±0.1% | G47: =IF(C47="","PENDING",IF(E47<=0.001,"PASS","FAIL")) -> PENDING
A48: FCF Year 5 | B48: ='DCF_INTC'!$G$31 -> -2.8363101e+08 | D48: =IF(C48="","PENDING",ABS(B48-C48)) -> PENDING | E48: =IF(OR(C48="",C48=0),"PENDING",ABS(B48-C48)/ABS(C48)) -> PENDING | F48: ±0.1% | G48: =IF(C48="","PENDING",IF(E48<=0.001,"PASS","FAIL")) -> PENDING
A49: Terminal Value | B49: ='DCF_INTC'!$B$34 -> -2.3156512e+09 | D49: =IF(C49="","PENDING",ABS(B49-C49)) -> PENDING | E49: =IF(OR(C49="",C49=0),"PENDING",ABS(B49-C49)/ABS(C49)) -> PENDING | F49: ±0.2% | G49: =IF(C49="","PENDING",IF(E49<=0.002,"PASS","FAIL")) -> PENDING
A50: PV of Explicit FCF | B50: ='DCF_INTC'!$B$39 -> -1.2052603e+09 | D50: =IF(C50="","PENDING",ABS(B50-C50)) -> PENDING | E50: =IF(OR(C50="",C50=0),"PENDING",ABS(B50-C50)/ABS(C50)) -> PENDING | F50: ±0.2% | G50: =IF(C50="","PENDING",IF(E50<=0.002,"PASS","FAIL")) -> PENDING
A51: PV of Terminal Value | B51: ='DCF_INTC'!$B$40 -> -1.1485565e+09 | D51: =IF(C51="","PENDING",ABS(B51-C51)) -> PENDING | E51: =IF(OR(C51="",C51=0),"PENDING",ABS(B51-C51)/ABS(C51)) -> PENDING | F51: ±0.2% | G51: =IF(C51="","PENDING",IF(E51<=0.002,"PASS","FAIL")) -> PENDING
A52: Enterprise Value | B52: ='DCF_INTC'!$B$41 -> -2.3538168e+09 | D52: =IF(C52="","PENDING",ABS(B52-C52)) -> PENDING | E52: =IF(OR(C52="",C52=0),"PENDING",ABS(B52-C52)/ABS(C52)) -> PENDING | F52: ±0.2% | G52: =IF(C52="","PENDING",IF(E52<=0.002,"PASS","FAIL")) -> PENDING
A53: Equity Value | B53: ='DCF_INTC'!$B$42 -> -3.4673817e+10 | D53: =IF(C53="","PENDING",ABS(B53-C53)) -> PENDING | E53: =IF(OR(C53="",C53=0),"PENDING",ABS(B53-C53)/ABS(C53)) -> PENDING | F53: ±0.2% | G53: =IF(C53="","PENDING",IF(E53<=0.002,"PASS","FAIL")) -> PENDING
A54: Intrinsic Value per Share | B54: ='DCF_INTC'!$B$43 -> -6.5594261 | D54: =IF(C54="","PENDING",ABS(B54-C54)) -> PENDING | E54: =IF(OR(C54="",C54=0),"PENDING",ABS(B54-C54)/ABS(C54)) -> PENDING | F54: ±0.5% | G54: =IF(C54="","PENDING",IF(E54<=0.005,"PASS","FAIL")) -> PENDING
A56: — VZ (VERIZON COMMUNICATIONS INC) —
A57: Revenue CAGR | B57: ='DCF_VZ'!$B$9 -> 0.0084578735 | D57: =IF(C57="","PENDING",ABS(B57-C57)) -> PENDING | E57: =IF(OR(C57="",C57=0),"PENDING",ABS(B57-C57)/ABS(C57)) -> PENDING | F57: ±0.01pp | G57: =IF(C57="","PENDING",IF(E57<=0.0001,"PASS","FAIL")) -> PENDING
A58: Operating Margin | B58: ='DCF_VZ'!$B$10 -> 0.21216289 | D58: =IF(C58="","PENDING",ABS(B58-C58)) -> PENDING | E58: =IF(OR(C58="",C58=0),"PENDING",ABS(B58-C58)/ABS(C58)) -> PENDING | F58: ±0.01pp | G58: =IF(C58="","PENDING",IF(E58<=0.0001,"PASS","FAIL")) -> PENDING
A59: Raw WACC | B59: ='DCF_VZ'!$B$20 -> 0.043949391 | D59: =IF(C59="","PENDING",ABS(B59-C59)) -> PENDING | E59: =IF(OR(C59="",C59=0),"PENDING",ABS(B59-C59)/ABS(C59)) -> PENDING | F59: ±0.05pp | G59: =IF(C59="","PENDING",IF(E59<=0.0005,"PASS","FAIL")) -> PENDING
A60: Final WACC | B60: ='DCF_VZ'!$B$21 -> 0.05 | D60: =IF(C60="","PENDING",ABS(B60-C60)) -> PENDING | E60: =IF(OR(C60="",C60=0),"PENDING",ABS(B60-C60)/ABS(C60)) -> PENDING | F60: ±0.05pp | G60: =IF(C60="","PENDING",IF(E60<=0.0005,"PASS","FAIL")) -> PENDING
A61: FCF Year 1 | B61: ='DCF_VZ'!$C$31 -> 2.1557635e+10 | D61: =IF(C61="","PENDING",ABS(B61-C61)) -> PENDING | E61: =IF(OR(C61="",C61=0),"PENDING",ABS(B61-C61)/ABS(C61)) -> PENDING | F61: ±0.1% | G61: =IF(C61="","PENDING",IF(E61<=0.001,"PASS","FAIL")) -> PENDING
