Workbook

Sheet Tolerances
A1: Tolerance constants -- single source of truth for every comparison table's Tolerance column
A2: Metric | B2: Tolerance | C2: Kind
A3: Revenue CAGR | B3: 0.0001 | C3: percentage points
A4: Operating Margin | B4: 0.0001 | C4: percentage points
A5: WACC | B5: 0.0005 | C5: percentage points
A6: Each FCF year | B6: 0.001 | C6: relative fraction
A7: Terminal Value | B7: 0.002 | C7: relative fraction
A8: PV of Explicit FCF | B8: 0.002 | C8: relative fraction
A9: PV of Terminal Value | B9: 0.002 | C9: relative fraction
A10: Enterprise Value | B10: 0.002 | C10: relative fraction
A11: Equity Value | B11: 0.002 | C11: relative fraction
A12: Intrinsic Value per Share | B12: 0.005 | C12: relative fraction
A13: Sensitivity IVPS (all tables) | B13: 0.005 | C13: relative fraction
A14: Zero-denominator floating-point carve-out (absolute $) | B14: 1e-06 | C14: absolute $

Sheet README
A1: DCF Codebase-to-Independent-Workbook Reconciliation (V2)
A2: Track A Phase 2C. This workbook reconciles src/dcf_model/dcf.py's production output against the independent workbook V2 (validation/independent_dcf/independent_dcf_validation_v2.xlsx), built from the corrected years_elapsed specification. V1 is preserved unchanged and never modified by this workbook or by any script in validation/dcf_reconciliation/.
A4: Sheets:
A5: - Tolerances: the single source of truth for every tolerance constant used elsewhere.
A6: - Base Reconciliation: all 14 required metrics x 4 companies, live-formula comparison.
A7: - Detail_<TICKER>: per-company base reconciliation + accurate sensitivity coverage counts.
A8: - Sensitivity Reconciliation: Table 1/2 full live-formula detail + coverage-count summary.
A9: - All Sensitivity Comparisons: EVERY Table 1-5 scalar comparison (908 rows), formula-driven.
A10: - Findings: narrative summary of what was (and wasn't) found.
A11: - Sign-off: commit/hash provenance (V1 AND V2) and outstanding second-reviewer requirement.
A13: Source commit: 776e76f56e6210f1050caa74c60962ed89162496 (branch remediation/valuation-engine-production-quality)
A14: V1 workbook SHA-256 (preserved, historical): 942b5f096cf546d63487add31eb29b1b690f0819f923f01436093f9bbc75eba1
... A17: PROFITABILITY NOT ESTABLISHED -- this workbook verifies calculation agreement between two independent implementations. It is not investment advice and does not establish that any company is profitable to trade.

Sheet Base Reconciliation
A1: Base-case reconciliation -- all four companies, all 14 required metrics
A2: Codebase/Workbook columns are hardcoded values imported from codebase_outputs.json and the independent workbook V2's cached cells (yellow fill). Absolute Difference / Relative-or-pp Difference / Tolerance / PASS-FAIL are live formulas (white fill). Number formats: percentages for rates, $ for dollar amounts, $0.00 for per-share values -- never conflated.
A4: Metric | B4: Codebase Output | C4: Workbook Output | D4: Absolute Difference | E4: Relative/pp Difference | F4: Tolerance | G4: PASS/FAIL | H4: Workbook Cell
A5: -- MSFT (Microsoft Corporation) --
A6: Historical Revenue CAGR | B6: 0.13741147 | C6: 0.13741147 | D6: =ABS(B6-C6) -> 0 | E6: =D6 -> 0 | F6: ='Tolerances'!$B$3 -> 0.0001 | G6: =IF(D6<=F6,"PASS","FAIL") -> PASS | H6: DCF_MSFT!B9
A7: Historical average Operating Margin | B7: 0.44175047 | C7: 0.44175047 | D7: =ABS(B7-C7) -> 0 | E7: =D7 -> 0 | F7: ='Tolerances'!$B$4 -> 0.0001 | G7: =IF(D7<=F7,"PASS","FAIL") -> PASS | H7: DCF_MSFT!B10
A8: WACC (final, clamped [5%,20%]) | B8: 0.10000422 | C8: 0.10000422 | D8: =ABS(B8-C8) -> 0 | E8: =D8 -> 0 | F8: ='Tolerances'!$B$5 -> 0.0005 | G8: =IF(D8<=F8,"PASS","FAIL") -> PASS | H8: DCF_MSFT!B21
A9: FCF Year 1 | B9: 1.3016281e+11 | C9: 1.3016281e+11 | D9: =ABS(B9-C9) -> 0 | E9: =IF(C9=0,"n/a (zero denom)",D9/ABS(C9)) -> 0 | F9: ='Tolerances'!$B$6 -> 0.001 | G9: =IF(C9=0,IF(D9<=0.000001,"PASS","FAIL"),IF(E9<=F9,"PASS","FAIL")) -> PASS | H9: DCF_MSFT!C31
A10: FCF Year 2 | B10: 1.4804868e+11 | C10: 1.4804868e+11 | D10: =ABS(B10-C10) -> 0 | E10: =IF(C10=0,"n/a (zero denom)",D10/ABS(C10)) -> 0 | F10: ='Tolerances'!$B$6 -> 0.001 | G10: =IF(C10=0,IF(D10<=0.000001,"PASS","FAIL"),IF(E10<=F10,"PASS","FAIL")) -> PASS | H10: DCF_MSFT!D31
A11: FCF Year 3 | B11: 1.6839226e+11 | C11: 1.6839226e+11 | D11: =ABS(B11-C11) -> 0 | E11: =IF(C11=0,"n/a (zero denom)",D11/ABS(C11)) -> 0 | F11: ='Tolerances'!$B$6 -> 0.001 | G11: =IF(C11=0,IF(D11<=0.000001,"PASS","FAIL"),IF(E11<=F11,"PASS","FAIL")) -> PASS | H11: DCF_MSFT!E31
A12: FCF Year 4 | B12: 1.9153129e+11 | C12: 1.9153129e+11 | D12: =ABS(B12-C12) -> 0 | E12: =IF(C12=0,"n/a (zero denom)",D12/ABS(C12)) -> 0 | F12: ='Tolerances'!$B$6 -> 0.001 | G12: =IF(C12=0,IF(D12<=0.000001,"PASS","FAIL"),IF(E12<=F12,"PASS","FAIL")) -> PASS | H12: DCF_MSFT!F31
A13: FCF Year 5 | B13: 2.1784989e+11 | C13: 2.1784989e+11 | D13: =ABS(B13-C13) -> 0 | E13: =IF(C13=0,"n/a (zero denom)",D13/ABS(C13)) -> 0 | F13: ='Tolerances'!$B$6 -> 0.001 | G13: =IF(C13=0,IF(D13<=0.000001,"PASS","FAIL"),IF(E13<=F13,"PASS","FAIL")) -> PASS | H13: DCF_MSFT!G31
A14: Terminal Value | B14: 2.9771145e+12 | C14: 2.9771145e+12 | D14: =ABS(B14-C14) -> 0 | E14: =IF(C14=0,"n/a (zero denom)",D14/ABS(C14)) -> 0 | F14: ='Tolerances'!$B$7 -> 0.002 | G14: =IF(C14=0,IF(D14<=0.000001,"PASS","FAIL"),IF(E14<=F14,"PASS","FAIL")) -> PASS | H14: DCF_MSFT!B34
A15: PV of Explicit FCF (sum of pv_fcf series) | B15: 6.3327836e+11 | C15: 6.3327836e+11 | D15: =ABS(B15-C15) -> 0 | E15: =IF(C15=0,"n/a (zero denom)",D15/ABS(C15)) -> 0 | F15: ='Tolerances'!$B$8 -> 0.002 | G15: =IF(C15=0,IF(D15<=0.000001,"PASS","FAIL"),IF(E15<=F15,"PASS","FAIL")) -> PASS | H15: DCF_MSFT!B39
A16: PV of Terminal Value | B16: 1.8485184e+12 | C16: 1.8485184e+12 | D16: =ABS(B16-C16) -> 0 | E16: =IF(C16=0,"n/a (zero denom)",D16/ABS(C16)) -> 0 | F16: ='Tolerances'!$B$9 -> 0.002 | G16: =IF(C16=0,IF(D16<=0.000001,"PASS","FAIL"),IF(E16<=F16,"PASS","FAIL")) -> PASS | H16: DCF_MSFT!B40
A17: Enterprise Value | B17: 2.4817968e+12 | C17: 2.4817968e+12 | D17: =ABS(B17-C17) -> 0 | E17: =IF(C17=0,"n/a (zero denom)",D17/ABS(C17)) -> 0 | F17: ='Tolerances'!$B$10 -> 0.002 | G17: =IF(C17=0,IF(D17<=0.000001,"PASS","FAIL"),IF(E17<=F17,"PASS","FAIL")) -> PASS | H17: DCF_MSFT!B41
A18: Equity Value | B18: 2.4624378e+12 | C18: 2.4624378e+12 | D18: =ABS(B18-C18) -> 0 | E18: =IF(C18=0,"n/a (zero denom)",D18/ABS(C18)) -> 0 | F18: ='Tolerances'!$B$11 -> 0.002 | G18: =IF(C18=0,IF(D18<=0.000001,"PASS","FAIL"),IF(E18<=F18,"PASS","FAIL")) -> PASS | H18: DCF_MSFT!B42
A19: Intrinsic Value per Share | B19: 331.61709 | C19: 331.61709 | D19: =ABS(B19-C19) -> 0 | E19: =IF(C19=0,"n/a (zero denom)",D19/ABS(C19)) -> 0 | F19: ='Tolerances'!$B$12 -> 0.005 | G19: =IF(C19=0,IF(D19<=0.000001,"PASS","FAIL"),IF(E19<=F19,"PASS","FAIL")) -> PASS | H19: DCF_MSFT!B43
A20: -- CAT (Caterpillar Inc.) --
A21: Historical Revenue CAGR | B21: 0.073095112 | C21: 0.073095112 | D21: =ABS(B21-C21) -> 0 | E21: =D21 -> 0 | F21: ='Tolerances'!$B$3 -> 0.0001 | G21: =IF(D21<=F21,"PASS","FAIL") -> PASS | H21: DCF_CAT!B9
A22: Historical average Operating Margin | B22: 0.16559502 | C22: 0.16559502 | D22: =ABS(B22-C22) -> 0 | E22: =D22 -> 0 | F22: ='Tolerances'!$B$4 -> 0.0001 | G22: =IF(D22<=F22,"PASS","FAIL") -> PASS | H22: DCF_CAT!B10
A23: WACC (final, clamped [5%,20%]) | B23: 0.12095875 | C23: 0.12095875 | D23: =ABS(B23-C23) -> 0 | E23: =D23 -> 0 | F23: ='Tolerances'!$B$5 -> 0.0005 | G23: =IF(D23<=F23,"PASS","FAIL") -> PASS | H23: DCF_CAT!B21
A24: FCF Year 1 | B24: 8.355205e+09 | C24: 8.355205e+09 | D24: =ABS(B24-C24) -> 0 | E24: =IF(C24=0,"n/a (zero denom)",D24/ABS(C24)) -> 0 | F24: ='Tolerances'!$B$6 -> 0.001 | G24: =IF(C24=0,IF(D24<=0.000001,"PASS","FAIL"),IF(E24<=F24,"PASS","FAIL")) -> PASS | H24: DCF_CAT!C31
A25: FCF Year 2 | B25: 8.9659296e+09 | C25: 8.9659296e+09 | D25: =ABS(B25-C25) -> 0 | E25: =IF(C25=0,"n/a (zero denom)",D25/ABS(C25)) -> 0 | F25: ='Tolerances'!$B$6 -> 0.001 | G25: =IF(C25=0,IF(D25<=0.000001,"PASS","FAIL"),IF(E25<=F25,"PASS","FAIL")) -> PASS | H25: DCF_CAT!D31
A26: FCF Year 3 | B26: 9.6212953e+09 | C26: 9.6212953e+09 | D26: =ABS(B26-C26) -> 0 | E26: =IF(C26=0,"n/a (zero denom)",D26/ABS(C26)) -> 0 | F26: ='Tolerances'!$B$6 -> 0.001 | G26: =IF(C26=0,IF(D26<=0.000001,"PASS","FAIL"),IF(E26<=F26,"PASS","FAIL")) -> PASS | H26: DCF_CAT!E31
A27: FCF Year 4 | B27: 1.0324565e+10 | C27: 1.0324565e+10 | D27: =ABS(B27-C27) -> 0 | E27: =IF(C27=0,"n/a (zero denom)",D27/ABS(C27)) -> 0 | F27: ='Tolerances'!$B$6 -> 0.001 | G27: =IF(C27=0,IF(D27<=0.000001,"PASS","FAIL"),IF(E27<=F27,"PASS","FAIL")) -> PASS | H27: DCF_CAT!F31
A28: FCF Year 5 | B28: 1.107924e+10 | C28: 1.107924e+10 | D28: =ABS(B28-C28) -> 0 | E28: =IF(C28=0,"n/a (zero denom)",D28/ABS(C28)) -> 0 | F28: ='Tolerances'!$B$6 -> 0.001 | G28: =IF(C28=0,IF(D28<=0.000001,"PASS","FAIL"),IF(E28<=F28,"PASS","FAIL")) -> PASS | H28: DCF_CAT!G31
A29: Terminal Value | B29: 1.1834482e+11 | C29: 1.1834482e+11 | D29: =ABS(B29-C29) -> 0 | E29: =IF(C29=0,"n/a (zero denom)",D29/ABS(C29)) -> 0 | F29: ='Tolerances'!$B$7 -> 0.002 | G29: =IF(C29=0,IF(D29<=0.000001,"PASS","FAIL"),IF(E29<=F29,"PASS","FAIL")) -> PASS | H29: DCF_CAT!B34
A30: PV of Explicit FCF (sum of pv_fcf series) | B30: 3.4218526e+10 | C30: 3.4218526e+10 | D30: =ABS(B30-C30) -> 0 | E30: =IF(C30=0,"n/a (zero denom)",D30/ABS(C30)) -> 0 | F30: ='Tolerances'!$B$8 -> 0.002 | G30: =IF(C30=0,IF(D30<=0.000001,"PASS","FAIL"),IF(E30<=F30,"PASS","FAIL")) -> PASS | H30: DCF_CAT!B39
A31: PV of Terminal Value | B31: 6.6865345e+10 | C31: 6.6865345e+10 | D31: =ABS(B31-C31) -> 0 | E31: =IF(C31=0,"n/a (zero denom)",D31/ABS(C31)) -> 0 | F31: ='Tolerances'!$B$9 -> 0.002 | G31: =IF(C31=0,IF(D31<=0.000001,"PASS","FAIL"),IF(E31<=F31,"PASS","FAIL")) -> PASS | H31: DCF_CAT!B40
A32: Enterprise Value | B32: 1.0108387e+11 | C32: 1.0108387e+11 | D32: =ABS(B32-C32) -> 0 | E32: =IF(C32=0,"n/a (zero denom)",D32/ABS(C32)) -> 0 | F32: ='Tolerances'!$B$10 -> 0.002 | G32: =IF(C32=0,IF(D32<=0.000001,"PASS","FAIL"),IF(E32<=F32,"PASS","FAIL")) -> PASS | H32: DCF_CAT!B41
A33: Equity Value | B33: 7.4853871e+10 | C33: 7.4853871e+10 | D33: =ABS(B33-C33) -> 0 | E33: =IF(C33=0,"n/a (zero denom)",D33/ABS(C33)) -> 0 | F33: ='Tolerances'!$B$11 -> 0.002 | G33: =IF(C33=0,IF(D33<=0.000001,"PASS","FAIL"),IF(E33<=F33,"PASS","FAIL")) -> PASS | H33: DCF_CAT!B42
A34: Intrinsic Value per Share | B34: 162.8409 | C34: 162.8409 | D34: =ABS(B34-C34) -> 0 | E34: =IF(C34=0,"n/a (zero denom)",D34/ABS(C34)) -> 0 | F34: ='Tolerances'!$B$12 -> 0.005 | G34: =IF(C34=0,IF(D34<=0.000001,"PASS","FAIL"),IF(E34<=F34,"PASS","FAIL")) -> PASS | H34: DCF_CAT!B43
A35: -- INTC (Intel Corporation) --
A36: Historical Revenue CAGR | B36: -0.095544173 | C36: -0.095544173 | D36: =ABS(B36-C36) -> 0 | E36: =D36 -> 0 | F36: ='Tolerances'!$B$3 -> 0.0001 | G36: =IF(D36<=F36,"PASS","FAIL") -> PASS | H36: DCF_INTC!B9
A37: Historical average Operating Margin | B37: 0.0046248517 | C37: 0.0046248517 | D37: =ABS(B37-C37) -> 0 | E37: =D37 -> 0 | F37: ='Tolerances'!$B$4 -> 0.0001 | G37: =IF(D37<=F37,"PASS","FAIL") -> PASS | H37: DCF_INTC!B10
A38: WACC (final, clamped [5%,20%]) | B38: 0.15054645 | C38: 0.15054645 | D38: =ABS(B38-C38) -> 0 | E38: =D38 -> 0 | F38: ='Tolerances'!$B$5 -> 0.0005 | G38: =IF(D38<=F38,"PASS","FAIL") -> PASS | H38: DCF_INTC!B21
A39: FCF Year 1 | B39: -4.2384226e+08 | C39: -4.2384226e+08 | D39: =ABS(B39-C39) -> 0 | E39: =IF(C39=0,"n/a (zero denom)",D39/ABS(C39)) -> 0 | F39: ='Tolerances'!$B$6 -> 0.001 | G39: =IF(C39=0,IF(D39<=0.000001,"PASS","FAIL"),IF(E39<=F39,"PASS","FAIL")) -> PASS | H39: DCF_INTC!C31
A40: FCF Year 2 | B40: -3.8334661e+08 | C40: -3.8334661e+08 | D40: =ABS(B40-C40) -> 0 | E40: =IF(C40=0,"n/a (zero denom)",D40/ABS(C40)) -> 0 | F40: ='Tolerances'!$B$6 -> 0.001 | G40: =IF(C40=0,IF(D40<=0.000001,"PASS","FAIL"),IF(E40<=F40,"PASS","FAIL")) -> PASS | H40: DCF_INTC!D31
A41: FCF Year 3 | B41: -3.4672007e+08 | C41: -3.4672007e+08 | D41: =ABS(B41-C41) -> 0 | E41: =IF(C41=0,"n/a (zero denom)",D41/ABS(C41)) -> 0 | F41: ='Tolerances'!$B$6 -> 0.001 | G41: =IF(C41=0,IF(D41<=0.000001,"PASS","FAIL"),IF(E41<=F41,"PASS","FAIL")) -> PASS | H41: DCF_INTC!E31
A42: FCF Year 4 | B42: -3.1359299e+08 | C42: -3.1359299e+08 | D42: =ABS(B42-C42) -> 0 | E42: =IF(C42=0,"n/a (zero denom)",D42/ABS(C42)) -> 0 | F42: ='Tolerances'!$B$6 -> 0.001 | G42: =IF(C42=0,IF(D42<=0.000001,"PASS","FAIL"),IF(E42<=F42,"PASS","FAIL")) -> PASS | H42: DCF_INTC!F31
A43: FCF Year 5 | B43: -2.8363101e+08 | C43: -2.8363101e+08 | D43: =ABS(B43-C43) -> 0 | E43: =IF(C43=0,"n/a (zero denom)",D43/ABS(C43)) -> 0 | F43: ='Tolerances'!$B$6 -> 0.001 | G43: =IF(C43=0,IF(D43<=0.000001,"PASS","FAIL"),IF(E43<=F43,"PASS","FAIL")) -> PASS | H43: DCF_INTC!G31
A44: Terminal Value | B44: -2.3156512e+09 | C44: -2.3156512e+09 | D44: =ABS(B44-C44) -> 0 | E44: =IF(C44=0,"n/a (zero denom)",D44/ABS(C44)) -> 0 | F44: ='Tolerances'!$B$7 -> 0.002 | G44: =IF(C44=0,IF(D44<=0.000001,"PASS","FAIL"),IF(E44<=F44,"PASS","FAIL")) -> PASS | H44: DCF_INTC!B34
A45: PV of Explicit FCF (sum of pv_fcf series) | B45: -1.2052603e+09 | C45: -1.2052603e+09 | D45: =ABS(B45-C45) -> 0 | E45: =IF(C45=0,"n/a (zero denom)",D45/ABS(C45)) -> 0 | F45: ='Tolerances'!$B$8 -> 0.002 | G45: =IF(C45=0,IF(D45<=0.000001,"PASS","FAIL"),IF(E45<=F45,"PASS","FAIL")) -> PASS | H45: DCF_INTC!B39
A46: PV of Terminal Value | B46: -1.1485565e+09 | C46: -1.1485565e+09 | D46: =ABS(B46-C46) -> 0 | E46: =IF(C46=0,"n/a (zero denom)",D46/ABS(C46)) -> 0 | F46: ='Tolerances'!$B$9 -> 0.002 | G46: =IF(C46=0,IF(D46<=0.000001,"PASS","FAIL"),IF(E46<=F46,"PASS","FAIL")) -> PASS | H46: DCF_INTC!B40
A47: Enterprise Value | B47: -2.3538168e+09 | C47: -2.3538168e+09 | D47: =ABS(B47-C47) -> 0 | E47: =IF(C47=0,"n/a (zero denom)",D47/ABS(C47)) -> 0 | F47: ='Tolerances'!$B$10 -> 0.002 | G47: =IF(C47=0,IF(D47<=0.000001,"PASS","FAIL"),IF(E47<=F47,"PASS","FAIL")) -> PASS | H47: DCF_INTC!B41
A48: Equity Value | B48: -3.4673817e+10 | C48: -3.4673817e+10 | D48: =ABS(B48-C48) -> 0 | E48: =IF(C48=0,"n/a (zero denom)",D48/ABS(C48)) -> 0 | F48: ='Tolerances'!$B$11 -> 0.002 | G48: =IF(C48=0,IF(D48<=0.000001,"PASS","FAIL"),IF(E48<=F48,"PASS","FAIL")) -> PASS | H48: DCF_INTC!B42
A49: Intrinsic Value per Share | B49: -6.5594261 | C49: -6.5594261 | D49: =ABS(B49-C49) -> 0 | E49: =IF(C49=0,"n/a (zero denom)",D49/ABS(C49)) -> 0 | F49: ='Tolerances'!$B$12 -> 0.005 | G49: =IF(C49=0,IF(D49<=0.000001,"PASS","FAIL"),IF(E49<=F49,"PASS","FAIL")) -> PASS | H49: DCF_INTC!B43
A50: -- VZ (Verizon Communications Inc.) --
A51: Historical Revenue CAGR | B51: 0.0084578735 | C51: 0.0084578735 | D51: =ABS(B51-C51) -> 0 | E51: =D51 -> 0 | F51: ='Tolerances'!$B$3 -> 0.0001 | G51: =IF(D51<=F51,"PASS","FAIL") -> PASS | H51: DCF_VZ!B9
A52: Historical average Operating Margin | B52: 0.21216289 | C52: 0.21216289 | D52: =ABS(B52-C52) -> 0 | E52: =D52 -> 0 | F52: ='Tolerances'!$B$4 -> 0.0001 | G52: =IF(D52<=F52,"PASS","FAIL") -> PASS | H52: DCF_VZ!B10
A53: WACC (final, clamped [5%,20%]) | B53: 0.05 | C53: 0.05 | D53: =ABS(B53-C53) -> 0 | E53: =D53 -> 0 | F53: ='Tolerances'!$B$5 -> 0.0005 | G53: =IF(D53<=F53,"PASS","FAIL") -> PASS | H53: DCF_VZ!B21
A54: FCF Year 1 | B54: 2.1557635e+10 | C54: 2.1557635e+10 | D54: =ABS(B54-C54) -> 0 | E54: =IF(C54=0,"n/a (zero denom)",D54/ABS(C54)) -> 0 | F54: ='Tolerances'!$B$6 -> 0.001 | G54: =IF(C54=0,IF(D54<=0.000001,"PASS","FAIL"),IF(E54<=F54,"PASS","FAIL")) -> PASS | H54: DCF_VZ!C31
A55: FCF Year 2 | B55: 2.1739967e+10 | C55: 2.1739967e+10 | D55: =ABS(B55-C55) -> 0 | E55: =IF(C55=0,"n/a (zero denom)",D55/ABS(C55)) -> 0 | F55: ='Tolerances'!$B$6 -> 0.001 | G55: =IF(C55=0,IF(D55<=0.000001,"PASS","FAIL"),IF(E55<=F55,"PASS","FAIL")) -> PASS | H55: DCF_VZ!D31
A56: FCF Year 3 | B56: 2.1923841e+10 | C56: 2.1923841e+10 | D56: =ABS(B56-C56) -> 0 | E56: =IF(C56=0,"n/a (zero denom)",D56/ABS(C56)) -> 0 | F56: ='Tolerances'!$B$6 -> 0.001 | G56: =IF(C56=0,IF(D56<=0.000001,"PASS","FAIL"),IF(E56<=F56,"PASS","FAIL")) -> PASS | H56: DCF_VZ!E31
A57: FCF Year 4 | B57: 2.210927e+10 | C57: 2.210927e+10 | D57: =ABS(B57-C57) -> 0 | E57: =IF(C57=0,"n/a (zero denom)",D57/ABS(C57)) -> 0 | F57: ='Tolerances'!$B$6 -> 0.001 | G57: =IF(C57=0,IF(D57<=0.000001,"PASS","FAIL"),IF(E57<=F57,"PASS","FAIL")) -> PASS | H57: DCF_VZ!F31
A58: FCF Year 5 | B58: 2.2296268e+10 | C58: 2.2296268e+10 | D58: =ABS(B58-C58) -> 0 | E58: =IF(C58=0,"n/a (zero denom)",D58/ABS(C58)) -> 0 | F58: ='Tolerances'!$B$6 -> 0.001 | G58: =IF(C58=0,IF(D58<=0.000001,"PASS","FAIL"),IF(E58<=F58,"PASS","FAIL")) -> PASS | H58: DCF_VZ!G31
A59: Terminal Value | B59: 9.1414697e+11 | C59: 9.1414697e+11 | D59: =ABS(B59-C59) -> 0 | E59: =IF(C59=0,"n/a (zero denom)",D59/ABS(C59)) -> 0 | F59: ='Tolerances'!$B$7 -> 0.002 | G59: =IF(C59=0,IF(D59<=0.000001,"PASS","FAIL"),IF(E59<=F59,"PASS","FAIL")) -> PASS | H59: DCF_VZ!B34
A60: PV of Explicit FCF (sum of pv_fcf series) | B60: 9.4847571e+10 | C60: 9.4847571e+10 | D60: =ABS(B60-C60) -> 0 | E60: =IF(C60=0,"n/a (zero denom)",D60/ABS(C60)) -> 0 | F60: ='Tolerances'!$B$8 -> 0.002 | G60: =IF(C60=0,IF(D60<=0.000001,"PASS","FAIL"),IF(E60<=F60,"PASS","FAIL")) -> PASS | H60: DCF_VZ!B39
A61: PV of Terminal Value | B61: 7.1625807e+11 | C61: 7.1625807e+11 | D61: =ABS(B61-C61) -> 0 | E61: =IF(C61=0,"n/a (zero denom)",D61/ABS(C61)) -> 0 | F61: ='Tolerances'!$B$9 -> 0.002 | G61: =IF(C61=0,IF(D61<=0.000001,"PASS","FAIL"),IF(E61<=F61,"PASS","FAIL")) -> PASS | H61: DCF_VZ!B40
A62: Enterprise Value | B62: 8.1110564e+11 | C62: 8.1110564e+11 | D62: =ABS(B62-C62) -> 0 | E62: =IF(C62=0,"n/a (zero denom)",D62/ABS(C62)) -> 0 | F62: ='Tolerances'!$B$10 -> 0.002 | G62: =IF(C62=0,IF(D62<=0.000001,"PASS","FAIL"),IF(E62<=F62,"PASS","FAIL")) -> PASS | H62: DCF_VZ!B41
A63: Equity Value | B63: 6.7200364e+11 | C63: 6.7200364e+11 | D63: =ABS(B63-C63) -> 0 | E63: =IF(C63=0,"n/a (zero denom)",D63/ABS(C63)) -> 0 | F63: ='Tolerances'!$B$11 -> 0.002 | G63: =IF(C63=0,IF(D63<=0.000001,"PASS","FAIL"),IF(E63<=F63,"PASS","FAIL")) -> PASS | H63: DCF_VZ!B42
A64: Intrinsic Value per Share | B64: 161.74248 | C64: 161.74248 | D64: =ABS(B64-C64) -> 0 | E64: =IF(C64=0,"n/a (zero denom)",D64/ABS(C64)) -> 0 | F64: ='Tolerances'!$B$12 -> 0.005 | G64: =IF(C64=0,IF(D64<=0.000001,"PASS","FAIL"),IF(E64<=F64,"PASS","FAIL")) -> PASS | H64: DCF_VZ!B43

Sheet Detail_MSFT
A1: Detailed base-case reconciliation -- MSFT (Microsoft Corporation)
A2: All metrics within tolerance.
A4: Metric | B4: Codebase Output | C4: Workbook Output | D4: Absolute Difference | E4: Relative/pp Difference | F4: Tolerance | G4: PASS/FAIL | H4: Workbook Cell
A5: Historical Revenue CAGR | B5: 0.13741147 | C5: 0.13741147 | D5: =ABS(B5-C5) -> 0 | E5: =D5 -> 0 | F5: ='Tolerances'!$B$3 -> 0.0001 | G5: =IF(D5<=F5,"PASS","FAIL") -> PASS | H5: DCF_MSFT!B9
A6: Historical average Operating Margin | B6: 0.44175047 | C6: 0.44175047 | D6: =ABS(B6-C6) -> 0 | E6: =D6 -> 0 | F6: ='Tolerances'!$B$4 -> 0.0001 | G6: =IF(D6<=F6,"PASS","FAIL") -> PASS | H6: DCF_MSFT!B10
A7: WACC (final, clamped [5%,20%]) | B7: 0.10000422 | C7: 0.10000422 | D7: =ABS(B7-C7) -> 0 | E7: =D7 -> 0 | F7: ='Tolerances'!$B$5 -> 0.0005 | G7: =IF(D7<=F7,"PASS","FAIL") -> PASS | H7: DCF_MSFT!B21
A8: FCF Year 1 | B8: 1.3016281e+11 | C8: 1.3016281e+11 | D8: =ABS(B8-C8) -> 0 | E8: =IF(C8=0,"n/a (zero denom)",D8/ABS(C8)) -> 0 | F8: ='Tolerances'!$B$6 -> 0.001 | G8: =IF(C8=0,IF(D8<=0.000001,"PASS","FAIL"),IF(E8<=F8,"PASS","FAIL")) -> PASS | H8: DCF_MSFT!C31
A9: FCF Year 2 | B9: 1.4804868e+11 | C9: 1.4804868e+11 | D9: =ABS(B9-C9) -> 0 | E9: =IF(C9=0,"n/a (zero denom)",D9/ABS(C9)) -> 0 | F9: ='Tolerances'!$B$6 -> 0.001 | G9: =IF(C9=0,IF(D9<=0.000001,"PASS","FAIL"),IF(E9<=F9,"PASS","FAIL")) -> PASS | H9: DCF_MSFT!D31
A10: FCF Year 3 | B10: 1.6839226e+11 | C10: 1.6839226e+11 | D10: =ABS(B10-C10) -> 0 | E10: =IF(C10=0,"n/a (zero denom)",D10/ABS(C10)) -> 0 | F10: ='Tolerances'!$B$6 -> 0.001 | G10: =IF(C10=0,IF(D10<=0.000001,"PASS","FAIL"),IF(E10<=F10,"PASS","FAIL")) -> PASS | H10: DCF_MSFT!E31
A11: FCF Year 4 | B11: 1.9153129e+11 | C11: 1.9153129e+11 | D11: =ABS(B11-C11) -> 0 | E11: =IF(C11=0,"n/a (zero denom)",D11/ABS(C11)) -> 0 | F11: ='Tolerances'!$B$6 -> 0.001 | G11: =IF(C11=0,IF(D11<=0.000001,"PASS","FAIL"),IF(E11<=F11,"PASS","FAIL")) -> PASS | H11: DCF_MSFT!F31
A12: FCF Year 5 | B12: 2.1784989e+11 | C12: 2.1784989e+11 | D12: =ABS(B12-C12) -> 0 | E12: =IF(C12=0,"n/a (zero denom)",D12/ABS(C12)) -> 0 | F12: ='Tolerances'!$B$6 -> 0.001 | G12: =IF(C12=0,IF(D12<=0.000001,"PASS","FAIL"),IF(E12<=F12,"PASS","FAIL")) -> PASS | H12: DCF_MSFT!G31
A13: Terminal Value | B13: 2.9771145e+12 | C13: 2.9771145e+12 | D13: =ABS(B13-C13) -> 0 | E13: =IF(C13=0,"n/a (zero denom)",D13/ABS(C13)) -> 0 | F13: ='Tolerances'!$B$7 -> 0.002 | G13: =IF(C13=0,IF(D13<=0.000001,"PASS","FAIL"),IF(E13<=F13,"PASS","FAIL")) -> PASS | H13: DCF_MSFT!B34
A14: PV of Explicit FCF (sum of pv_fcf series) | B14: 6.3327836e+11 | C14: 6.3327836e+11 | D14: =ABS(B14-C14) -> 0 | E14: =IF(C14=0,"n/a (zero denom)",D14/ABS(C14)) -> 0 | F14: ='Tolerances'!$B$8 -> 0.002 | G14: =IF(C14=0,IF(D14<=0.000001,"PASS","FAIL"),IF(E14<=F14,"PASS","FAIL")) -> PASS | H14: DCF_MSFT!B39
A15: PV of Terminal Value | B15: 1.8485184e+12 | C15: 1.8485184e+12 | D15: =ABS(B15-C15) -> 0 | E15: =IF(C15=0,"n/a (zero denom)",D15/ABS(C15)) -> 0 | F15: ='Tolerances'!$B$9 -> 0.002 | G15: =IF(C15=0,IF(D15<=0.000001,"PASS","FAIL"),IF(E15<=F15,"PASS","FAIL")) -> PASS | H15: DCF_MSFT!B40
A16: Enterprise Value | B16: 2.4817968e+12 | C16: 2.4817968e+12 | D16: =ABS(B16-C16) -> 0 | E16: =IF(C16=0,"n/a (zero denom)",D16/ABS(C16)) -> 0 | F16: ='Tolerances'!$B$10 -> 0.002 | G16: =IF(C16=0,IF(D16<=0.000001,"PASS","FAIL"),IF(E16<=F16,"PASS","FAIL")) -> PASS | H16: DCF_MSFT!B41
A17: Equity Value | B17: 2.4624378e+12 | C17: 2.4624378e+12 | D17: =ABS(B17-C17) -> 0 | E17: =IF(C17=0,"n/a (zero denom)",D17/ABS(C17)) -> 0 | F17: ='Tolerances'!$B$11 -> 0.002 | G17: =IF(C17=0,IF(D17<=0.000001,"PASS","FAIL"),IF(E17<=F17,"PASS","FAIL")) -> PASS | H17: DCF_MSFT!B42
A18: Intrinsic Value per Share | B18: 331.61709 | C18: 331.61709 | D18: =ABS(B18-C18) -> 0 | E18: =IF(C18=0,"n/a (zero denom)",D18/ABS(C18)) -> 0 | F18: ='Tolerances'!$B$12 -> 0.005 | G18: =IF(C18=0,IF(D18<=0.000001,"PASS","FAIL"),IF(E18<=F18,"PASS","FAIL")) -> PASS | H18: DCF_MSFT!B43
A20: Sensitivity reconciliation coverage (full per-cell detail: 'All Sensitivity Comparisons' sheet)
A21: Table | B21: Scenario Rows | C21: Outputs / Row | D21: Scalar Comparisons | E21: All Pass
A22: Table 1 -- WACC | B22: 7 | C22: 4 | D22: =B22*C22 -> 28 | E22: PASS
A23: Table 2 -- Terminal growth | B23: 7 | C23: 4 | D23: =B23*C23 -> 28 | E23: PASS
A24: Table 3 -- Revenue growth | B24: 8 | C24: 9 | D24: =B24*C24 -> 72 | E24: PASS
A25: Table 4 -- Operating margin | B25: 7 | C25: 9 | D25: =B25*C25 -> 63 | E25: PASS
A26: Table 5 -- WACC x g two-way grid | B26: 36 | C26: 1 | D26: =B26*C26 -> 36 | E26: PASS
A27: TOTAL (this company) | D27: =SUM(D22:D26) -> 227

Sheet Detail_CAT
A1: Detailed base-case reconciliation -- CAT (Caterpillar Inc.)
A2: All metrics within tolerance.
A4: Metric | B4: Codebase Output | C4: Workbook Output | D4: Absolute Difference | E4: Relative/pp Difference | F4: Tolerance | G4: PASS/FAIL | H4: Workbook Cell
A5: Historical Revenue CAGR | B5: 0.073095112 | C5: 0.073095112 | D5: =ABS(B5-C5) -> 0 | E5: =D5 -> 0 | F5: ='Tolerances'!$B$3 -> 0.0001 | G5: =IF(D5<=F5,"PASS","FAIL") -> PASS | H5: DCF_CAT!B9
A6: Historical average Operating Margin | B6: 0.16559502 | C6: 0.16559502 | D6: =ABS(B6-C6) -> 0 | E6: =D6 -> 0 | F6: ='Tolerances'!$B$4 -> 0.0001 | G6: =IF(D6<=F6,"PASS","FAIL") -> PASS | H6: DCF_CAT!B10
A7: WACC (final, clamped [5%,20%]) | B7: 0.12095875 | C7: 0.12095875 | D7: =ABS(B7-C7) -> 0 | E7: =D7 -> 0 | F7: ='Tolerances'!$B$5 -> 0.0005 | G7: =IF(D7<=F7,"PASS","FAIL") -> PASS | H7: DCF_CAT!B21
A8: FCF Year 1 | B8: 8.355205e+09 | C8: 8.355205e+09 | D8: =ABS(B8-C8) -> 0 | E8: =IF(C8=0,"n/a (zero denom)",D8/ABS(C8)) -> 0 | F8: ='Tolerances'!$B$6 -> 0.001 | G8: =IF(C8=0,IF(D8<=0.000001,"PASS","FAIL"),IF(E8<=F8,"PASS","FAIL")) -> PASS | H8: DCF_CAT!C31
A9: FCF Year 2 | B9: 8.9659296e+09 | C9: 8.9659296e+09 | D9: =ABS(B9-C9) -> 0 | E9: =IF(C9=0,"n/a (zero denom)",D9/ABS(C9)) -> 0 | F9: ='Tolerances'!$B$6 -> 0.001 | G9: =IF(C9=0,IF(D9<=0.000001,"PASS","FAIL"),IF(E9<=F9,"PASS","FAIL")) -> PASS | H9: DCF_CAT!D31
A10: FCF Year 3 | B10: 9.6212953e+09 | C10: 9.6212953e+09 | D10: =ABS(B10-C10) -> 0 | E10: =IF(C10=0,"n/a (zero denom)",D10/ABS(C10)) -> 0 | F10: ='Tolerances'!$B$6 -> 0.001 | G10: =IF(C10=0,IF(D10<=0.000001,"PASS","FAIL"),IF(E10<=F10,"PASS","FAIL")) -> PASS | H10: DCF_CAT!E31
A11: FCF Year 4 | B11: 1.0324565e+10 | C11: 1.0324565e+10 | D11: =ABS(B11-C11) -> 0 | E11: =IF(C11=0,"n/a (zero denom)",D11/ABS(C11)) -> 0 | F11: ='Tolerances'!$B$6 -> 0.001 | G11: =IF(C11=0,IF(D11<=0.000001,"PASS","FAIL"),IF(E11<=F11,"PASS","FAIL")) -> PASS | H11: DCF_CAT!F31
A12: FCF Year 5 | B12: 1.107924e+10 | C12: 1.107924e+10 | D12: =ABS(B12-C12) -> 0 | E12: =IF(C12=0,"n/a (zero denom)",D12/ABS(C12)) -> 0 | F12: ='Tolerances'!$B$6 -> 0.001 | G12: =IF(C12=0,IF(D12<=0.000001,"PASS","FAIL"),IF(E12<=F12,"PASS","FAIL")) -> PASS | H12: DCF_CAT!G31
A13: Terminal Value | B13: 1.1834482e+11 | C13: 1.1834482e+11 | D13: =ABS(B13-C13) -> 0 | E13: =IF(C13=0,"n/a (zero denom)",D13/ABS(C13)) -> 0 | F13: ='Tolerances'!$B$7 -> 0.002 | G13: =IF(C13=0,IF(D13<=0.000001,"PASS","FAIL"),IF(E13<=F13,"PASS","FAIL")) -> PASS | H13: DCF_CAT!B34
A14: PV of Explicit FCF (sum of pv_fcf series) | B14: 3.4218526e+10 | C14: 3.4218526e+10 | D14: =ABS(B14-C14) -> 0 | E14: =IF(C14=0,"n/a (zero denom)",D14/ABS(C14)) -> 0 | F14: ='Tolerances'!$B$8 -> 0.002 | G14: =IF(C14=0,IF(D14<=0.000001,"PASS","FAIL"),IF(E14<=F14,"PASS","FAIL")) -> PASS | H14: DCF_CAT!B39
A15: PV of Terminal Value | B15: 6.6865345e+10 | C15: 6.6865345e+10 | D15: =ABS(B15-C15) -> 0 | E15: =IF(C15=0,"n/a (zero denom)",D15/ABS(C15)) -> 0 | F15: ='Tolerances'!$B$9 -> 0.002 | G15: =IF(C15=0,IF(D15<=0.000001,"PASS","FAIL"),IF(E15<=F15,"PASS","FAIL")) -> PASS | H15: DCF_CAT!B40
A16: Enterprise Value | B16: 1.0108387e+11 | C16: 1.0108387e+11 | D16: =ABS(B16-C16) -> 0 | E16: =IF(C16=0,"n/a (zero denom)",D16/ABS(C16)) -> 0 | F16: ='Tolerances'!$B$10 -> 0.002 | G16: =IF(C16=0,IF(D16<=0.000001,"PASS","FAIL"),IF(E16<=F16,"PASS","FAIL")) -> PASS | H16: DCF_CAT!B41
A17: Equity Value | B17: 7.4853871e+10 | C17: 7.4853871e+10 | D17: =ABS(B17-C17) -> 0 | E17: =IF(C17=0,"n/a (zero denom)",D17/ABS(C17)) -> 0 | F17: ='Tolerances'!$B$11 -> 0.002 | G17: =IF(C17=0,IF(D17<=0.000001,"PASS","FAIL"),IF(E17<=F17,"PASS","FAIL")) -> PASS | H17: DCF_CAT!B42
A18: Intrinsic Value per Share | B18: 162.8409 | C18: 162.8409 | D18: =ABS(B18-C18) -> 0 | E18: =IF(C18=0,"n/a (zero denom)",D18/ABS(C18)) -> 0 | F18: ='Tolerances'!$B$12 -> 0.005 | G18: =IF(C18=0,IF(D18<=0.000001,"PASS","FAIL"),IF(E18<=F18,"PASS","FAIL")) -> PASS | H18: DCF_CAT!B43
A20: Sensitivity reconciliation coverage (full per-cell detail: 'All Sensitivity Comparisons' sheet)
A21: Table | B21: Scenario Rows | C21: Outputs / Row | D21: Scalar Comparisons | E21: All Pass
A22: Table 1 -- WACC | B22: 7 | C22: 4 | D22: =B22*C22 -> 28 | E22: PASS
A23: Table 2 -- Terminal growth | B23: 7 | C23: 4 | D23: =B23*C23 -> 28 | E23: PASS
A24: Table 3 -- Revenue growth | B24: 8 | C24: 9 | D24: =B24*C24 -> 72 | E24: PASS
A25: Table 4 -- Operating margin | B25: 7 | C25: 9 | D25: =B25*C25 -> 63 | E25: PASS
A26: Table 5 -- WACC x g two-way grid | B26: 36 | C26: 1 | D26: =B26*C26 -> 36 | E26: PASS
A27: TOTAL (this company) | D27: =SUM(D22:D26) -> 227

Sheet Detail_INTC
A1: Detailed base-case reconciliation -- INTC (Intel Corporation)
A2: All metrics within tolerance.
A4: Metric | B4: Codebase Output | C4: Workbook Output | D4: Absolute Difference | E4: Relative/pp Difference | F4: Tolerance | G4: PASS/FAIL | H4: Workbook Cell
A5: Historical Revenue CAGR | B5: -0.095544173 | C5: -0.095544173 | D5: =ABS(B5-C5) -> 0 | E5: =D5 -> 0 | F5: ='Tolerances'!$B$3 -> 0.0001 | G5: =IF(D5<=F5,"PASS","FAIL") -> PASS | H5: DCF_INTC!B9
A6: Historical average Operating Margin | B6: 0.0046248517 | C6: 0.0046248517 | D6: =ABS(B6-C6) -> 0 | E6: =D6 -> 0 | F6: ='Tolerances'!$B$4 -> 0.0001 | G6: =IF(D6<=F6,"PASS","FAIL") -> PASS | H6: DCF_INTC!B10
A7: WACC (final, clamped [5%,20%]) | B7: 0.15054645 | C7: 0.15054645 | D7: =ABS(B7-C7) -> 0 | E7: =D7 -> 0 | F7: ='Tolerances'!$B$5 -> 0.0005 | G7: =IF(D7<=F7,"PASS","FAIL") -> PASS | H7: DCF_INTC!B21
A8: FCF Year 1 | B8: -4.2384226e+08 | C8: -4.2384226e+08 | D8: =ABS(B8-C8) -> 0 | E8: =IF(C8=0,"n/a (zero denom)",D8/ABS(C8)) -> 0 | F8: ='Tolerances'!$B$6 -> 0.001 | G8: =IF(C8=0,IF(D8<=0.000001,"PASS","FAIL"),IF(E8<=F8,"PASS","FAIL")) -> PASS | H8: DCF_INTC!C31
A9: FCF Year 2 | B9: -3.8334661e+08 | C9: -3.8334661e+08 | D9: =ABS(B9-C9) -> 0 | E9: =IF(C9=0,"n/a (zero denom)",D9/ABS(C9)) -> 0 | F9: ='Tolerances'!$B$6 -> 0.001 | G9: =IF(C9=0,IF(D9<=0.000001,"PASS","FAIL"),IF(E9<=F9,"PASS","FAIL")) -> PASS | H9: DCF_INTC!D31
A10: FCF Year 3 | B10: -3.4672007e+08 | C10: -3.4672007e+08 | D10: =ABS(B10-C10) -> 0 | E10: =IF(C10=0,"n/a (zero denom)",D10/ABS(C10)) -> 0 | F10: ='Tolerances'!$B$6 -> 0.001 | G10: =IF(C10=0,IF(D10<=0.000001,"PASS","FAIL"),IF(E10<=F10,"PASS","FAIL")) -> PASS | H10: DCF_INTC!E31
A11: FCF Year 4 | B11: -3.1359299e+08 | C11: -3.1359299e+08 | D11: =ABS(B11-C11) -> 0 | E11: =IF(C11=0,"n/a (zero denom)",D11/ABS(C11)) -> 0 | F11: ='Tolerances'!$B$6 -> 0.001 | G11: =IF(C11=0,IF(D11<=0.000001,"PASS","FAIL"),IF(E11<=F11,"PASS","FAIL")) -> PASS | H11: DCF_INTC!F31
A12: FCF Year 5 | B12: -2.8363101e+08 | C12: -2.8363101e+08 | D12: =ABS(B12-C12) -> 0 | E12: =IF(C12=0,"n/a (zero denom)",D12/ABS(C12)) -> 0 | F12: ='Tolerances'!$B$6 -> 0.001 | G12: =IF(C12=0,IF(D12<=0.000001,"PASS","FAIL"),IF(E12<=F12,"PASS","FAIL")) -> PASS | H12: DCF_INTC!G31
A13: Terminal Value | B13: -2.3156512e+09 | C13: -2.3156512e+09 | D13: =ABS(B13-C13) -> 0 | E13: =IF(C13=0,"n/a (zero denom)",D13/ABS(C13)) -> 0 | F13: ='Tolerances'!$B$7 -> 0.002 | G13: =IF(C13=0,IF(D13<=0.000001,"PASS","FAIL"),IF(E13<=F13,"PASS","FAIL")) -> PASS | H13: DCF_INTC!B34
A14: PV of Explicit FCF (sum of pv_fcf series) | B14: -1.2052603e+09 | C14: -1.2052603e+09 | D14: =ABS(B14-C14) -> 0 | E14: =IF(C14=0,"n/a (zero denom)",D14/ABS(C14)) -> 0 | F14: ='Tolerances'!$B$8 -> 0.002 | G14: =IF(C14=0,IF(D14<=0.000001,"PASS","FAIL"),IF(E14<=F14,"PASS","FAIL")) -> PASS | H14: DCF_INTC!B39
A15: PV of Terminal Value | B15: -1.1485565e+09 | C15: -1.1485565e+09 | D15: =ABS(B15-C15) -> 0 | E15: =IF(C15=0,"n/a (zero denom)",D15/ABS(C15)) -> 0 | F15: ='Tolerances'!$B$9 -> 0.002 | G15: =IF(C15=0,IF(D15<=0.000001,"PASS","FAIL"),IF(E15<=F15,"PASS","FAIL")) -> PASS | H15: DCF_INTC!B40
A16: Enterprise Value | B16: -2.3538168e+09 | C16: -2.3538168e+09 | D16: =ABS(B16-C16) -> 0 | E16: =IF(C16=0,"n/a (zero denom)",D16/ABS(C16)) -> 0 | F16: ='Tolerances'!$B$10 -> 0.002 | G16: =IF(C16=0,IF(D16<=0.000001,"PASS","FAIL"),IF(E16<=F16,"PASS","FAIL")) -> PASS | H16: DCF_INTC!B41
A17: Equity Value | B17: -3.4673817e+10 | C17: -3.4673817e+10 | D17: =ABS(B17-C17) -> 0 | E17: =IF(C17=0,"n/a (zero denom)",D17/ABS(C17)) -> 0 | F17: ='Tolerances'!$B$11 -> 0.002 | G17: =IF(C17=0,IF(D17<=0.000001,"PASS","FAIL"),IF(E17<=F17,"PASS","FAIL")) -> PASS | H17: DCF_INTC!B42
A18: Intrinsic Value per Share | B18: -6.5594261 | C18: -6.5594261 | D18: =ABS(B18-C18) -> 0 | E18: =IF(C18=0,"n/a (zero denom)",D18/ABS(C18)) -> 0 | F18: ='Tolerances'!$B$12 -> 0.005 | G18: =IF(C18=0,IF(D18<=0.000001,"PASS","FAIL"),IF(E18<=F18,"PASS","FAIL")) -> PASS | H18: DCF_INTC!B43
A20: Sensitivity reconciliation coverage (full per-cell detail: 'All Sensitivity Comparisons' sheet)
A21: Table | B21: Scenario Rows | C21: Outputs / Row | D21: Scalar Comparisons | E21: All Pass
A22: Table 1 -- WACC | B22: 7 | C22: 4 | D22: =B22*C22 -> 28 | E22: PASS
A23: Table 2 -- Terminal growth | B23: 7 | C23: 4 | D23: =B23*C23 -> 28 | E23: PASS
A24: Table 3 -- Revenue growth | B24: 8 | C24: 9 | D24: =B24*C24 -> 72 | E24: PASS
A25: Table 4 -- Operating margin | B25: 7 | C25: 9 | D25: =B25*C25 -> 63 | E25: PASS
A26: Table 5 -- WACC x g two-way grid | B26: 36 | C26: 1 | D26: =B26*C26 -> 36 | E26: PASS
A27: TOTAL (this company) | D27: =SUM(D22:D26) -> 227

Sheet Detail_VZ
A1: Detailed base-case reconciliation -- VZ (Verizon Communications Inc.)
A2: All metrics within tolerance.
A4: Metric | B4: Codebase Output | C4: Workbook Output | D4: Absolute Difference | E4: Relative/pp Difference | F4: Tolerance | G4: PASS/FAIL | H4: Workbook Cell
A5: Historical Revenue CAGR | B5: 0.0084578735 | C5: 0.0084578735 | D5: =ABS(B5-C5) -> 0 | E5: =D5 -> 0 | F5: ='Tolerances'!$B$3 -> 0.0001 | G5: =IF(D5<=F5,"PASS","FAIL") -> PASS | H5: DCF_VZ!B9
A6: Historical average Operating Margin | B6: 0.21216289 | C6: 0.21216289 | D6: =ABS(B6-C6) -> 0 | E6: =D6 -> 0 | F6: ='Tolerances'!$B$4 -> 0.0001 | G6: =IF(D6<=F6,"PASS","FAIL") -> PASS | H6: DCF_VZ!B10
A7: WACC (final, clamped [5%,20%]) | B7: 0.05 | C7: 0.05 | D7: =ABS(B7-C7) -> 0 | E7: =D7 -> 0 | F7: ='Tolerances'!$B$5 -> 0.0005 | G7: =IF(D7<=F7,"PASS","FAIL") -> PASS | H7: DCF_VZ!B21
A8: FCF Year 1 | B8: 2.1557635e+10 | C8: 2.1557635e+10 | D8: =ABS(B8-C8) -> 0 | E8: =IF(C8=0,"n/a (zero denom)",D8/ABS(C8)) -> 0 | F8: ='Tolerances'!$B$6 -> 0.001 | G8: =IF(C8=0,IF(D8<=0.000001,"PASS","FAIL"),IF(E8<=F8,"PASS","FAIL")) -> PASS | H8: DCF_VZ!C31
A9: FCF Year 2 | B9: 2.1739967e+10 | C9: 2.1739967e+10 | D9: =ABS(B9-C9) -> 0 | E9: =IF(C9=0,"n/a (zero denom)",D9/ABS(C9)) -> 0 | F9: ='Tolerances'!$B$6 -> 0.001 | G9: =IF(C9=0,IF(D9<=0.000001,"PASS","FAIL"),IF(E9<=F9,"PASS","FAIL")) -> PASS | H9: DCF_VZ!D31
A10: FCF Year 3 | B10: 2.1923841e+10 | C10: 2.1923841e+10 | D10: =ABS(B10-C10) -> 0 | E10: =IF(C10=0,"n/a (zero denom)",D10/ABS(C10)) -> 0 | F10: ='Tolerances'!$B$6 -> 0.001 | G10: =IF(C10=0,IF(D10<=0.000001,"PASS","FAIL"),IF(E10<=F10,"PASS","FAIL")) -> PASS | H10: DCF_VZ!E31
A11: FCF Year 4 | B11: 2.210927e+10 | C11: 2.210927e+10 | D11: =ABS(B11-C11) -> 0 | E11: =IF(C11=0,"n/a (zero denom)",D11/ABS(C11)) -> 0 | F11: ='Tolerances'!$B$6 -> 0.001 | G11: =IF(C11=0,IF(D11<=0.000001,"PASS","FAIL"),IF(E11<=F11,"PASS","FAIL")) -> PASS | H11: DCF_VZ!F31
A12: FCF Year 5 | B12: 2.2296268e+10 | C12: 2.2296268e+10 | D12: =ABS(B12-C12) -> 0 | E12: =IF(C12=0,"n/a (zero denom)",D12/ABS(C12)) -> 0 | F12: ='Tolerances'!$B$6 -> 0.001 | G12: =IF(C12=0,IF(D12<=0.000001,"PASS","FAIL"),IF(E12<=F12,"PASS","FAIL")) -> PASS | H12: DCF_VZ!G31
A13: Terminal Value | B13: 9.1414697e+11 | C13: 9.1414697e+11 | D13: =ABS(B13-C13) -> 0 | E13: =IF(C13=0,"n/a (zero denom)",D13/ABS(C13)) -> 0 | F13: ='Tolerances'!$B$7 -> 0.002 | G13: =IF(C13=0,IF(D13<=0.000001,"PASS","FAIL"),IF(E13<=F13,"PASS","FAIL")) -> PASS | H13: DCF_VZ!B34
A14: PV of Explicit FCF (sum of pv_fcf series) | B14: 9.4847571e+10 | C14: 9.4847571e+10 | D14: =ABS(B14-C14) -> 0 | E14: =IF(C14=0,"n/a (zero denom)",D14/ABS(C14)) -> 0 | F14: ='Tolerances'!$B$8 -> 0.002 | G14: =IF(C14=0,IF(D14<=0.000001,"PASS","FAIL"),IF(E14<=F14,"PASS","FAIL")) -> PASS | H14: DCF_VZ!B39
A15: PV of Terminal Value | B15: 7.1625807e+11 | C15: 7.1625807e+11 | D15: =ABS(B15-C15) -> 0 | E15: =IF(C15=0,"n/a (zero denom)",D15/ABS(C15)) -> 0 | F15: ='Tolerances'!$B$9 -> 0.002 | G15: =IF(C15=0,IF(D15<=0.000001,"PASS","FAIL"),IF(E15<=F15,"PASS","FAIL")) -> PASS | H15: DCF_VZ!B40
A16: Enterprise Value | B16: 8.1110564e+11 | C16: 8.1110564e+11 | D16: =ABS(B16-C16) -> 0 | E16: =IF(C16=0,"n/a (zero denom)",D16/ABS(C16)) -> 0 | F16: ='Tolerances'!$B$10 -> 0.002 | G16: =IF(C16=0,IF(D16<=0.000001,"PASS","FAIL"),IF(E16<=F16,"PASS","FAIL")) -> PASS | H16: DCF_VZ!B41
A17: Equity Value | B17: 6.7200364e+11 | C17: 6.7200364e+11 | D17: =ABS(B17-C17) -> 0 | E17: =IF(C17=0,"n/a (zero denom)",D17/ABS(C17)) -> 0 | F17: ='Tolerances'!$B$11 -> 0.002 | G17: =IF(C17=0,IF(D17<=0.000001,"PASS","FAIL"),IF(E17<=F17,"PASS","FAIL")) -> PASS | H17: DCF_VZ!B42
A18: Intrinsic Value per Share | B18: 161.74248 | C18: 161.74248 | D18: =ABS(B18-C18) -> 0 | E18: =IF(C18=0,"n/a (zero denom)",D18/ABS(C18)) -> 0 | F18: ='Tolerances'!$B$12 -> 0.005 | G18: =IF(C18=0,IF(D18<=0.000001,"PASS","FAIL"),IF(E18<=F18,"PASS","FAIL")) -> PASS | H18: DCF_VZ!B43
A20: Sensitivity reconciliation coverage (full per-cell detail: 'All Sensitivity Comparisons' sheet)
A21: Table | B21: Scenario Rows | C21: Outputs / Row | D21: Scalar Comparisons | E21: All Pass
A22: Table 1 -- WACC | B22: 7 | C22: 4 | D22: =B22*C22 -> 28 | E22: PASS
A23: Table 2 -- Terminal growth | B23: 7 | C23: 4 | D23: =B23*C23 -> 28 | E23: PASS
A24: Table 3 -- Revenue growth | B24: 8 | C24: 9 | D24: =B24*C24 -> 72 | E24: PASS
A25: Table 4 -- Operating margin | B25: 7 | C25: 9 | D25: =B25*C25 -> 63 | E25: PASS
A26: Table 5 -- WACC x g two-way grid | B26: 36 | C26: 1 | D26: =B26*C26 -> 36 | E26: PASS
A27: TOTAL (this company) | D27: =SUM(D22:D26) -> 227

Sheet Sensitivity Reconciliation
A1: Sensitivity reconciliation -- production recompute vs. workbook V2 cached grid, all four companies
A2: Table 1 (WACC) and Table 2 (terminal growth) IVPS rows shown here with full live-formula reconciliation for quick visual scanning. ALL FIVE tables' full per-scalar-comparison detail (908 rows total across four companies) is on the 'All Sensitivity Comparisons' sheet -- never summarized-out to JSON only.
A4: Coverage summary -- scenario rows vs. actual scalar comparisons (Finding 3 fix)
A5: Ticker | B5: Table | C5: Scenario Rows | D5: Outputs / Row | E5: Scalar Comparisons | F5: All Pass
A6: MSFT | B6: Table 1 -- WACC | C6: 7 | D6: 4 | E6: =C6*D6 -> 28 | F6: PASS
A7: MSFT | B7: Table 2 -- Terminal growth | C7: 7 | D7: 4 | E7: =C7*D7 -> 28 | F7: PASS
A8: MSFT | B8: Table 3 -- Revenue growth | C8: 8 | D8: 9 | E8: =C8*D8 -> 72 | F8: PASS
A9: MSFT | B9: Table 4 -- Operating margin | C9: 7 | D9: 9 | E9: =C9*D9 -> 63 | F9: PASS
A10: MSFT | B10: Table 5 -- WACC x g two-way grid | C10: 36 | D10: 1 | E10: =C10*D10 -> 36 | F10: PASS
A11: CAT | B11: Table 1 -- WACC | C11: 7 | D11: 4 | E11: =C11*D11 -> 28 | F11: PASS
A12: CAT | B12: Table 2 -- Terminal growth | C12: 7 | D12: 4 | E12: =C12*D12 -> 28 | F12: PASS
A13: CAT | B13: Table 3 -- Revenue growth | C13: 8 | D13: 9 | E13: =C13*D13 -> 72 | F13: PASS
A14: CAT | B14: Table 4 -- Operating margin | C14: 7 | D14: 9 | E14: =C14*D14 -> 63 | F14: PASS
A15: CAT | B15: Table 5 -- WACC x g two-way grid | C15: 36 | D15: 1 | E15: =C15*D15 -> 36 | F15: PASS
A16: INTC | B16: Table 1 -- WACC | C16: 7 | D16: 4 | E16: =C16*D16 -> 28 | F16: PASS
A17: INTC | B17: Table 2 -- Terminal growth | C17: 7 | D17: 4 | E17: =C17*D17 -> 28 | F17: PASS
... A25: VZ | B25: Table 5 -- WACC x g two-way grid | C25: 36 | D25: 1 | E25: =C25*D25 -> 36 | F25: PASS
A26: GRAND TOTAL (4 companies x 5 tables) | E26: =SUM(E5:E25) -> 908
A28: -- MSFT (Microsoft Corporation) --
A29: Table 1 -- WACC sensitivity (Intrinsic Value/Share)
A30: WACC | B30: Codebase IVPS | C30: Workbook IVPS | D30: Abs. Diff | E30: Rel. Diff | F30: Tolerance | G30: PASS/FAIL
A31: 0.05 | B31: 1038.4359 | C31: 1038.4359 | D31: =ABS(B31-C31) -> 0 | E31: =IF(C31=0,"n/a (zero denom)",D31/ABS(C31)) -> 0 | F31: ='Tolerances'!$B$13 -> 0.005 | G31: =IF(C31=0,IF(D31<=0.000001,"PASS","FAIL"),IF(E31<=F31,"PASS","FAIL")) -> PASS
A32: 0.075 | B32: 507.88514 | C32: 507.88514 | D32: =ABS(B32-C32) -> 0 | E32: =IF(C32=0,"n/a (zero denom)",D32/ABS(C32)) -> 0 | F32: ='Tolerances'!$B$13 -> 0.005 | G32: =IF(C32=0,IF(D32<=0.000001,"PASS","FAIL"),IF(E32<=F32,"PASS","FAIL")) -> PASS
A33: 0.1 | B33: 331.63686 | C33: 331.63686 | D33: =ABS(B33-C33) -> 5.6843419e-14 | E33: =IF(C33=0,"n/a (zero denom)",D33/ABS(C33)) -> 1.714026e-16 | F33: ='Tolerances'!$B$13 -> 0.005 | G33: =IF(C33=0,IF(D33<=0.000001,"PASS","FAIL"),IF(E33<=F33,"PASS","FAIL")) -> PASS
A34: 0.125 | B34: 243.91251 | C34: 243.91251 | D34: =ABS(B34-C34) -> 0 | E34: =IF(C34=0,"n/a (zero denom)",D34/ABS(C34)) -> 0 | F34: ='Tolerances'!$B$13 -> 0.005 | G34: =IF(C34=0,IF(D34<=0.000001,"PASS","FAIL"),IF(E34<=F34,"PASS","FAIL")) -> PASS
A35: 0.15 | B35: 191.56202 | C35: 191.56202 | D35: =ABS(B35-C35) -> 0 | E35: =IF(C35=0,"n/a (zero denom)",D35/ABS(C35)) -> 0 | F35: ='Tolerances'!$B$13 -> 0.005 | G35: =IF(C35=0,IF(D35<=0.000001,"PASS","FAIL"),IF(E35<=F35,"PASS","FAIL")) -> PASS
A36: 0.175 | B36: 156.87263 | C36: 156.87263 | D36: =ABS(B36-C36) -> 0 | E36: =IF(C36=0,"n/a (zero denom)",D36/ABS(C36)) -> 0 | F36: ='Tolerances'!$B$13 -> 0.005 | G36: =IF(C36=0,IF(D36<=0.000001,"PASS","FAIL"),IF(E36<=F36,"PASS","FAIL")) -> PASS
A37: 0.2 | B37: 132.25604 | C37: 132.25604 | D37: =ABS(B37-C37) -> 0 | E37: =IF(C37=0,"n/a (zero denom)",D37/ABS(C37)) -> 0 | F37: ='Tolerances'!$B$13 -> 0.005 | G37: =IF(C37=0,IF(D37<=0.000001,"PASS","FAIL"),IF(E37<=F37,"PASS","FAIL")) -> PASS
A38: Table 2 -- Terminal growth sensitivity (Intrinsic Value/Share)
A39: Terminal g | B39: Codebase IVPS | C39: Workbook IVPS | D39: Abs. Diff | E39: Rel. Diff | F39: Tolerance | G39: PASS/FAIL
A40: 0 | B40: 264.83076 | C40: 264.83076 | D40: =ABS(B40-C40) -> 0 | E40: =IF(C40=0,"n/a (zero denom)",D40/ABS(C40)) -> 0 | F40: ='Tolerances'!$B$13 -> 0.005 | G40: =IF(C40=0,IF(D40<=0.000001,"PASS","FAIL"),IF(E40<=F40,"PASS","FAIL")) -> PASS
A41: 0.01 | B41: 287.09308 | C41: 287.09308 | D41: =ABS(B41-C41) -> 0 | E41: =IF(C41=0,"n/a (zero denom)",D41/ABS(C41)) -> 0 | F41: ='Tolerances'!$B$13 -> 0.005 | G41: =IF(C41=0,IF(D41<=0.000001,"PASS","FAIL"),IF(E41<=F41,"PASS","FAIL")) -> PASS
A42: 0.02 | B42: 314.92068 | C42: 314.92068 | D42: =ABS(B42-C42) -> 0 | E42: =IF(C42=0,"n/a (zero denom)",D42/ABS(C42)) -> 0 | F42: ='Tolerances'!$B$13 -> 0.005 | G42: =IF(C42=0,IF(D42<=0.000001,"PASS","FAIL"),IF(E42<=F42,"PASS","FAIL")) -> PASS
A43: 0.025 | B43: 331.61709 | C43: 331.61709 | D43: =ABS(B43-C43) -> 0 | E43: =IF(C43=0,"n/a (zero denom)",D43/ABS(C43)) -> 0 | F43: ='Tolerances'!$B$13 -> 0.005 | G43: =IF(C43=0,IF(D43<=0.000001,"PASS","FAIL"),IF(E43<=F43,"PASS","FAIL")) -> PASS
A44: 0.03 | B44: 350.69856 | C44: 350.69856 | D44: =ABS(B44-C44) -> 0 | E44: =IF(C44=0,"n/a (zero denom)",D44/ABS(C44)) -> 0 | F44: ='Tolerances'!$B$13 -> 0.005 | G44: =IF(C44=0,IF(D44<=0.000001,"PASS","FAIL"),IF(E44<=F44,"PASS","FAIL")) -> PASS
A45: 0.04 | B45: 398.40155 | C45: 398.40155 | D45: =ABS(B45-C45) -> 0 | E45: =IF(C45=0,"n/a (zero denom)",D45/ABS(C45)) -> 0 | F45: ='Tolerances'!$B$13 -> 0.005 | G45: =IF(C45=0,IF(D45<=0.000001,"PASS","FAIL"),IF(E45<=F45,"PASS","FAIL")) -> PASS
A46: 0.05 | B46: 465.18413 | C46: 465.18413 | D46: =ABS(B46-C46) -> 0 | E46: =IF(C46=0,"n/a (zero denom)",D46/ABS(C46)) -> 0 | F46: ='Tolerances'!$B$13 -> 0.005 | G46: =IF(C46=0,IF(D46<=0.000001,"PASS","FAIL"),IF(E46<=F46,"PASS","FAIL")) -> PASS
A47: Tables 3/4/5 -- see 'All Sensitivity Comparisons' sheet for full detail. Summary: T3=PASS, T4=PASS, T5=PASS (36/36 cells).
A49: -- CAT (Caterpillar Inc.) --
A50: Table 1 -- WACC sensitivity (Intrinsic Value/Share)
A51: WACC | B51: Codebase IVPS | C51: Workbook IVPS | D51: Abs. Diff | E51: Rel. Diff | F51: Tolerance | G51: PASS/FAIL
A52: 0.05 | B52: 807.66151 | C52: 807.66151 | D52: =ABS(B52-C52) -> 0 | E52: =IF(C52=0,"n/a (zero denom)",D52/ABS(C52)) -> 0 | F52: ='Tolerances'!$B$13 -> 0.005 | G52: =IF(C52=0,IF(D52<=0.000001,"PASS","FAIL"),IF(E52<=F52,"PASS","FAIL")) -> PASS
A53: 0.075 | B53: 371.34814 | C53: 371.34814 | D53: =ABS(B53-C53) -> 0 | E53: =IF(C53=0,"n/a (zero denom)",D53/ABS(C53)) -> 0 | F53: ='Tolerances'!$B$13 -> 0.005 | G53: =IF(C53=0,IF(D53<=0.000001,"PASS","FAIL"),IF(E53<=F53,"PASS","FAIL")) -> PASS
A54: 0.1 | B54: 226.14434 | C54: 226.14434 | D54: =ABS(B54-C54) -> 0 | E54: =IF(C54=0,"n/a (zero denom)",D54/ABS(C54)) -> 0 | F54: ='Tolerances'!$B$13 -> 0.005 | G54: =IF(C54=0,IF(D54<=0.000001,"PASS","FAIL"),IF(E54<=F54,"PASS","FAIL")) -> PASS
A55: 0.125 | B55: 153.698 | C55: 153.698 | D55: =ABS(B55-C55) -> 0 | E55: =IF(C55=0,"n/a (zero denom)",D55/ABS(C55)) -> 0 | F55: ='Tolerances'!$B$13 -> 0.005 | G55: =IF(C55=0,IF(D55<=0.000001,"PASS","FAIL"),IF(E55<=F55,"PASS","FAIL")) -> PASS
A56: 0.15 | B56: 110.34085 | C56: 110.34085 | D56: =ABS(B56-C56) -> 0 | E56: =IF(C56=0,"n/a (zero denom)",D56/ABS(C56)) -> 0 | F56: ='Tolerances'!$B$13 -> 0.005 | G56: =IF(C56=0,IF(D56<=0.000001,"PASS","FAIL"),IF(E56<=F56,"PASS","FAIL")) -> PASS
A57: 0.175 | B57: 81.518342 | C57: 81.518342 | D57: =ABS(B57-C57) -> 0 | E57: =IF(C57=0,"n/a (zero denom)",D57/ABS(C57)) -> 0 | F57: ='Tolerances'!$B$13 -> 0.005 | G57: =IF(C57=0,IF(D57<=0.000001,"PASS","FAIL"),IF(E57<=F57,"PASS","FAIL")) -> PASS
A58: 0.2 | B58: 60.993889 | C58: 60.993889 | D58: =ABS(B58-C58) -> 0 | E58: =IF(C58=0,"n/a (zero denom)",D58/ABS(C58)) -> 0 | F58: ='Tolerances'!$B$13 -> 0.005 | G58: =IF(C58=0,IF(D58<=0.000001,"PASS","FAIL"),IF(E58<=F58,"PASS","FAIL")) -> PASS
A59: Table 2 -- Terminal growth sensitivity (Intrinsic Value/Share)
A60: Terminal g | B60: Codebase IVPS | C60: Workbook IVPS | D60: Abs. Diff | E60: Rel. Diff | F60: Tolerance | G60: PASS/FAIL
A61: 0 | B61: 129.96188 | C61: 129.96188 | D61: =ABS(B61-C61) -> 0 | E61: =IF(C61=0,"n/a (zero denom)",D61/ABS(C61)) -> 0 | F61: ='Tolerances'!$B$13 -> 0.005 | G61: =IF(C61=0,IF(D61<=0.000001,"PASS","FAIL"),IF(E61<=F61,"PASS","FAIL")) -> PASS
A62: 0.01 | B62: 141.33558 | C62: 141.33558 | D62: =ABS(B62-C62) -> 0 | E62: =IF(C62=0,"n/a (zero denom)",D62/ABS(C62)) -> 0 | F62: ='Tolerances'!$B$13 -> 0.005 | G62: =IF(C62=0,IF(D62<=0.000001,"PASS","FAIL"),IF(E62<=F62,"PASS","FAIL")) -> PASS
A63: 0.02 | B63: 154.96242 | C63: 154.96242 | D63: =ABS(B63-C63) -> 0 | E63: =IF(C63=0,"n/a (zero denom)",D63/ABS(C63)) -> 0 | F63: ='Tolerances'!$B$13 -> 0.005 | G63: =IF(C63=0,IF(D63<=0.000001,"PASS","FAIL"),IF(E63<=F63,"PASS","FAIL")) -> PASS
A64: 0.025 | B64: 162.8409 | C64: 162.8409 | D64: =ABS(B64-C64) -> 0 | E64: =IF(C64=0,"n/a (zero denom)",D64/ABS(C64)) -> 0 | F64: ='Tolerances'!$B$13 -> 0.005 | G64: =IF(C64=0,IF(D64<=0.000001,"PASS","FAIL"),IF(E64<=F64,"PASS","FAIL")) -> PASS
A65: 0.03 | B65: 171.58553 | C65: 171.58553 | D65: =ABS(B65-C65) -> 0 | E65: =IF(C65=0,"n/a (zero denom)",D65/ABS(C65)) -> 0 | F65: ='Tolerances'!$B$13 -> 0.005 | G65: =IF(C65=0,IF(D65<=0.000001,"PASS","FAIL"),IF(E65<=F65,"PASS","FAIL")) -> PASS
A66: 0.04 | B66: 192.3152 | C66: 192.3152 | D66: =ABS(B66-C66) -> 0 | E66: =IF(C66=0,"n/a (zero denom)",D66/ABS(C66)) -> 0 | F66: ='Tolerances'!$B$13 -> 0.005 | G66: =IF(C66=0,IF(D66<=0.000001,"PASS","FAIL"),IF(E66<=F66,"PASS","FAIL")) -> PASS
A67: 0.05 | B67: 218.88761 | C67: 218.88761 | D67: =ABS(B67-C67) -> 0 | E67: =IF(C67=0,"n/a (zero denom)",D67/ABS(C67)) -> 0 | F67: ='Tolerances'!$B$13 -> 0.005 | G67: =IF(C67=0,IF(D67<=0.000001,"PASS","FAIL"),IF(E67<=F67,"PASS","FAIL")) -> PASS
A68: Tables 3/4/5 -- see 'All Sensitivity Comparisons' sheet for full detail. Summary: T3=PASS, T4=PASS, T5=PASS (36/36 cells).
A70: -- INTC (Intel Corporation) --
A71: Table 1 -- WACC sensitivity (Intrinsic Value/Share)
A72: WACC | B72: Codebase IVPS | C72: Workbook IVPS | D72: Abs. Diff | E72: Rel. Diff | F72: Tolerance | G72: PASS/FAIL
A73: 0.05 | B73: -8.1274633 | C73: -8.1274633 | D73: =ABS(B73-C73) -> 0 | E73: =IF(C73=0,"n/a (zero denom)",D73/ABS(C73)) -> 0 | F73: ='Tolerances'!$B$13 -> 0.005 | G73: =IF(C73=0,IF(D73<=0.000001,"PASS","FAIL"),IF(E73<=F73,"PASS","FAIL")) -> PASS
A74: 0.075 | B74: -7.1522544 | C74: -7.1522544 | D74: =ABS(B74-C74) -> 0 | E74: =IF(C74=0,"n/a (zero denom)",D74/ABS(C74)) -> 0 | F74: ='Tolerances'!$B$13 -> 0.005 | G74: =IF(C74=0,IF(D74<=0.000001,"PASS","FAIL"),IF(E74<=F74,"PASS","FAIL")) -> PASS
A75: 0.1 | B75: -6.8254022 | C75: -6.8254022 | D75: =ABS(B75-C75) -> 0 | E75: =IF(C75=0,"n/a (zero denom)",D75/ABS(C75)) -> 0 | F75: ='Tolerances'!$B$13 -> 0.005 | G75: =IF(C75=0,IF(D75<=0.000001,"PASS","FAIL"),IF(E75<=F75,"PASS","FAIL")) -> PASS
A76: 0.125 | B76: -6.660787 | C76: -6.660787 | D76: =ABS(B76-C76) -> 0 | E76: =IF(C76=0,"n/a (zero denom)",D76/ABS(C76)) -> 0 | F76: ='Tolerances'!$B$13 -> 0.005 | G76: =IF(C76=0,IF(D76<=0.000001,"PASS","FAIL"),IF(E76<=F76,"PASS","FAIL")) -> PASS
A77: 0.15 | B77: -6.5611692 | C77: -6.5611692 | D77: =ABS(B77-C77) -> 0 | E77: =IF(C77=0,"n/a (zero denom)",D77/ABS(C77)) -> 0 | F77: ='Tolerances'!$B$13 -> 0.005 | G77: =IF(C77=0,IF(D77<=0.000001,"PASS","FAIL"),IF(E77<=F77,"PASS","FAIL")) -> PASS
A78: 0.175 | B78: -6.4941244 | C78: -6.4941244 | D78: =ABS(B78-C78) -> 0 | E78: =IF(C78=0,"n/a (zero denom)",D78/ABS(C78)) -> 0 | F78: ='Tolerances'!$B$13 -> 0.005 | G78: =IF(C78=0,IF(D78<=0.000001,"PASS","FAIL"),IF(E78<=F78,"PASS","FAIL")) -> PASS
A79: 0.2 | B79: -6.4457485 | C79: -6.4457485 | D79: =ABS(B79-C79) -> 0 | E79: =IF(C79=0,"n/a (zero denom)",D79/ABS(C79)) -> 0 | F79: ='Tolerances'!$B$13 -> 0.005 | G79: =IF(C79=0,IF(D79<=0.000001,"PASS","FAIL"),IF(E79<=F79,"PASS","FAIL")) -> PASS
A80: Table 2 -- Terminal growth sensitivity (Intrinsic Value/Share)
A81: Terminal g | B81: Codebase IVPS | C81: Workbook IVPS | D81: Abs. Diff | E81: Rel. Diff | F81: Tolerance | G81: PASS/FAIL
A82: 0 | B82: -6.518925 | C82: -6.518925 | D82: =ABS(B82-C82) -> 0 | E82: =IF(C82=0,"n/a (zero denom)",D82/ABS(C82)) -> 0 | F82: ='Tolerances'!$B$13 -> 0.005 | G82: =IF(C82=0,IF(D82<=0.000001,"PASS","FAIL"),IF(E82<=F82,"PASS","FAIL")) -> PASS
A83: 0.01 | B83: -6.5333965 | C83: -6.5333965 | D83: =ABS(B83-C83) -> 0 | E83: =IF(C83=0,"n/a (zero denom)",D83/ABS(C83)) -> 0 | F83: ='Tolerances'!$B$13 -> 0.005 | G83: =IF(C83=0,IF(D83<=0.000001,"PASS","FAIL"),IF(E83<=F83,"PASS","FAIL")) -> PASS
A84: 0.02 | B84: -6.5500849 | C84: -6.5500849 | D84: =ABS(B84-C84) -> 0 | E84: =IF(C84=0,"n/a (zero denom)",D84/ABS(C84)) -> 0 | F84: ='Tolerances'!$B$13 -> 0.005 | G84: =IF(C84=0,IF(D84<=0.000001,"PASS","FAIL"),IF(E84<=F84,"PASS","FAIL")) -> PASS
A85: 0.025 | B85: -6.5594261 | C85: -6.5594261 | D85: =ABS(B85-C85) -> 0 | E85: =IF(C85=0,"n/a (zero denom)",D85/ABS(C85)) -> 0 | F85: ='Tolerances'!$B$13 -> 0.005 | G85: =IF(C85=0,IF(D85<=0.000001,"PASS","FAIL"),IF(E85<=F85,"PASS","FAIL")) -> PASS
A86: 0.03 | B86: -6.5695422 | C86: -6.5695422 | D86: =ABS(B86-C86) -> 0 | E86: =IF(C86=0,"n/a (zero denom)",D86/ABS(C86)) -> 0 | F86: ='Tolerances'!$B$13 -> 0.005 | G86: =IF(C86=0,IF(D86<=0.000001,"PASS","FAIL"),IF(E86<=F86,"PASS","FAIL")) -> PASS
A87: 0.04 | B87: -6.5925196 | C87: -6.5925196 | D87: =ABS(B87-C87) -> 0 | E87: =IF(C87=0,"n/a (zero denom)",D87/ABS(C87)) -> 0 | F87: ='Tolerances'!$B$13 -> 0.005 | G87: =IF(C87=0,IF(D87<=0.000001,"PASS","FAIL"),IF(E87<=F87,"PASS","FAIL")) -> PASS
A88: 0.05 | B88: -6.6200676 | C88: -6.6200676 | D88: =ABS(B88-C88) -> 0 | E88: =IF(C88=0,"n/a (zero denom)",D88/ABS(C88)) -> 0 | F88: ='Tolerances'!$B$13 -> 0.005 | G88: =IF(C88=0,IF(D88<=0.000001,"PASS","FAIL"),IF(E88<=F88,"PASS","FAIL")) -> PASS
A89: Tables 3/4/5 -- see 'All Sensitivity Comparisons' sheet for full detail. Summary: T3=PASS, T4=PASS, T5=PASS (36/36 cells).
A91: -- VZ (Verizon Communications Inc.) --
A92: Table 1 -- WACC sensitivity (Intrinsic Value/Share)
A93: WACC | B93: Codebase IVPS | C93: Workbook IVPS | D93: Abs. Diff | E93: Rel. Diff | F93: Tolerance | G93: PASS/FAIL
A94: 0.05 | B94: 161.74248 | C94: 161.74248 | D94: =ABS(B94-C94) -> 0 | E94: =IF(C94=0,"n/a (zero denom)",D94/ABS(C94)) -> 0 | F94: ='Tolerances'!$B$13 -> 0.005 | G94: =IF(C94=0,IF(D94<=0.000001,"PASS","FAIL"),IF(E94<=F94,"PASS","FAIL")) -> PASS
A95: 0.075 | B95: 64.474323 | C95: 64.474323 | D95: =ABS(B95-C95) -> 0 | E95: =IF(C95=0,"n/a (zero denom)",D95/ABS(C95)) -> 0 | F95: ='Tolerances'!$B$13 -> 0.005 | G95: =IF(C95=0,IF(D95<=0.000001,"PASS","FAIL"),IF(E95<=F95,"PASS","FAIL")) -> PASS
A96: 0.1 | B96: 32.031595 | C96: 32.031595 | D96: =ABS(B96-C96) -> 0 | E96: =IF(C96=0,"n/a (zero denom)",D96/ABS(C96)) -> 0 | F96: ='Tolerances'!$B$13 -> 0.005 | G96: =IF(C96=0,IF(D96<=0.000001,"PASS","FAIL"),IF(E96<=F96,"PASS","FAIL")) -> PASS
A97: 0.125 | B97: 15.796913 | C97: 15.796913 | D97: =ABS(B97-C97) -> 0 | E97: =IF(C97=0,"n/a (zero denom)",D97/ABS(C97)) -> 0 | F97: ='Tolerances'!$B$13 -> 0.005 | G97: =IF(C97=0,IF(D97<=0.000001,"PASS","FAIL"),IF(E97<=F97,"PASS","FAIL")) -> PASS
A98: 0.15 | B98: 6.0466191 | C98: 6.0466191 | D98: =ABS(B98-C98) -> 0 | E98: =IF(C98=0,"n/a (zero denom)",D98/ABS(C98)) -> 0 | F98: ='Tolerances'!$B$13 -> 0.005 | G98: =IF(C98=0,IF(D98<=0.000001,"PASS","FAIL"),IF(E98<=F98,"PASS","FAIL")) -> PASS
A99: 0.175 | B99: -0.46063484 | C99: -0.46063484 | D99: =ABS(B99-C99) -> 0 | E99: =IF(C99=0,"n/a (zero denom)",D99/ABS(C99)) -> 0 | F99: ='Tolerances'!$B$13 -> 0.005 | G99: =IF(C99=0,IF(D99<=0.000001,"PASS","FAIL"),IF(E99<=F99,"PASS","FAIL")) -> PASS
A100: 0.2 | B100: -5.1140905 | C100: -5.1140905 | D100: =ABS(B100-C100) -> 0 | E100: =IF(C100=0,"n/a (zero denom)",D100/ABS(C100)) -> 0 | F100: ='Tolerances'!$B$13 -> 0.005 | G100: =IF(C100=0,IF(D100<=0.000001,"PASS","FAIL"),IF(E100<=F100,"PASS","FAIL")) -> PASS
A101: Table 2 -- Terminal growth sensitivity (Intrinsic Value/Share)
A102: Terminal g | B102: Codebase IVPS | C102: Workbook IVPS | D102: Abs. Diff | E102: Rel. Diff | F102: Tolerance | G102: PASS/FAIL
A103: 0 | B103: 73.443143 | C103: 73.443143 | D103: =ABS(B103-C103) -> 0 | E103: =IF(C103=0,"n/a (zero denom)",D103/ABS(C103)) -> 0 | F103: ='Tolerances'!$B$13 -> 0.005 | G103: =IF(C103=0,IF(D103<=0.000001,"PASS","FAIL"),IF(E103<=F103,"PASS","FAIL")) -> PASS
A104: 0.01 | B104: 95.517977 | C104: 95.517977 | D104: =ABS(B104-C104) -> 0 | E104: =IF(C104=0,"n/a (zero denom)",D104/ABS(C104)) -> 0 | F104: ='Tolerances'!$B$13 -> 0.005 | G104: =IF(C104=0,IF(D104<=0.000001,"PASS","FAIL"),IF(E104<=F104,"PASS","FAIL")) -> PASS
A105: 0.02 | B105: 132.30937 | C105: 132.30937 | D105: =ABS(B105-C105) -> 0 | E105: =IF(C105=0,"n/a (zero denom)",D105/ABS(C105)) -> 0 | F105: ='Tolerances'!$B$13 -> 0.005 | G105: =IF(C105=0,IF(D105<=0.000001,"PASS","FAIL"),IF(E105<=F105,"PASS","FAIL")) -> PASS
A106: 0.025 | B106: 161.74248 | C106: 161.74248 | D106: =ABS(B106-C106) -> 0 | E106: =IF(C106=0,"n/a (zero denom)",D106/ABS(C106)) -> 0 | F106: ='Tolerances'!$B$13 -> 0.005 | G106: =IF(C106=0,IF(D106<=0.000001,"PASS","FAIL"),IF(E106<=F106,"PASS","FAIL")) -> PASS
A107: 0.03 | B107: 205.89215 | C107: 205.89215 | D107: =ABS(B107-C107) -> 0 | E107: =IF(C107=0,"n/a (zero denom)",D107/ABS(C107)) -> 0 | F107: ='Tolerances'!$B$13 -> 0.005 | G107: =IF(C107=0,IF(D107<=0.000001,"PASS","FAIL"),IF(E107<=F107,"PASS","FAIL")) -> PASS
A108: 0.04 | B108: 426.64049 | C108: 426.64049 | D108: =ABS(B108-C108) -> 0 | E108: =IF(C108=0,"n/a (zero denom)",D108/ABS(C108)) -> 0 | F108: ='Tolerances'!$B$13 -> 0.005 | G108: =IF(C108=0,IF(D108<=0.000001,"PASS","FAIL"),IF(E108<=F108,"PASS","FAIL")) -> PASS
A109: 0.05 | B109: n/a | C109: n/a | G109: PASS
A110: Tables 3/4/5 -- see 'All Sensitivity Comparisons' sheet for full detail. Summary: T3=PASS, T4=PASS, T5=PASS (36/36 cells).

Sheet All Sensitivity Comparisons
A1: All sensitivity scalar comparisons -- Tables 1-5, all four companies (908 rows)
A2: One row per individual scalar comparison (a single output metric within a single sensitivity scenario). Codebase/Workbook columns are hardcoded imports (yellow); Absolute Difference / Relative-or-pp Difference / PASS-FAIL are live formulas (white), with Tolerance a formula reference to the 'Tolerances' sheet's single source of truth.
A4: Ticker | B4: Table | C4: Scenario | D4: Output Metric | E4: Codebase Value | F4: Workbook Value | G4: Absolute Difference | H4: Relative/pp Difference | I4: Tolerance | J4: PASS/FAIL | K4: Notes
A5: MSFT | B5: Table 1 -- WACC | C5: WACC=5.0000% | D5: Terminal Value | E5: 8.9318455e+12 | F5: 8.9318455e+12 | G5: =ABS(E5-F5) -> 0 | H5: =IF(F5=0,"n/a (zero denom)",G5/ABS(F5)) -> 0 | I5: ='Tolerances'!$B$7 -> 0.002 | J5: =IF(F5=0,IF(G5<=0.000001,"PASS","FAIL"),IF(H5<=I5,"PASS","FAIL")) -> PASS
A6: MSFT | B6: Table 1 -- WACC | C6: WACC=5.0000% | D6: Enterprise Value | E6: 7.7303117e+12 | F6: 7.7303117e+12 | G6: =ABS(E6-F6) -> 0 | H6: =IF(F6=0,"n/a (zero denom)",G6/ABS(F6)) -> 0 | I6: ='Tolerances'!$B$10 -> 0.002 | J6: =IF(F6=0,IF(G6<=0.000001,"PASS","FAIL"),IF(H6<=I6,"PASS","FAIL")) -> PASS
A7: MSFT | B7: Table 1 -- WACC | C7: WACC=5.0000% | D7: Equity Value | E7: 7.7109527e+12 | F7: 7.7109527e+12 | G7: =ABS(E7-F7) -> 0 | H7: =IF(F7=0,"n/a (zero denom)",G7/ABS(F7)) -> 0 | I7: ='Tolerances'!$B$11 -> 0.002 | J7: =IF(F7=0,IF(G7<=0.000001,"PASS","FAIL"),IF(H7<=I7,"PASS","FAIL")) -> PASS
A8: MSFT | B8: Table 1 -- WACC | C8: WACC=5.0000% | D8: Intrinsic Value per Share | E8: 1038.4359 | F8: 1038.4359 | G8: =ABS(E8-F8) -> 0 | H8: =IF(F8=0,"n/a (zero denom)",G8/ABS(F8)) -> 0 | I8: ='Tolerances'!$B$13 -> 0.005 | J8: =IF(F8=0,IF(G8<=0.000001,"PASS","FAIL"),IF(H8<=I8,"PASS","FAIL")) -> PASS
A9: MSFT | B9: Table 1 -- WACC | C9: WACC=7.5000% | D9: Terminal Value | E9: 4.4659228e+12 | F9: 4.4659228e+12 | G9: =ABS(E9-F9) -> 0 | H9: =IF(F9=0,"n/a (zero denom)",G9/ABS(F9)) -> 0 | I9: ='Tolerances'!$B$7 -> 0.002 | J9: =IF(F9=0,IF(G9<=0.000001,"PASS","FAIL"),IF(H9<=I9,"PASS","FAIL")) -> PASS
A10: MSFT | B10: Table 1 -- WACC | C10: WACC=7.5000% | D10: Enterprise Value | E10: 3.7906832e+12 | F10: 3.7906832e+12 | G10: =ABS(E10-F10) -> 0 | H10: =IF(F10=0,"n/a (zero denom)",G10/ABS(F10)) -> 0 | I10: ='Tolerances'!$B$10 -> 0.002 | J10: =IF(F10=0,IF(G10<=0.000001,"PASS","FAIL"),IF(H10<=I10,"PASS","FAIL")) -> PASS
A11: MSFT | B11: Table 1 -- WACC | C11: WACC=7.5000% | D11: Equity Value | E11: 3.7713242e+12 | F11: 3.7713242e+12 | G11: =ABS(E11-F11) -> 0 | H11: =IF(F11=0,"n/a (zero denom)",G11/ABS(F11)) -> 0 | I11: ='Tolerances'!$B$11 -> 0.002 | J11: =IF(F11=0,IF(G11<=0.000001,"PASS","FAIL"),IF(H11<=I11,"PASS","FAIL")) -> PASS
A12: MSFT | B12: Table 1 -- WACC | C12: WACC=7.5000% | D12: Intrinsic Value per Share | E12: 507.88514 | F12: 507.88514 | G12: =ABS(E12-F12) -> 0 | H12: =IF(F12=0,"n/a (zero denom)",G12/ABS(F12)) -> 0 | I12: ='Tolerances'!$B$13 -> 0.005 | J12: =IF(F12=0,IF(G12<=0.000001,"PASS","FAIL"),IF(H12<=I12,"PASS","FAIL")) -> PASS
A13: MSFT | B13: Table 1 -- WACC | C13: WACC=10.0000% | D13: Terminal Value | E13: 2.9772818e+12 | F13: 2.9772818e+12 | G13: =ABS(E13-F13) -> 0 | H13: =IF(F13=0,"n/a (zero denom)",G13/ABS(F13)) -> 0 | I13: ='Tolerances'!$B$7 -> 0.002 | J13: =IF(F13=0,IF(G13<=0.000001,"PASS","FAIL"),IF(H13<=I13,"PASS","FAIL")) -> PASS
A14: MSFT | B14: Table 1 -- WACC | C14: WACC=10.0000% | D14: Enterprise Value | E14: 2.4819436e+12 | F14: 2.4819436e+12 | G14: =ABS(E14-F14) -> 0.00048828125 | H14: =IF(F14=0,"n/a (zero denom)",G14/ABS(F14)) -> 1.9673342e-16 | I14: ='Tolerances'!$B$10 -> 0.002 | J14: =IF(F14=0,IF(G14<=0.000001,"PASS","FAIL"),IF(H14<=I14,"PASS","FAIL")) -> PASS
A15: MSFT | B15: Table 1 -- WACC | C15: WACC=10.0000% | D15: Equity Value | E15: 2.4625846e+12 | F15: 2.4625846e+12 | G15: =ABS(E15-F15) -> 0.00048828125 | H15: =IF(F15=0,"n/a (zero denom)",G15/ABS(F15)) -> 1.9827999e-16 | I15: ='Tolerances'!$B$11 -> 0.002 | J15: =IF(F15=0,IF(G15<=0.000001,"PASS","FAIL"),IF(H15<=I15,"PASS","FAIL")) -> PASS
A16: MSFT | B16: Table 1 -- WACC | C16: WACC=10.0000% | D16: Intrinsic Value per Share | E16: 331.63686 | F16: 331.63686 | G16: =ABS(E16-F16) -> 5.6843419e-14 | H16: =IF(F16=0,"n/a (zero denom)",G16/ABS(F16)) -> 1.714026e-16 | I16: ='Tolerances'!$B$13 -> 0.005 | J16: =IF(F16=0,IF(G16<=0.000001,"PASS","FAIL"),IF(H16<=I16,"PASS","FAIL")) -> PASS
A17: MSFT | B17: Table 1 -- WACC | C17: WACC=12.5000% | D17: Terminal Value | E17: 2.2329614e+12 | F17: 2.2329614e+12 | G17: =ABS(E17-F17) -> 0 | H17: =IF(F17=0,"n/a (zero denom)",G17/ABS(F17)) -> 0 | I17: ='Tolerances'!$B$7 -> 0.002 | J17: =IF(F17=0,IF(G17<=0.000001,"PASS","FAIL"),IF(H17<=I17,"PASS","FAIL")) -> PASS
A18: MSFT | B18: Table 1 -- WACC | C18: WACC=12.5000% | D18: Enterprise Value | E18: 1.8305425e+12 | F18: 1.8305425e+12 | G18: =ABS(E18-F18) -> 0 | H18: =IF(F18=0,"n/a (zero denom)",G18/ABS(F18)) -> 0 | I18: ='Tolerances'!$B$10 -> 0.002 | J18: =IF(F18=0,IF(G18<=0.000001,"PASS","FAIL"),IF(H18<=I18,"PASS","FAIL")) -> PASS
A19: MSFT | B19: Table 1 -- WACC | C19: WACC=12.5000% | D19: Equity Value | E19: 1.8111835e+12 | F19: 1.8111835e+12 | G19: =ABS(E19-F19) -> 0 | H19: =IF(F19=0,"n/a (zero denom)",G19/ABS(F19)) -> 0 | I19: ='Tolerances'!$B$11 -> 0.002 | J19: =IF(F19=0,IF(G19<=0.000001,"PASS","FAIL"),IF(H19<=I19,"PASS","FAIL")) -> PASS
A20: MSFT | B20: Table 1 -- WACC | C20: WACC=12.5000% | D20: Intrinsic Value per Share | E20: 243.91251 | F20: 243.91251 | G20: =ABS(E20-F20) -> 0 | H20: =IF(F20=0,"n/a (zero denom)",G20/ABS(F20)) -> 0 | I20: ='Tolerances'!$B$13 -> 0.005 | J20: =IF(F20=0,IF(G20<=0.000001,"PASS","FAIL"),IF(H20<=I20,"PASS","FAIL")) -> PASS
A21: MSFT | B21: Table 1 -- WACC | C21: WACC=15.0000% | D21: Terminal Value | E21: 1.7863691e+12 | F21: 1.7863691e+12 | G21: =ABS(E21-F21) -> 0 | H21: =IF(F21=0,"n/a (zero denom)",G21/ABS(F21)) -> 0 | I21: ='Tolerances'!$B$7 -> 0.002 | J21: =IF(F21=0,IF(G21<=0.000001,"PASS","FAIL"),IF(H21<=I21,"PASS","FAIL")) -> PASS
A22: MSFT | B22: Table 1 -- WACC | C22: WACC=15.0000% | D22: Enterprise Value | E22: 1.4418115e+12 | F22: 1.4418115e+12 | G22: =ABS(E22-F22) -> 0 | H22: =IF(F22=0,"n/a (zero denom)",G22/ABS(F22)) -> 0 | I22: ='Tolerances'!$B$10 -> 0.002 | J22: =IF(F22=0,IF(G22<=0.000001,"PASS","FAIL"),IF(H22<=I22,"PASS","FAIL")) -> PASS
A23: MSFT | B23: Table 1 -- WACC | C23: WACC=15.0000% | D23: Equity Value | E23: 1.4224525e+12 | F23: 1.4224525e+12 | G23: =ABS(E23-F23) -> 0 | H23: =IF(F23=0,"n/a (zero denom)",G23/ABS(F23)) -> 0 | I23: ='Tolerances'!$B$11 -> 0.002 | J23: =IF(F23=0,IF(G23<=0.000001,"PASS","FAIL"),IF(H23<=I23,"PASS","FAIL")) -> PASS
A24: MSFT | B24: Table 1 -- WACC | C24: WACC=15.0000% | D24: Intrinsic Value per Share | E24: 191.56202 | F24: 191.56202 | G24: =ABS(E24-F24) -> 0 | H24: =IF(F24=0,"n/a (zero denom)",G24/ABS(F24)) -> 0 | I24: ='Tolerances'!$B$13 -> 0.005 | J24: =IF(F24=0,IF(G24<=0.000001,"PASS","FAIL"),IF(H24<=I24,"PASS","FAIL")) -> PASS
A25: MSFT | B25: Table 1 -- WACC | C25: WACC=17.5000% | D25: Terminal Value | E25: 1.4886409e+12 | F25: 1.4886409e+12 | G25: =ABS(E25-F25) -> 0 | H25: =IF(F25=0,"n/a (zero denom)",G25/ABS(F25)) -> 0 | I25: ='Tolerances'!$B$7 -> 0.002 | J25: =IF(F25=0,IF(G25<=0.000001,"PASS","FAIL"),IF(H25<=I25,"PASS","FAIL")) -> PASS
A26: MSFT | B26: Table 1 -- WACC | C26: WACC=17.5000% | D26: Enterprise Value | E26: 1.1842238e+12 | F26: 1.1842238e+12 | G26: =ABS(E26-F26) -> 0 | H26: =IF(F26=0,"n/a (zero denom)",G26/ABS(F26)) -> 0 | I26: ='Tolerances'!$B$10 -> 0.002 | J26: =IF(F26=0,IF(G26<=0.000001,"PASS","FAIL"),IF(H26<=I26,"PASS","FAIL")) -> PASS
A27: MSFT | B27: Table 1 -- WACC | C27: WACC=17.5000% | D27: Equity Value | E27: 1.1648648e+12 | F27: 1.1648648e+12 | G27: =ABS(E27-F27) -> 0 | H27: =IF(F27=0,"n/a (zero denom)",G27/ABS(F27)) -> 0 | I27: ='Tolerances'!$B$11 -> 0.002 | J27: =IF(F27=0,IF(G27<=0.000001,"PASS","FAIL"),IF(H27<=I27,"PASS","FAIL")) -> PASS
A28: MSFT | B28: Table 1 -- WACC | C28: WACC=17.5000% | D28: Intrinsic Value per Share | E28: 156.87263 | F28: 156.87263 | G28: =ABS(E28-F28) -> 0 | H28: =IF(F28=0,"n/a (zero denom)",G28/ABS(F28)) -> 0 | I28: ='Tolerances'!$B$13 -> 0.005 | J28: =IF(F28=0,IF(G28<=0.000001,"PASS","FAIL"),IF(H28<=I28,"PASS","FAIL")) -> PASS
A29: MSFT | B29: Table 1 -- WACC | C29: WACC=20.0000% | D29: Terminal Value | E29: 1.2759779e+12 | F29: 1.2759779e+12 | G29: =ABS(E29-F29) -> 0 | H29: =IF(F29=0,"n/a (zero denom)",G29/ABS(F29)) -> 0 | I29: ='Tolerances'!$B$7 -> 0.002 | J29: =IF(F29=0,IF(G29<=0.000001,"PASS","FAIL"),IF(H29<=I29,"PASS","FAIL")) -> PASS
A30: MSFT | B30: Table 1 -- WACC | C30: WACC=20.0000% | D30: Enterprise Value | E30: 1.0014323e+12 | F30: 1.0014323e+12 | G30: =ABS(E30-F30) -> 0.00012207031 | H30: =IF(F30=0,"n/a (zero denom)",G30/ABS(F30)) -> 1.2189572e-16 | I30: ='Tolerances'!$B$10 -> 0.002 | J30: =IF(F30=0,IF(G30<=0.000001,"PASS","FAIL"),IF(H30<=I30,"PASS","FAIL")) -> PASS
A31: MSFT | B31: Table 1 -- WACC | C31: WACC=20.0000% | D31: Equity Value | E31: 9.8207328e+11 | F31: 9.8207328e+11 | G31: =ABS(E31-F31) -> 0.00012207031 | H31: =IF(F31=0,"n/a (zero denom)",G31/ABS(F31)) -> 1.2429858e-16 | I31: ='Tolerances'!$B$11 -> 0.002 | J31: =IF(F31=0,IF(G31<=0.000001,"PASS","FAIL"),IF(H31<=I31,"PASS","FAIL")) -> PASS
A32: MSFT | B32: Table 1 -- WACC | C32: WACC=20.0000% | D32: Intrinsic Value per Share | E32: 132.25604 | F32: 132.25604 | G32: =ABS(E32-F32) -> 0 | H32: =IF(F32=0,"n/a (zero denom)",G32/ABS(F32)) -> 0 | I32: ='Tolerances'!$B$13 -> 0.005 | J32: =IF(F32=0,IF(G32<=0.000001,"PASS","FAIL"),IF(H32<=I32,"PASS","FAIL")) -> PASS
A33: MSFT | B33: Table 2 -- Terminal growth | C33: g=0.0000% | D33: Terminal Value | E33: 2.1784071e+12 | F33: 2.1784071e+12 | G33: =ABS(E33-F33) -> 0 | H33: =IF(F33=0,"n/a (zero denom)",G33/ABS(F33)) -> 0 | I33: ='Tolerances'!$B$7 -> 0.002 | J33: =IF(F33=0,IF(G33<=0.000001,"PASS","FAIL"),IF(H33<=I33,"PASS","FAIL")) -> PASS
A34: MSFT | B34: Table 2 -- Terminal growth | C34: g=0.0000% | D34: Enterprise Value | E34: 1.9858718e+12 | F34: 1.9858718e+12 | G34: =ABS(E34-F34) -> 0 | H34: =IF(F34=0,"n/a (zero denom)",G34/ABS(F34)) -> 0 | I34: ='Tolerances'!$B$10 -> 0.002 | J34: =IF(F34=0,IF(G34<=0.000001,"PASS","FAIL"),IF(H34<=I34,"PASS","FAIL")) -> PASS
A35: MSFT | B35: Table 2 -- Terminal growth | C35: g=0.0000% | D35: Equity Value | E35: 1.9665128e+12 | F35: 1.9665128e+12 | G35: =ABS(E35-F35) -> 0 | H35: =IF(F35=0,"n/a (zero denom)",G35/ABS(F35)) -> 0 | I35: ='Tolerances'!$B$11 -> 0.002 | J35: =IF(F35=0,IF(G35<=0.000001,"PASS","FAIL"),IF(H35<=I35,"PASS","FAIL")) -> PASS
A36: MSFT | B36: Table 2 -- Terminal growth | C36: g=0.0000% | D36: Intrinsic Value per Share | E36: 264.83076 | F36: 264.83076 | G36: =ABS(E36-F36) -> 0 | H36: =IF(F36=0,"n/a (zero denom)",G36/ABS(F36)) -> 0 | I36: ='Tolerances'!$B$13 -> 0.005 | J36: =IF(F36=0,IF(G36<=0.000001,"PASS","FAIL"),IF(H36<=I36,"PASS","FAIL")) -> PASS
A37: MSFT | B37: Table 2 -- Terminal growth | C37: g=1.0000% | D37: Terminal Value | E37: 2.4446454e+12 | F37: 2.4446454e+12 | G37: =ABS(E37-F37) -> 0 | H37: =IF(F37=0,"n/a (zero denom)",G37/ABS(F37)) -> 0 | I37: ='Tolerances'!$B$7 -> 0.002 | J37: =IF(F37=0,IF(G37<=0.000001,"PASS","FAIL"),IF(H37<=I37,"PASS","FAIL")) -> PASS
A38: MSFT | B38: Table 2 -- Terminal growth | C38: g=1.0000% | D38: Enterprise Value | E38: 2.1511817e+12 | F38: 2.1511817e+12 | G38: =ABS(E38-F38) -> 0 | H38: =IF(F38=0,"n/a (zero denom)",G38/ABS(F38)) -> 0 | I38: ='Tolerances'!$B$10 -> 0.002 | J38: =IF(F38=0,IF(G38<=0.000001,"PASS","FAIL"),IF(H38<=I38,"PASS","FAIL")) -> PASS
A39: MSFT | B39: Table 2 -- Terminal growth | C39: g=1.0000% | D39: Equity Value | E39: 2.1318227e+12 | F39: 2.1318227e+12 | G39: =ABS(E39-F39) -> 0 | H39: =IF(F39=0,"n/a (zero denom)",G39/ABS(F39)) -> 0 | I39: ='Tolerances'!$B$11 -> 0.002 | J39: =IF(F39=0,IF(G39<=0.000001,"PASS","FAIL"),IF(H39<=I39,"PASS","FAIL")) -> PASS
A40: MSFT | B40: Table 2 -- Terminal growth | C40: g=1.0000% | D40: Intrinsic Value per Share | E40: 287.09308 | F40: 287.09308 | G40: =ABS(E40-F40) -> 0 | H40: =IF(F40=0,"n/a (zero denom)",G40/ABS(F40)) -> 0 | I40: ='Tolerances'!$B$13 -> 0.005 | J40: =IF(F40=0,IF(G40<=0.000001,"PASS","FAIL"),IF(H40<=I40,"PASS","FAIL")) -> PASS
A41: MSFT | B41: Table 2 -- Terminal growth | C41: g=2.0000% | D41: Terminal Value | E41: 2.7774397e+12 | F41: 2.7774397e+12 | G41: =ABS(E41-F41) -> 0 | H41: =IF(F41=0,"n/a (zero denom)",G41/ABS(F41)) -> 0 | I41: ='Tolerances'!$B$7 -> 0.002 | J41: =IF(F41=0,IF(G41<=0.000001,"PASS","FAIL"),IF(H41<=I41,"PASS","FAIL")) -> PASS
A42: MSFT | B42: Table 2 -- Terminal growth | C42: g=2.0000% | D42: Enterprise Value | E42: 2.3578169e+12 | F42: 2.3578169e+12 | G42: =ABS(E42-F42) -> 0 | H42: =IF(F42=0,"n/a (zero denom)",G42/ABS(F42)) -> 0 | I42: ='Tolerances'!$B$10 -> 0.002 | J42: =IF(F42=0,IF(G42<=0.000001,"PASS","FAIL"),IF(H42<=I42,"PASS","FAIL")) -> PASS
A43: MSFT | B43: Table 2 -- Terminal growth | C43: g=2.0000% | D43: Equity Value | E43: 2.3384579e+12 | F43: 2.3384579e+12 | G43: =ABS(E43-F43) -> 0 | H43: =IF(F43=0,"n/a (zero denom)",G43/ABS(F43)) -> 0 | I43: ='Tolerances'!$B$11 -> 0.002 | J43: =IF(F43=0,IF(G43<=0.000001,"PASS","FAIL"),IF(H43<=I43,"PASS","FAIL")) -> PASS
A44: MSFT | B44: Table 2 -- Terminal growth | C44: g=2.0000% | D44: Intrinsic Value per Share | E44: 314.92068 | F44: 314.92068 | G44: =ABS(E44-F44) -> 0 | H44: =IF(F44=0,"n/a (zero denom)",G44/ABS(F44)) -> 0 | I44: ='Tolerances'!$B$13 -> 0.005 | J44: =IF(F44=0,IF(G44<=0.000001,"PASS","FAIL"),IF(H44<=I44,"PASS","FAIL")) -> PASS
A45: MSFT | B45: Table 2 -- Terminal growth | C45: g=2.5000% | D45: Terminal Value | E45: 2.9771145e+12 | F45: 2.9771145e+12 | G45: =ABS(E45-F45) -> 0 | H45: =IF(F45=0,"n/a (zero denom)",G45/ABS(F45)) -> 0 | I45: ='Tolerances'!$B$7 -> 0.002 | J45: =IF(F45=0,IF(G45<=0.000001,"PASS","FAIL"),IF(H45<=I45,"PASS","FAIL")) -> PASS
A46: MSFT | B46: Table 2 -- Terminal growth | C46: g=2.5000% | D46: Enterprise Value | E46: 2.4817968e+12 | F46: 2.4817968e+12 | G46: =ABS(E46-F46) -> 0 | H46: =IF(F46=0,"n/a (zero denom)",G46/ABS(F46)) -> 0 | I46: ='Tolerances'!$B$10 -> 0.002 | J46: =IF(F46=0,IF(G46<=0.000001,"PASS","FAIL"),IF(H46<=I46,"PASS","FAIL")) -> PASS
A47: MSFT | B47: Table 2 -- Terminal growth | C47: g=2.5000% | D47: Equity Value | E47: 2.4624378e+12 | F47: 2.4624378e+12 | G47: =ABS(E47-F47) -> 0 | H47: =IF(F47=0,"n/a (zero denom)",G47/ABS(F47)) -> 0 | I47: ='Tolerances'!$B$11 -> 0.002 | J47: =IF(F47=0,IF(G47<=0.000001,"PASS","FAIL"),IF(H47<=I47,"PASS","FAIL")) -> PASS
A48: MSFT | B48: Table 2 -- Terminal growth | C48: g=2.5000% | D48: Intrinsic Value per Share | E48: 331.61709 | F48: 331.61709 | G48: =ABS(E48-F48) -> 0 | H48: =IF(F48=0,"n/a (zero denom)",G48/ABS(F48)) -> 0 | I48: ='Tolerances'!$B$13 -> 0.005 | J48: =IF(F48=0,IF(G48<=0.000001,"PASS","FAIL"),IF(H48<=I48,"PASS","FAIL")) -> PASS
A49: MSFT | B49: Table 2 -- Terminal growth | C49: g=3.0000% | D49: Terminal Value | E49: 3.2053125e+12 | F49: 3.2053125e+12 | G49: =ABS(E49-F49) -> 0 | H49: =IF(F49=0,"n/a (zero denom)",G49/ABS(F49)) -> 0 | I49: ='Tolerances'!$B$7 -> 0.002 | J49: =IF(F49=0,IF(G49<=0.000001,"PASS","FAIL"),IF(H49<=I49,"PASS","FAIL")) -> PASS
A50: MSFT | B50: Table 2 -- Terminal growth | C50: g=3.0000% | D50: Enterprise Value | E50: 2.6234871e+12 | F50: 2.6234871e+12 | G50: =ABS(E50-F50) -> 0 | H50: =IF(F50=0,"n/a (zero denom)",G50/ABS(F50)) -> 0 | I50: ='Tolerances'!$B$10 -> 0.002 | J50: =IF(F50=0,IF(G50<=0.000001,"PASS","FAIL"),IF(H50<=I50,"PASS","FAIL")) -> PASS
A51: MSFT | B51: Table 2 -- Terminal growth | C51: g=3.0000% | D51: Equity Value | E51: 2.6041281e+12 | F51: 2.6041281e+12 | G51: =ABS(E51-F51) -> 0 | H51: =IF(F51=0,"n/a (zero denom)",G51/ABS(F51)) -> 0 | I51: ='Tolerances'!$B$11 -> 0.002 | J51: =IF(F51=0,IF(G51<=0.000001,"PASS","FAIL"),IF(H51<=I51,"PASS","FAIL")) -> PASS
A52: MSFT | B52: Table 2 -- Terminal growth | C52: g=3.0000% | D52: Intrinsic Value per Share | E52: 350.69856 | F52: 350.69856 | G52: =ABS(E52-F52) -> 0 | H52: =IF(F52=0,"n/a (zero denom)",G52/ABS(F52)) -> 0 | I52: ='Tolerances'!$B$13 -> 0.005 | J52: =IF(F52=0,IF(G52<=0.000001,"PASS","FAIL"),IF(H52<=I52,"PASS","FAIL")) -> PASS
A53: MSFT | B53: Table 2 -- Terminal growth | C53: g=4.0000% | D53: Terminal Value | E53: 3.7757995e+12 | F53: 3.7757995e+12 | G53: =ABS(E53-F53) -> 0 | H53: =IF(F53=0,"n/a (zero denom)",G53/ABS(F53)) -> 0 | I53: ='Tolerances'!$B$7 -> 0.002 | J53: =IF(F53=0,IF(G53<=0.000001,"PASS","FAIL"),IF(H53<=I53,"PASS","FAIL")) -> PASS
A54: MSFT | B54: Table 2 -- Terminal growth | C54: g=4.0000% | D54: Enterprise Value | E54: 2.9777078e+12 | F54: 2.9777078e+12 | G54: =ABS(E54-F54) -> 0 | H54: =IF(F54=0,"n/a (zero denom)",G54/ABS(F54)) -> 0 | I54: ='Tolerances'!$B$10 -> 0.002 | J54: =IF(F54=0,IF(G54<=0.000001,"PASS","FAIL"),IF(H54<=I54,"PASS","FAIL")) -> PASS
A55: MSFT | B55: Table 2 -- Terminal growth | C55: g=4.0000% | D55: Equity Value | E55: 2.9583488e+12 | F55: 2.9583488e+12 | G55: =ABS(E55-F55) -> 0 | H55: =IF(F55=0,"n/a (zero denom)",G55/ABS(F55)) -> 0 | I55: ='Tolerances'!$B$11 -> 0.002 | J55: =IF(F55=0,IF(G55<=0.000001,"PASS","FAIL"),IF(H55<=I55,"PASS","FAIL")) -> PASS
A56: MSFT | B56: Table 2 -- Terminal growth | C56: g=4.0000% | D56: Intrinsic Value per Share | E56: 398.40155 | F56: 398.40155 | G56: =ABS(E56-F56) -> 0 | H56: =IF(F56=0,"n/a (zero denom)",G56/ABS(F56)) -> 0 | I56: ='Tolerances'!$B$13 -> 0.005 | J56: =IF(F56=0,IF(G56<=0.000001,"PASS","FAIL"),IF(H56<=I56,"PASS","FAIL")) -> PASS
A57: MSFT | B57: Table 2 -- Terminal growth | C57: g=5.0000% | D57: Terminal Value | E57: 4.574462e+12 | F57: 4.574462e+12 | G57: =ABS(E57-F57) -> 0 | H57: =IF(F57=0,"n/a (zero denom)",G57/ABS(F57)) -> 0 | I57: ='Tolerances'!$B$7 -> 0.002 | J57: =IF(F57=0,IF(G57<=0.000001,"PASS","FAIL"),IF(H57<=I57,"PASS","FAIL")) -> PASS
A58: MSFT | B58: Table 2 -- Terminal growth | C58: g=5.0000% | D58: Enterprise Value | E58: 3.4736049e+12 | F58: 3.4736049e+12 | G58: =ABS(E58-F58) -> 0 | H58: =IF(F58=0,"n/a (zero denom)",G58/ABS(F58)) -> 0 | I58: ='Tolerances'!$B$10 -> 0.002 | J58: =IF(F58=0,IF(G58<=0.000001,"PASS","FAIL"),IF(H58<=I58,"PASS","FAIL")) -> PASS
A59: MSFT | B59: Table 2 -- Terminal growth | C59: g=5.0000% | D59: Equity Value | E59: 3.4542459e+12 | F59: 3.4542459e+12 | G59: =ABS(E59-F59) -> 0 | H59: =IF(F59=0,"n/a (zero denom)",G59/ABS(F59)) -> 0 | I59: ='Tolerances'!$B$11 -> 0.002 | J59: =IF(F59=0,IF(G59<=0.000001,"PASS","FAIL"),IF(H59<=I59,"PASS","FAIL")) -> PASS
A60: MSFT | B60: Table 2 -- Terminal growth | C60: g=5.0000% | D60: Intrinsic Value per Share | E60: 465.18413 | F60: 465.18413 | G60: =ABS(E60-F60) -> 0 | H60: =IF(F60=0,"n/a (zero denom)",G60/ABS(F60)) -> 0 | I60: ='Tolerances'!$B$13 -> 0.005 | J60: =IF(F60=0,IF(G60<=0.000001,"PASS","FAIL"),IF(H60<=I60,"PASS","FAIL")) -> PASS
A61: MSFT | B61: Table 3 -- Revenue growth | C61: RevGrowth=-10.0000% | D61: FCF Year 1 | E61: 1.0368662e+11 | F61: 1.0368662e+11 | G61: =ABS(E61-F61) -> 0 | H61: =IF(F61=0,"n/a (zero denom)",G61/ABS(F61)) -> 0 | I61: ='Tolerances'!$B$6 -> 0.001 | J61: =IF(F61=0,IF(G61<=0.000001,"PASS","FAIL"),IF(H61<=I61,"PASS","FAIL")) -> PASS
A62: MSFT | B62: Table 3 -- Revenue growth | C62: RevGrowth=-10.0000% | D62: FCF Year 2 | E62: 9.3317962e+10 | F62: 9.3317962e+10 | G62: =ABS(E62-F62) -> 0 | H62: =IF(F62=0,"n/a (zero denom)",G62/ABS(F62)) -> 0 | I62: ='Tolerances'!$B$6 -> 0.001 | J62: =IF(F62=0,IF(G62<=0.000001,"PASS","FAIL"),IF(H62<=I62,"PASS","FAIL")) -> PASS
A63: MSFT | B63: Table 3 -- Revenue growth | C63: RevGrowth=-10.0000% | D63: FCF Year 3 | E63: 8.3986166e+10 | F63: 8.3986166e+10 | G63: =ABS(E63-F63) -> 0 | H63: =IF(F63=0,"n/a (zero denom)",G63/ABS(F63)) -> 0 | I63: ='Tolerances'!$B$6 -> 0.001 | J63: =IF(F63=0,IF(G63<=0.000001,"PASS","FAIL"),IF(H63<=I63,"PASS","FAIL")) -> PASS
A64: MSFT | B64: Table 3 -- Revenue growth | C64: RevGrowth=-10.0000% | D64: FCF Year 4 | E64: 7.5587549e+10 | F64: 7.5587549e+10 | G64: =ABS(E64-F64) -> 0 | H64: =IF(F64=0,"n/a (zero denom)",G64/ABS(F64)) -> 0 | I64: ='Tolerances'!$B$6 -> 0.001 | J64: =IF(F64=0,IF(G64<=0.000001,"PASS","FAIL"),IF(H64<=I64,"PASS","FAIL")) -> PASS
A65: MSFT | B65: Table 3 -- Revenue growth | C65: RevGrowth=-10.0000% | D65: FCF Year 5 | E65: 6.8028794e+10 | F65: 6.8028794e+10 | G65: =ABS(E65-F65) -> 0 | H65: =IF(F65=0,"n/a (zero denom)",G65/ABS(F65)) -> 0 | I65: ='Tolerances'!$B$6 -> 0.001 | J65: =IF(F65=0,IF(G65<=0.000001,"PASS","FAIL"),IF(H65<=I65,"PASS","FAIL")) -> PASS
A66: MSFT | B66: Table 3 -- Revenue growth | C66: RevGrowth=-10.0000% | D66: Terminal Value | E66: 9.2967459e+11 | F66: 9.2967459e+11 | G66: =ABS(E66-F66) -> 0 | H66: =IF(F66=0,"n/a (zero denom)",G66/ABS(F66)) -> 0 | I66: ='Tolerances'!$B$7 -> 0.002 | J66: =IF(F66=0,IF(G66<=0.000001,"PASS","FAIL"),IF(H66<=I66,"PASS","FAIL")) -> PASS
A67: MSFT | B67: Table 3 -- Revenue growth | C67: RevGrowth=-10.0000% | D67: Enterprise Value | E67: 9.0559118e+11 | F67: 9.0559118e+11 | G67: =ABS(E67-F67) -> 0 | H67: =IF(F67=0,"n/a (zero denom)",G67/ABS(F67)) -> 0 | I67: ='Tolerances'!$B$10 -> 0.002 | J67: =IF(F67=0,IF(G67<=0.000001,"PASS","FAIL"),IF(H67<=I67,"PASS","FAIL")) -> PASS
A68: MSFT | B68: Table 3 -- Revenue growth | C68: RevGrowth=-10.0000% | D68: Equity Value | E68: 8.8623218e+11 | F68: 8.8623218e+11 | G68: =ABS(E68-F68) -> 0 | H68: =IF(F68=0,"n/a (zero denom)",G68/ABS(F68)) -> 0 | I68: ='Tolerances'!$B$11 -> 0.002 | J68: =IF(F68=0,IF(G68<=0.000001,"PASS","FAIL"),IF(H68<=I68,"PASS","FAIL")) -> PASS
A69: MSFT | B69: Table 3 -- Revenue growth | C69: RevGrowth=-10.0000% | D69: Intrinsic Value per Share | E69: 119.3491 | F69: 119.3491 | G69: =ABS(E69-F69) -> 0 | H69: =IF(F69=0,"n/a (zero denom)",G69/ABS(F69)) -> 0 | I69: ='Tolerances'!$B$13 -> 0.005 | J69: =IF(F69=0,IF(G69<=0.000001,"PASS","FAIL"),IF(H69<=I69,"PASS","FAIL")) -> PASS
A70: MSFT | B70: Table 3 -- Revenue growth | C70: RevGrowth=-5.0000% | D70: FCF Year 1 | E70: 1.0926264e+11 | F70: 1.0926264e+11 | G70: =ABS(E70-F70) -> 0 | H70: =IF(F70=0,"n/a (zero denom)",G70/ABS(F70)) -> 0 | I70: ='Tolerances'!$B$6 -> 0.001 | J70: =IF(F70=0,IF(G70<=0.000001,"PASS","FAIL"),IF(H70<=I70,"PASS","FAIL")) -> PASS
A71: MSFT | B71: Table 3 -- Revenue growth | C71: RevGrowth=-5.0000% | D71: FCF Year 2 | E71: 1.0379951e+11 | F71: 1.0379951e+11 | G71: =ABS(E71-F71) -> 0 | H71: =IF(F71=0,"n/a (zero denom)",G71/ABS(F71)) -> 0 | I71: ='Tolerances'!$B$6 -> 0.001 | J71: =IF(F71=0,IF(G71<=0.000001,"PASS","FAIL"),IF(H71<=I71,"PASS","FAIL")) -> PASS
A72: MSFT | B72: Table 3 -- Revenue growth | C72: RevGrowth=-5.0000% | D72: FCF Year 3 | E72: 9.860953e+10 | F72: 9.860953e+10 | G72: =ABS(E72-F72) -> 0 | H72: =IF(F72=0,"n/a (zero denom)",G72/ABS(F72)) -> 0 | I72: ='Tolerances'!$B$6 -> 0.001 | J72: =IF(F72=0,IF(G72<=0.000001,"PASS","FAIL"),IF(H72<=I72,"PASS","FAIL")) -> PASS
A73: MSFT | B73: Table 3 -- Revenue growth | C73: RevGrowth=-5.0000% | D73: FCF Year 4 | E73: 9.3679054e+10 | F73: 9.3679054e+10 | G73: =ABS(E73-F73) -> 0 | H73: =IF(F73=0,"n/a (zero denom)",G73/ABS(F73)) -> 0 | I73: ='Tolerances'!$B$6 -> 0.001 | J73: =IF(F73=0,IF(G73<=0.000001,"PASS","FAIL"),IF(H73<=I73,"PASS","FAIL")) -> PASS
A74: MSFT | B74: Table 3 -- Revenue growth | C74: RevGrowth=-5.0000% | D74: FCF Year 5 | E74: 8.8995101e+10 | F74: 8.8995101e+10 | G74: =ABS(E74-F74) -> 0 | H74: =IF(F74=0,"n/a (zero denom)",G74/ABS(F74)) -> 0 | I74: ='Tolerances'!$B$6 -> 0.001 | J74: =IF(F74=0,IF(G74<=0.000001,"PASS","FAIL"),IF(H74<=I74,"PASS","FAIL")) -> PASS
A75: MSFT | B75: Table 3 -- Revenue growth | C75: RevGrowth=-5.0000% | D75: Terminal Value | E75: 1.216198e+12 | F75: 1.216198e+12 | G75: =ABS(E75-F75) -> 0 | H75: =IF(F75=0,"n/a (zero denom)",G75/ABS(F75)) -> 0 | I75: ='Tolerances'!$B$7 -> 0.002 | J75: =IF(F75=0,IF(G75<=0.000001,"PASS","FAIL"),IF(H75<=I75,"PASS","FAIL")) -> PASS
A76: MSFT | B76: Table 3 -- Revenue growth | C76: RevGrowth=-5.0000% | D76: Enterprise Value | E76: 1.1335891e+12 | F76: 1.1335891e+12 | G76: =ABS(E76-F76) -> 0 | H76: =IF(F76=0,"n/a (zero denom)",G76/ABS(F76)) -> 0 | I76: ='Tolerances'!$B$10 -> 0.002 | J76: =IF(F76=0,IF(G76<=0.000001,"PASS","FAIL"),IF(H76<=I76,"PASS","FAIL")) -> PASS
A77: MSFT | B77: Table 3 -- Revenue growth | C77: RevGrowth=-5.0000% | D77: Equity Value | E77: 1.1142301e+12 | F77: 1.1142301e+12 | G77: =ABS(E77-F77) -> 0 | H77: =IF(F77=0,"n/a (zero denom)",G77/ABS(F77)) -> 0 | I77: ='Tolerances'!$B$11 -> 0.002 | J77: =IF(F77=0,IF(G77<=0.000001,"PASS","FAIL"),IF(H77<=I77,"PASS","FAIL")) -> PASS
A78: MSFT | B78: Table 3 -- Revenue growth | C78: RevGrowth=-5.0000% | D78: Intrinsic Value per Share | E78: 150.05363 | F78: 150.05363 | G78: =ABS(E78-F78) -> 0 | H78: =IF(F78=0,"n/a (zero denom)",G78/ABS(F78)) -> 0 | I78: ='Tolerances'!$B$13 -> 0.005 | J78: =IF(F78=0,IF(G78<=0.000001,"PASS","FAIL"),IF(H78<=I78,"PASS","FAIL")) -> PASS
A79: MSFT | B79: Table 3 -- Revenue growth | C79: RevGrowth=0.0000% | D79: FCF Year 1 | E79: 1.1483865e+11 | F79: 1.1483865e+11 | G79: =ABS(E79-F79) -> 0 | H79: =IF(F79=0,"n/a (zero denom)",G79/ABS(F79)) -> 0 | I79: ='Tolerances'!$B$6 -> 0.001 | J79: =IF(F79=0,IF(G79<=0.000001,"PASS","FAIL"),IF(H79<=I79,"PASS","FAIL")) -> PASS
A80: MSFT | B80: Table 3 -- Revenue growth | C80: RevGrowth=0.0000% | D80: FCF Year 2 | E80: 1.1483865e+11 | F80: 1.1483865e+11 | G80: =ABS(E80-F80) -> 0 | H80: =IF(F80=0,"n/a (zero denom)",G80/ABS(F80)) -> 0 | I80: ='Tolerances'!$B$6 -> 0.001 | J80: =IF(F80=0,IF(G80<=0.000001,"PASS","FAIL"),IF(H80<=I80,"PASS","FAIL")) -> PASS
A81: MSFT | B81: Table 3 -- Revenue growth | C81: RevGrowth=0.0000% | D81: FCF Year 3 | E81: 1.1483865e+11 | F81: 1.1483865e+11 | G81: =ABS(E81-F81) -> 0 | H81: =IF(F81=0,"n/a (zero denom)",G81/ABS(F81)) -> 0 | I81: ='Tolerances'!$B$6 -> 0.001 | J81: =IF(F81=0,IF(G81<=0.000001,"PASS","FAIL"),IF(H81<=I81,"PASS","FAIL")) -> PASS
A82: MSFT | B82: Table 3 -- Revenue growth | C82: RevGrowth=0.0000% | D82: FCF Year 4 | E82: 1.1483865e+11 | F82: 1.1483865e+11 | G82: =ABS(E82-F82) -> 0 | H82: =IF(F82=0,"n/a (zero denom)",G82/ABS(F82)) -> 0 | I82: ='Tolerances'!$B$6 -> 0.001 | J82: =IF(F82=0,IF(G82<=0.000001,"PASS","FAIL"),IF(H82<=I82,"PASS","FAIL")) -> PASS
A83: MSFT | B83: Table 3 -- Revenue growth | C83: RevGrowth=0.0000% | D83: FCF Year 5 | E83: 1.1483865e+11 | F83: 1.1483865e+11 | G83: =ABS(E83-F83) -> 0 | H83: =IF(F83=0,"n/a (zero denom)",G83/ABS(F83)) -> 0 | I83: ='Tolerances'!$B$6 -> 0.001 | J83: =IF(F83=0,IF(G83<=0.000001,"PASS","FAIL"),IF(H83<=I83,"PASS","FAIL")) -> PASS
A84: MSFT | B84: Table 3 -- Revenue growth | C84: RevGrowth=0.0000% | D84: Terminal Value | E84: 1.5693733e+12 | F84: 1.5693733e+12 | G84: =ABS(E84-F84) -> 0 | H84: =IF(F84=0,"n/a (zero denom)",G84/ABS(F84)) -> 0 | I84: ='Tolerances'!$B$7 -> 0.002 | J84: =IF(F84=0,IF(G84<=0.000001,"PASS","FAIL"),IF(H84<=I84,"PASS","FAIL")) -> PASS
A85: MSFT | B85: Table 3 -- Revenue growth | C85: RevGrowth=0.0000% | D85: Enterprise Value | E85: 1.4097628e+12 | F85: 1.4097628e+12 | G85: =ABS(E85-F85) -> 0 | H85: =IF(F85=0,"n/a (zero denom)",G85/ABS(F85)) -> 0 | I85: ='Tolerances'!$B$10 -> 0.002 | J85: =IF(F85=0,IF(G85<=0.000001,"PASS","FAIL"),IF(H85<=I85,"PASS","FAIL")) -> PASS
A86: MSFT | B86: Table 3 -- Revenue growth | C86: RevGrowth=0.0000% | D86: Equity Value | E86: 1.3904038e+12 | F86: 1.3904038e+12 | G86: =ABS(E86-F86) -> 0 | H86: =IF(F86=0,"n/a (zero denom)",G86/ABS(F86)) -> 0 | I86: ='Tolerances'!$B$11 -> 0.002 | J86: =IF(F86=0,IF(G86<=0.000001,"PASS","FAIL"),IF(H86<=I86,"PASS","FAIL")) -> PASS
A87: MSFT | B87: Table 3 -- Revenue growth | C87: RevGrowth=0.0000% | D87: Intrinsic Value per Share | E87: 187.24602 | F87: 187.24602 | G87: =ABS(E87-F87) -> 0 | H87: =IF(F87=0,"n/a (zero denom)",G87/ABS(F87)) -> 0 | I87: ='Tolerances'!$B$13 -> 0.005 | J87: =IF(F87=0,IF(G87<=0.000001,"PASS","FAIL"),IF(H87<=I87,"PASS","FAIL")) -> PASS
A88: MSFT | B88: Table 3 -- Revenue growth | C88: RevGrowth=5.0000% | D88: FCF Year 1 | E88: 1.2041466e+11 | F88: 1.2041466e+11 | G88: =ABS(E88-F88) -> 0 | H88: =IF(F88=0,"n/a (zero denom)",G88/ABS(F88)) -> 0 | I88: ='Tolerances'!$B$6 -> 0.001 | J88: =IF(F88=0,IF(G88<=0.000001,"PASS","FAIL"),IF(H88<=I88,"PASS","FAIL")) -> PASS
A89: MSFT | B89: Table 3 -- Revenue growth | C89: RevGrowth=5.0000% | D89: FCF Year 2 | E89: 1.264354e+11 | F89: 1.264354e+11 | G89: =ABS(E89-F89) -> 0 | H89: =IF(F89=0,"n/a (zero denom)",G89/ABS(F89)) -> 0 | I89: ='Tolerances'!$B$6 -> 0.001 | J89: =IF(F89=0,IF(G89<=0.000001,"PASS","FAIL"),IF(H89<=I89,"PASS","FAIL")) -> PASS
A90: MSFT | B90: Table 3 -- Revenue growth | C90: RevGrowth=5.0000% | D90: FCF Year 3 | E90: 1.3275717e+11 | F90: 1.3275717e+11 | G90: =ABS(E90-F90) -> 0 | H90: =IF(F90=0,"n/a (zero denom)",G90/ABS(F90)) -> 0 | I90: ='Tolerances'!$B$6 -> 0.001 | J90: =IF(F90=0,IF(G90<=0.000001,"PASS","FAIL"),IF(H90<=I90,"PASS","FAIL")) -> PASS
A91: MSFT | B91: Table 3 -- Revenue growth | C91: RevGrowth=5.0000% | D91: FCF Year 4 | E91: 1.3939502e+11 | F91: 1.3939502e+11 | G91: =ABS(E91-F91) -> 0 | H91: =IF(F91=0,"n/a (zero denom)",G91/ABS(F91)) -> 0 | I91: ='Tolerances'!$B$6 -> 0.001 | J91: =IF(F91=0,IF(G91<=0.000001,"PASS","FAIL"),IF(H91<=I91,"PASS","FAIL")) -> PASS
A92: MSFT | B92: Table 3 -- Revenue growth | C92: RevGrowth=5.0000% | D92: FCF Year 5 | E92: 1.4636478e+11 | F92: 1.4636478e+11 | G92: =ABS(E92-F92) -> 0 | H92: =IF(F92=0,"n/a (zero denom)",G92/ABS(F92)) -> 0 | I92: ='Tolerances'!$B$6 -> 0.001 | J92: =IF(F92=0,IF(G92<=0.000001,"PASS","FAIL"),IF(H92<=I92,"PASS","FAIL")) -> PASS
A93: MSFT | B93: Table 3 -- Revenue growth | C93: RevGrowth=5.0000% | D93: Terminal Value | E93: 2.0002062e+12 | F93: 2.0002062e+12 | G93: =ABS(E93-F93) -> 0 | H93: =IF(F93=0,"n/a (zero denom)",G93/ABS(F93)) -> 0 | I93: ='Tolerances'!$B$7 -> 0.002 | J93: =IF(F93=0,IF(G93<=0.000001,"PASS","FAIL"),IF(H93<=I93,"PASS","FAIL")) -> PASS
A94: MSFT | B94: Table 3 -- Revenue growth | C94: RevGrowth=5.0000% | D94: Enterprise Value | E94: 1.7417333e+12 | F94: 1.7417333e+12 | G94: =ABS(E94-F94) -> 0 | H94: =IF(F94=0,"n/a (zero denom)",G94/ABS(F94)) -> 0 | I94: ='Tolerances'!$B$10 -> 0.002 | J94: =IF(F94=0,IF(G94<=0.000001,"PASS","FAIL"),IF(H94<=I94,"PASS","FAIL")) -> PASS
A95: MSFT | B95: Table 3 -- Revenue growth | C95: RevGrowth=5.0000% | D95: Equity Value | E95: 1.7223743e+12 | F95: 1.7223743e+12 | G95: =ABS(E95-F95) -> 0 | H95: =IF(F95=0,"n/a (zero denom)",G95/ABS(F95)) -> 0 | I95: ='Tolerances'!$B$11 -> 0.002 | J95: =IF(F95=0,IF(G95<=0.000001,"PASS","FAIL"),IF(H95<=I95,"PASS","FAIL")) -> PASS
A96: MSFT | B96: Table 3 -- Revenue growth | C96: RevGrowth=5.0000% | D96: Intrinsic Value per Share | E96: 231.95257 | F96: 231.95257 | G96: =ABS(E96-F96) -> 0 | H96: =IF(F96=0,"n/a (zero denom)",G96/ABS(F96)) -> 0 | I96: ='Tolerances'!$B$13 -> 0.005 | J96: =IF(F96=0,IF(G96<=0.000001,"PASS","FAIL"),IF(H96<=I96,"PASS","FAIL")) -> PASS
A97: MSFT | B97: Table 3 -- Revenue growth | C97: RevGrowth=10.0000% | D97: FCF Year 1 | E97: 1.2599068e+11 | F97: 1.2599068e+11 | G97: =ABS(E97-F97) -> 0 | H97: =IF(F97=0,"n/a (zero denom)",G97/ABS(F97)) -> 0 | I97: ='Tolerances'!$B$6 -> 0.001 | J97: =IF(F97=0,IF(G97<=0.000001,"PASS","FAIL"),IF(H97<=I97,"PASS","FAIL")) -> PASS
A98: MSFT | B98: Table 3 -- Revenue growth | C98: RevGrowth=10.0000% | D98: FCF Year 2 | E98: 1.3858974e+11 | F98: 1.3858974e+11 | G98: =ABS(E98-F98) -> 0 | H98: =IF(F98=0,"n/a (zero denom)",G98/ABS(F98)) -> 0 | I98: ='Tolerances'!$B$6 -> 0.001 | J98: =IF(F98=0,IF(G98<=0.000001,"PASS","FAIL"),IF(H98<=I98,"PASS","FAIL")) -> PASS
A99: MSFT | B99: Table 3 -- Revenue growth | C99: RevGrowth=10.0000% | D99: FCF Year 3 | E99: 1.5244872e+11 | F99: 1.5244872e+11 | G99: =ABS(E99-F99) -> 0 | H99: =IF(F99=0,"n/a (zero denom)",G99/ABS(F99)) -> 0 | I99: ='Tolerances'!$B$6 -> 0.001 | J99: =IF(F99=0,IF(G99<=0.000001,"PASS","FAIL"),IF(H99<=I99,"PASS","FAIL")) -> PASS
A100: MSFT | B100: Table 3 -- Revenue growth | C100: RevGrowth=10.0000% | D100: FCF Year 4 | E100: 1.6769359e+11 | F100: 1.6769359e+11 | G100: =ABS(E100-F100) -> 0 | H100: =IF(F100=0,"n/a (zero denom)",G100/ABS(F100)) -> 0 | I100: ='Tolerances'!$B$6 -> 0.001 | J100: =IF(F100=0,IF(G100<=0.000001,"PASS","FAIL"),IF(H100<=I100,"PASS","FAIL")) -> PASS
A101: MSFT | B101: Table 3 -- Revenue growth | C101: RevGrowth=10.0000% | D101: FCF Year 5 | E101: 1.8446295e+11 | F101: 1.8446295e+11 | G101: =ABS(E101-F101) -> 0 | H101: =IF(F101=0,"n/a (zero denom)",G101/ABS(F101)) -> 0 | I101: ='Tolerances'!$B$6 -> 0.001 | J101: =IF(F101=0,IF(G101<=0.000001,"PASS","FAIL"),IF(H101<=I101,"PASS","FAIL")) -> PASS
...

Sheet Findings
A1: Findings
A3: Overall verdict: GO
A4: Reconciliation target: independent workbook V2 (independent_dcf_validation_v2.xlsx), built in Track A Phase 2C from the corrected years_elapsed specification (A-028/L-019). V1 (independent_dcf_validation.xlsx) is preserved unchanged; its original Phase 2B NO-GO evidence is archived at validation/dcf_reconciliation/history/phase2b_initial_no_go/ and was never edited.
A5: No base-case divergence found in any company against V2. Phase 2B's original NO-GO (against V1) was caused by V1's 'years_elapsed = COUNT(periods)-1' convention, which did NOT conform to the now-clarified specification (docs/model-specifications/dcf.md's years_elapsed = actual elapsed calendar days / 365.25) for a company on an irregular fiscal calendar (INTC). V1's convention is not described as having been correct under the clarified specification -- it was a reasonable resolution of a genuine ambiguity that the clarification has since closed. Production code (src/dcf_model/dcf.py) required NO change: its existing calculate_historical_revenue_cagr implementation already computed years_elapsed via actual elapsed calendar days, which is what the specification was clarified to require.
A6: Directional bias: MSFT, CAT, and VZ match V2 to full floating-point precision on every required metric (zero signed difference) -- no bias to investigate among them.
A7: INTC sensitivity tables show a documented, mathematically-correct inverted direction (IV rises with WACC, falls with terminal growth, falls with revenue growth) caused by negative base-case FCF -- both V2 and the production recompute agree on every inverted direction.
A8: Sensitivity coverage: 908 total scalar comparisons across four companies (227 per company: Table 1=28, Table 2=28, Table 3=72, Table 4=63, Table 5=36) -- every one appears as its own row on the 'All Sensitivity Comparisons' sheet, not only in reconciliation_results.json.

Sheet Sign-off
A1: Sign-off
A3: Source implementation commit | B3: 776e76f56e6210f1050caa74c60962ed89162496
A4: Branch | B4: remediation/valuation-engine-production-quality
A5: V1 independent workbook SHA-256 (preserved, historical) | B5: 942b5f096cf546d63487add31eb29b1b690f0819f923f01436093f9bbc75eba1
A6: V2 independent workbook SHA-256 (reconciliation target) | B6: cd2d225cfe0825ff56aa8f866c3b80b6bec5f87a8b02dc3f76724e4abdd27d6b
A7: Frozen snapshot SHA-256 (MSFT) | B7: 7c50a3e9fb2d27095a890ad8d11732d4ccc72ef9350998604adb3af7a3c845a8
A8: Frozen snapshot SHA-256 (CAT) | B8: 651d366c01415c2da33733058dabb9ac6e4f40cdf5b20e743c0b83ebc3a52c93
A9: Frozen snapshot SHA-256 (INTC) | B9: d73e4b40bce2442a75affde82aaa563ffdea9c68c7257e70cc325663cff24930
A10: Frozen snapshot SHA-256 (VZ) | B10: 77b8ea27b8decaff5fe3b4aad857c632a852445eda0b7f2342f594cd3c4b5f3d
A11: Overall reconciliation status | B11: GO
A12: Profitability established? | B12: NOT ESTABLISHED -- this reconciliation checks calculation agreement only
A13: Second-reviewer sign-off | B13: PENDING -- not performed in this session
